Workbook

Sheet 25.04
B2: this month is | E2: July | F2: 2025 | K2: 29625000
H3: =sum(H7:H10) -> 29625000 | K3: =K2-H7-H8-H9 -> 11325000
B4: How much money do you have coming in? and spend out? | K4: 625000
D5: ( + ) | F5: (-) | J5: ( + )
B6: Month | C6: Date | D6: SOURCE | E6: Name | F6: Account | G6: Fund | H6: AMOUNT | J6: Fund | K6: Account
C7: 45840 | D7: House rental money | E7: Xuân trả tiền thuê nhà | H7: 13300000 | J7: Togohub management | K7: Cash
C8: 45840 | D8: Family | E8: bà đưa tiền của Nghĩa | H8: 4000000 | K8: Cash
C9: 45840 | D9: Family | E9: bà̀ cho sinh nhật | H9: 1000000 | K9: Cash
C10: 45840 | D10: Banking interest | E10: lãi ngân hàng | H10: 11325000
C11: 45839 | E11: đi chợ | F11: Vietcombank | G11: Go Market | H11: 1825316
C12: 45847 | E12: đi chợ | F12: Vietcombank | G12: Go Market | H12: 1578328
C13: 45839 | E13: đồ ăn | F13: Vietcombank | G13: Extra meal | H13: 176500
C14: 45844 | E14: cafe | F14: Cash | G14: Café | H14: 195000
C15: 45844 | E15: cafe | F15: Cash | G15: Café | H15: 125000
C323: 45322
C324: 45322
C325: 45322
C326: 45322
C327: 45322
C328: 45322
C329: 45322
E412: TOTAL (A) | H412: =sum(H7:H411) -> 33525144
B414: How much money do you have going out? | E414: =#REF! -> #REF!
B417: How much money do you have available to you?
B418: TOTAL (A) | D418: - | E418: TOTAL (B) | F418: = | H418: TOTAL (C)
B419: =H412 -> 33525144 | E419: =#REF! -> #REF! | H419: =B419-E419 -> #REF!
B421: How much money do you want to save
B422: TOTAL (D) | E422: ='Spending 25.04'!H89+#REF! -> #REF!
B424: What for?
B430: How much should you spend?
B431: TOTAL (C) | D431: - | E431: TOTAL (D) | F431: = | H431: TOTAL (E) (PER MONTH)
B432: =H419 -> #REF! | E432: =E422 -> #REF! | H432: =H419-E422 -> #REF!
B434: TOTAL (E) | D434: / | E434: No OF WEEKS | F434: = | H434: TOTAL (PER WEEK)
B435: =H432 -> #REF! | E435: 5 | H435: =B435/E435 -> #REF!
B437: NOTES

Sheet Spending 25.04
C1: Chi tiêu thực tế
E2: (-) | U2: ( + )
E3: Cash | F3: BIDV | G3: Vietcombank | H3: Vp bank Lady | I3: Moca | J3: Momo | K3: Zalo | L3: Saving | M3: Loan | N3: Total out | P3: % | Q3: % | T3: Cash | U3: BIDV | V3: Vietcombank | W3: Vp bank Lady | X3: Moca | Y3: Momo | Z3: Zalo | AA3: Saving | AB3: Loan | AC3: Total in
C4: 1 | D4: Education | E4: =sumifs('25.04'!$H$7:$H$411,'25.04'!$G$7:$G$411,$D4,'25.04'!$F$7:$F$411,E$3) -> 0 | F4: =sumifs('25.04'!$H$7:$H$411,'25.04'!$G$7:$G$411,$D4,'25.04'!$F$7:$F$411,F$3) -> 0 | G4: =sumifs('25.04'!$H$7:$H$411,'25.04'!$G$7:$G$411,$D4,'25.04'!$F$7:$F$411,G$3) -> 0 | H4: =sumifs('25.04'!$H$7:$H$411,'25.04'!$G$7:$G$411,$D4,'25.04'!$F$7:$F$411,H$3) -> 0 | I4: =sumifs('25.04'!$H$7:$H$411,'25.04'!$G$7:$G$411,$D4,'25.04'!$F$7:$F$411,I$3) -> 0 | J4: =sumifs('25.04'!$H$7:$H$411,'25.04'!$G$7:$G$411,$D4,'25.04'!$F$7:$F$411,J$3) -> 0 | K4: =sumifs('25.04'!$H$7:$H$411,'25.04'!$G$7:$G$411,$D4,'25.04'!$F$7:$F$411,K$3) -> 0 | L4: =sumifs('25.04'!$H$7:$H$411,'25.04'!$G$7:$G$411,$D4,'25.04'!$F$7:$F$411,L$3) -> 0 | M4: =sumifs('25.04'!$H$7:$H$411,'25.04'!$G$7:$G$411,$D4,'25.04'!$F$7:$F$411,M$3) -> 0 | N4: =sum(E4:M4) -> 0 | P4: =N4/sum(N$4:N$9) -> #DIV/0! | R4: =sum(N4:N9) -> 0 | S4: =R4/sum($R$4:$R$49) -> 0 | T4: =sumifs('25.04'!$H$7:$H$411,'25.04'!$J$7:$J$411,$D4,'25.04'!$K$7:$K$411,T$3) -> 0 | U4: =sumifs('25.04'!$H$7:$H$411,'25.04'!$J$7:$J$411,$D4,'25.04'!$K$7:$K$411,U$3) -> 0 | V4: =sumifs('25.04'!$H$7:$H$411,'25.04'!$J$7:$J$411,$D4,'25.04'!$K$7:$K$411,V$3) -> 0 | W4: =sumifs('25.04'!$H$7:$H$411,'25.04'!$J$7:$J$411,$D4,'25.04'!$K$7:$K$411,W$3) -> 0 | X4: =sumifs('25.04'!$H$7:$H$411,'25.04'!$J$7:$J$411,$D4,'25.04'!$K$7:$K$411,X$3) -> 0 | Y4: =sumifs('25.04'!$H$7:$H$411,'25.04'!$J$7:$J$411,$D4,'25.04'!$K$7:$K$411,Y$3) -> 0 | Z4: =sumifs('25.04'!$H$7:$H$411,'25.04'!$J$7:$J$411,$D4,'25.04'!$K$7:$K$411,Z$3) -> 0 | AA4: =sumifs('25.04'!$H$7:$H$411,'25.04'!$J$7:$J$411,$D4,'25.04'!$K$7:$K$411,AA$3) -> 0 | AB4: =sumifs('25.04'!$H$7:$H$411,'25.04'!$J$7:$J$411,$D4,'25.04'!$K$7:$K$411,AB$3) -> 0 | AC4: =sum(T4:AB4) -> 0
A5: 1 | B5: Education | C5: 44927 | D5: Education fee | E5: =sumifs('25.04'!$H$7:$H$411,'25.04'!$G$7:$G$411,$D5,'25.04'!$F$7:$F$411,E$3) -> 0 | F5: =sumifs('25.04'!$H$7:$H$411,'25.04'!$G$7:$G$411,$D5,'25.04'!$F$7:$F$411,F$3) -> 0 | G5: =sumifs('25.04'!$H$7:$H$411,'25.04'!$G$7:$G$411,$D5,'25.04'!$F$7:$F$411,G$3) -> 0 | H5: =sumifs('25.04'!$H$7:$H$411,'25.04'!$G$7:$G$411,$D5,'25.04'!$F$7:$F$411,H$3) -> 0 | I5: =sumifs('25.04'!$H$7:$H$411,'25.04'!$G$7:$G$411,$D5,'25.04'!$F$7:$F$411,I$3) -> 0 | J5: =sumifs('25.04'!$H$7:$H$411,'25.04'!$G$7:$G$411,$D5,'25.04'!$F$7:$F$411,J$3) -> 0 | K5: =sumifs('25.04'!$H$7:$H$411,'25.04'!$G$7:$G$411,$D5,'25.04'!$F$7:$F$411,K$3) -> 0 | L5: =sumifs('25.04'!$H$7:$H$411,'25.04'!$G$7:$G$411,$D5,'25.04'!$F$7:$F$411,L$3) -> 0 | M5: =sumifs('25.04'!$H$7:$H$411,'25.04'!$G$7:$G$411,$D5,'25.04'!$F$7:$F$411,M$3) -> 0 | N5: =sum(E5:M5) -> 0 | P5: =N5/sum(N$4:N$9) -> #DIV/0! | T5: =sumifs('25.04'!$H$7:$H$411,'25.04'!$J$7:$J$411,$D5,'25.04'!$K$7:$K$411,T$3) -> 0 | U5: =sumifs('25.04'!$H$7:$H$411,'25.04'!$J$7:$J$411,$D5,'25.04'!$K$7:$K$411,U$3) -> 0 | V5: =sumifs('25.04'!$H$7:$H$411,'25.04'!$J$7:$J$411,$D5,'25.04'!$K$7:$K$411,V$3) -> 0 | W5: =sumifs('25.04'!$H$7:$H$411,'25.04'!$J$7:$J$411,$D5,'25.04'!$K$7:$K$411,W$3) -> 0 | X5: =sumifs('25.04'!$H$7:$H$411,'25.04'!$J$7:$J$411,$D5,'25.04'!$K$7:$K$411,X$3) -> 0 | Y5: =sumifs('25.04'!$H$7:$H$411,'25.04'!$J$7:$J$411,$D5,'25.04'!$K$7:$K$411,Y$3) -> 0 | Z5: =sumifs('25.04'!$H$7:$H$411,'25.04'!$J$7:$J$411,$D5,'25.04'!$K$7:$K$411,Z$3) -> 0 | AA5: =sumifs('25.04'!$H$7:$H$411,'25.04'!$J$7:$J$411,$D5,'25.04'!$K$7:$K$411,AA$3) -> 0 | AB5: =sumifs('25.04'!$H$7:$H$411,'25.04'!$J$7:$J$411,$D5,'25.04'!$K$7:$K$411,AB$3) -> 0 | AC5: =sum(T5:AB5) -> 0
C6: 44958 | D6: Extra Education fee | E6: =sumifs('25.04'!$H$7:$H$411,'25.04'!$G$7:$G$411,$D6,'25.04'!$F$7:$F$411,E$3) -> 0 | F6: =sumifs('25.04'!$H$7:$H$411,'25.04'!$G$7:$G$411,$D6,'25.04'!$F$7:$F$411,F$3) -> 0 | G6: =sumifs('25.04'!$H$7:$H$411,'25.04'!$G$7:$G$411,$D6,'25.04'!$F$7:$F$411,G$3) -> 0 | H6: =sumifs('25.04'!$H$7:$H$411,'25.04'!$G$7:$G$411,$D6,'25.04'!$F$7:$F$411,H$3) -> 0 | I6: =sumifs('25.04'!$H$7:$H$411,'25.04'!$G$7:$G$411,$D6,'25.04'!$F$7:$F$411,I$3) -> 0 | J6: =sumifs('25.04'!$H$7:$H$411,'25.04'!$G$7:$G$411,$D6,'25.04'!$F$7:$F$411,J$3) -> 0 | K6: =sumifs('25.04'!$H$7:$H$411,'25.04'!$G$7:$G$411,$D6,'25.04'!$F$7:$F$411,K$3) -> 0 | L6: =sumifs('25.04'!$H$7:$H$411,'25.04'!$G$7:$G$411,$D6,'25.04'!$F$7:$F$411,L$3) -> 0 | M6: =sumifs('25.04'!$H$7:$H$411,'25.04'!$G$7:$G$411,$D6,'25.04'!$F$7:$F$411,M$3) -> 0 | N6: =sum(E6:M6) -> 0 | P6: =N6/sum(N$4:N$9) -> #DIV/0! | T6: =sumifs('25.04'!$H$7:$H$411,'25.04'!$J$7:$J$411,$D6,'25.04'!$K$7:$K$411,T$3) -> 0 | U6: =sumifs('25.04'!$H$7:$H$411,'25.04'!$J$7:$J$411,$D6,'25.04'!$K$7:$K$411,U$3) -> 0 | V6: =sumifs('25.04'!$H$7:$H$411,'25.04'!$J$7:$J$411,$D6,'25.04'!$K$7:$K$411,V$3) -> 0 | W6: =sumifs('25.04'!$H$7:$H$411,'25.04'!$J$7:$J$411,$D6,'25.04'!$K$7:$K$411,W$3) -> 0 | X6: =sumifs('25.04'!$H$7:$H$411,'25.04'!$J$7:$J$411,$D6,'25.04'!$K$7:$K$411,X$3) -> 0 | Y6: =sumifs('25.04'!$H$7:$H$411,'25.04'!$J$7:$J$411,$D6,'25.04'!$K$7:$K$411,Y$3) -> 0 | Z6: =sumifs('25.04'!$H$7:$H$411,'25.04'!$J$7:$J$411,$D6,'25.04'!$K$7:$K$411,Z$3) -> 0 | AA6: =sumifs('25.04'!$H$7:$H$411,'25.04'!$J$7:$J$411,$D6,'25.04'!$K$7:$K$411,AA$3) -> 0 | AB6: =sumifs('25.04'!$H$7:$H$411,'25.04'!$J$7:$J$411,$D6,'25.04'!$K$7:$K$411,AB$3) -> 0 | AC6: =sum(T6:AB6) -> 0
C7: 44986 | D7: Talent Education fee | E7: =sumifs('25.04'!$H$7:$H$411,'25.04'!$G$7:$G$411,$D7,'25.04'!$F$7:$F$411,E$3) -> 0 | F7: =sumifs('25.04'!$H$7:$H$411,'25.04'!$G$7:$G$411,$D7,'25.04'!$F$7:$F$411,F$3) -> 0 | G7: =sumifs('25.04'!$H$7:$H$411,'25.04'!$G$7:$G$411,$D7,'25.04'!$F$7:$F$411,G$3) -> 0 | H7: =sumifs('25.04'!$H$7:$H$411,'25.04'!$G$7:$G$411,$D7,'25.04'!$F$7:$F$411,H$3) -> 0 | I7: =sumifs('25.04'!$H$7:$H$411,'25.04'!$G$7:$G$411,$D7,'25.04'!$F$7:$F$411,I$3) -> 0 | J7: =sumifs('25.04'!$H$7:$H$411,'25.04'!$G$7:$G$411,$D7,'25.04'!$F$7:$F$411,J$3) -> 0 | K7: =sumifs('25.04'!$H$7:$H$411,'25.04'!$G$7:$G$411,$D7,'25.04'!$F$7:$F$411,K$3) -> 0 | L7: =sumifs('25.04'!$H$7:$H$411,'25.04'!$G$7:$G$411,$D7,'25.04'!$F$7:$F$411,L$3) -> 0 | M7: =sumifs('25.04'!$H$7:$H$411,'25.04'!$G$7:$G$411,$D7,'25.04'!$F$7:$F$411,M$3) -> 0 | N7: =sum(E7:M7) -> 0 | P7: =N7/sum(N$4:N$9) -> #DIV/0! | T7: =sumifs('25.04'!$H$7:$H$411,'25.04'!$J$7:$J$411,$D7,'25.04'!$K$7:$K$411,T$3) -> 0 | U7: =sumifs('25.04'!$H$7:$H$411,'25.04'!$J$7:$J$411,$D7,'25.04'!$K$7:$K$411,U$3) -> 0 | V7: =sumifs('25.04'!$H$7:$H$411,'25.04'!$J$7:$J$411,$D7,'25.04'!$K$7:$K$411,V$3) -> 0 | W7: =sumifs('25.04'!$H$7:$H$411,'25.04'!$J$7:$J$411,$D7,'25.04'!$K$7:$K$411,W$3) -> 0 | X7: =sumifs('25.04'!$H$7:$H$411,'25.04'!$J$7:$J$411,$D7,'25.04'!$K$7:$K$411,X$3) -> 0 | Y7: =sumifs('25.04'!$H$7:$H$411,'25.04'!$J$7:$J$411,$D7,'25.04'!$K$7:$K$411,Y$3) -> 0 | Z7: =sumifs('25.04'!$H$7:$H$411,'25.04'!$J$7:$J$411,$D7,'25.04'!$K$7:$K$411,Z$3) -> 0 | AA7: =sumifs('25.04'!$H$7:$H$411,'25.04'!$J$7:$J$411,$D7,'25.04'!$K$7:$K$411,AA$3) -> 0 | AB7: =sumifs('25.04'!$H$7:$H$411,'25.04'!$J$7:$J$411,$D7,'25.04'!$K$7:$K$411,AB$3) -> 0 | AC7: =sum(T7:AB7) -> 0
C8: 45017 | D8: Books | E8: =sumifs('25.04'!$H$7:$H$411,'25.04'!$G$7:$G$411,$D8,'25.04'!$F$7:$F$411,E$3) -> 0 | F8: =sumifs('25.04'!$H$7:$H$411,'25.04'!$G$7:$G$411,$D8,'25.04'!$F$7:$F$411,F$3) -> 0 | G8: =sumifs('25.04'!$H$7:$H$411,'25.04'!$G$7:$G$411,$D8,'25.04'!$F$7:$F$411,G$3) -> 0 | H8: =sumifs('25.04'!$H$7:$H$411,'25.04'!$G$7:$G$411,$D8,'25.04'!$F$7:$F$411,H$3) -> 0 | I8: =sumifs('25.04'!$H$7:$H$411,'25.04'!$G$7:$G$411,$D8,'25.04'!$F$7:$F$411,I$3) -> 0 | J8: =sumifs('25.04'!$H$7:$H$411,'25.04'!$G$7:$G$411,$D8,'25.04'!$F$7:$F$411,J$3) -> 0 | K8: =sumifs('25.04'!$H$7:$H$411,'25.04'!$G$7:$G$411,$D8,'25.04'!$F$7:$F$411,K$3) -> 0 | L8: =sumifs('25.04'!$H$7:$H$411,'25.04'!$G$7:$G$411,$D8,'25.04'!$F$7:$F$411,L$3) -> 0 | M8: =sumifs('25.04'!$H$7:$H$411,'25.04'!$G$7:$G$411,$D8,'25.04'!$F$7:$F$411,M$3) -> 0 | N8: =sum(E8:M8) -> 0 | P8: =N8/sum(N$4:N$9) -> #DIV/0! | T8: =sumifs('25.04'!$H$7:$H$411,'25.04'!$J$7:$J$411,$D8,'25.04'!$K$7:$K$411,T$3) -> 0 | U8: =sumifs('25.04'!$H$7:$H$411,'25.04'!$J$7:$J$411,$D8,'25.04'!$K$7:$K$411,U$3) -> 0 | V8: =sumifs('25.04'!$H$7:$H$411,'25.04'!$J$7:$J$411,$D8,'25.04'!$K$7:$K$411,V$3) -> 0 | W8: =sumifs('25.04'!$H$7:$H$411,'25.04'!$J$7:$J$411,$D8,'25.04'!$K$7:$K$411,W$3) -> 0 | X8: =sumifs('25.04'!$H$7:$H$411,'25.04'!$J$7:$J$411,$D8,'25.04'!$K$7:$K$411,X$3) -> 0 | Y8: =sumifs('25.04'!$H$7:$H$411,'25.04'!$J$7:$J$411,$D8,'25.04'!$K$7:$K$411,Y$3) -> 0 | Z8: =sumifs('25.04'!$H$7:$H$411,'25.04'!$J$7:$J$411,$D8,'25.04'!$K$7:$K$411,Z$3) -> 0 | AA8: =sumifs('25.04'!$H$7:$H$411,'25.04'!$J$7:$J$411,$D8,'25.04'!$K$7:$K$411,AA$3) -> 0 | AB8: =sumifs('25.04'!$H$7:$H$411,'25.04'!$J$7:$J$411,$D8,'25.04'!$K$7:$K$411,AB$3) -> 0 | AC8: =sum(T8:AB8) -> 0
C9: 45047 | D9: Stationery | E9: =sumifs('25.04'!$H$7:$H$411,'25.04'!$G$7:$G$411,$D9,'25.04'!$F$7:$F$411,E$3) -> 0 | F9: =sumifs('25.04'!$H$7:$H$411,'25.04'!$G$7:$G$411,$D9,'25.04'!$F$7:$F$411,F$3) -> 0 | G9: =sumifs('25.04'!$H$7:$H$411,'25.04'!$G$7:$G$411,$D9,'25.04'!$F$7:$F$411,G$3) -> 0 | H9: =sumifs('25.04'!$H$7:$H$411,'25.04'!$G$7:$G$411,$D9,'25.04'!$F$7:$F$411,H$3) -> 0 | I9: =sumifs('25.04'!$H$7:$H$411,'25.04'!$G$7:$G$411,$D9,'25.04'!$F$7:$F$411,I$3) -> 0 | J9: =sumifs('25.04'!$H$7:$H$411,'25.04'!$G$7:$G$411,$D9,'25.04'!$F$7:$F$411,J$3) -> 0 | K9: =sumifs('25.04'!$H$7:$H$411,'25.04'!$G$7:$G$411,$D9,'25.04'!$F$7:$F$411,K$3) -> 0 | L9: =sumifs('25.04'!$H$7:$H$411,'25.04'!$G$7:$G$411,$D9,'25.04'!$F$7:$F$411,L$3) -> 0 | M9: =sumifs('25.04'!$H$7:$H$411,'25.04'!$G$7:$G$411,$D9,'25.04'!$F$7:$F$411,M$3) -> 0 | N9: =sum(E9:M9) -> 0 | P9: =N9/sum(N$4:N$9) -> #DIV/0! | T9: =sumifs('25.04'!$H$7:$H$411,'25.04'!$J$7:$J$411,$D9,'25.04'!$K$7:$K$411,T$3) -> 0 | U9: =sumifs('25.04'!$H$7:$H$411,'25.04'!$J$7:$J$411,$D9,'25.04'!$K$7:$K$411,U$3) -> 0 | V9: =sumifs('25.04'!$H$7:$H$411,'25.04'!$J$7:$J$411,$D9,'25.04'!$K$7:$K$411,V$3) -> 0 | W9: =sumifs('25.04'!$H$7:$H$411,'25.04'!$J$7:$J$411,$D9,'25.04'!$K$7:$K$411,W$3) -> 0 | X9: =sumifs('25.04'!$H$7:$H$411,'25.04'!$J$7:$J$411,$D9,'25.04'!$K$7:$K$411,X$3) -> 0 | Y9: =sumifs('25.04'!$H$7:$H$411,'25.04'!$J$7:$J$411,$D9,'25.04'!$K$7:$K$411,Y$3) -> 0 | Z9: =sumifs('25.04'!$H$7:$H$411,'25.04'!$J$7:$J$411,$D9,'25.04'!$K$7:$K$411,Z$3) -> 0 | AA9: =sumifs('25.04'!$H$7:$H$411,'25.04'!$J$7:$J$411,$D9,'25.04'!$K$7:$K$411,AA$3) -> 0 | AB9: =sumifs('25.04'!$H$7:$H$411,'25.04'!$J$7:$J$411,$D9,'25.04'!$K$7:$K$411,AB$3) -> 0 | AC9: =sum(T9:AB9) -> 0
C10: 2 | D10: Enjoy | E10: =sumifs('25.04'!$H$7:$H$411,'25.04'!$G$7:$G$411,$D10,'25.04'!$F$7:$F$411,E$3) -> 0 | F10: =sumifs('25.04'!$H$7:$H$411,'25.04'!$G$7:$G$411,$D10,'25.04'!$F$7:$F$411,F$3) -> 0 | G10: =sumifs('25.04'!$H$7:$H$411,'25.04'!$G$7:$G$411,$D10,'25.04'!$F$7:$F$411,G$3) -> 0 | H10: =sumifs('25.04'!$H$7:$H$411,'25.04'!$G$7:$G$411,$D10,'25.04'!$F$7:$F$411,H$3) -> 0 | I10: =sumifs('25.04'!$H$7:$H$411,'25.04'!$G$7:$G$411,$D10,'25.04'!$F$7:$F$411,I$3) -> 0 | J10: =sumifs('25.04'!$H$7:$H$411,'25.04'!$G$7:$G$411,$D10,'25.04'!$F$7:$F$411,J$3) -> 0 | K10: =sumifs('25.04'!$H$7:$H$411,'25.04'!$G$7:$G$411,$D10,'25.04'!$F$7:$F$411,K$3) -> 0 | L10: =sumifs('25.04'!$H$7:$H$411,'25.04'!$G$7:$G$411,$D10,'25.04'!$F$7:$F$411,L$3) -> 0 | M10: =sumifs('25.04'!$H$7:$H$411,'25.04'!$G$7:$G$411,$D10,'25.04'!$F$7:$F$411,M$3) -> 0 | N10: =sum(E10:M10) -> 0 | P10: =N10/sum(N$10:N$16) -> 0 | R10: =sum(N10:N16) -> 320000 | S10: =R10/sum($R$4:$R$49) -> 1 | T10: =sumifs('25.04'!$H$7:$H$411,'25.04'!$J$7:$J$411,$D10,'25.04'!$K$7:$K$411,T$3) -> 0 | U10: =sumifs('25.04'!$H$7:$H$411,'25.04'!$J$7:$J$411,$D10,'25.04'!$K$7:$K$411,U$3) -> 0 | V10: =sumifs('25.04'!$H$7:$H$411,'25.04'!$J$7:$J$411,$D10,'25.04'!$K$7:$K$411,V$3) -> 0 | W10: =sumifs('25.04'!$H$7:$H$411,'25.04'!$J$7:$J$411,$D10,'25.04'!$K$7:$K$411,W$3) -> 0 | X10: =sumifs('25.04'!$H$7:$H$411,'25.04'!$J$7:$J$411,$D10,'25.04'!$K$7:$K$411,X$3) -> 0 | Y10: =sumifs('25.04'!$H$7:$H$411,'25.04'!$J$7:$J$411,$D10,'25.04'!$K$7:$K$411,Y$3) -> 0 | Z10: =sumifs('25.04'!$H$7:$H$411,'25.04'!$J$7:$J$411,$D10,'25.04'!$K$7:$K$411,Z$3) -> 0 | AA10: =sumifs('25.04'!$H$7:$H$411,'25.04'!$J$7:$J$411,$D10,'25.04'!$K$7:$K$411,AA$3) -> 0 | AB10: =sumifs('25.04'!$H$7:$H$411,'25.04'!$J$7:$J$411,$D10,'25.04'!$K$7:$K$411,AB$3) -> 0 | AC10: =sum(T10:AB10) -> 0
A11: 2 | B11: Enjoy | C11: 44928 | D11: Travel | E11: =sumifs('25.04'!$H$7:$H$411,'25.04'!$G$7:$G$411,$D11,'25.04'!$F$7:$F$411,E$3) -> 0 | F11: =sumifs('25.04'!$H$7:$H$411,'25.04'!$G$7:$G$411,$D11,'25.04'!$F$7:$F$411,F$3) -> 0 | G11: =sumifs('25.04'!$H$7:$H$411,'25.04'!$G$7:$G$411,$D11,'25.04'!$F$7:$F$411,G$3) -> 0 | H11: =sumifs('25.04'!$H$7:$H$411,'25.04'!$G$7:$G$411,$D11,'25.04'!$F$7:$F$411,H$3) -> 0 | I11: =sumifs('25.04'!$H$7:$H$411,'25.04'!$G$7:$G$411,$D11,'25.04'!$F$7:$F$411,I$3) -> 0 | J11: =sumifs('25.04'!$H$7:$H$411,'25.04'!$G$7:$G$411,$D11,'25.04'!$F$7:$F$411,J$3) -> 0 | K11: =sumifs('25.04'!$H$7:$H$411,'25.04'!$G$7:$G$411,$D11,'25.04'!$F$7:$F$411,K$3) -> 0 | L11: =sumifs('25.04'!$H$7:$H$411,'25.04'!$G$7:$G$411,$D11,'25.04'!$F$7:$F$411,L$3) -> 0 | M11: =sumifs('25.04'!$H$7:$H$411,'25.04'!$G$7:$G$411,$D11,'25.04'!$F$7:$F$411,M$3) -> 0 | N11: =sum(E11:M11) -> 0 | P11: =N11/sum(N$10:N$16) -> 0 | T11: =sumifs('25.04'!$H$7:$H$411,'25.04'!$J$7:$J$411,$D11,'25.04'!$K$7:$K$411,T$3) -> 0 | U11: =sumifs('25.04'!$H$7:$H$411,'25.04'!$J$7:$J$411,$D11,'25.04'!$K$7:$K$411,U$3) -> 0 | V11: =sumifs('25.04'!$H$7:$H$411,'25.04'!$J$7:$J$411,$D11,'25.04'!$K$7:$K$411,V$3) -> 0 | W11: =sumifs('25.04'!$H$7:$H$411,'25.04'!$J$7:$J$411,$D11,'25.04'!$K$7:$K$411,W$3) -> 0 | X11: =sumifs('25.04'!$H$7:$H$411,'25.04'!$J$7:$J$411,$D11,'25.04'!$K$7:$K$411,X$3) -> 0 | Y11: =sumifs('25.04'!$H$7:$H$411,'25.04'!$J$7:$J$411,$D11,'25.04'!$K$7:$K$411,Y$3) -> 0 | Z11: =sumifs('25.04'!$H$7:$H$411,'25.04'!$J$7:$J$411,$D11,'25.04'!$K$7:$K$411,Z$3) -> 0 | AA11: =sumifs('25.04'!$H$7:$H$411,'25.04'!$J$7:$J$411,$D11,'25.04'!$K$7:$K$411,AA$3) -> 0 | AB11: =sumifs('25.04'!$H$7:$H$411,'25.04'!$J$7:$J$411,$D11,'25.04'!$K$7:$K$411,AB$3) -> 0 | AC11: =sum(T11:AB11) -> 0
C12: 44959 | D12: Café | E12: =sumifs('25.04'!$H$7:$H$411,'25.04'!$G$7:$G$411,$D12,'25.04'!$F$7:$F$411,E$3) -> 320000 | F12: =sumifs('25.04'!$H$7:$H$411,'25.04'!$G$7:$G$411,$D12,'25.04'!$F$7:$F$411,F$3) -> 0 | G12: =sumifs('25.04'!$H$7:$H$411,'25.04'!$G$7:$G$411,$D12,'25.04'!$F$7:$F$411,G$3) -> 0 | H12: =sumifs('25.04'!$H$7:$H$411,'25.04'!$G$7:$G$411,$D12,'25.04'!$F$7:$F$411,H$3) -> 0 | I12: =sumifs('25.04'!$H$7:$H$411,'25.04'!$G$7:$G$411,$D12,'25.04'!$F$7:$F$411,I$3) -> 0 | J12: =sumifs('25.04'!$H$7:$H$411,'25.04'!$G$7:$G$411,$D12,'25.04'!$F$7:$F$411,J$3) -> 0 | K12: =sumifs('25.04'!$H$7:$H$411,'25.04'!$G$7:$G$411,$D12,'25.04'!$F$7:$F$411,K$3) -> 0 | L12: =sumifs('25.04'!$H$7:$H$411,'25.04'!$G$7:$G$411,$D12,'25.04'!$F$7:$F$411,L$3) -> 0 | M12: =sumifs('25.04'!$H$7:$H$411,'25.04'!$G$7:$G$411,$D12,'25.04'!$F$7:$F$411,M$3) -> 0 | N12: =sum(E12:M12) -> 320000 | P12: =N12/sum(N$10:N$16) -> 1 | T12: =sumifs('25.04'!$H$7:$H$411,'25.04'!$J$7:$J$411,$D12,'25.04'!$K$7:$K$411,T$3) -> 0 | U12: =sumifs('25.04'!$H$7:$H$411,'25.04'!$J$7:$J$411,$D12,'25.04'!$K$7:$K$411,U$3) -> 0 | V12: =sumifs('25.04'!$H$7:$H$411,'25.04'!$J$7:$J$411,$D12,'25.04'!$K$7:$K$411,V$3) -> 0 | W12: =sumifs('25.04'!$H$7:$H$411,'25.04'!$J$7:$J$411,$D12,'25.04'!$K$7:$K$411,W$3) -> 0 | X12: =sumifs('25.04'!$H$7:$H$411,'25.04'!$J$7:$J$411,$D12,'25.04'!$K$7:$K$411,X$3) -> 0 | Y12: =sumifs('25.04'!$H$7:$H$411,'25.04'!$J$7:$J$411,$D12,'25.04'!$K$7:$K$411,Y$3) -> 0 | Z12: =sumifs('25.04'!$H$7:$H$411,'25.04'!$J$7:$J$411,$D12,'25.04'!$K$7:$K$411,Z$3) -> 0 | AA12: =sumifs('25.04'!$H$7:$H$411,'25.04'!$J$7:$J$411,$D12,'25.04'!$K$7:$K$411,AA$3) -> 0 | AB12: =sumifs('25.04'!$H$7:$H$411,'25.04'!$J$7:$J$411,$D12,'25.04'!$K$7:$K$411,AB$3) -> 0 | AC12: =sum(T12:AB12) -> 0
C13: 44987 | D13: Restaurant | E13: =sumifs('25.04'!$H$7:$H$411,'25.04'!$G$7:$G$411,$D13,'25.04'!$F$7:$F$411,E$3) -> 0 | F13: =sumifs('25.04'!$H$7:$H$411,'25.04'!$G$7:$G$411,$D13,'25.04'!$F$7:$F$411,F$3) -> 0 | G13: =sumifs('25.04'!$H$7:$H$411,'25.04'!$G$7:$G$411,$D13,'25.04'!$F$7:$F$411,G$3) -> 0 | H13: =sumifs('25.04'!$H$7:$H$411,'25.04'!$G$7:$G$411,$D13,'25.04'!$F$7:$F$411,H$3) -> 0 | I13: =sumifs('25.04'!$H$7:$H$411,'25.04'!$G$7:$G$411,$D13,'25.04'!$F$7:$F$411,I$3) -> 0 | J13: =sumifs('25.04'!$H$7:$H$411,'25.04'!$G$7:$G$411,$D13,'25.04'!$F$7:$F$411,J$3) -> 0 | K13: =sumifs('25.04'!$H$7:$H$411,'25.04'!$G$7:$G$411,$D13,'25.04'!$F$7:$F$411,K$3) -> 0 | L13: =sumifs('25.04'!$H$7:$H$411,'25.04'!$G$7:$G$411,$D13,'25.04'!$F$7:$F$411,L$3) -> 0 | M13: =sumifs('25.04'!$H$7:$H$411,'25.04'!$G$7:$G$411,$D13,'25.04'!$F$7:$F$411,M$3) -> 0 | N13: =sum(E13:M13) -> 0 | P13: =N13/sum(N$10:N$16) -> 0 | T13: =sumifs('25.04'!$H$7:$H$411,'25.04'!$J$7:$J$411,$D13,'25.04'!$K$7:$K$411,T$3) -> 0 | U13: =sumifs('25.04'!$H$7:$H$411,'25.04'!$J$7:$J$411,$D13,'25.04'!$K$7:$K$411,U$3) -> 0 | V13: =sumifs('25.04'!$H$7:$H$411,'25.04'!$J$7:$J$411,$D13,'25.04'!$K$7:$K$411,V$3) -> 0 | W13: =sumifs('25.04'!$H$7:$H$411,'25.04'!$J$7:$J$411,$D13,'25.04'!$K$7:$K$411,W$3) -> 0 | X13: =sumifs('25.04'!$H$7:$H$411,'25.04'!$J$7:$J$411,$D13,'25.04'!$K$7:$K$411,X$3) -> 0 | Y13: =sumifs('25.04'!$H$7:$H$411,'25.04'!$J$7:$J$411,$D13,'25.04'!$K$7:$K$411,Y$3) -> 0 | Z13: =sumifs('25.04'!$H$7:$H$411,'25.04'!$J$7:$J$411,$D13,'25.04'!$K$7:$K$411,Z$3) -> 0 | AA13: =sumifs('25.04'!$H$7:$H$411,'25.04'!$J$7:$J$411,$D13,'25.04'!$K$7:$K$411,AA$3) -> 0 | AB13: =sumifs('25.04'!$H$7:$H$411,'25.04'!$J$7:$J$411,$D13,'25.04'!$K$7:$K$411,AB$3) -> 0 | AC13: =sum(T13:AB13) -> 0
C14: 45018 | D14: Sightseeing | E14: =sumifs('25.04'!$H$7:$H$411,'25.04'!$G$7:$G$411,$D14,'25.04'!$F$7:$F$411,E$3) -> 0 | F14: =sumifs('25.04'!$H$7:$H$411,'25.04'!$G$7:$G$411,$D14,'25.04'!$F$7:$F$411,F$3) -> 0 | G14: =sumifs('25.04'!$H$7:$H$411,'25.04'!$G$7:$G$411,$D14,'25.04'!$F$7:$F$411,G$3) -> 0 | H14: =sumifs('25.04'!$H$7:$H$411,'25.04'!$G$7:$G$411,$D14,'25.04'!$F$7:$F$411,H$3) -> 0 | I14: =sumifs('25.04'!$H$7:$H$411,'25.04'!$G$7:$G$411,$D14,'25.04'!$F$7:$F$411,I$3) -> 0 | J14: =sumifs('25.04'!$H$7:$H$411,'25.04'!$G$7:$G$411,$D14,'25.04'!$F$7:$F$411,J$3) -> 0 | K14: =sumifs('25.04'!$H$7:$H$411,'25.04'!$G$7:$G$411,$D14,'25.04'!$F$7:$F$411,K$3) -> 0 | L14: =sumifs('25.04'!$H$7:$H$411,'25.04'!$G$7:$G$411,$D14,'25.04'!$F$7:$F$411,L$3) -> 0 | M14: =sumifs('25.04'!$H$7:$H$411,'25.04'!$G$7:$G$411,$D14,'25.04'!$F$7:$F$411,M$3) -> 0 | N14: =sum(E14:M14) -> 0 | P14: =N14/sum(N$10:N$16) -> 0 | T14: =sumifs('25.04'!$H$7:$H$411,'25.04'!$J$7:$J$411,$D14,'25.04'!$K$7:$K$411,T$3) -> 0 | U14: =sumifs('25.04'!$H$7:$H$411,'25.04'!$J$7:$J$411,$D14,'25.04'!$K$7:$K$411,U$3) -> 0 | V14: =sumifs('25.04'!$H$7:$H$411,'25.04'!$J$7:$J$411,$D14,'25.04'!$K$7:$K$411,V$3) -> 0 | W14: =sumifs('25.04'!$H$7:$H$411,'25.04'!$J$7:$J$411,$D14,'25.04'!$K$7:$K$411,W$3) -> 0 | X14: =sumifs('25.04'!$H$7:$H$411,'25.04'!$J$7:$J$411,$D14,'25.04'!$K$7:$K$411,X$3) -> 0 | Y14: =sumifs('25.04'!$H$7:$H$411,'25.04'!$J$7:$J$411,$D14,'25.04'!$K$7:$K$411,Y$3) -> 0 | Z14: =sumifs('25.04'!$H$7:$H$411,'25.04'!$J$7:$J$411,$D14,'25.04'!$K$7:$K$411,Z$3) -> 0 | AA14: =sumifs('25.04'!$H$7:$H$411,'25.04'!$J$7:$J$411,$D14,'25.04'!$K$7:$K$411,AA$3) -> 0 | AB14: =sumifs('25.04'!$H$7:$H$411,'25.04'!$J$7:$J$411,$D14,'25.04'!$K$7:$K$411,AB$3) -> 0 | AC14: =sum(T14:AB14) -> 0
C15: 45048 | D15: Exhibition | E15: =sumifs('25.04'!$H$7:$H$411,'25.04'!$G$7:$G$411,$D15,'25.04'!$F$7:$F$411,E$3) -> 0 | F15: =sumifs('25.04'!$H$7:$H$411,'25.04'!$G$7:$G$411,$D15,'25.04'!$F$7:$F$411,F$3) -> 0 | G15: =sumifs('25.04'!$H$7:$H$411,'25.04'!$G$7:$G$411,$D15,'25.04'!$F$7:$F$411,G$3) -> 0 | H15: =sumifs('25.04'!$H$7:$H$411,'25.04'!$G$7:$G$411,$D15,'25.04'!$F$7:$F$411,H$3) -> 0 | I15: =sumifs('25.04'!$H$7:$H$411,'25.04'!$G$7:$G$411,$D15,'25.04'!$F$7:$F$411,I$3) -> 0 | J15: =sumifs('25.04'!$H$7:$H$411,'25.04'!$G$7:$G$411,$D15,'25.04'!$F$7:$F$411,J$3) -> 0 | K15: =sumifs('25.04'!$H$7:$H$411,'25.04'!$G$7:$G$411,$D15,'25.04'!$F$7:$F$411,K$3) -> 0 | L15: =sumifs('25.04'!$H$7:$H$411,'25.04'!$G$7:$G$411,$D15,'25.04'!$F$7:$F$411,L$3) -> 0 | M15: =sumifs('25.04'!$H$7:$H$411,'25.04'!$G$7:$G$411,$D15,'25.04'!$F$7:$F$411,M$3) -> 0 | N15: =sum(E15:M15) -> 0 | P15: =N15/sum(N$10:N$16) -> 0 | T15: =sumifs('25.04'!$H$7:$H$411,'25.04'!$J$7:$J$411,$D15,'25.04'!$K$7:$K$411,T$3) -> 0 | U15: =sumifs('25.04'!$H$7:$H$411,'25.04'!$J$7:$J$411,$D15,'25.04'!$K$7:$K$411,U$3) -> 0 | V15: =sumifs('25.04'!$H$7:$H$411,'25.04'!$J$7:$J$411,$D15,'25.04'!$K$7:$K$411,V$3) -> 0 | W15: =sumifs('25.04'!$H$7:$H$411,'25.04'!$J$7:$J$411,$D15,'25.04'!$K$7:$K$411,W$3) -> 0 | X15: =sumifs('25.04'!$H$7:$H$411,'25.04'!$J$7:$J$411,$D15,'25.04'!$K$7:$K$411,X$3) -> 0 | Y15: =sumifs('25.04'!$H$7:$H$411,'25.04'!$J$7:$J$411,$D15,'25.04'!$K$7:$K$411,Y$3) -> 0 | Z15: =sumifs('25.04'!$H$7:$H$411,'25.04'!$J$7:$J$411,$D15,'25.04'!$K$7:$K$411,Z$3) -> 0 | AA15: =sumifs('25.04'!$H$7:$H$411,'25.04'!$J$7:$J$411,$D15,'25.04'!$K$7:$K$411,AA$3) -> 0 | AB15: =sumifs('25.04'!$H$7:$H$411,'25.04'!$J$7:$J$411,$D15,'25.04'!$K$7:$K$411,AB$3) -> 0 | AC15: =sum(T15:AB15) -> 0
C16: 45079 | D16: Museum | E16: =sumifs('25.04'!$H$7:$H$411,'25.04'!$G$7:$G$411,$D16,'25.04'!$F$7:$F$411,E$3) -> 0 | F16: =sumifs('25.04'!$H$7:$H$411,'25.04'!$G$7:$G$411,$D16,'25.04'!$F$7:$F$411,F$3) -> 0 | G16: =sumifs('25.04'!$H$7:$H$411,'25.04'!$G$7:$G$411,$D16,'25.04'!$F$7:$F$411,G$3) -> 0 | H16: =sumifs('25.04'!$H$7:$H$411,'25.04'!$G$7:$G$411,$D16,'25.04'!$F$7:$F$411,H$3) -> 0 | I16: =sumifs('25.04'!$H$7:$H$411,'25.04'!$G$7:$G$411,$D16,'25.04'!$F$7:$F$411,I$3) -> 0 | J16: =sumifs('25.04'!$H$7:$H$411,'25.04'!$G$7:$G$411,$D16,'25.04'!$F$7:$F$411,J$3) -> 0 | K16: =sumifs('25.04'!$H$7:$H$411,'25.04'!$G$7:$G$411,$D16,'25.04'!$F$7:$F$411,K$3) -> 0 | L16: =sumifs('25.04'!$H$7:$H$411,'25.04'!$G$7:$G$411,$D16,'25.04'!$F$7:$F$411,L$3) -> 0 | M16: =sumifs('25.04'!$H$7:$H$411,'25.04'!$G$7:$G$411,$D16,'25.04'!$F$7:$F$411,M$3) -> 0 | N16: =sum(E16:M16) -> 0 | P16: =N16/sum(N$10:N$16) -> 0 | T16: =sumifs('25.04'!$H$7:$H$411,'25.04'!$J$7:$J$411,$D16,'25.04'!$K$7:$K$411,T$3) -> 0 | U16: =sumifs('25.04'!$H$7:$H$411,'25.04'!$J$7:$J$411,$D16,'25.04'!$K$7:$K$411,U$3) -> 0 | V16: =sumifs('25.04'!$H$7:$H$411,'25.04'!$J$7:$J$411,$D16,'25.04'!$K$7:$K$411,V$3) -> 0 | W16: =sumifs('25.04'!$H$7:$H$411,'25.04'!$J$7:$J$411,$D16,'25.04'!$K$7:$K$411,W$3) -> 0 | X16: =sumifs('25.04'!$H$7:$H$411,'25.04'!$J$7:$J$411,$D16,'25.04'!$K$7:$K$411,X$3) -> 0 | Y16: =sumifs('25.04'!$H$7:$H$411,'25.04'!$J$7:$J$411,$D16,'25.04'!$K$7:$K$411,Y$3) -> 0 | Z16: =sumifs('25.04'!$H$7:$H$411,'25.04'!$J$7:$J$411,$D16,'25.04'!$K$7:$K$411,Z$3) -> 0 | AA16: =sumifs('25.04'!$H$7:$H$411,'25.04'!$J$7:$J$411,$D16,'25.04'!$K$7:$K$411,AA$3) -> 0 | AB16: =sumifs('25.04'!$H$7:$H$411,'25.04'!$J$7:$J$411,$D16,'25.04'!$K$7:$K$411,AB$3) -> 0 | AC16: =sum(T16:AB16) -> 0
C17: 3 | D17: For give | E17: =sumifs('25.04'!$H$7:$H$411,'25.04'!$G$7:$G$411,$D17,'25.04'!$F$7:$F$411,E$3) -> 0 | F17: =sumifs('25.04'!$H$7:$H$411,'25.04'!$G$7:$G$411,$D17,'25.04'!$F$7:$F$411,F$3) -> 0 | G17: =sumifs('25.04'!$H$7:$H$411,'25.04'!$G$7:$G$411,$D17,'25.04'!$F$7:$F$411,G$3) -> 0 | H17: =sumifs('25.04'!$H$7:$H$411,'25.04'!$G$7:$G$411,$D17,'25.04'!$F$7:$F$411,H$3) -> 0 | I17: =sumifs('25.04'!$H$7:$H$411,'25.04'!$G$7:$G$411,$D17,'25.04'!$F$7:$F$411,I$3) -> 0 | J17: =sumifs('25.04'!$H$7:$H$411,'25.04'!$G$7:$G$411,$D17,'25.04'!$F$7:$F$411,J$3) -> 0 | K17: =sumifs('25.04'!$H$7:$H$411,'25.04'!$G$7:$G$411,$D17,'25.04'!$F$7:$F$411,K$3) -> 0 | L17: =sumifs('25.04'!$H$7:$H$411,'25.04'!$G$7:$G$411,$D17,'25.04'!$F$7:$F$411,L$3) -> 0 | M17: =sumifs('25.04'!$H$7:$H$411,'25.04'!$G$7:$G$411,$D17,'25.04'!$F$7:$F$411,M$3) -> 0 | N17: =sum(E17:M17) -> 0 | P17: =N17/sum(N$17:N$22) -> #DIV/0! | R17: =sum(N17:N22) -> 0 | S17: =R17/sum($R$4:$R$49) -> 0 | T17: =sumifs('25.04'!$H$7:$H$411,'25.04'!$J$7:$J$411,$D17,'25.04'!$K$7:$K$411,T$3) -> 0 | U17: =sumifs('25.04'!$H$7:$H$411,'25.04'!$J$7:$J$411,$D17,'25.04'!$K$7:$K$411,U$3) -> 0 | V17: =sumifs('25.04'!$H$7:$H$411,'25.04'!$J$7:$J$411,$D17,'25.04'!$K$7:$K$411,V$3) -> 0 | W17: =sumifs('25.04'!$H$7:$H$411,'25.04'!$J$7:$J$411,$D17,'25.04'!$K$7:$K$411,W$3) -> 0 | X17: =sumifs('25.04'!$H$7:$H$411,'25.04'!$J$7:$J$411,$D17,'25.04'!$K$7:$K$411,X$3) -> 0 | Y17: =sumifs('25.04'!$H$7:$H$411,'25.04'!$J$7:$J$411,$D17,'25.04'!$K$7:$K$411,Y$3) -> 0 | Z17: =sumifs('25.04'!$H$7:$H$411,'25.04'!$J$7:$J$411,$D17,'25.04'!$K$7:$K$411,Z$3) -> 0 | AA17: =sumifs('25.04'!$H$7:$H$411,'25.04'!$J$7:$J$411,$D17,'25.04'!$K$7:$K$411,AA$3) -> 0 | AB17: =sumifs('25.04'!$H$7:$H$411,'25.04'!$J$7:$J$411,$D17,'25.04'!$K$7:$K$411,AB$3) -> 0 | AC17: =sum(T17:AB17) -> 0
A18: 3 | B18: For give | C18: 44929 | D18: Funeral | E18: =sumifs('25.04'!$H$7:$H$411,'25.04'!$G$7:$G$411,$D18,'25.04'!$F$7:$F$411,E$3) -> 0 | F18: =sumifs('25.04'!$H$7:$H$411,'25.04'!$G$7:$G$411,$D18,'25.04'!$F$7:$F$411,F$3) -> 0 | G18: =sumifs('25.04'!$H$7:$H$411,'25.04'!$G$7:$G$411,$D18,'25.04'!$F$7:$F$411,G$3) -> 0 | H18: =sumifs('25.04'!$H$7:$H$411,'25.04'!$G$7:$G$411,$D18,'25.04'!$F$7:$F$411,H$3) -> 0 | I18: =sumifs('25.04'!$H$7:$H$411,'25.04'!$G$7:$G$411,$D18,'25.04'!$F$7:$F$411,I$3) -> 0 | J18: =sumifs('25.04'!$H$7:$H$411,'25.04'!$G$7:$G$411,$D18,'25.04'!$F$7:$F$411,J$3) -> 0 | K18: =sumifs('25.04'!$H$7:$H$411,'25.04'!$G$7:$G$411,$D18,'25.04'!$F$7:$F$411,K$3) -> 0 | L18: =sumifs('25.04'!$H$7:$H$411,'25.04'!$G$7:$G$411,$D18,'25.04'!$F$7:$F$411,L$3) -> 0 | M18: =sumifs('25.04'!$H$7:$H$411,'25.04'!$G$7:$G$411,$D18,'25.04'!$F$7:$F$411,M$3) -> 0 | N18: =sum(E18:M18) -> 0 | P18: =N18/sum(N$17:N$22) -> #DIV/0! | T18: =sumifs('25.04'!$H$7:$H$411,'25.04'!$J$7:$J$411,$D18,'25.04'!$K$7:$K$411,T$3) -> 0 | U18: =sumifs('25.04'!$H$7:$H$411,'25.04'!$J$7:$J$411,$D18,'25.04'!$K$7:$K$411,U$3) -> 0 | V18: =sumifs('25.04'!$H$7:$H$411,'25.04'!$J$7:$J$411,$D18,'25.04'!$K$7:$K$411,V$3) -> 0 | W18: =sumifs('25.04'!$H$7:$H$411,'25.04'!$J$7:$J$411,$D18,'25.04'!$K$7:$K$411,W$3) -> 0 | X18: =sumifs('25.04'!$H$7:$H$411,'25.04'!$J$7:$J$411,$D18,'25.04'!$K$7:$K$411,X$3) -> 0 | Y18: =sumifs('25.04'!$H$7:$H$411,'25.04'!$J$7:$J$411,$D18,'25.04'!$K$7:$K$411,Y$3) -> 0 | Z18: =sumifs('25.04'!$H$7:$H$411,'25.04'!$J$7:$J$411,$D18,'25.04'!$K$7:$K$411,Z$3) -> 0 | AA18: =sumifs('25.04'!$H$7:$H$411,'25.04'!$J$7:$J$411,$D18,'25.04'!$K$7:$K$411,AA$3) -> 0 | AB18: =sumifs('25.04'!$H$7:$H$411,'25.04'!$J$7:$J$411,$D18,'25.04'!$K$7:$K$411,AB$3) -> 0 | AC18: =sum(T18:AB18) -> 0
C19: 44960 | D19: Wedding | E19: =sumifs('25.04'!$H$7:$H$411,'25.04'!$G$7:$G$411,$D19,'25.04'!$F$7:$F$411,E$3) -> 0 | F19: =sumifs('25.04'!$H$7:$H$411,'25.04'!$G$7:$G$411,$D19,'25.04'!$F$7:$F$411,F$3) -> 0 | G19: =sumifs('25.04'!$H$7:$H$411,'25.04'!$G$7:$G$411,$D19,'25.04'!$F$7:$F$411,G$3) -> 0 | H19: =sumifs('25.04'!$H$7:$H$411,'25.04'!$G$7:$G$411,$D19,'25.04'!$F$7:$F$411,H$3) -> 0 | I19: =sumifs('25.04'!$H$7:$H$411,'25.04'!$G$7:$G$411,$D19,'25.04'!$F$7:$F$411,I$3) -> 0 | J19: =sumifs('25.04'!$H$7:$H$411,'25.04'!$G$7:$G$411,$D19,'25.04'!$F$7:$F$411,J$3) -> 0 | K19: =sumifs('25.04'!$H$7:$H$411,'25.04'!$G$7:$G$411,$D19,'25.04'!$F$7:$F$411,K$3) -> 0 | L19: =sumifs('25.04'!$H$7:$H$411,'25.04'!$G$7:$G$411,$D19,'25.04'!$F$7:$F$411,L$3) -> 0 | M19: =sumifs('25.04'!$H$7:$H$411,'25.04'!$G$7:$G$411,$D19,'25.04'!$F$7:$F$411,M$3) -> 0 | N19: =sum(E19:M19) -> 0 | P19: =N19/sum(N$17:N$22) -> #DIV/0! | T19: =sumifs('25.04'!$H$7:$H$411,'25.04'!$J$7:$J$411,$D19,'25.04'!$K$7:$K$411,T$3) -> 0 | U19: =sumifs('25.04'!$H$7:$H$411,'25.04'!$J$7:$J$411,$D19,'25.04'!$K$7:$K$411,U$3) -> 0 | V19: =sumifs('25.04'!$H$7:$H$411,'25.04'!$J$7:$J$411,$D19,'25.04'!$K$7:$K$411,V$3) -> 0 | W19: =sumifs('25.04'!$H$7:$H$411,'25.04'!$J$7:$J$411,$D19,'25.04'!$K$7:$K$411,W$3) -> 0 | X19: =sumifs('25.04'!$H$7:$H$411,'25.04'!$J$7:$J$411,$D19,'25.04'!$K$7:$K$411,X$3) -> 0 | Y19: =sumifs('25.04'!$H$7:$H$411,'25.04'!$J$7:$J$411,$D19,'25.04'!$K$7:$K$411,Y$3) -> 0 | Z19: =sumifs('25.04'!$H$7:$H$411,'25.04'!$J$7:$J$411,$D19,'25.04'!$K$7:$K$411,Z$3) -> 0 | AA19: =sumifs('25.04'!$H$7:$H$411,'25.04'!$J$7:$J$411,$D19,'25.04'!$K$7:$K$411,AA$3) -> 0 | AB19: =sumifs('25.04'!$H$7:$H$411,'25.04'!$J$7:$J$411,$D19,'25.04'!$K$7:$K$411,AB$3) -> 0 | AC19: =sum(T19:AB19) -> 0
C20: 44988 | D20: Gift | E20: =sumifs('25.04'!$H$7:$H$411,'25.04'!$G$7:$G$411,$D20,'25.04'!$F$7:$F$411,E$3) -> 0 | F20: =sumifs('25.04'!$H$7:$H$411,'25.04'!$G$7:$G$411,$D20,'25.04'!$F$7:$F$411,F$3) -> 0 | G20: =sumifs('25.04'!$H$7:$H$411,'25.04'!$G$7:$G$411,$D20,'25.04'!$F$7:$F$411,G$3) -> 0 | H20: =sumifs('25.04'!$H$7:$H$411,'25.04'!$G$7:$G$411,$D20,'25.04'!$F$7:$F$411,H$3) -> 0 | I20: =sumifs('25.04'!$H$7:$H$411,'25.04'!$G$7:$G$411,$D20,'25.04'!$F$7:$F$411,I$3) -> 0 | J20: =sumifs('25.04'!$H$7:$H$411,'25.04'!$G$7:$G$411,$D20,'25.04'!$F$7:$F$411,J$3) -> 0 | K20: =sumifs('25.04'!$H$7:$H$411,'25.04'!$G$7:$G$411,$D20,'25.04'!$F$7:$F$411,K$3) -> 0 | L20: =sumifs('25.04'!$H$7:$H$411,'25.04'!$G$7:$G$411,$D20,'25.04'!$F$7:$F$411,L$3) -> 0 | M20: =sumifs('25.04'!$H$7:$H$411,'25.04'!$G$7:$G$411,$D20,'25.04'!$F$7:$F$411,M$3) -> 0 | N20: =sum(E20:M20) -> 0 | P20: =N20/sum(N$17:N$22) -> #DIV/0! | T20: =sumifs('25.04'!$H$7:$H$411,'25.04'!$J$7:$J$411,$D20,'25.04'!$K$7:$K$411,T$3) -> 0 | U20: =sumifs('25.04'!$H$7:$H$411,'25.04'!$J$7:$J$411,$D20,'25.04'!$K$7:$K$411,U$3) -> 0 | V20: =sumifs('25.04'!$H$7:$H$411,'25.04'!$J$7:$J$411,$D20,'25.04'!$K$7:$K$411,V$3) -> 0 | W20: =sumifs('25.04'!$H$7:$H$411,'25.04'!$J$7:$J$411,$D20,'25.04'!$K$7:$K$411,W$3) -> 0 | X20: =sumifs('25.04'!$H$7:$H$411,'25.04'!$J$7:$J$411,$D20,'25.04'!$K$7:$K$411,X$3) -> 0 | Y20: =sumifs('25.04'!$H$7:$H$411,'25.04'!$J$7:$J$411,$D20,'25.04'!$K$7:$K$411,Y$3) -> 0 | Z20: =sumifs('25.04'!$H$7:$H$411,'25.04'!$J$7:$J$411,$D20,'25.04'!$K$7:$K$411,Z$3) -> 0 | AA20: =sumifs('25.04'!$H$7:$H$411,'25.04'!$J$7:$J$411,$D20,'25.04'!$K$7:$K$411,AA$3) -> 0 | AB20: =sumifs('25.04'!$H$7:$H$411,'25.04'!$J$7:$J$411,$D20,'25.04'!$K$7:$K$411,AB$3) -> 0 | AC20: =sum(T20:AB20) -> 0
C21: 45019 | D21: Charity | E21: =sumifs('25.04'!$H$7:$H$411,'25.04'!$G$7:$G$411,$D21,'25.04'!$F$7:$F$411,E$3) -> 0 | F21: =sumifs('25.04'!$H$7:$H$411,'25.04'!$G$7:$G$411,$D21,'25.04'!$F$7:$F$411,F$3) -> 0 | G21: =sumifs('25.04'!$H$7:$H$411,'25.04'!$G$7:$G$411,$D21,'25.04'!$F$7:$F$411,G$3) -> 0 | H21: =sumifs('25.04'!$H$7:$H$411,'25.04'!$G$7:$G$411,$D21,'25.04'!$F$7:$F$411,H$3) -> 0 | I21: =sumifs('25.04'!$H$7:$H$411,'25.04'!$G$7:$G$411,$D21,'25.04'!$F$7:$F$411,I$3) -> 0 | J21: =sumifs('25.04'!$H$7:$H$411,'25.04'!$G$7:$G$411,$D21,'25.04'!$F$7:$F$411,J$3) -> 0 | K21: =sumifs('25.04'!$H$7:$H$411,'25.04'!$G$7:$G$411,$D21,'25.04'!$F$7:$F$411,K$3) -> 0 | L21: =sumifs('25.04'!$H$7:$H$411,'25.04'!$G$7:$G$411,$D21,'25.04'!$F$7:$F$411,L$3) -> 0 | M21: =sumifs('25.04'!$H$7:$H$411,'25.04'!$G$7:$G$411,$D21,'25.04'!$F$7:$F$411,M$3) -> 0 | N21: =sum(E21:M21) -> 0 | P21: =N21/sum(N$17:N$22) -> #DIV/0! | T21: =sumifs('25.04'!$H$7:$H$411,'25.04'!$J$7:$J$411,$D21,'25.04'!$K$7:$K$411,T$3) -> 0 | U21: =sumifs('25.04'!$H$7:$H$411,'25.04'!$J$7:$J$411,$D21,'25.04'!$K$7:$K$411,U$3) -> 0 | V21: =sumifs('25.04'!$H$7:$H$411,'25.04'!$J$7:$J$411,$D21,'25.04'!$K$7:$K$411,V$3) -> 0 | W21: =sumifs('25.04'!$H$7:$H$411,'25.04'!$J$7:$J$411,$D21,'25.04'!$K$7:$K$411,W$3) -> 0 | X21: =sumifs('25.04'!$H$7:$H$411,'25.04'!$J$7:$J$411,$D21,'25.04'!$K$7:$K$411,X$3) -> 0 | Y21: =sumifs('25.04'!$H$7:$H$411,'25.04'!$J$7:$J$411,$D21,'25.04'!$K$7:$K$411,Y$3) -> 0 | Z21: =sumifs('25.04'!$H$7:$H$411,'25.04'!$J$7:$J$411,$D21,'25.04'!$K$7:$K$411,Z$3) -> 0 | AA21: =sumifs('25.04'!$H$7:$H$411,'25.04'!$J$7:$J$411,$D21,'25.04'!$K$7:$K$411,AA$3) -> 0 | AB21: =sumifs('25.04'!$H$7:$H$411,'25.04'!$J$7:$J$411,$D21,'25.04'!$K$7:$K$411,AB$3) -> 0 | AC21: =sum(T21:AB21) -> 0
C22: 45049 | D22: Spirituality | E22: =sumifs('25.04'!$H$7:$H$411,'25.04'!$G$7:$G$411,$D22,'25.04'!$F$7:$F$411,E$3) -> 0 | F22: =sumifs('25.04'!$H$7:$H$411,'25.04'!$G$7:$G$411,$D22,'25.04'!$F$7:$F$411,F$3) -> 0 | G22: =sumifs('25.04'!$H$7:$H$411,'25.04'!$G$7:$G$411,$D22,'25.04'!$F$7:$F$411,G$3) -> 0 | H22: =sumifs('25.04'!$H$7:$H$411,'25.04'!$G$7:$G$411,$D22,'25.04'!$F$7:$F$411,H$3) -> 0 | I22: =sumifs('25.04'!$H$7:$H$411,'25.04'!$G$7:$G$411,$D22,'25.04'!$F$7:$F$411,I$3) -> 0 | J22: =sumifs('25.04'!$H$7:$H$411,'25.04'!$G$7:$G$411,$D22,'25.04'!$F$7:$F$411,J$3) -> 0 | K22: =sumifs('25.04'!$H$7:$H$411,'25.04'!$G$7:$G$411,$D22,'25.04'!$F$7:$F$411,K$3) -> 0 | L22: =sumifs('25.04'!$H$7:$H$411,'25.04'!$G$7:$G$411,$D22,'25.04'!$F$7:$F$411,L$3) -> 0 | M22: =sumifs('25.04'!$H$7:$H$411,'25.04'!$G$7:$G$411,$D22,'25.04'!$F$7:$F$411,M$3) -> 0 | N22: =sum(E22:M22) -> 0 | P22: =N22/sum(N$17:N$22) -> #DIV/0! | T22: =sumifs('25.04'!$H$7:$H$411,'25.04'!$J$7:$J$411,$D22,'25.04'!$K$7:$K$411,T$3) -> 0 | U22: =sumifs('25.04'!$H$7:$H$411,'25.04'!$J$7:$J$411,$D22,'25.04'!$K$7:$K$411,U$3) -> 0 | V22: =sumifs('25.04'!$H$7:$H$411,'25.04'!$J$7:$J$411,$D22,'25.04'!$K$7:$K$411,V$3) -> 0 | W22: =sumifs('25.04'!$H$7:$H$411,'25.04'!$J$7:$J$411,$D22,'25.04'!$K$7:$K$411,W$3) -> 0 | X22: =sumifs('25.04'!$H$7:$H$411,'25.04'!$J$7:$J$411,$D22,'25.04'!$K$7:$K$411,X$3) -> 0 | Y22: =sumifs('25.04'!$H$7:$H$411,'25.04'!$J$7:$J$411,$D22,'25.04'!$K$7:$K$411,Y$3) -> 0 | Z22: =sumifs('25.04'!$H$7:$H$411,'25.04'!$J$7:$J$411,$D22,'25.04'!$K$7:$K$411,Z$3) -> 0 | AA22: =sumifs('25.04'!$H$7:$H$411,'25.04'!$J$7:$J$411,$D22,'25.04'!$K$7:$K$411,AA$3) -> 0 | AB22: =sumifs('25.04'!$H$7:$H$411,'25.04'!$J$7:$J$411,$D22,'25.04'!$K$7:$K$411,AB$3) -> 0 | AC22: =sum(T22:AB22) -> 0
C23: 4 | D23: Health | E23: =sumifs('25.04'!$H$7:$H$411,'25.04'!$G$7:$G$411,$D23,'25.04'!$F$7:$F$411,E$3) -> 0 | F23: =sumifs('25.04'!$H$7:$H$411,'25.04'!$G$7:$G$411,$D23,'25.04'!$F$7:$F$411,F$3) -> 0 | G23: =sumifs('25.04'!$H$7:$H$411,'25.04'!$G$7:$G$411,$D23,'25.04'!$F$7:$F$411,G$3) -> 0 | H23: =sumifs('25.04'!$H$7:$H$411,'25.04'!$G$7:$G$411,$D23,'25.04'!$F$7:$F$411,H$3) -> 0 | I23: =sumifs('25.04'!$H$7:$H$411,'25.04'!$G$7:$G$411,$D23,'25.04'!$F$7:$F$411,I$3) -> 0 | J23: =sumifs('25.04'!$H$7:$H$411,'25.04'!$G$7:$G$411,$D23,'25.04'!$F$7:$F$411,J$3) -> 0 | K23: =sumifs('25.04'!$H$7:$H$411,'25.04'!$G$7:$G$411,$D23,'25.04'!$F$7:$F$411,K$3) -> 0 | L23: =sumifs('25.04'!$H$7:$H$411,'25.04'!$G$7:$G$411,$D23,'25.04'!$F$7:$F$411,L$3) -> 0 | M23: =sumifs('25.04'!$H$7:$H$411,'25.04'!$G$7:$G$411,$D23,'25.04'!$F$7:$F$411,M$3) -> 0 | N23: =sum(E23:M23) -> 0 | P23: =N23/sum(N$23:N$28) -> #DIV/0! | R23: =sum(N23:N28) -> 0 | S23: =R22/sum($R$4:$R$49) -> 0 | T23: =sumifs('25.04'!$H$7:$H$411,'25.04'!$J$7:$J$411,$D23,'25.04'!$K$7:$K$411,T$3) -> 0 | U23: =sumifs('25.04'!$H$7:$H$411,'25.04'!$J$7:$J$411,$D23,'25.04'!$K$7:$K$411,U$3) -> 0 | V23: =sumifs('25.04'!$H$7:$H$411,'25.04'!$J$7:$J$411,$D23,'25.04'!$K$7:$K$411,V$3) -> 0 | W23: =sumifs('25.04'!$H$7:$H$411,'25.04'!$J$7:$J$411,$D23,'25.04'!$K$7:$K$411,W$3) -> 0 | X23: =sumifs('25.04'!$H$7:$H$411,'25.04'!$J$7:$J$411,$D23,'25.04'!$K$7:$K$411,X$3) -> 0 | Y23: =sumifs('25.04'!$H$7:$H$411,'25.04'!$J$7:$J$411,$D23,'25.04'!$K$7:$K$411,Y$3) -> 0 | Z23: =sumifs('25.04'!$H$7:$H$411,'25.04'!$J$7:$J$411,$D23,'25.04'!$K$7:$K$411,Z$3) -> 0 | AA23: =sumifs('25.04'!$H$7:$H$411,'25.04'!$J$7:$J$411,$D23,'25.04'!$K$7:$K$411,AA$3) -> 0 | AB23: =sumifs('25.04'!$H$7:$H$411,'25.04'!$J$7:$J$411,$D23,'25.04'!$K$7:$K$411,AB$3) -> 0 | AC23: =sum(T23:AB23) -> 0
A24: 4 | B24: Health | C24: 44930 | D24: Medical exam | E24: =sumifs('25.04'!$H$7:$H$411,'25.04'!$G$7:$G$411,$D24,'25.04'!$F$7:$F$411,E$3) -> 0 | F24: =sumifs('25.04'!$H$7:$H$411,'25.04'!$G$7:$G$411,$D24,'25.04'!$F$7:$F$411,F$3) -> 0 | G24: =sumifs('25.04'!$H$7:$H$411,'25.04'!$G$7:$G$411,$D24,'25.04'!$F$7:$F$411,G$3) -> 0 | H24: =sumifs('25.04'!$H$7:$H$411,'25.04'!$G$7:$G$411,$D24,'25.04'!$F$7:$F$411,H$3) -> 0 | I24: =sumifs('25.04'!$H$7:$H$411,'25.04'!$G$7:$G$411,$D24,'25.04'!$F$7:$F$411,I$3) -> 0 | J24: =sumifs('25.04'!$H$7:$H$411,'25.04'!$G$7:$G$411,$D24,'25.04'!$F$7:$F$411,J$3) -> 0 | K24: =sumifs('25.04'!$H$7:$H$411,'25.04'!$G$7:$G$411,$D24,'25.04'!$F$7:$F$411,K$3) -> 0 | L24: =sumifs('25.04'!$H$7:$H$411,'25.04'!$G$7:$G$411,$D24,'25.04'!$F$7:$F$411,L$3) -> 0 | M24: =sumifs('25.04'!$H$7:$H$411,'25.04'!$G$7:$G$411,$D24,'25.04'!$F$7:$F$411,M$3) -> 0 | N24: =sum(E24:M24) -> 0 | P24: =N24/sum(N$23:N$28) -> #DIV/0! | T24: =sumifs('25.04'!$H$7:$H$411,'25.04'!$J$7:$J$411,$D24,'25.04'!$K$7:$K$411,T$3) -> 0 | U24: =sumifs('25.04'!$H$7:$H$411,'25.04'!$J$7:$J$411,$D24,'25.04'!$K$7:$K$411,U$3) -> 0 | V24: =sumifs('25.04'!$H$7:$H$411,'25.04'!$J$7:$J$411,$D24,'25.04'!$K$7:$K$411,V$3) -> 0 | W24: =sumifs('25.04'!$H$7:$H$411,'25.04'!$J$7:$J$411,$D24,'25.04'!$K$7:$K$411,W$3) -> 0 | X24: =sumifs('25.04'!$H$7:$H$411,'25.04'!$J$7:$J$411,$D24,'25.04'!$K$7:$K$411,X$3) -> 0 | Y24: =sumifs('25.04'!$H$7:$H$411,'25.04'!$J$7:$J$411,$D24,'25.04'!$K$7:$K$411,Y$3) -> 0 | Z24: =sumifs('25.04'!$H$7:$H$411,'25.04'!$J$7:$J$411,$D24,'25.04'!$K$7:$K$411,Z$3) -> 0 | AA24: =sumifs('25.04'!$H$7:$H$411,'25.04'!$J$7:$J$411,$D24,'25.04'!$K$7:$K$411,AA$3) -> 0 | AB24: =sumifs('25.04'!$H$7:$H$411,'25.04'!$J$7:$J$411,$D24,'25.04'!$K$7:$K$411,AB$3) -> 0 | AC24: =sum(T24:AB24) -> 0
D25: Tablets | E25: =sumifs('25.04'!$H$7:$H$411,'25.04'!$G$7:$G$411,$D25,'25.04'!$F$7:$F$411,E$3) -> 0 | F25: =sumifs('25.04'!$H$7:$H$411,'25.04'!$G$7:$G$411,$D25,'25.04'!$F$7:$F$411,F$3) -> 0 | G25: =sumifs('25.04'!$H$7:$H$411,'25.04'!$G$7:$G$411,$D25,'25.04'!$F$7:$F$411,G$3) -> 0 | H25: =sumifs('25.04'!$H$7:$H$411,'25.04'!$G$7:$G$411,$D25,'25.04'!$F$7:$F$411,H$3) -> 0 | I25: =sumifs('25.04'!$H$7:$H$411,'25.04'!$G$7:$G$411,$D25,'25.04'!$F$7:$F$411,I$3) -> 0 | J25: =sumifs('25.04'!$H$7:$H$411,'25.04'!$G$7:$G$411,$D25,'25.04'!$F$7:$F$411,J$3) -> 0 | K25: =sumifs('25.04'!$H$7:$H$411,'25.04'!$G$7:$G$411,$D25,'25.04'!$F$7:$F$411,K$3) -> 0 | L25: =sumifs('25.04'!$H$7:$H$411,'25.04'!$G$7:$G$411,$D25,'25.04'!$F$7:$F$411,L$3) -> 0 | M25: =sumifs('25.04'!$H$7:$H$411,'25.04'!$G$7:$G$411,$D25,'25.04'!$F$7:$F$411,M$3) -> 0 | N25: =sum(E25:M25) -> 0
C26: 44961 | D26: Body care | E26: =sumifs('25.04'!$H$7:$H$411,'25.04'!$G$7:$G$411,$D26,'25.04'!$F$7:$F$411,E$3) -> 0 | F26: =sumifs('25.04'!$H$7:$H$411,'25.04'!$G$7:$G$411,$D26,'25.04'!$F$7:$F$411,F$3) -> 0 | G26: =sumifs('25.04'!$H$7:$H$411,'25.04'!$G$7:$G$411,$D26,'25.04'!$F$7:$F$411,G$3) -> 0 | H26: =sumifs('25.04'!$H$7:$H$411,'25.04'!$G$7:$G$411,$D26,'25.04'!$F$7:$F$411,H$3) -> 0 | I26: =sumifs('25.04'!$H$7:$H$411,'25.04'!$G$7:$G$411,$D26,'25.04'!$F$7:$F$411,I$3) -> 0 | J26: =sumifs('25.04'!$H$7:$H$411,'25.04'!$G$7:$G$411,$D26,'25.04'!$F$7:$F$411,J$3) -> 0 | K26: =sumifs('25.04'!$H$7:$H$411,'25.04'!$G$7:$G$411,$D26,'25.04'!$F$7:$F$411,K$3) -> 0 | L26: =sumifs('25.04'!$H$7:$H$411,'25.04'!$G$7:$G$411,$D26,'25.04'!$F$7:$F$411,L$3) -> 0 | M26: =sumifs('25.04'!$H$7:$H$411,'25.04'!$G$7:$G$411,$D26,'25.04'!$F$7:$F$411,M$3) -> 0 | N26: =sum(E26:M26) -> 0 | P26: =N26/sum(N$23:N$28) -> #DIV/0! | T26: =sumifs('25.04'!$H$7:$H$411,'25.04'!$J$7:$J$411,$D26,'25.04'!$K$7:$K$411,T$3) -> 0 | U26: =sumifs('25.04'!$H$7:$H$411,'25.04'!$J$7:$J$411,$D26,'25.04'!$K$7:$K$411,U$3) -> 0 | V26: =sumifs('25.04'!$H$7:$H$411,'25.04'!$J$7:$J$411,$D26,'25.04'!$K$7:$K$411,V$3) -> 0 | W26: =sumifs('25.04'!$H$7:$H$411,'25.04'!$J$7:$J$411,$D26,'25.04'!$K$7:$K$411,W$3) -> 0 | X26: =sumifs('25.04'!$H$7:$H$411,'25.04'!$J$7:$J$411,$D26,'25.04'!$K$7:$K$411,X$3) -> 0 | Y26: =sumifs('25.04'!$H$7:$H$411,'25.04'!$J$7:$J$411,$D26,'25.04'!$K$7:$K$411,Y$3) -> 0 | Z26: =sumifs('25.04'!$H$7:$H$411,'25.04'!$J$7:$J$411,$D26,'25.04'!$K$7:$K$411,Z$3) -> 0 | AA26: =sumifs('25.04'!$H$7:$H$411,'25.04'!$J$7:$J$411,$D26,'25.04'!$K$7:$K$411,AA$3) -> 0 | AB26: =sumifs('25.04'!$H$7:$H$411,'25.04'!$J$7:$J$411,$D26,'25.04'!$K$7:$K$411,AB$3) -> 0 | AC26: =sum(T26:AB26) -> 0
C27: 44989 | D27: Cosmetic | E27: =sumifs('25.04'!$H$7:$H$411,'25.04'!$G$7:$G$411,$D27,'25.04'!$F$7:$F$411,E$3) -> 0 | G27: =sumifs('25.04'!$H$7:$H$411,'25.04'!$G$7:$G$411,$D27,'25.04'!$F$7:$F$411,G$3) -> 0 | H27: =sumifs('25.04'!$H$7:$H$411,'25.04'!$G$7:$G$411,$D27,'25.04'!$F$7:$F$411,H$3) -> 0 | I27: =sumifs('25.04'!$H$7:$H$411,'25.04'!$G$7:$G$411,$D27,'25.04'!$F$7:$F$411,I$3) -> 0 | J27: =sumifs('25.04'!$H$7:$H$411,'25.04'!$G$7:$G$411,$D27,'25.04'!$F$7:$F$411,J$3) -> 0 | K27: =sumifs('25.04'!$H$7:$H$411,'25.04'!$G$7:$G$411,$D27,'25.04'!$F$7:$F$411,K$3) -> 0 | L27: =sumifs('25.04'!$H$7:$H$411,'25.04'!$G$7:$G$411,$D27,'25.04'!$F$7:$F$411,L$3) -> 0 | M27: =sumifs('25.04'!$H$7:$H$411,'25.04'!$G$7:$G$411,$D27,'25.04'!$F$7:$F$411,M$3) -> 0 | N27: =sum(E27:M27) -> 0 | P27: =N27/sum(N$23:N$28) -> #DIV/0! | T27: =sumifs('25.04'!$H$7:$H$411,'25.04'!$J$7:$J$411,$D27,'25.04'!$K$7:$K$411,T$3) -> 0 | U27: =sumifs('25.04'!$H$7:$H$411,'25.04'!$J$7:$J$411,$D27,'25.04'!$K$7:$K$411,U$3) -> 0 | V27: =sumifs('25.04'!$H$7:$H$411,'25.04'!$J$7:$J$411,$D27,'25.04'!$K$7:$K$411,V$3) -> 0 | W27: =sumifs('25.04'!$H$7:$H$411,'25.04'!$J$7:$J$411,$D27,'25.04'!$K$7:$K$411,W$3) -> 0 | X27: =sumifs('25.04'!$H$7:$H$411,'25.04'!$J$7:$J$411,$D27,'25.04'!$K$7:$K$411,X$3) -> 0 | Y27: =sumifs('25.04'!$H$7:$H$411,'25.04'!$J$7:$J$411,$D27,'25.04'!$K$7:$K$411,Y$3) -> 0 | Z27: =sumifs('25.04'!$H$7:$H$411,'25.04'!$J$7:$J$411,$D27,'25.04'!$K$7:$K$411,Z$3) -> 0 | AA27: =sumifs('25.04'!$H$7:$H$411,'25.04'!$J$7:$J$411,$D27,'25.04'!$K$7:$K$411,AA$3) -> 0 | AB27: =sumifs('25.04'!$H$7:$H$411,'25.04'!$J$7:$J$411,$D27,'25.04'!$K$7:$K$411,AB$3) -> 0 | AC27: =sum(T27:AB27) -> 0
C28: 45020 | D28: Medical Insurrance | E28: =sumifs('25.04'!$H$7:$H$411,'25.04'!$G$7:$G$411,$D28,'25.04'!$F$7:$F$411,E$3) -> 0 | F28: =sumifs('25.04'!$H$7:$H$411,'25.04'!$G$7:$G$411,$D28,'25.04'!$F$7:$F$411,F$3) -> 0 | G28: =sumifs('25.04'!$H$7:$H$411,'25.04'!$G$7:$G$411,$D28,'25.04'!$F$7:$F$411,G$3) -> 0 | H28: =sumifs('25.04'!$H$7:$H$411,'25.04'!$G$7:$G$411,$D28,'25.04'!$F$7:$F$411,H$3) -> 0 | I28: =sumifs('25.04'!$H$7:$H$411,'25.04'!$G$7:$G$411,$D28,'25.04'!$F$7:$F$411,I$3) -> 0 | J28: =sumifs('25.04'!$H$7:$H$411,'25.04'!$G$7:$G$411,$D28,'25.04'!$F$7:$F$411,J$3) -> 0 | K28: =sumifs('25.04'!$H$7:$H$411,'25.04'!$G$7:$G$411,$D28,'25.04'!$F$7:$F$411,K$3) -> 0 | L28: =sumifs('25.04'!$H$7:$H$411,'25.04'!$G$7:$G$411,$D28,'25.04'!$F$7:$F$411,L$3) -> 0 | M28: =sumifs('25.04'!$H$7:$H$411,'25.04'!$G$7:$G$411,$D28,'25.04'!$F$7:$F$411,M$3) -> 0 | N28: =sum(E28:M28) -> 0 | P28: =N28/sum(N$23:N$28) -> #DIV/0! | T28: =sumifs('25.04'!$H$7:$H$411,'25.04'!$J$7:$J$411,$D28,'25.04'!$K$7:$K$411,T$3) -> 0 | U28: =sumifs('25.04'!$H$7:$H$411,'25.04'!$J$7:$J$411,$D28,'25.04'!$K$7:$K$411,U$3) -> 0 | V28: =sumifs('25.04'!$H$7:$H$411,'25.04'!$J$7:$J$411,$D28,'25.04'!$K$7:$K$411,V$3) -> 0 | W28: =sumifs('25.04'!$H$7:$H$411,'25.04'!$J$7:$J$411,$D28,'25.04'!$K$7:$K$411,W$3) -> 0 | X28: =sumifs('25.04'!$H$7:$H$411,'25.04'!$J$7:$J$411,$D28,'25.04'!$K$7:$K$411,X$3) -> 0 | Y28: =sumifs('25.04'!$H$7:$H$411,'25.04'!$J$7:$J$411,$D28,'25.04'!$K$7:$K$411,Y$3) -> 0 | Z28: =sumifs('25.04'!$H$7:$H$411,'25.04'!$J$7:$J$411,$D28,'25.04'!$K$7:$K$411,Z$3) -> 0 | AA28: =sumifs('25.04'!$H$7:$H$411,'25.04'!$J$7:$J$411,$D28,'25.04'!$K$7:$K$411,AA$3) -> 0 | AB28: =sumifs('25.04'!$H$7:$H$411,'25.04'!$J$7:$J$411,$D28,'25.04'!$K$7:$K$411,AB$3) -> 0 | AC28: =sum(T28:AB28) -> 0
A29: 5 | B29: Living | C29: a | D29: Go Market | E29: =sumifs('25.04'!$H$7:$H$411,'25.04'!$G$7:$G$411,$D29,'25.04'!$F$7:$F$411,E$3) -> 0 | F29: =sumifs('25.04'!$H$7:$H$411,'25.04'!$G$7:$G$411,$D29,'25.04'!$F$7:$F$411,F$3) -> 0 | G29: =sumifs('25.04'!$H$7:$H$411,'25.04'!$G$7:$G$411,$D29,'25.04'!$F$7:$F$411,G$3) -> 3403644 | H29: =sumifs('25.04'!$H$7:$H$411,'25.04'!$G$7:$G$411,$D29,'25.04'!$F$7:$F$411,H$3) -> 0 | I29: =sumifs('25.04'!$H$7:$H$411,'25.04'!$G$7:$G$411,$D29,'25.04'!$F$7:$F$411,I$3) -> 0 | J29: =sumifs('25.04'!$H$7:$H$411,'25.04'!$G$7:$G$411,$D29,'25.04'!$F$7:$F$411,J$3) -> 0 | K29: =sumifs('25.04'!$H$7:$H$411,'25.04'!$G$7:$G$411,$D29,'25.04'!$F$7:$F$411,K$3) -> 0 | L29: =sumifs('25.04'!$H$7:$H$411,'25.04'!$G$7:$G$411,$D29,'25.04'!$F$7:$F$411,L$3) -> 0 | M29: =sumifs('25.04'!$H$7:$H$411,'25.04'!$G$7:$G$411,$D29,'25.04'!$F$7:$F$411,M$3) -> 0 | N29: =sum(E29:M29) -> 3403644 | P29: =N29/sum(N$29:N$47) -> 0.95070031 | Q29: =N29/sum(N$29:N$31) -> 0.95070031 | T29: =sumifs('25.04'!$H$7:$H$411,'25.04'!$J$7:$J$411,$D29,'25.04'!$K$7:$K$411,T$3) -> 0 | U29: =sumifs('25.04'!$H$7:$H$411,'25.04'!$J$7:$J$411,$D29,'25.04'!$K$7:$K$411,U$3) -> 0 | V29: =sumifs('25.04'!$H$7:$H$411,'25.04'!$J$7:$J$411,$D29,'25.04'!$K$7:$K$411,V$3) -> 0 | W29: =sumifs('25.04'!$H$7:$H$411,'25.04'!$J$7:$J$411,$D29,'25.04'!$K$7:$K$411,W$3) -> 0 | X29: =sumifs('25.04'!$H$7:$H$411,'25.04'!$J$7:$J$411,$D29,'25.04'!$K$7:$K$411,X$3) -> 0 | Y29: =sumifs('25.04'!$H$7:$H$411,'25.04'!$J$7:$J$411,$D29,'25.04'!$K$7:$K$411,Y$3) -> 0 | Z29: =sumifs('25.04'!$H$7:$H$411,'25.04'!$J$7:$J$411,$D29,'25.04'!$K$7:$K$411,Z$3) -> 0 | AA29: =sumifs('25.04'!$H$7:$H$411,'25.04'!$J$7:$J$411,$D29,'25.04'!$K$7:$K$411,AA$3) -> 0 | AB29: =sumifs('25.04'!$H$7:$H$411,'25.04'!$J$7:$J$411,$D29,'25.04'!$K$7:$K$411,AB$3) -> 0 | AC29: =sum(T29:AB29) -> 0
C30: b | D30: Breakfast | E30: =sumifs('25.04'!$H$7:$H$411,'25.04'!$G$7:$G$411,$D30,'25.04'!$F$7:$F$411,E$3) -> 0 | F30: =sumifs('25.04'!$H$7:$H$411,'25.04'!$G$7:$G$411,$D30,'25.04'!$F$7:$F$411,F$3) -> 0 | G30: =sumifs('25.04'!$H$7:$H$411,'25.04'!$G$7:$G$411,$D30,'25.04'!$F$7:$F$411,G$3) -> 0 | H30: =sumifs('25.04'!$H$7:$H$411,'25.04'!$G$7:$G$411,$D30,'25.04'!$F$7:$F$411,H$3) -> 0 | I30: =sumifs('25.04'!$H$7:$H$411,'25.04'!$G$7:$G$411,$D30,'25.04'!$F$7:$F$411,I$3) -> 0 | J30: =sumifs('25.04'!$H$7:$H$411,'25.04'!$G$7:$G$411,$D30,'25.04'!$F$7:$F$411,J$3) -> 0 | K30: =sumifs('25.04'!$H$7:$H$411,'25.04'!$G$7:$G$411,$D30,'25.04'!$F$7:$F$411,K$3) -> 0 | L30: =sumifs('25.04'!$H$7:$H$411,'25.04'!$G$7:$G$411,$D30,'25.04'!$F$7:$F$411,L$3) -> 0 | M30: =sumifs('25.04'!$H$7:$H$411,'25.04'!$G$7:$G$411,$D30,'25.04'!$F$7:$F$411,M$3) -> 0 | N30: =sum(E30:M30) -> 0 | P30: =N30/sum(N$29:N$47) -> 0 | Q30: =N30/sum(N$29:N$31) -> 0 | T30: =sumifs('25.04'!$H$7:$H$411,'25.04'!$J$7:$J$411,$D30,'25.04'!$K$7:$K$411,T$3) -> 0 | U30: =sumifs('25.04'!$H$7:$H$411,'25.04'!$J$7:$J$411,$D30,'25.04'!$K$7:$K$411,U$3) -> 0 | V30: =sumifs('25.04'!$H$7:$H$411,'25.04'!$J$7:$J$411,$D30,'25.04'!$K$7:$K$411,V$3) -> 0 | W30: =sumifs('25.04'!$H$7:$H$411,'25.04'!$J$7:$J$411,$D30,'25.04'!$K$7:$K$411,W$3) -> 0 | X30: =sumifs('25.04'!$H$7:$H$411,'25.04'!$J$7:$J$411,$D30,'25.04'!$K$7:$K$411,X$3) -> 0 | Y30: =sumifs('25.04'!$H$7:$H$411,'25.04'!$J$7:$J$411,$D30,'25.04'!$K$7:$K$411,Y$3) -> 0 | Z30: =sumifs('25.04'!$H$7:$H$411,'25.04'!$J$7:$J$411,$D30,'25.04'!$K$7:$K$411,Z$3) -> 0 | AA30: =sumifs('25.04'!$H$7:$H$411,'25.04'!$J$7:$J$411,$D30,'25.04'!$K$7:$K$411,AA$3) -> 0 | AB30: =sumifs('25.04'!$H$7:$H$411,'25.04'!$J$7:$J$411,$D30,'25.04'!$K$7:$K$411,AB$3) -> 0 | AC30: =sum(T30:AB30) -> 0
C31: c | D31: Extra meal | E31: =sumifs('25.04'!$H$7:$H$411,'25.04'!$G$7:$G$411,$D31,'25.04'!$F$7:$F$411,E$3) -> 0 | F31: =sumifs('25.04'!$H$7:$H$411,'25.04'!$G$7:$G$411,$D31,'25.04'!$F$7:$F$411,F$3) -> 0 | G31: =sumifs('25.04'!$H$7:$H$411,'25.04'!$G$7:$G$411,$D31,'25.04'!$F$7:$F$411,G$3) -> 176500 | H31: =sumifs('25.04'!$H$7:$H$411,'25.04'!$G$7:$G$411,$D31,'25.04'!$F$7:$F$411,H$3) -> 0 | I31: =sumifs('25.04'!$H$7:$H$411,'25.04'!$G$7:$G$411,$D31,'25.04'!$F$7:$F$411,I$3) -> 0 | J31: =sumifs('25.04'!$H$7:$H$411,'25.04'!$G$7:$G$411,$D31,'25.04'!$F$7:$F$411,J$3) -> 0 | K31: =sumifs('25.04'!$H$7:$H$411,'25.04'!$G$7:$G$411,$D31,'25.04'!$F$7:$F$411,K$3) -> 0 | L31: =sumifs('25.04'!$H$7:$H$411,'25.04'!$G$7:$G$411,$D31,'25.04'!$F$7:$F$411,L$3) -> 0 | M31: =sumifs('25.04'!$H$7:$H$411,'25.04'!$G$7:$G$411,$D31,'25.04'!$F$7:$F$411,M$3) -> 0 | N31: =sum(E31:M31) -> 176500 | P31: =N31/sum(N$29:N$47) -> 0.049299693 | Q31: =N31/sum(N$29:N$31) -> 0.049299693 | T31: =sumifs('25.04'!$H$7:$H$411,'25.04'!$J$7:$J$411,$D31,'25.04'!$K$7:$K$411,T$3) -> 0 | U31: =sumifs('25.04'!$H$7:$H$411,'25.04'!$J$7:$J$411,$D31,'25.04'!$K$7:$K$411,U$3) -> 0 | V31: =sumifs('25.04'!$H$7:$H$411,'25.04'!$J$7:$J$411,$D31,'25.04'!$K$7:$K$411,V$3) -> 0 | W31: =sumifs('25.04'!$H$7:$H$411,'25.04'!$J$7:$J$411,$D31,'25.04'!$K$7:$K$411,W$3) -> 0 | X31: =sumifs('25.04'!$H$7:$H$411,'25.04'!$J$7:$J$411,$D31,'25.04'!$K$7:$K$411,X$3) -> 0 | Y31: =sumifs('25.04'!$H$7:$H$411,'25.04'!$J$7:$J$411,$D31,'25.04'!$K$7:$K$411,Y$3) -> 0 | Z31: =sumifs('25.04'!$H$7:$H$411,'25.04'!$J$7:$J$411,$D31,'25.04'!$K$7:$K$411,Z$3) -> 0 | AA31: =sumifs('25.04'!$H$7:$H$411,'25.04'!$J$7:$J$411,$D31,'25.04'!$K$7:$K$411,AA$3) -> 0 | AB31: =sumifs('25.04'!$H$7:$H$411,'25.04'!$J$7:$J$411,$D31,'25.04'!$K$7:$K$411,AB$3) -> 0 | AC31: =sum(T31:AB31) -> 0
C32: d | D32: Nghĩa | E32: =sumifs('25.04'!$H$7:$H$411,'25.04'!$G$7:$G$411,$D32,'25.04'!$F$7:$F$411,E$3) -> 0 | F32: =sumifs('25.04'!$H$7:$H$411,'25.04'!$G$7:$G$411,$D32,'25.04'!$F$7:$F$411,F$3) -> 0 | G32: =sumifs('25.04'!$H$7:$H$411,'25.04'!$G$7:$G$411,$D32,'25.04'!$F$7:$F$411,G$3) -> 0 | H32: =sumifs('25.04'!$H$7:$H$411,'25.04'!$G$7:$G$411,$D32,'25.04'!$F$7:$F$411,H$3) -> 0 | I32: =sumifs('25.04'!$H$7:$H$411,'25.04'!$G$7:$G$411,$D32,'25.04'!$F$7:$F$411,I$3) -> 0 | J32: =sumifs('25.04'!$H$7:$H$411,'25.04'!$G$7:$G$411,$D32,'25.04'!$F$7:$F$411,J$3) -> 0 | K32: =sumifs('25.04'!$H$7:$H$411,'25.04'!$G$7:$G$411,$D32,'25.04'!$F$7:$F$411,K$3) -> 0 | L32: =sumifs('25.04'!$H$7:$H$411,'25.04'!$G$7:$G$411,$D32,'25.04'!$F$7:$F$411,L$3) -> 0 | M32: =sumifs('25.04'!$H$7:$H$411,'25.04'!$G$7:$G$411,$D32,'25.04'!$F$7:$F$411,M$3) -> 0 | N32: =sum(E32:M32) -> 0 | P32: =N32/sum(N$29:N$47) -> 0 | Q32: =N32/sum(N$32:N$35) -> #DIV/0! | T32: =sumifs('25.04'!$H$7:$H$411,'25.04'!$J$7:$J$411,$D32,'25.04'!$K$7:$K$411,T$3) -> 0 | U32: =sumifs('25.04'!$H$7:$H$411,'25.04'!$J$7:$J$411,$D32,'25.04'!$K$7:$K$411,U$3) -> 0 | V32: =sumifs('25.04'!$H$7:$H$411,'25.04'!$J$7:$J$411,$D32,'25.04'!$K$7:$K$411,V$3) -> 0 | W32: =sumifs('25.04'!$H$7:$H$411,'25.04'!$J$7:$J$411,$D32,'25.04'!$K$7:$K$411,W$3) -> 0 | X32: =sumifs('25.04'!$H$7:$H$411,'25.04'!$J$7:$J$411,$D32,'25.04'!$K$7:$K$411,X$3) -> 0 | Y32: =sumifs('25.04'!$H$7:$H$411,'25.04'!$J$7:$J$411,$D32,'25.04'!$K$7:$K$411,Y$3) -> 0 | Z32: =sumifs('25.04'!$H$7:$H$411,'25.04'!$J$7:$J$411,$D32,'25.04'!$K$7:$K$411,Z$3) -> 0 | AA32: =sumifs('25.04'!$H$7:$H$411,'25.04'!$J$7:$J$411,$D32,'25.04'!$K$7:$K$411,AA$3) -> 0 | AB32: =sumifs('25.04'!$H$7:$H$411,'25.04'!$J$7:$J$411,$D32,'25.04'!$K$7:$K$411,AB$3) -> 0 | AC32: =sum(T32:AB32) -> 0
C33: e | D33: Mai | E33: =sumifs('25.04'!$H$7:$H$411,'25.04'!$G$7:$G$411,$D33,'25.04'!$F$7:$F$411,E$3) -> 0 | F33: =sumifs('25.04'!$H$7:$H$411,'25.04'!$G$7:$G$411,$D33,'25.04'!$F$7:$F$411,F$3) -> 0 | G33: =sumifs('25.04'!$H$7:$H$411,'25.04'!$G$7:$G$411,$D33,'25.04'!$F$7:$F$411,G$3) -> 0 | H33: =sumifs('25.04'!$H$7:$H$411,'25.04'!$G$7:$G$411,$D33,'25.04'!$F$7:$F$411,H$3) -> 0 | I33: =sumifs('25.04'!$H$7:$H$411,'25.04'!$G$7:$G$411,$D33,'25.04'!$F$7:$F$411,I$3) -> 0 | J33: =sumifs('25.04'!$H$7:$H$411,'25.04'!$G$7:$G$411,$D33,'25.04'!$F$7:$F$411,J$3) -> 0 | K33: =sumifs('25.04'!$H$7:$H$411,'25.04'!$G$7:$G$411,$D33,'25.04'!$F$7:$F$411,K$3) -> 0 | L33: =sumifs('25.04'!$H$7:$H$411,'25.04'!$G$7:$G$411,$D33,'25.04'!$F$7:$F$411,L$3) -> 0 | M33: =sumifs('25.04'!$H$7:$H$411,'25.04'!$G$7:$G$411,$D33,'25.04'!$F$7:$F$411,M$3) -> 0 | N33: =sum(E33:M33) -> 0 | P33: =N33/sum(N$29:N$47) -> 0 | Q33: =N33/sum(N$32:N$35) -> #DIV/0! | T33: =sumifs('25.04'!$H$7:$H$411,'25.04'!$J$7:$J$411,$D33,'25.04'!$K$7:$K$411,T$3) -> 0 | U33: =sumifs('25.04'!$H$7:$H$411,'25.04'!$J$7:$J$411,$D33,'25.04'!$K$7:$K$411,U$3) -> 0 | V33: =sumifs('25.04'!$H$7:$H$411,'25.04'!$J$7:$J$411,$D33,'25.04'!$K$7:$K$411,V$3) -> 0 | W33: =sumifs('25.04'!$H$7:$H$411,'25.04'!$J$7:$J$411,$D33,'25.04'!$K$7:$K$411,W$3) -> 0 | X33: =sumifs('25.04'!$H$7:$H$411,'25.04'!$J$7:$J$411,$D33,'25.04'!$K$7:$K$411,X$3) -> 0 | Y33: =sumifs('25.04'!$H$7:$H$411,'25.04'!$J$7:$J$411,$D33,'25.04'!$K$7:$K$411,Y$3) -> 0 | Z33: =sumifs('25.04'!$H$7:$H$411,'25.04'!$J$7:$J$411,$D33,'25.04'!$K$7:$K$411,Z$3) -> 0 | AA33: =sumifs('25.04'!$H$7:$H$411,'25.04'!$J$7:$J$411,$D33,'25.04'!$K$7:$K$411,AA$3) -> 0 | AB33: =sumifs('25.04'!$H$7:$H$411,'25.04'!$J$7:$J$411,$D33,'25.04'!$K$7:$K$411,AB$3) -> 0 | AC33: =sum(T33:AB33) -> 0
C34: g | D34: Totto | E34: =sumifs('25.04'!$H$7:$H$411,'25.04'!$G$7:$G$411,$D34,'25.04'!$F$7:$F$411,E$3) -> 0 | F34: =sumifs('25.04'!$H$7:$H$411,'25.04'!$G$7:$G$411,$D34,'25.04'!$F$7:$F$411,F$3) -> 0 | G34: =sumifs('25.04'!$H$7:$H$411,'25.04'!$G$7:$G$411,$D34,'25.04'!$F$7:$F$411,G$3) -> 0 | H34: =sumifs('25.04'!$H$7:$H$411,'25.04'!$G$7:$G$411,$D34,'25.04'!$F$7:$F$411,H$3) -> 0 | I34: =sumifs('25.04'!$H$7:$H$411,'25.04'!$G$7:$G$411,$D34,'25.04'!$F$7:$F$411,I$3) -> 0 | J34: =sumifs('25.04'!$H$7:$H$411,'25.04'!$G$7:$G$411,$D34,'25.04'!$F$7:$F$411,J$3) -> 0 | K34: =sumifs('25.04'!$H$7:$H$411,'25.04'!$G$7:$G$411,$D34,'25.04'!$F$7:$F$411,K$3) -> 0 | L34: =sumifs('25.04'!$H$7:$H$411,'25.04'!$G$7:$G$411,$D34,'25.04'!$F$7:$F$411,L$3) -> 0 | M34: =sumifs('25.04'!$H$7:$H$411,'25.04'!$G$7:$G$411,$D34,'25.04'!$F$7:$F$411,M$3) -> 0 | N34: =sum(E34:M34) -> 0 | P34: =N34/sum(N$29:N$47) -> 0 | Q34: =N34/sum(N$32:N$35) -> #DIV/0! | T34: =sumifs('25.04'!$H$7:$H$411,'25.04'!$J$7:$J$411,$D34,'25.04'!$K$7:$K$411,T$3) -> 0 | U34: =sumifs('25.04'!$H$7:$H$411,'25.04'!$J$7:$J$411,$D34,'25.04'!$K$7:$K$411,U$3) -> 0 | V34: =sumifs('25.04'!$H$7:$H$411,'25.04'!$J$7:$J$411,$D34,'25.04'!$K$7:$K$411,V$3) -> 0 | W34: =sumifs('25.04'!$H$7:$H$411,'25.04'!$J$7:$J$411,$D34,'25.04'!$K$7:$K$411,W$3) -> 0 | X34: =sumifs('25.04'!$H$7:$H$411,'25.04'!$J$7:$J$411,$D34,'25.04'!$K$7:$K$411,X$3) -> 0 | Y34: =sumifs('25.04'!$H$7:$H$411,'25.04'!$J$7:$J$411,$D34,'25.04'!$K$7:$K$411,Y$3) -> 0 | Z34: =sumifs('25.04'!$H$7:$H$411,'25.04'!$J$7:$J$411,$D34,'25.04'!$K$7:$K$411,Z$3) -> 0 | AA34: =sumifs('25.04'!$H$7:$H$411,'25.04'!$J$7:$J$411,$D34,'25.04'!$K$7:$K$411,AA$3) -> 0 | AB34: =sumifs('25.04'!$H$7:$H$411,'25.04'!$J$7:$J$411,$D34,'25.04'!$K$7:$K$411,AB$3) -> 0 | AC34: =sum(T34:AB34) -> 0
C35: h | D35: Lego | E35: =sumifs('25.04'!$H$7:$H$411,'25.04'!$G$7:$G$411,$D35,'25.04'!$F$7:$F$411,E$3) -> 0 | F35: =sumifs('25.04'!$H$7:$H$411,'25.04'!$G$7:$G$411,$D35,'25.04'!$F$7:$F$411,F$3) -> 0 | G35: =sumifs('25.04'!$H$7:$H$411,'25.04'!$G$7:$G$411,$D35,'25.04'!$F$7:$F$411,G$3) -> 0 | H35: =sumifs('25.04'!$H$7:$H$411,'25.04'!$G$7:$G$411,$D35,'25.04'!$F$7:$F$411,H$3) -> 0 | I35: =sumifs('25.04'!$H$7:$H$411,'25.04'!$G$7:$G$411,$D35,'25.04'!$F$7:$F$411,I$3) -> 0 | J35: =sumifs('25.04'!$H$7:$H$411,'25.04'!$G$7:$G$411,$D35,'25.04'!$F$7:$F$411,J$3) -> 0 | K35: =sumifs('25.04'!$H$7:$H$411,'25.04'!$G$7:$G$411,$D35,'25.04'!$F$7:$F$411,K$3) -> 0 | L35: =sumifs('25.04'!$H$7:$H$411,'25.04'!$G$7:$G$411,$D35,'25.04'!$F$7:$F$411,L$3) -> 0 | M35: =sumifs('25.04'!$H$7:$H$411,'25.04'!$G$7:$G$411,$D35,'25.04'!$F$7:$F$411,M$3) -> 0 | N35: =sum(E35:M35) -> 0 | P35: =N35/sum(N$29:N$47) -> 0 | Q35: =N35/sum(N$32:N$35) -> #DIV/0! | T35: =sumifs('25.04'!$H$7:$H$411,'25.04'!$J$7:$J$411,$D35,'25.04'!$K$7:$K$411,T$3) -> 0 | U35: =sumifs('25.04'!$H$7:$H$411,'25.04'!$J$7:$J$411,$D35,'25.04'!$K$7:$K$411,U$3) -> 0 | V35: =sumifs('25.04'!$H$7:$H$411,'25.04'!$J$7:$J$411,$D35,'25.04'!$K$7:$K$411,V$3) -> 0 | W35: =sumifs('25.04'!$H$7:$H$411,'25.04'!$J$7:$J$411,$D35,'25.04'!$K$7:$K$411,W$3) -> 0 | X35: =sumifs('25.04'!$H$7:$H$411,'25.04'!$J$7:$J$411,$D35,'25.04'!$K$7:$K$411,X$3) -> 0 | Y35: =sumifs('25.04'!$H$7:$H$411,'25.04'!$J$7:$J$411,$D35,'25.04'!$K$7:$K$411,Y$3) -> 0 | Z35: =sumifs('25.04'!$H$7:$H$411,'25.04'!$J$7:$J$411,$D35,'25.04'!$K$7:$K$411,Z$3) -> 0 | AA35: =sumifs('25.04'!$H$7:$H$411,'25.04'!$J$7:$J$411,$D35,'25.04'!$K$7:$K$411,AA$3) -> 0 | AB35: =sumifs('25.04'!$H$7:$H$411,'25.04'!$J$7:$J$411,$D35,'25.04'!$K$7:$K$411,AB$3) -> 0 | AC35: =sum(T35:AB35) -> 0
C36: i | D36: Phone | E36: =sumifs('25.04'!$H$7:$H$411,'25.04'!$G$7:$G$411,$D36,'25.04'!$F$7:$F$411,E$3) -> 0 | F36: =sumifs('25.04'!$H$7:$H$411,'25.04'!$G$7:$G$411,$D36,'25.04'!$F$7:$F$411,F$3) -> 0 | G36: =sumifs('25.04'!$H$7:$H$411,'25.04'!$G$7:$G$411,$D36,'25.04'!$F$7:$F$411,G$3) -> 0 | H36: =sumifs('25.04'!$H$7:$H$411,'25.04'!$G$7:$G$411,$D36,'25.04'!$F$7:$F$411,H$3) -> 0 | I36: =sumifs('25.04'!$H$7:$H$411,'25.04'!$G$7:$G$411,$D36,'25.04'!$F$7:$F$411,I$3) -> 0 | J36: =sumifs('25.04'!$H$7:$H$411,'25.04'!$G$7:$G$411,$D36,'25.04'!$F$7:$F$411,J$3) -> 0 | K36: =sumifs('25.04'!$H$7:$H$411,'25.04'!$G$7:$G$411,$D36,'25.04'!$F$7:$F$411,K$3) -> 0 | L36: =sumifs('25.04'!$H$7:$H$411,'25.04'!$G$7:$G$411,$D36,'25.04'!$F$7:$F$411,L$3) -> 0 | M36: =sumifs('25.04'!$H$7:$H$411,'25.04'!$G$7:$G$411,$D36,'25.04'!$F$7:$F$411,M$3) -> 0 | N36: =sum(E36:M36) -> 0 | P36: =N36/sum(N$29:N$47) -> 0 | Q36: =N36/sum(N$36:N$40) -> #DIV/0! | T36: =sumifs('25.04'!$H$7:$H$411,'25.04'!$J$7:$J$411,$D36,'25.04'!$K$7:$K$411,T$3) -> 0 | U36: =sumifs('25.04'!$H$7:$H$411,'25.04'!$J$7:$J$411,$D36,'25.04'!$K$7:$K$411,U$3) -> 0 | V36: =sumifs('25.04'!$H$7:$H$411,'25.04'!$J$7:$J$411,$D36,'25.04'!$K$7:$K$411,V$3) -> 0 | W36: =sumifs('25.04'!$H$7:$H$411,'25.04'!$J$7:$J$411,$D36,'25.04'!$K$7:$K$411,W$3) -> 0 | X36: =sumifs('25.04'!$H$7:$H$411,'25.04'!$J$7:$J$411,$D36,'25.04'!$K$7:$K$411,X$3) -> 0 | Y36: =sumifs('25.04'!$H$7:$H$411,'25.04'!$J$7:$J$411,$D36,'25.04'!$K$7:$K$411,Y$3) -> 0 | Z36: =sumifs('25.04'!$H$7:$H$411,'25.04'!$J$7:$J$411,$D36,'25.04'!$K$7:$K$411,Z$3) -> 0 | AA36: =sumifs('25.04'!$H$7:$H$411,'25.04'!$J$7:$J$411,$D36,'25.04'!$K$7:$K$411,AA$3) -> 0 | AB36: =sumifs('25.04'!$H$7:$H$411,'25.04'!$J$7:$J$411,$D36,'25.04'!$K$7:$K$411,AB$3) -> 0 | AC36: =sum(T36:AB36) -> 0
D37: Papers
C38: j | D38: Internet | E38: =sumifs('25.04'!$H$7:$H$411,'25.04'!$G$7:$G$411,$D38,'25.04'!$F$7:$F$411,E$3) -> 0 | F38: =sumifs('25.04'!$H$7:$H$411,'25.04'!$G$7:$G$411,$D38,'25.04'!$F$7:$F$411,F$3) -> 0 | G38: =sumifs('25.04'!$H$7:$H$411,'25.04'!$G$7:$G$411,$D38,'25.04'!$F$7:$F$411,G$3) -> 0 | H38: =sumifs('25.04'!$H$7:$H$411,'25.04'!$G$7:$G$411,$D38,'25.04'!$F$7:$F$411,H$3) -> 0 | I38: =sumifs('25.04'!$H$7:$H$411,'25.04'!$G$7:$G$411,$D38,'25.04'!$F$7:$F$411,I$3) -> 0 | J38: =sumifs('25.04'!$H$7:$H$411,'25.04'!$G$7:$G$411,$D38,'25.04'!$F$7:$F$411,J$3) -> 0 | K38: =sumifs('25.04'!$H$7:$H$411,'25.04'!$G$7:$G$411,$D38,'25.04'!$F$7:$F$411,K$3) -> 0 | L38: =sumifs('25.04'!$H$7:$H$411,'25.04'!$G$7:$G$411,$D38,'25.04'!$F$7:$F$411,L$3) -> 0 | M38: =sumifs('25.04'!$H$7:$H$411,'25.04'!$G$7:$G$411,$D38,'25.04'!$F$7:$F$411,M$3) -> 0 | N38: =sum(E38:M38) -> 0 | P38: =N38/sum(N$29:N$47) -> 0 | Q38: =N38/sum(N$36:N$40) -> #DIV/0! | T38: =sumifs('25.04'!$H$7:$H$411,'25.04'!$J$7:$J$411,$D38,'25.04'!$K$7:$K$411,T$3) -> 0 | U38: =sumifs('25.04'!$H$7:$H$411,'25.04'!$J$7:$J$411,$D38,'25.04'!$K$7:$K$411,U$3) -> 0 | V38: =sumifs('25.04'!$H$7:$H$411,'25.04'!$J$7:$J$411,$D38,'25.04'!$K$7:$K$411,V$3) -> 0 | W38: =sumifs('25.04'!$H$7:$H$411,'25.04'!$J$7:$J$411,$D38,'25.04'!$K$7:$K$411,W$3) -> 0 | X38: =sumifs('25.04'!$H$7:$H$411,'25.04'!$J$7:$J$411,$D38,'25.04'!$K$7:$K$411,X$3) -> 0 | Y38: =sumifs('25.04'!$H$7:$H$411,'25.04'!$J$7:$J$411,$D38,'25.04'!$K$7:$K$411,Y$3) -> 0 | Z38: =sumifs('25.04'!$H$7:$H$411,'25.04'!$J$7:$J$411,$D38,'25.04'!$K$7:$K$411,Z$3) -> 0 | AA38: =sumifs('25.04'!$H$7:$H$411,'25.04'!$J$7:$J$411,$D38,'25.04'!$K$7:$K$411,AA$3) -> 0 | AB38: =sumifs('25.04'!$H$7:$H$411,'25.04'!$J$7:$J$411,$D38,'25.04'!$K$7:$K$411,AB$3) -> 0 | AC38: =sum(T38:AB38) -> 0
C39: k | D39: Spotify | E39: =sumifs('25.04'!$H$7:$H$411,'25.04'!$G$7:$G$411,$D39,'25.04'!$F$7:$F$411,E$3) -> 0 | F39: =sumifs('25.04'!$H$7:$H$411,'25.04'!$G$7:$G$411,$D39,'25.04'!$F$7:$F$411,F$3) -> 0 | G39: =sumifs('25.04'!$H$7:$H$411,'25.04'!$G$7:$G$411,$D39,'25.04'!$F$7:$F$411,G$3) -> 0 | H39: =sumifs('25.04'!$H$7:$H$411,'25.04'!$G$7:$G$411,$D39,'25.04'!$F$7:$F$411,H$3) -> 0 | I39: =sumifs('25.04'!$H$7:$H$411,'25.04'!$G$7:$G$411,$D39,'25.04'!$F$7:$F$411,I$3) -> 0 | J39: =sumifs('25.04'!$H$7:$H$411,'25.04'!$G$7:$G$411,$D39,'25.04'!$F$7:$F$411,J$3) -> 0 | K39: =sumifs('25.04'!$H$7:$H$411,'25.04'!$G$7:$G$411,$D39,'25.04'!$F$7:$F$411,K$3) -> 0 | L39: =sumifs('25.04'!$H$7:$H$411,'25.04'!$G$7:$G$411,$D39,'25.04'!$F$7:$F$411,L$3) -> 0 | M39: =sumifs('25.04'!$H$7:$H$411,'25.04'!$G$7:$G$411,$D39,'25.04'!$F$7:$F$411,M$3) -> 0 | N39: =sum(E39:M39) -> 0 | P39: =N39/sum(N$29:N$47) -> 0 | Q39: =N39/sum(N$36:N$40) -> #DIV/0! | T39: =sumifs('25.04'!$H$7:$H$411,'25.04'!$J$7:$J$411,$D39,'25.04'!$K$7:$K$411,T$3) -> 0 | U39: =sumifs('25.04'!$H$7:$H$411,'25.04'!$J$7:$J$411,$D39,'25.04'!$K$7:$K$411,U$3) -> 0 | V39: =sumifs('25.04'!$H$7:$H$411,'25.04'!$J$7:$J$411,$D39,'25.04'!$K$7:$K$411,V$3) -> 0 | W39: =sumifs('25.04'!$H$7:$H$411,'25.04'!$J$7:$J$411,$D39,'25.04'!$K$7:$K$411,W$3) -> 0 | X39: =sumifs('25.04'!$H$7:$H$411,'25.04'!$J$7:$J$411,$D39,'25.04'!$K$7:$K$411,X$3) -> 0 | Y39: =sumifs('25.04'!$H$7:$H$411,'25.04'!$J$7:$J$411,$D39,'25.04'!$K$7:$K$411,Y$3) -> 0 | Z39: =sumifs('25.04'!$H$7:$H$411,'25.04'!$J$7:$J$411,$D39,'25.04'!$K$7:$K$411,Z$3) -> 0 | AA39: =sumifs('25.04'!$H$7:$H$411,'25.04'!$J$7:$J$411,$D39,'25.04'!$K$7:$K$411,AA$3) -> 0 | AB39: =sumifs('25.04'!$H$7:$H$411,'25.04'!$J$7:$J$411,$D39,'25.04'!$K$7:$K$411,AB$3) -> 0 | AC39: =sum(T39:AB39) -> 0
C40: l | D40: Banking information | E40: =sumifs('25.04'!$H$7:$H$411,'25.04'!$G$7:$G$411,$D40,'25.04'!$F$7:$F$411,E$3) -> 0 | F40: =sumifs('25.04'!$H$7:$H$411,'25.04'!$G$7:$G$411,$D40,'25.04'!$F$7:$F$411,F$3) -> 0 | G40: =sumifs('25.04'!$H$7:$H$411,'25.04'!$G$7:$G$411,$D40,'25.04'!$F$7:$F$411,G$3) -> 0 | H40: =sumifs('25.04'!$H$7:$H$411,'25.04'!$G$7:$G$411,$D40,'25.04'!$F$7:$F$411,H$3) -> 0 | I40: =sumifs('25.04'!$H$7:$H$411,'25.04'!$G$7:$G$411,$D40,'25.04'!$F$7:$F$411,I$3) -> 0 | J40: =sumifs('25.04'!$H$7:$H$411,'25.04'!$G$7:$G$411,$D40,'25.04'!$F$7:$F$411,J$3) -> 0 | K40: =sumifs('25.04'!$H$7:$H$411,'25.04'!$G$7:$G$411,$D40,'25.04'!$F$7:$F$411,K$3) -> 0 | L40: =sumifs('25.04'!$H$7:$H$411,'25.04'!$G$7:$G$411,$D40,'25.04'!$F$7:$F$411,L$3) -> 0 | M40: =sumifs('25.04'!$H$7:$H$411,'25.04'!$G$7:$G$411,$D40,'25.04'!$F$7:$F$411,M$3) -> 0 | N40: =sum(E40:M40) -> 0 | P40: =N40/sum(N$29:N$47) -> 0 | Q40: =N40/sum(N$36:N$40) -> #DIV/0! | T40: =sumifs('25.04'!$H$7:$H$411,'25.04'!$J$7:$J$411,$D40,'25.04'!$K$7:$K$411,T$3) -> 0 | U40: =sumifs('25.04'!$H$7:$H$411,'25.04'!$J$7:$J$411,$D40,'25.04'!$K$7:$K$411,U$3) -> 0 | V40: =sumifs('25.04'!$H$7:$H$411,'25.04'!$J$7:$J$411,$D40,'25.04'!$K$7:$K$411,V$3) -> 0 | W40: =sumifs('25.04'!$H$7:$H$411,'25.04'!$J$7:$J$411,$D40,'25.04'!$K$7:$K$411,W$3) -> 0 | X40: =sumifs('25.04'!$H$7:$H$411,'25.04'!$J$7:$J$411,$D40,'25.04'!$K$7:$K$411,X$3) -> 0 | Y40: =sumifs('25.04'!$H$7:$H$411,'25.04'!$J$7:$J$411,$D40,'25.04'!$K$7:$K$411,Y$3) -> 0 | Z40: =sumifs('25.04'!$H$7:$H$411,'25.04'!$J$7:$J$411,$D40,'25.04'!$K$7:$K$411,Z$3) -> 0 | AA40: =sumifs('25.04'!$H$7:$H$411,'25.04'!$J$7:$J$411,$D40,'25.04'!$K$7:$K$411,AA$3) -> 0 | AB40: =sumifs('25.04'!$H$7:$H$411,'25.04'!$J$7:$J$411,$D40,'25.04'!$K$7:$K$411,AB$3) -> 0 | AC40: =sum(T40:AB40) -> 0
C41: m | D41: Fuel | E41: =sumifs('25.04'!$H$7:$H$411,'25.04'!$G$7:$G$411,$D41,'25.04'!$F$7:$F$411,E$3) -> 0 | F41: =sumifs('25.04'!$H$7:$H$411,'25.04'!$G$7:$G$411,$D41,'25.04'!$F$7:$F$411,F$3) -> 0 | G41: =sumifs('25.04'!$H$7:$H$411,'25.04'!$G$7:$G$411,$D41,'25.04'!$F$7:$F$411,G$3) -> 0 | H41: =sumifs('25.04'!$H$7:$H$411,'25.04'!$G$7:$G$411,$D41,'25.04'!$F$7:$F$411,H$3) -> 0 | I41: =sumifs('25.04'!$H$7:$H$411,'25.04'!$G$7:$G$411,$D41,'25.04'!$F$7:$F$411,I$3) -> 0 | J41: =sumifs('25.04'!$H$7:$H$411,'25.04'!$G$7:$G$411,$D41,'25.04'!$F$7:$F$411,J$3) -> 0 | K41: =sumifs('25.04'!$H$7:$H$411,'25.04'!$G$7:$G$411,$D41,'25.04'!$F$7:$F$411,K$3) -> 0 | L41: =sumifs('25.04'!$H$7:$H$411,'25.04'!$G$7:$G$411,$D41,'25.04'!$F$7:$F$411,L$3) -> 0 | M41: =sumifs('25.04'!$H$7:$H$411,'25.04'!$G$7:$G$411,$D41,'25.04'!$F$7:$F$411,M$3) -> 0 | N41: =sum(E41:M41) -> 0 | P41: =N41/sum(N$29:N$47) -> 0 | Q41: =N41/sum(N$41:N$43) -> #DIV/0! | T41: =sumifs('25.04'!$H$7:$H$411,'25.04'!$J$7:$J$411,$D41,'25.04'!$K$7:$K$411,T$3) -> 0 | U41: =sumifs('25.04'!$H$7:$H$411,'25.04'!$J$7:$J$411,$D41,'25.04'!$K$7:$K$411,U$3) -> 0 | V41: =sumifs('25.04'!$H$7:$H$411,'25.04'!$J$7:$J$411,$D41,'25.04'!$K$7:$K$411,V$3) -> 0 | W41: =sumifs('25.04'!$H$7:$H$411,'25.04'!$J$7:$J$411,$D41,'25.04'!$K$7:$K$411,W$3) -> 0 | X41: =sumifs('25.04'!$H$7:$H$411,'25.04'!$J$7:$J$411,$D41,'25.04'!$K$7:$K$411,X$3) -> 0 | Y41: =sumifs('25.04'!$H$7:$H$411,'25.04'!$J$7:$J$411,$D41,'25.04'!$K$7:$K$411,Y$3) -> 0 | Z41: =sumifs('25.04'!$H$7:$H$411,'25.04'!$J$7:$J$411,$D41,'25.04'!$K$7:$K$411,Z$3) -> 0 | AA41: =sumifs('25.04'!$H$7:$H$411,'25.04'!$J$7:$J$411,$D41,'25.04'!$K$7:$K$411,AA$3) -> 0 | AB41: =sumifs('25.04'!$H$7:$H$411,'25.04'!$J$7:$J$411,$D41,'25.04'!$K$7:$K$411,AB$3) -> 0 | AC41: =sum(T41:AB41) -> 0
C42: n | D42: Motorcycle maintenance | E42: =sumifs('25.04'!$H$7:$H$411,'25.04'!$G$7:$G$411,$D42,'25.04'!$F$7:$F$411,E$3) -> 0 | F42: =sumifs('25.04'!$H$7:$H$411,'25.04'!$G$7:$G$411,$D42,'25.04'!$F$7:$F$411,F$3) -> 0 | G42: =sumifs('25.04'!$H$7:$H$411,'25.04'!$G$7:$G$411,$D42,'25.04'!$F$7:$F$411,G$3) -> 0 | H42: =sumifs('25.04'!$H$7:$H$411,'25.04'!$G$7:$G$411,$D42,'25.04'!$F$7:$F$411,H$3) -> 0 | I42: =sumifs('25.04'!$H$7:$H$411,'25.04'!$G$7:$G$411,$D42,'25.04'!$F$7:$F$411,I$3) -> 0 | J42: =sumifs('25.04'!$H$7:$H$411,'25.04'!$G$7:$G$411,$D42,'25.04'!$F$7:$F$411,J$3) -> 0 | K42: =sumifs('25.04'!$H$7:$H$411,'25.04'!$G$7:$G$411,$D42,'25.04'!$F$7:$F$411,K$3) -> 0 | L42: =sumifs('25.04'!$H$7:$H$411,'25.04'!$G$7:$G$411,$D42,'25.04'!$F$7:$F$411,L$3) -> 0 | M42: =sumifs('25.04'!$H$7:$H$411,'25.04'!$G$7:$G$411,$D42,'25.04'!$F$7:$F$411,M$3) -> 0 | N42: =sum(E42:M42) -> 0 | P42: =N42/sum(N$29:N$47) -> 0 | Q42: =N42/sum(N$41:N$43) -> #DIV/0! | T42: =sumifs('25.04'!$H$7:$H$411,'25.04'!$J$7:$J$411,$D42,'25.04'!$K$7:$K$411,T$3) -> 0 | U42: =sumifs('25.04'!$H$7:$H$411,'25.04'!$J$7:$J$411,$D42,'25.04'!$K$7:$K$411,U$3) -> 0 | V42: =sumifs('25.04'!$H$7:$H$411,'25.04'!$J$7:$J$411,$D42,'25.04'!$K$7:$K$411,V$3) -> 0 | W42: =sumifs('25.04'!$H$7:$H$411,'25.04'!$J$7:$J$411,$D42,'25.04'!$K$7:$K$411,W$3) -> 0 | X42: =sumifs('25.04'!$H$7:$H$411,'25.04'!$J$7:$J$411,$D42,'25.04'!$K$7:$K$411,X$3) -> 0 | Y42: =sumifs('25.04'!$H$7:$H$411,'25.04'!$J$7:$J$411,$D42,'25.04'!$K$7:$K$411,Y$3) -> 0 | Z42: =sumifs('25.04'!$H$7:$H$411,'25.04'!$J$7:$J$411,$D42,'25.04'!$K$7:$K$411,Z$3) -> 0 | AA42: =sumifs('25.04'!$H$7:$H$411,'25.04'!$J$7:$J$411,$D42,'25.04'!$K$7:$K$411,AA$3) -> 0 | AB42: =sumifs('25.04'!$H$7:$H$411,'25.04'!$J$7:$J$411,$D42,'25.04'!$K$7:$K$411,AB$3) -> 0 | AC42: =sum(T42:AB42) -> 0
C43: o | D43: Parking | E43: =sumifs('25.04'!$H$7:$H$411,'25.04'!$G$7:$G$411,$D43,'25.04'!$F$7:$F$411,E$3) -> 0 | F43: =sumifs('25.04'!$H$7:$H$411,'25.04'!$G$7:$G$411,$D43,'25.04'!$F$7:$F$411,F$3) -> 0 | G43: =sumifs('25.04'!$H$7:$H$411,'25.04'!$G$7:$G$411,$D43,'25.04'!$F$7:$F$411,G$3) -> 0 | H43: =sumifs('25.04'!$H$7:$H$411,'25.04'!$G$7:$G$411,$D43,'25.04'!$F$7:$F$411,H$3) -> 0 | I43: =sumifs('25.04'!$H$7:$H$411,'25.04'!$G$7:$G$411,$D43,'25.04'!$F$7:$F$411,I$3) -> 0 | J43: =sumifs('25.04'!$H$7:$H$411,'25.04'!$G$7:$G$411,$D43,'25.04'!$F$7:$F$411,J$3) -> 0 | K43: =sumifs('25.04'!$H$7:$H$411,'25.04'!$G$7:$G$411,$D43,'25.04'!$F$7:$F$411,K$3) -> 0 | L43: =sumifs('25.04'!$H$7:$H$411,'25.04'!$G$7:$G$411,$D43,'25.04'!$F$7:$F$411,L$3) -> 0 | M43: =sumifs('25.04'!$H$7:$H$411,'25.04'!$G$7:$G$411,$D43,'25.04'!$F$7:$F$411,M$3) -> 0 | N43: =sum(E43:M43) -> 0 | P43: =N43/sum(N$29:N$47) -> 0 | Q43: =N43/sum(N$41:N$43) -> #DIV/0! | T43: =sumifs('25.04'!$H$7:$H$411,'25.04'!$J$7:$J$411,$D43,'25.04'!$K$7:$K$411,T$3) -> 0 | U43: =sumifs('25.04'!$H$7:$H$411,'25.04'!$J$7:$J$411,$D43,'25.04'!$K$7:$K$411,U$3) -> 0 | V43: =sumifs('25.04'!$H$7:$H$411,'25.04'!$J$7:$J$411,$D43,'25.04'!$K$7:$K$411,V$3) -> 0 | W43: =sumifs('25.04'!$H$7:$H$411,'25.04'!$J$7:$J$411,$D43,'25.04'!$K$7:$K$411,W$3) -> 0 | X43: =sumifs('25.04'!$H$7:$H$411,'25.04'!$J$7:$J$411,$D43,'25.04'!$K$7:$K$411,X$3) -> 0 | Y43: =sumifs('25.04'!$H$7:$H$411,'25.04'!$J$7:$J$411,$D43,'25.04'!$K$7:$K$411,Y$3) -> 0 | Z43: =sumifs('25.04'!$H$7:$H$411,'25.04'!$J$7:$J$411,$D43,'25.04'!$K$7:$K$411,Z$3) -> 0 | AA43: =sumifs('25.04'!$H$7:$H$411,'25.04'!$J$7:$J$411,$D43,'25.04'!$K$7:$K$411,AA$3) -> 0 | AB43: =sumifs('25.04'!$H$7:$H$411,'25.04'!$J$7:$J$411,$D43,'25.04'!$K$7:$K$411,AB$3) -> 0 | AC43: =sum(T43:AB43) -> 0
C44: p | D44: Cleaning home | E44: =sumifs('25.04'!$H$7:$H$411,'25.04'!$G$7:$G$411,$D44,'25.04'!$F$7:$F$411,E$3) -> 0 | F44: =sumifs('25.04'!$H$7:$H$411,'25.04'!$G$7:$G$411,$D44,'25.04'!$F$7:$F$411,F$3) -> 0 | G44: =sumifs('25.04'!$H$7:$H$411,'25.04'!$G$7:$G$411,$D44,'25.04'!$F$7:$F$411,G$3) -> 0 | H44: =sumifs('25.04'!$H$7:$H$411,'25.04'!$G$7:$G$411,$D44,'25.04'!$F$7:$F$411,H$3) -> 0 | I44: =sumifs('25.04'!$H$7:$H$411,'25.04'!$G$7:$G$411,$D44,'25.04'!$F$7:$F$411,I$3) -> 0 | J44: =sumifs('25.04'!$H$7:$H$411,'25.04'!$G$7:$G$411,$D44,'25.04'!$F$7:$F$411,J$3) -> 0 | K44: =sumifs('25.04'!$H$7:$H$411,'25.04'!$G$7:$G$411,$D44,'25.04'!$F$7:$F$411,K$3) -> 0 | L44: =sumifs('25.04'!$H$7:$H$411,'25.04'!$G$7:$G$411,$D44,'25.04'!$F$7:$F$411,L$3) -> 0 | M44: =sumifs('25.04'!$H$7:$H$411,'25.04'!$G$7:$G$411,$D44,'25.04'!$F$7:$F$411,M$3) -> 0 | N44: =sum(E44:M44) -> 0 | P44: =N44/sum(N$29:N$47) -> 0 | Q44: =N44/sum(N$44:N$46) -> #DIV/0! | T44: =sumifs('25.04'!$H$7:$H$411,'25.04'!$J$7:$J$411,$D44,'25.04'!$K$7:$K$411,T$3) -> 0 | U44: =sumifs('25.04'!$H$7:$H$411,'25.04'!$J$7:$J$411,$D44,'25.04'!$K$7:$K$411,U$3) -> 0 | V44: =sumifs('25.04'!$H$7:$H$411,'25.04'!$J$7:$J$411,$D44,'25.04'!$K$7:$K$411,V$3) -> 0 | W44: =sumifs('25.04'!$H$7:$H$411,'25.04'!$J$7:$J$411,$D44,'25.04'!$K$7:$K$411,W$3) -> 0 | X44: =sumifs('25.04'!$H$7:$H$411,'25.04'!$J$7:$J$411,$D44,'25.04'!$K$7:$K$411,X$3) -> 0 | Y44: =sumifs('25.04'!$H$7:$H$411,'25.04'!$J$7:$J$411,$D44,'25.04'!$K$7:$K$411,Y$3) -> 0 | Z44: =sumifs('25.04'!$H$7:$H$411,'25.04'!$J$7:$J$411,$D44,'25.04'!$K$7:$K$411,Z$3) -> 0 | AA44: =sumifs('25.04'!$H$7:$H$411,'25.04'!$J$7:$J$411,$D44,'25.04'!$K$7:$K$411,AA$3) -> 0 | AB44: =sumifs('25.04'!$H$7:$H$411,'25.04'!$J$7:$J$411,$D44,'25.04'!$K$7:$K$411,AB$3) -> 0 | AC44: =sum(T44:AB44) -> 0
C45: q | D45: House shopping | E45: =sumifs('25.04'!$H$7:$H$411,'25.04'!$G$7:$G$411,$D45,'25.04'!$F$7:$F$411,E$3) -> 0 | F45: =sumifs('25.04'!$H$7:$H$411,'25.04'!$G$7:$G$411,$D45,'25.04'!$F$7:$F$411,F$3) -> 0 | G45: =sumifs('25.04'!$H$7:$H$411,'25.04'!$G$7:$G$411,$D45,'25.04'!$F$7:$F$411,G$3) -> 0 | H45: =sumifs('25.04'!$H$7:$H$411,'25.04'!$G$7:$G$411,$D45,'25.04'!$F$7:$F$411,H$3) -> 0 | I45: =sumifs('25.04'!$H$7:$H$411,'25.04'!$G$7:$G$411,$D45,'25.04'!$F$7:$F$411,I$3) -> 0 | J45: =sumifs('25.04'!$H$7:$H$411,'25.04'!$G$7:$G$411,$D45,'25.04'!$F$7:$F$411,J$3) -> 0 | K45: =sumifs('25.04'!$H$7:$H$411,'25.04'!$G$7:$G$411,$D45,'25.04'!$F$7:$F$411,K$3) -> 0 | L45: =sumifs('25.04'!$H$7:$H$411,'25.04'!$G$7:$G$411,$D45,'25.04'!$F$7:$F$411,L$3) -> 0 | M45: =sumifs('25.04'!$H$7:$H$411,'25.04'!$G$7:$G$411,$D45,'25.04'!$F$7:$F$411,M$3) -> 0 | N45: =sum(E45:M45) -> 0 | P45: =N45/sum(N$29:N$47) -> 0 | Q45: =N45/sum(N$44:N$46) -> #DIV/0! | T45: =sumifs('25.04'!$H$7:$H$411,'25.04'!$J$7:$J$411,$D45,'25.04'!$K$7:$K$411,T$3) -> 0 | U45: =sumifs('25.04'!$H$7:$H$411,'25.04'!$J$7:$J$411,$D45,'25.04'!$K$7:$K$411,U$3) -> 0 | V45: =sumifs('25.04'!$H$7:$H$411,'25.04'!$J$7:$J$411,$D45,'25.04'!$K$7:$K$411,V$3) -> 0 | W45: =sumifs('25.04'!$H$7:$H$411,'25.04'!$J$7:$J$411,$D45,'25.04'!$K$7:$K$411,W$3) -> 0 | X45: =sumifs('25.04'!$H$7:$H$411,'25.04'!$J$7:$J$411,$D45,'25.04'!$K$7:$K$411,X$3) -> 0 | Y45: =sumifs('25.04'!$H$7:$H$411,'25.04'!$J$7:$J$411,$D45,'25.04'!$K$7:$K$411,Y$3) -> 0 | Z45: =sumifs('25.04'!$H$7:$H$411,'25.04'!$J$7:$J$411,$D45,'25.04'!$K$7:$K$411,Z$3) -> 0 | AA45: =sumifs('25.04'!$H$7:$H$411,'25.04'!$J$7:$J$411,$D45,'25.04'!$K$7:$K$411,AA$3) -> 0 | AB45: =sumifs('25.04'!$H$7:$H$411,'25.04'!$J$7:$J$411,$D45,'25.04'!$K$7:$K$411,AB$3) -> 0 | AC45: =sum(T45:AB45) -> 0
C46: r | D46: House repair | E46: =sumifs('25.04'!$H$7:$H$411,'25.04'!$G$7:$G$411,$D46,'25.04'!$F$7:$F$411,E$3) -> 0 | F46: =sumifs('25.04'!$H$7:$H$411,'25.04'!$G$7:$G$411,$D46,'25.04'!$F$7:$F$411,F$3) -> 0 | G46: =sumifs('25.04'!$H$7:$H$411,'25.04'!$G$7:$G$411,$D46,'25.04'!$F$7:$F$411,G$3) -> 0 | H46: =sumifs('25.04'!$H$7:$H$411,'25.04'!$G$7:$G$411,$D46,'25.04'!$F$7:$F$411,H$3) -> 0 | I46: =sumifs('25.04'!$H$7:$H$411,'25.04'!$G$7:$G$411,$D46,'25.04'!$F$7:$F$411,I$3) -> 0 | J46: =sumifs('25.04'!$H$7:$H$411,'25.04'!$G$7:$G$411,$D46,'25.04'!$F$7:$F$411,J$3) -> 0 | K46: =sumifs('25.04'!$H$7:$H$411,'25.04'!$G$7:$G$411,$D46,'25.04'!$F$7:$F$411,K$3) -> 0 | L46: =sumifs('25.04'!$H$7:$H$411,'25.04'!$G$7:$G$411,$D46,'25.04'!$F$7:$F$411,L$3) -> 0 | M46: =sumifs('25.04'!$H$7:$H$411,'25.04'!$G$7:$G$411,$D46,'25.04'!$F$7:$F$411,M$3) -> 0 | N46: =sum(E46:M46) -> 0 | P46: =N46/sum(N$29:N$47) -> 0 | Q46: =N46/sum(N$44:N$46) -> #DIV/0! | T46: =sumifs('25.04'!$H$7:$H$411,'25.04'!$J$7:$J$411,$D46,'25.04'!$K$7:$K$411,T$3) -> 0 | U46: =sumifs('25.04'!$H$7:$H$411,'25.04'!$J$7:$J$411,$D46,'25.04'!$K$7:$K$411,U$3) -> 0 | V46: =sumifs('25.04'!$H$7:$H$411,'25.04'!$J$7:$J$411,$D46,'25.04'!$K$7:$K$411,V$3) -> 0 | W46: =sumifs('25.04'!$H$7:$H$411,'25.04'!$J$7:$J$411,$D46,'25.04'!$K$7:$K$411,W$3) -> 0 | X46: =sumifs('25.04'!$H$7:$H$411,'25.04'!$J$7:$J$411,$D46,'25.04'!$K$7:$K$411,X$3) -> 0 | Y46: =sumifs('25.04'!$H$7:$H$411,'25.04'!$J$7:$J$411,$D46,'25.04'!$K$7:$K$411,Y$3) -> 0 | Z46: =sumifs('25.04'!$H$7:$H$411,'25.04'!$J$7:$J$411,$D46,'25.04'!$K$7:$K$411,Z$3) -> 0 | AA46: =sumifs('25.04'!$H$7:$H$411,'25.04'!$J$7:$J$411,$D46,'25.04'!$K$7:$K$411,AA$3) -> 0 | AB46: =sumifs('25.04'!$H$7:$H$411,'25.04'!$J$7:$J$411,$D46,'25.04'!$K$7:$K$411,AB$3) -> 0 | AC46: =sum(T46:AB46) -> 0
C47: s | D47: Electricity | E47: =sumifs('25.04'!$H$7:$H$411,'25.04'!$G$7:$G$411,$D47,'25.04'!$F$7:$F$411,E$3) -> 0 | F47: =sumifs('25.04'!$H$7:$H$411,'25.04'!$G$7:$G$411,$D47,'25.04'!$F$7:$F$411,F$3) -> 0 | G47: =sumifs('25.04'!$H$7:$H$411,'25.04'!$G$7:$G$411,$D47,'25.04'!$F$7:$F$411,G$3) -> 0 | H47: =sumifs('25.04'!$H$7:$H$411,'25.04'!$G$7:$G$411,$D47,'25.04'!$F$7:$F$411,H$3) -> 0 | I47: =sumifs('25.04'!$H$7:$H$411,'25.04'!$G$7:$G$411,$D47,'25.04'!$F$7:$F$411,I$3) -> 0 | J47: =sumifs('25.04'!$H$7:$H$411,'25.04'!$G$7:$G$411,$D47,'25.04'!$F$7:$F$411,J$3) -> 0 | K47: =sumifs('25.04'!$H$7:$H$411,'25.04'!$G$7:$G$411,$D47,'25.04'!$F$7:$F$411,K$3) -> 0 | L47: =sumifs('25.04'!$H$7:$H$411,'25.04'!$G$7:$G$411,$D47,'25.04'!$F$7:$F$411,L$3) -> 0 | M47: =sumifs('25.04'!$H$7:$H$411,'25.04'!$G$7:$G$411,$D47,'25.04'!$F$7:$F$411,M$3) -> 0 | N47: =sum(E47:M47) -> 0 | P47: =N47/sum(N$29:N$47) -> 0 | T47: =sumifs('25.04'!$H$7:$H$411,'25.04'!$J$7:$J$411,$D47,'25.04'!$K$7:$K$411,T$3) -> 0 | U47: =sumifs('25.04'!$H$7:$H$411,'25.04'!$J$7:$J$411,$D47,'25.04'!$K$7:$K$411,U$3) -> 0 | V47: =sumifs('25.04'!$H$7:$H$411,'25.04'!$J$7:$J$411,$D47,'25.04'!$K$7:$K$411,V$3) -> 0 | W47: =sumifs('25.04'!$H$7:$H$411,'25.04'!$J$7:$J$411,$D47,'25.04'!$K$7:$K$411,W$3) -> 0 | X47: =sumifs('25.04'!$H$7:$H$411,'25.04'!$J$7:$J$411,$D47,'25.04'!$K$7:$K$411,X$3) -> 0 | Y47: =sumifs('25.04'!$H$7:$H$411,'25.04'!$J$7:$J$411,$D47,'25.04'!$K$7:$K$411,Y$3) -> 0 | Z47: =sumifs('25.04'!$H$7:$H$411,'25.04'!$J$7:$J$411,$D47,'25.04'!$K$7:$K$411,Z$3) -> 0 | AA47: =sumifs('25.04'!$H$7:$H$411,'25.04'!$J$7:$J$411,$D47,'25.04'!$K$7:$K$411,AA$3) -> 0 | AB47: =sumifs('25.04'!$H$7:$H$411,'25.04'!$J$7:$J$411,$D47,'25.04'!$K$7:$K$411,AB$3) -> 0 | AC47: =sum(T47:AB47) -> 0
A48: 6 | B48: Savings | C48: 44932 | D48: Savings | E48: =sumifs('25.04'!$H$7:$H$411,'25.04'!$G$7:$G$411,$D48,'25.04'!$F$7:$F$411,E$3) -> 0 | F48: =sumifs('25.04'!$H$7:$H$411,'25.04'!$G$7:$G$411,$D48,'25.04'!$F$7:$F$411,F$3) -> 0 | G48: =sumifs('25.04'!$H$7:$H$411,'25.04'!$G$7:$G$411,$D48,'25.04'!$F$7:$F$411,G$3) -> 0 | H48: =sumifs('25.04'!$H$7:$H$411,'25.04'!$G$7:$G$411,$D48,'25.04'!$F$7:$F$411,H$3) -> 0 | I48: =sumifs('25.04'!$H$7:$H$411,'25.04'!$G$7:$G$411,$D48,'25.04'!$F$7:$F$411,I$3) -> 0 | J48: =sumifs('25.04'!$H$7:$H$411,'25.04'!$G$7:$G$411,$D48,'25.04'!$F$7:$F$411,J$3) -> 0 | K48: =sumifs('25.04'!$H$7:$H$411,'25.04'!$G$7:$G$411,$D48,'25.04'!$F$7:$F$411,K$3) -> 0 | L48: =sumifs('25.04'!$H$7:$H$411,'25.04'!$G$7:$G$411,$D48,'25.04'!$F$7:$F$411,L$3) -> 0 | M48: =sumifs('25.04'!$H$7:$H$411,'25.04'!$G$7:$G$411,$D48,'25.04'!$F$7:$F$411,M$3) -> 0 | N48: =sum(E48:M48) -> 0 | P48: =N48/sum(N$48:N$49) -> #DIV/0! | T48: =sumifs('25.04'!$H$7:$H$411,'25.04'!$J$7:$J$411,$D48,'25.04'!$K$7:$K$411,T$3) -> 0 | U48: =sumifs('25.04'!$H$7:$H$411,'25.04'!$J$7:$J$411,$D48,'25.04'!$K$7:$K$411,U$3) -> 0 | V48: =sumifs('25.04'!$H$7:$H$411,'25.04'!$J$7:$J$411,$D48,'25.04'!$K$7:$K$411,V$3) -> 0 | W48: =sumifs('25.04'!$H$7:$H$411,'25.04'!$J$7:$J$411,$D48,'25.04'!$K$7:$K$411,W$3) -> 0 | X48: =sumifs('25.04'!$H$7:$H$411,'25.04'!$J$7:$J$411,$D48,'25.04'!$K$7:$K$411,X$3) -> 0 | Y48: =sumifs('25.04'!$H$7:$H$411,'25.04'!$J$7:$J$411,$D48,'25.04'!$K$7:$K$411,Y$3) -> 0 | Z48: =sumifs('25.04'!$H$7:$H$411,'25.04'!$J$7:$J$411,$D48,'25.04'!$K$7:$K$411,Z$3) -> 0 | AA48: =sumifs('25.04'!$H$7:$H$411,'25.04'!$J$7:$J$411,$D48,'25.04'!$K$7:$K$411,AA$3) -> 0 | AB48: =sumifs('25.04'!$H$7:$H$411,'25.04'!$J$7:$J$411,$D48,'25.04'!$K$7:$K$411,AB$3) -> 0 | AC48: =sum(T48:AB48) -> 0
C49: 44963 | D49: Life Insurance | E49: =sumifs('25.04'!$H$7:$H$411,'25.04'!$G$7:$G$411,$D49,'25.04'!$F$7:$F$411,E$3) -> 0 | F49: =sumifs('25.04'!$H$7:$H$411,'25.04'!$G$7:$G$411,$D49,'25.04'!$F$7:$F$411,F$3) -> 0 | G49: =sumifs('25.04'!$H$7:$H$411,'25.04'!$G$7:$G$411,$D49,'25.04'!$F$7:$F$411,G$3) -> 0 | H49: =sumifs('25.04'!$H$7:$H$411,'25.04'!$G$7:$G$411,$D49,'25.04'!$F$7:$F$411,H$3) -> 0 | I49: =sumifs('25.04'!$H$7:$H$411,'25.04'!$G$7:$G$411,$D49,'25.04'!$F$7:$F$411,I$3) -> 0 | J49: =sumifs('25.04'!$H$7:$H$411,'25.04'!$G$7:$G$411,$D49,'25.04'!$F$7:$F$411,J$3) -> 0 | K49: =sumifs('25.04'!$H$7:$H$411,'25.04'!$G$7:$G$411,$D49,'25.04'!$F$7:$F$411,K$3) -> 0 | L49: =sumifs('25.04'!$H$7:$H$411,'25.04'!$G$7:$G$411,$D49,'25.04'!$F$7:$F$411,L$3) -> 0 | M49: =sumifs('25.04'!$H$7:$H$411,'25.04'!$G$7:$G$411,$D49,'25.04'!$F$7:$F$411,M$3) -> 0 | N49: =sum(E49:M49) -> 0 | P49: =N49/sum(N$48:N$49) -> #DIV/0! | T49: =sumifs('25.04'!$H$7:$H$411,'25.04'!$J$7:$J$411,$D49,'25.04'!$K$7:$K$411,T$3) -> 0 | U49: =sumifs('25.04'!$H$7:$H$411,'25.04'!$J$7:$J$411,$D49,'25.04'!$K$7:$K$411,U$3) -> 0 | V49: =sumifs('25.04'!$H$7:$H$411,'25.04'!$J$7:$J$411,$D49,'25.04'!$K$7:$K$411,V$3) -> 0 | W49: =sumifs('25.04'!$H$7:$H$411,'25.04'!$J$7:$J$411,$D49,'25.04'!$K$7:$K$411,W$3) -> 0 | X49: =sumifs('25.04'!$H$7:$H$411,'25.04'!$J$7:$J$411,$D49,'25.04'!$K$7:$K$411,X$3) -> 0 | Y49: =sumifs('25.04'!$H$7:$H$411,'25.04'!$J$7:$J$411,$D49,'25.04'!$K$7:$K$411,Y$3) -> 0 | Z49: =sumifs('25.04'!$H$7:$H$411,'25.04'!$J$7:$J$411,$D49,'25.04'!$K$7:$K$411,Z$3) -> 0 | AA49: =sumifs('25.04'!$H$7:$H$411,'25.04'!$J$7:$J$411,$D49,'25.04'!$K$7:$K$411,AA$3) -> 0 | AB49: =sumifs('25.04'!$H$7:$H$411,'25.04'!$J$7:$J$411,$D49,'25.04'!$K$7:$K$411,AB$3) -> 0 | AC49: =sum(T49:AB49) -> 0
A50: 7 | B50: N&M studio | C50: 44933 | D50: Design | E50: =sumifs('25.04'!$H$7:$H$411,'25.04'!$G$7:$G$411,$D50,'25.04'!$F$7:$F$411,E$3) -> 0 | F50: =sumifs('25.04'!$H$7:$H$411,'25.04'!$G$7:$G$411,$D50,'25.04'!$F$7:$F$411,F$3) -> 0 | G50: =sumifs('25.04'!$H$7:$H$411,'25.04'!$G$7:$G$411,$D50,'25.04'!$F$7:$F$411,G$3) -> 0 | H50: =sumifs('25.04'!$H$7:$H$411,'25.04'!$G$7:$G$411,$D50,'25.04'!$F$7:$F$411,H$3) -> 0 | I50: =sumifs('25.04'!$H$7:$H$411,'25.04'!$G$7:$G$411,$D50,'25.04'!$F$7:$F$411,I$3) -> 0 | J50: =sumifs('25.04'!$H$7:$H$411,'25.04'!$G$7:$G$411,$D50,'25.04'!$F$7:$F$411,J$3) -> 0 | K50: =sumifs('25.04'!$H$7:$H$411,'25.04'!$G$7:$G$411,$D50,'25.04'!$F$7:$F$411,K$3) -> 0 | L50: =sumifs('25.04'!$H$7:$H$411,'25.04'!$G$7:$G$411,$D50,'25.04'!$F$7:$F$411,L$3) -> 0 | M50: =sumifs('25.04'!$H$7:$H$411,'25.04'!$G$7:$G$411,$D50,'25.04'!$F$7:$F$411,M$3) -> 0 | N50: =sum(E50:M50) -> 0 | P50: =N50/sum(N$50:N$51) -> #DIV/0! | T50: =sumifs('25.04'!$H$7:$H$411,'25.04'!$J$7:$J$411,$D50,'25.04'!$K$7:$K$411,T$3) -> 0 | U50: =sumifs('25.04'!$H$7:$H$411,'25.04'!$J$7:$J$411,$D50,'25.04'!$K$7:$K$411,U$3) -> 0 | V50: =sumifs('25.04'!$H$7:$H$411,'25.04'!$J$7:$J$411,$D50,'25.04'!$K$7:$K$411,V$3) -> 0 | W50: =sumifs('25.04'!$H$7:$H$411,'25.04'!$J$7:$J$411,$D50,'25.04'!$K$7:$K$411,W$3) -> 0 | X50: =sumifs('25.04'!$H$7:$H$411,'25.04'!$J$7:$J$411,$D50,'25.04'!$K$7:$K$411,X$3) -> 0 | Y50: =sumifs('25.04'!$H$7:$H$411,'25.04'!$J$7:$J$411,$D50,'25.04'!$K$7:$K$411,Y$3) -> 0 | Z50: =sumifs('25.04'!$H$7:$H$411,'25.04'!$J$7:$J$411,$D50,'25.04'!$K$7:$K$411,Z$3) -> 0 | AA50: =sumifs('25.04'!$H$7:$H$411,'25.04'!$J$7:$J$411,$D50,'25.04'!$K$7:$K$411,AA$3) -> 0 | AB50: =sumifs('25.04'!$H$7:$H$411,'25.04'!$J$7:$J$411,$D50,'25.04'!$K$7:$K$411,AB$3) -> 0 | AC50: =sum(T50:AB50) -> 0
C51: 44964 | D51: Construction | E51: =sumifs('25.04'!$H$7:$H$411,'25.04'!$G$7:$G$411,$D51,'25.04'!$F$7:$F$411,E$3) -> 0 | F51: =sumifs('25.04'!$H$7:$H$411,'25.04'!$G$7:$G$411,$D51,'25.04'!$F$7:$F$411,F$3) -> 0 | G51: =sumifs('25.04'!$H$7:$H$411,'25.04'!$G$7:$G$411,$D51,'25.04'!$F$7:$F$411,G$3) -> 0 | H51: =sumifs('25.04'!$H$7:$H$411,'25.04'!$G$7:$G$411,$D51,'25.04'!$F$7:$F$411,H$3) -> 0 | I51: =sumifs('25.04'!$H$7:$H$411,'25.04'!$G$7:$G$411,$D51,'25.04'!$F$7:$F$411,I$3) -> 0 | J51: =sumifs('25.04'!$H$7:$H$411,'25.04'!$G$7:$G$411,$D51,'25.04'!$F$7:$F$411,J$3) -> 0 | K51: =sumifs('25.04'!$H$7:$H$411,'25.04'!$G$7:$G$411,$D51,'25.04'!$F$7:$F$411,K$3) -> 0 | L51: =sumifs('25.04'!$H$7:$H$411,'25.04'!$G$7:$G$411,$D51,'25.04'!$F$7:$F$411,L$3) -> 0 | M51: =sumifs('25.04'!$H$7:$H$411,'25.04'!$G$7:$G$411,$D51,'25.04'!$F$7:$F$411,M$3) -> 0 | N51: =sum(E51:M51) -> 0 | P51: =N51/sum(N$50:N$51) -> #DIV/0! | T51: =sumifs('25.04'!$H$7:$H$411,'25.04'!$J$7:$J$411,$D51,'25.04'!$K$7:$K$411,T$3) -> 0 | U51: =sumifs('25.04'!$H$7:$H$411,'25.04'!$J$7:$J$411,$D51,'25.04'!$K$7:$K$411,U$3) -> 0 | V51: =sumifs('25.04'!$H$7:$H$411,'25.04'!$J$7:$J$411,$D51,'25.04'!$K$7:$K$411,V$3) -> 0 | W51: =sumifs('25.04'!$H$7:$H$411,'25.04'!$J$7:$J$411,$D51,'25.04'!$K$7:$K$411,W$3) -> 0 | X51: =sumifs('25.04'!$H$7:$H$411,'25.04'!$J$7:$J$411,$D51,'25.04'!$K$7:$K$411,X$3) -> 0 | Y51: =sumifs('25.04'!$H$7:$H$411,'25.04'!$J$7:$J$411,$D51,'25.04'!$K$7:$K$411,Y$3) -> 0 | Z51: =sumifs('25.04'!$H$7:$H$411,'25.04'!$J$7:$J$411,$D51,'25.04'!$K$7:$K$411,Z$3) -> 0 | AA51: =sumifs('25.04'!$H$7:$H$411,'25.04'!$J$7:$J$411,$D51,'25.04'!$K$7:$K$411,AA$3) -> 0 | AB51: =sumifs('25.04'!$H$7:$H$411,'25.04'!$J$7:$J$411,$D51,'25.04'!$K$7:$K$411,AB$3) -> 0 | AC51: =sum(T51:AB51) -> 0
A52: 8 | B52: Togohub management | C52: 44934 | D52: T. Electricity | E52: =sumifs('25.04'!$H$7:$H$411,'25.04'!$G$7:$G$411,$D52,'25.04'!$F$7:$F$411,E$3) -> 0 | F52: =sumifs('25.04'!$H$7:$H$411,'25.04'!$G$7:$G$411,$D52,'25.04'!$F$7:$F$411,F$3) -> 0 | G52: =sumifs('25.04'!$H$7:$H$411,'25.04'!$G$7:$G$411,$D52,'25.04'!$F$7:$F$411,G$3) -> 0 | H52: =sumifs('25.04'!$H$7:$H$411,'25.04'!$G$7:$G$411,$D52,'25.04'!$F$7:$F$411,H$3) -> 0 | I52: =sumifs('25.04'!$H$7:$H$411,'25.04'!$G$7:$G$411,$D52,'25.04'!$F$7:$F$411,I$3) -> 0 | J52: =sumifs('25.04'!$H$7:$H$411,'25.04'!$G$7:$G$411,$D52,'25.04'!$F$7:$F$411,J$3) -> 0 | K52: =sumifs('25.04'!$H$7:$H$411,'25.04'!$G$7:$G$411,$D52,'25.04'!$F$7:$F$411,K$3) -> 0 | L52: =sumifs('25.04'!$H$7:$H$411,'25.04'!$G$7:$G$411,$D52,'25.04'!$F$7:$F$411,L$3) -> 0 | M52: =sumifs('25.04'!$H$7:$H$411,'25.04'!$G$7:$G$411,$D52,'25.04'!$F$7:$F$411,M$3) -> 0 | N52: =sum(E52:M52) -> 0 | P52: =N52/sum(N$52:N$59) -> #DIV/0! | S52: =N52+N53 -> 0 | T52: =sumifs('25.04'!$H$7:$H$411,'25.04'!$J$7:$J$411,$D52,'25.04'!$K$7:$K$411,T$3) -> 0 | U52: =sumifs('25.04'!$H$7:$H$411,'25.04'!$J$7:$J$411,$D52,'25.04'!$K$7:$K$411,U$3) -> 0 | V52: =sumifs('25.04'!$H$7:$H$411,'25.04'!$J$7:$J$411,$D52,'25.04'!$K$7:$K$411,V$3) -> 0 | W52: =sumifs('25.04'!$H$7:$H$411,'25.04'!$J$7:$J$411,$D52,'25.04'!$K$7:$K$411,W$3) -> 0 | X52: =sumifs('25.04'!$H$7:$H$411,'25.04'!$J$7:$J$411,$D52,'25.04'!$K$7:$K$411,X$3) -> 0 | Y52: =sumifs('25.04'!$H$7:$H$411,'25.04'!$J$7:$J$411,$D52,'25.04'!$K$7:$K$411,Y$3) -> 0 | Z52: =sumifs('25.04'!$H$7:$H$411,'25.04'!$J$7:$J$411,$D52,'25.04'!$K$7:$K$411,Z$3) -> 0 | AA52: =sumifs('25.04'!$H$7:$H$411,'25.04'!$J$7:$J$411,$D52,'25.04'!$K$7:$K$411,AA$3) -> 0 | AB52: =sumifs('25.04'!$H$7:$H$411,'25.04'!$J$7:$J$411,$D52,'25.04'!$K$7:$K$411,AB$3) -> 0 | AC52: =sum(T52:AB52) -> 0
C53: 44965 | D53: T. Water | E53: =sumifs('25.04'!$H$7:$H$411,'25.04'!$G$7:$G$411,$D53,'25.04'!$F$7:$F$411,E$3) -> 0 | F53: =sumifs('25.04'!$H$7:$H$411,'25.04'!$G$7:$G$411,$D53,'25.04'!$F$7:$F$411,F$3) -> 0 | G53: =sumifs('25.04'!$H$7:$H$411,'25.04'!$G$7:$G$411,$D53,'25.04'!$F$7:$F$411,G$3) -> 0 | H53: =sumifs('25.04'!$H$7:$H$411,'25.04'!$G$7:$G$411,$D53,'25.04'!$F$7:$F$411,H$3) -> 0 | I53: =sumifs('25.04'!$H$7:$H$411,'25.04'!$G$7:$G$411,$D53,'25.04'!$F$7:$F$411,I$3) -> 0 | J53: =sumifs('25.04'!$H$7:$H$411,'25.04'!$G$7:$G$411,$D53,'25.04'!$F$7:$F$411,J$3) -> 0 | K53: =sumifs('25.04'!$H$7:$H$411,'25.04'!$G$7:$G$411,$D53,'25.04'!$F$7:$F$411,K$3) -> 0 | L53: =sumifs('25.04'!$H$7:$H$411,'25.04'!$G$7:$G$411,$D53,'25.04'!$F$7:$F$411,L$3) -> 0 | M53: =sumifs('25.04'!$H$7:$H$411,'25.04'!$G$7:$G$411,$D53,'25.04'!$F$7:$F$411,M$3) -> 0 | N53: =sum(E53:M53) -> 0 | P53: =N53/sum(N$52:N$59) -> #DIV/0! | S53: =AC52+AC53 -> 0 | T53: =sumifs('25.04'!$H$7:$H$411,'25.04'!$J$7:$J$411,$D53,'25.04'!$K$7:$K$411,T$3) -> 0 | U53: =sumifs('25.04'!$H$7:$H$411,'25.04'!$J$7:$J$411,$D53,'25.04'!$K$7:$K$411,U$3) -> 0 | V53: =sumifs('25.04'!$H$7:$H$411,'25.04'!$J$7:$J$411,$D53,'25.04'!$K$7:$K$411,V$3) -> 0 | W53: =sumifs('25.04'!$H$7:$H$411,'25.04'!$J$7:$J$411,$D53,'25.04'!$K$7:$K$411,W$3) -> 0 | X53: =sumifs('25.04'!$H$7:$H$411,'25.04'!$J$7:$J$411,$D53,'25.04'!$K$7:$K$411,X$3) -> 0 | Y53: =sumifs('25.04'!$H$7:$H$411,'25.04'!$J$7:$J$411,$D53,'25.04'!$K$7:$K$411,Y$3) -> 0 | Z53: =sumifs('25.04'!$H$7:$H$411,'25.04'!$J$7:$J$411,$D53,'25.04'!$K$7:$K$411,Z$3) -> 0 | AA53: =sumifs('25.04'!$H$7:$H$411,'25.04'!$J$7:$J$411,$D53,'25.04'!$K$7:$K$411,AA$3) -> 0 | AB53: =sumifs('25.04'!$H$7:$H$411,'25.04'!$J$7:$J$411,$D53,'25.04'!$K$7:$K$411,AB$3) -> 0 | AC53: =sum(T53:AB53) -> 0
C54: 44993 | D54: T. Cleaning | E54: =sumifs('25.04'!$H$7:$H$411,'25.04'!$G$7:$G$411,$D54,'25.04'!$F$7:$F$411,E$3) -> 0 | F54: =sumifs('25.04'!$H$7:$H$411,'25.04'!$G$7:$G$411,$D54,'25.04'!$F$7:$F$411,F$3) -> 0 | G54: =sumifs('25.04'!$H$7:$H$411,'25.04'!$G$7:$G$411,$D54,'25.04'!$F$7:$F$411,G$3) -> 0 | H54: =sumifs('25.04'!$H$7:$H$411,'25.04'!$G$7:$G$411,$D54,'25.04'!$F$7:$F$411,H$3) -> 0 | I54: =sumifs('25.04'!$H$7:$H$411,'25.04'!$G$7:$G$411,$D54,'25.04'!$F$7:$F$411,I$3) -> 0 | J54: =sumifs('25.04'!$H$7:$H$411,'25.04'!$G$7:$G$411,$D54,'25.04'!$F$7:$F$411,J$3) -> 0 | K54: =sumifs('25.04'!$H$7:$H$411,'25.04'!$G$7:$G$411,$D54,'25.04'!$F$7:$F$411,K$3) -> 0 | L54: =sumifs('25.04'!$H$7:$H$411,'25.04'!$G$7:$G$411,$D54,'25.04'!$F$7:$F$411,L$3) -> 0 | M54: =sumifs('25.04'!$H$7:$H$411,'25.04'!$G$7:$G$411,$D54,'25.04'!$F$7:$F$411,M$3) -> 0 | N54: =sum(E54:M54) -> 0 | P54: =N54/sum(N$52:N$59) -> #DIV/0! | S54: =S52-S53 -> 0 | T54: =sumifs('25.04'!$H$7:$H$411,'25.04'!$J$7:$J$411,$D54,'25.04'!$K$7:$K$411,T$3) -> 0 | U54: =sumifs('25.04'!$H$7:$H$411,'25.04'!$J$7:$J$411,$D54,'25.04'!$K$7:$K$411,U$3) -> 0 | V54: =sumifs('25.04'!$H$7:$H$411,'25.04'!$J$7:$J$411,$D54,'25.04'!$K$7:$K$411,V$3) -> 0 | W54: =sumifs('25.04'!$H$7:$H$411,'25.04'!$J$7:$J$411,$D54,'25.04'!$K$7:$K$411,W$3) -> 0 | X54: =sumifs('25.04'!$H$7:$H$411,'25.04'!$J$7:$J$411,$D54,'25.04'!$K$7:$K$411,X$3) -> 0 | Y54: =sumifs('25.04'!$H$7:$H$411,'25.04'!$J$7:$J$411,$D54,'25.04'!$K$7:$K$411,Y$3) -> 0 | Z54: =sumifs('25.04'!$H$7:$H$411,'25.04'!$J$7:$J$411,$D54,'25.04'!$K$7:$K$411,Z$3) -> 0 | AA54: =sumifs('25.04'!$H$7:$H$411,'25.04'!$J$7:$J$411,$D54,'25.04'!$K$7:$K$411,AA$3) -> 0 | AB54: =sumifs('25.04'!$H$7:$H$411,'25.04'!$J$7:$J$411,$D54,'25.04'!$K$7:$K$411,AB$3) -> 0 | AC54: =sum(T54:AB54) -> 0
C55: 45024 | D55: T. shopping | E55: =sumifs('25.04'!$H$7:$H$411,'25.04'!$G$7:$G$411,$D55,'25.04'!$F$7:$F$411,E$3) -> 0 | F55: =sumifs('25.04'!$H$7:$H$411,'25.04'!$G$7:$G$411,$D55,'25.04'!$F$7:$F$411,F$3) -> 0 | G55: =sumifs('25.04'!$H$7:$H$411,'25.04'!$G$7:$G$411,$D55,'25.04'!$F$7:$F$411,G$3) -> 0 | H55: =sumifs('25.04'!$H$7:$H$411,'25.04'!$G$7:$G$411,$D55,'25.04'!$F$7:$F$411,H$3) -> 0 | I55: =sumifs('25.04'!$H$7:$H$411,'25.04'!$G$7:$G$411,$D55,'25.04'!$F$7:$F$411,I$3) -> 0 | J55: =sumifs('25.04'!$H$7:$H$411,'25.04'!$G$7:$G$411,$D55,'25.04'!$F$7:$F$411,J$3) -> 0 | K55: =sumifs('25.04'!$H$7:$H$411,'25.04'!$G$7:$G$411,$D55,'25.04'!$F$7:$F$411,K$3) -> 0 | L55: =sumifs('25.04'!$H$7:$H$411,'25.04'!$G$7:$G$411,$D55,'25.04'!$F$7:$F$411,L$3) -> 0 | M55: =sumifs('25.04'!$H$7:$H$411,'25.04'!$G$7:$G$411,$D55,'25.04'!$F$7:$F$411,M$3) -> 0 | N55: =sum(E55:M55) -> 0 | P55: =N55/sum(N$52:N$59) -> #DIV/0! | T55: =sumifs('25.04'!$H$7:$H$411,'25.04'!$J$7:$J$411,$D55,'25.04'!$K$7:$K$411,T$3) -> 0 | U55: =sumifs('25.04'!$H$7:$H$411,'25.04'!$J$7:$J$411,$D55,'25.04'!$K$7:$K$411,U$3) -> 0 | V55: =sumifs('25.04'!$H$7:$H$411,'25.04'!$J$7:$J$411,$D55,'25.04'!$K$7:$K$411,V$3) -> 0 | W55: =sumifs('25.04'!$H$7:$H$411,'25.04'!$J$7:$J$411,$D55,'25.04'!$K$7:$K$411,W$3) -> 0 | X55: =sumifs('25.04'!$H$7:$H$411,'25.04'!$J$7:$J$411,$D55,'25.04'!$K$7:$K$411,X$3) -> 0 | Y55: =sumifs('25.04'!$H$7:$H$411,'25.04'!$J$7:$J$411,$D55,'25.04'!$K$7:$K$411,Y$3) -> 0 | Z55: =sumifs('25.04'!$H$7:$H$411,'25.04'!$J$7:$J$411,$D55,'25.04'!$K$7:$K$411,Z$3) -> 0 | AA55: =sumifs('25.04'!$H$7:$H$411,'25.04'!$J$7:$J$411,$D55,'25.04'!$K$7:$K$411,AA$3) -> 0 | AB55: =sumifs('25.04'!$H$7:$H$411,'25.04'!$J$7:$J$411,$D55,'25.04'!$K$7:$K$411,AB$3) -> 0 | AC55: =sum(T55:AB55) -> 0
C56: 45054 | D56: T. Mainternance | E56: =sumifs('25.04'!$H$7:$H$411,'25.04'!$G$7:$G$411,$D56,'25.04'!$F$7:$F$411,E$3) -> 0 | F56: =sumifs('25.04'!$H$7:$H$411,'25.04'!$G$7:$G$411,$D56,'25.04'!$F$7:$F$411,F$3) -> 0 | G56: =sumifs('25.04'!$H$7:$H$411,'25.04'!$G$7:$G$411,$D56,'25.04'!$F$7:$F$411,G$3) -> 0 | H56: =sumifs('25.04'!$H$7:$H$411,'25.04'!$G$7:$G$411,$D56,'25.04'!$F$7:$F$411,H$3) -> 0 | I56: =sumifs('25.04'!$H$7:$H$411,'25.04'!$G$7:$G$411,$D56,'25.04'!$F$7:$F$411,I$3) -> 0 | J56: =sumifs('25.04'!$H$7:$H$411,'25.04'!$G$7:$G$411,$D56,'25.04'!$F$7:$F$411,J$3) -> 0 | K56: =sumifs('25.04'!$H$7:$H$411,'25.04'!$G$7:$G$411,$D56,'25.04'!$F$7:$F$411,K$3) -> 0 | L56: =sumifs('25.04'!$H$7:$H$411,'25.04'!$G$7:$G$411,$D56,'25.04'!$F$7:$F$411,L$3) -> 0 | M56: =sumifs('25.04'!$H$7:$H$411,'25.04'!$G$7:$G$411,$D56,'25.04'!$F$7:$F$411,M$3) -> 0 | N56: =sum(E56:M56) -> 0 | P56: =N56/sum(N$52:N$59) -> #DIV/0! | T56: =sumifs('25.04'!$H$7:$H$411,'25.04'!$J$7:$J$411,$D56,'25.04'!$K$7:$K$411,T$3) -> 0 | U56: =sumifs('25.04'!$H$7:$H$411,'25.04'!$J$7:$J$411,$D56,'25.04'!$K$7:$K$411,U$3) -> 0 | V56: =sumifs('25.04'!$H$7:$H$411,'25.04'!$J$7:$J$411,$D56,'25.04'!$K$7:$K$411,V$3) -> 0 | W56: =sumifs('25.04'!$H$7:$H$411,'25.04'!$J$7:$J$411,$D56,'25.04'!$K$7:$K$411,W$3) -> 0 | X56: =sumifs('25.04'!$H$7:$H$411,'25.04'!$J$7:$J$411,$D56,'25.04'!$K$7:$K$411,X$3) -> 0 | Y56: =sumifs('25.04'!$H$7:$H$411,'25.04'!$J$7:$J$411,$D56,'25.04'!$K$7:$K$411,Y$3) -> 0 | Z56: =sumifs('25.04'!$H$7:$H$411,'25.04'!$J$7:$J$411,$D56,'25.04'!$K$7:$K$411,Z$3) -> 0 | AA56: =sumifs('25.04'!$H$7:$H$411,'25.04'!$J$7:$J$411,$D56,'25.04'!$K$7:$K$411,AA$3) -> 0 | AB56: =sumifs('25.04'!$H$7:$H$411,'25.04'!$J$7:$J$411,$D56,'25.04'!$K$7:$K$411,AB$3) -> 0 | AC56: =sum(T56:AB56) -> 0
C57: 45085 | D57: T. Exchange | E57: =sumifs('25.04'!$H$7:$H$411,'25.04'!$G$7:$G$411,$D57,'25.04'!$F$7:$F$411,E$3) -> 0 | F57: =sumifs('25.04'!$H$7:$H$411,'25.04'!$G$7:$G$411,$D57,'25.04'!$F$7:$F$411,F$3) -> 0 | G57: =sumifs('25.04'!$H$7:$H$411,'25.04'!$G$7:$G$411,$D57,'25.04'!$F$7:$F$411,G$3) -> 0 | H57: =sumifs('25.04'!$H$7:$H$411,'25.04'!$G$7:$G$411,$D57,'25.04'!$F$7:$F$411,H$3) -> 0 | I57: =sumifs('25.04'!$H$7:$H$411,'25.04'!$G$7:$G$411,$D57,'25.04'!$F$7:$F$411,I$3) -> 0 | J57: =sumifs('25.04'!$H$7:$H$411,'25.04'!$G$7:$G$411,$D57,'25.04'!$F$7:$F$411,J$3) -> 0 | K57: =sumifs('25.04'!$H$7:$H$411,'25.04'!$G$7:$G$411,$D57,'25.04'!$F$7:$F$411,K$3) -> 0 | L57: =sumifs('25.04'!$H$7:$H$411,'25.04'!$G$7:$G$411,$D57,'25.04'!$F$7:$F$411,L$3) -> 0 | M57: =sumifs('25.04'!$H$7:$H$411,'25.04'!$G$7:$G$411,$D57,'25.04'!$F$7:$F$411,M$3) -> 0 | N57: =sum(E57:M57) -> 0 | P57: =N57/sum(N$52:N$59) -> #DIV/0! | T57: =sumifs('25.04'!$H$7:$H$411,'25.04'!$J$7:$J$411,$D57,'25.04'!$K$7:$K$411,T$3) -> 0 | U57: =sumifs('25.04'!$H$7:$H$411,'25.04'!$J$7:$J$411,$D57,'25.04'!$K$7:$K$411,U$3) -> 0 | V57: =sumifs('25.04'!$H$7:$H$411,'25.04'!$J$7:$J$411,$D57,'25.04'!$K$7:$K$411,V$3) -> 0 | W57: =sumifs('25.04'!$H$7:$H$411,'25.04'!$J$7:$J$411,$D57,'25.04'!$K$7:$K$411,W$3) -> 0 | X57: =sumifs('25.04'!$H$7:$H$411,'25.04'!$J$7:$J$411,$D57,'25.04'!$K$7:$K$411,X$3) -> 0 | Y57: =sumifs('25.04'!$H$7:$H$411,'25.04'!$J$7:$J$411,$D57,'25.04'!$K$7:$K$411,Y$3) -> 0 | Z57: =sumifs('25.04'!$H$7:$H$411,'25.04'!$J$7:$J$411,$D57,'25.04'!$K$7:$K$411,Z$3) -> 0 | AA57: =sumifs('25.04'!$H$7:$H$411,'25.04'!$J$7:$J$411,$D57,'25.04'!$K$7:$K$411,AA$3) -> 0 | AB57: =sumifs('25.04'!$H$7:$H$411,'25.04'!$J$7:$J$411,$D57,'25.04'!$K$7:$K$411,AB$3) -> 0 | AC57: =sum(T57:AB57) -> 0
C58: 45115 | D58: T. Tax & Social | E58: =sumifs('25.04'!$H$7:$H$411,'25.04'!$G$7:$G$411,$D58,'25.04'!$F$7:$F$411,E$3) -> 0 | F58: =sumifs('25.04'!$H$7:$H$411,'25.04'!$G$7:$G$411,$D58,'25.04'!$F$7:$F$411,F$3) -> 0 | G58: =sumifs('25.04'!$H$7:$H$411,'25.04'!$G$7:$G$411,$D58,'25.04'!$F$7:$F$411,G$3) -> 0 | H58: =sumifs('25.04'!$H$7:$H$411,'25.04'!$G$7:$G$411,$D58,'25.04'!$F$7:$F$411,H$3) -> 0 | I58: =sumifs('25.04'!$H$7:$H$411,'25.04'!$G$7:$G$411,$D58,'25.04'!$F$7:$F$411,I$3) -> 0 | J58: =sumifs('25.04'!$H$7:$H$411,'25.04'!$G$7:$G$411,$D58,'25.04'!$F$7:$F$411,J$3) -> 0 | K58: =sumifs('25.04'!$H$7:$H$411,'25.04'!$G$7:$G$411,$D58,'25.04'!$F$7:$F$411,K$3) -> 0 | L58: =sumifs('25.04'!$H$7:$H$411,'25.04'!$G$7:$G$411,$D58,'25.04'!$F$7:$F$411,L$3) -> 0 | M58: =sumifs('25.04'!$H$7:$H$411,'25.04'!$G$7:$G$411,$D58,'25.04'!$F$7:$F$411,M$3) -> 0 | N58: =sum(E58:M58) -> 0 | P58: =N58/sum(N$52:N$59) -> #DIV/0! | T58: =sumifs('25.04'!$H$7:$H$411,'25.04'!$J$7:$J$411,$D58,'25.04'!$K$7:$K$411,T$3) -> 0 | U58: =sumifs('25.04'!$H$7:$H$411,'25.04'!$J$7:$J$411,$D58,'25.04'!$K$7:$K$411,U$3) -> 0 | V58: =sumifs('25.04'!$H$7:$H$411,'25.04'!$J$7:$J$411,$D58,'25.04'!$K$7:$K$411,V$3) -> 0 | W58: =sumifs('25.04'!$H$7:$H$411,'25.04'!$J$7:$J$411,$D58,'25.04'!$K$7:$K$411,W$3) -> 0 | X58: =sumifs('25.04'!$H$7:$H$411,'25.04'!$J$7:$J$411,$D58,'25.04'!$K$7:$K$411,X$3) -> 0 | Y58: =sumifs('25.04'!$H$7:$H$411,'25.04'!$J$7:$J$411,$D58,'25.04'!$K$7:$K$411,Y$3) -> 0 | Z58: =sumifs('25.04'!$H$7:$H$411,'25.04'!$J$7:$J$411,$D58,'25.04'!$K$7:$K$411,Z$3) -> 0 | AA58: =sumifs('25.04'!$H$7:$H$411,'25.04'!$J$7:$J$411,$D58,'25.04'!$K$7:$K$411,AA$3) -> 0 | AB58: =sumifs('25.04'!$H$7:$H$411,'25.04'!$J$7:$J$411,$D58,'25.04'!$K$7:$K$411,AB$3) -> 0 | AC58: =sum(T58:AB58) -> 0
C59: 45146 | D59: T. Renovation | E59: =sumifs('25.04'!$H$7:$H$411,'25.04'!$G$7:$G$411,$D59,'25.04'!$F$7:$F$411,E$3) -> 0 | F59: =sumifs('25.04'!$H$7:$H$411,'25.04'!$G$7:$G$411,$D59,'25.04'!$F$7:$F$411,F$3) -> 0 | G59: =sumifs('25.04'!$H$7:$H$411,'25.04'!$G$7:$G$411,$D59,'25.04'!$F$7:$F$411,G$3) -> 0 | H59: =sumifs('25.04'!$H$7:$H$411,'25.04'!$G$7:$G$411,$D59,'25.04'!$F$7:$F$411,H$3) -> 0 | I59: =sumifs('25.04'!$H$7:$H$411,'25.04'!$G$7:$G$411,$D59,'25.04'!$F$7:$F$411,I$3) -> 0 | J59: =sumifs('25.04'!$H$7:$H$411,'25.04'!$G$7:$G$411,$D59,'25.04'!$F$7:$F$411,J$3) -> 0 | K59: =sumifs('25.04'!$H$7:$H$411,'25.04'!$G$7:$G$411,$D59,'25.04'!$F$7:$F$411,K$3) -> 0 | L59: =sumifs('25.04'!$H$7:$H$411,'25.04'!$G$7:$G$411,$D59,'25.04'!$F$7:$F$411,L$3) -> 0 | M59: =sumifs('25.04'!$H$7:$H$411,'25.04'!$G$7:$G$411,$D59,'25.04'!$F$7:$F$411,M$3) -> 0 | N59: =sum(E59:M59) -> 0 | P59: =N59/sum(N$52:N$59) -> #DIV/0! | T59: =sumifs('25.04'!$H$7:$H$411,'25.04'!$J$7:$J$411,$D59,'25.04'!$K$7:$K$411,T$3) -> 0 | U59: =sumifs('25.04'!$H$7:$H$411,'25.04'!$J$7:$J$411,$D59,'25.04'!$K$7:$K$411,U$3) -> 0 | V59: =sumifs('25.04'!$H$7:$H$411,'25.04'!$J$7:$J$411,$D59,'25.04'!$K$7:$K$411,V$3) -> 0 | W59: =sumifs('25.04'!$H$7:$H$411,'25.04'!$J$7:$J$411,$D59,'25.04'!$K$7:$K$411,W$3) -> 0 | X59: =sumifs('25.04'!$H$7:$H$411,'25.04'!$J$7:$J$411,$D59,'25.04'!$K$7:$K$411,X$3) -> 0 | Y59: =sumifs('25.04'!$H$7:$H$411,'25.04'!$J$7:$J$411,$D59,'25.04'!$K$7:$K$411,Y$3) -> 0 | Z59: =sumifs('25.04'!$H$7:$H$411,'25.04'!$J$7:$J$411,$D59,'25.04'!$K$7:$K$411,Z$3) -> 0 | AA59: =sumifs('25.04'!$H$7:$H$411,'25.04'!$J$7:$J$411,$D59,'25.04'!$K$7:$K$411,AA$3) -> 0 | AB59: =sumifs('25.04'!$H$7:$H$411,'25.04'!$J$7:$J$411,$D59,'25.04'!$K$7:$K$411,AB$3) -> 0 | AC59: =sum(T59:AB59) -> 0
D60: Total | E60: =sum(E4:E59) -> 320000 | F60: =sum(F4:F59) -> 0 | G60: =sum(G4:G59) -> 3580144 | H60: =sum(H4:H59) -> 0 | I60: =sum(I4:I59) -> 0 | J60: =sum(J4:J59) -> 0 | K60: =sum(K4:K59) -> 0 | L60: =sum(L4:L59) -> 0 | ... N60: =sum(N4:N59) -> 3900144 | P60: =sum(P4:P59) -> #DIV/0! | Q60: =sum(Q4:Q59) -> #DIV/0! | T60: =sum(T4:T59) -> 0 | U60: =sum(U4:U59) -> 0 | V60: =sum(V4:V59) -> 0 | W60: =sum(W4:W59) -> 0 | X60: =sum(X4:X59) -> 0 | Y60: =sum(Y4:Y59) -> 0 | Z60: =sum(Z4:Z59) -> 0 | AA60: =sum(AA4:AA59) -> 0 | ... AC60: =sum(AC4:AC59) -> 0
C62: Accounts | D62: Account | E62: Cash | F62: BIDV | G62: Vietcombank | H62: Vp bank Lady | I62: Moca | J62: Momo | K62: Zalo | L62: Saving | T62: Sổ tiết kiệm | U62: Stt | V62: Số tiền | W62: Bắt đầu | Y62: Kết thúc | Z62: Số tháng | AA62: Tỉ lệ lãi | AB62: Cuối kì
D63: Balance | E63: =397000+40000 -> 437000 | F63: 3850110 | G63: 62001574 | H63: -1665854 | I63: 0 | J63: 14250 | K63: 3088 | L63: =V74 -> 2849500000 | N63: =M75+N75+O75+P75+Q75+R75 -> 101674950 | U63: 1 | V63: 220000000 | W63: 45551 | Y63: 45733 | Z63: =(Y63-W63)/30 -> 6.0666667 | AA63: 0.056 | AB63: =V63+V63*AA63/12*Z63 -> 2.2622844e+08
D64: In | E64: =sumifs('25.04'!$H$7:$H$411,'25.04'!$K$7:$K$411,E$62) -> 18300000 | F64: =sumifs('25.04'!$H$7:$H$411,'25.04'!$K$7:$K$411,F$62) -> 0 | G64: =sumifs('25.04'!$H$7:$H$411,'25.04'!$K$7:$K$411,G$62) -> 0 | H64: =sumifs('25.04'!$H$7:$H$411,'25.04'!$K$7:$K$411,H$62) -> 0 | I64: =sumifs('25.04'!$H$7:$H$411,'25.04'!$K$7:$K$411,I$62) -> 0 | J64: =sumifs('25.04'!$H$7:$H$411,'25.04'!$K$7:$K$411,J$62) -> 0 | K64: =sumifs('25.04'!$H$7:$H$411,'25.04'!$K$7:$K$411,K$62) -> 0 | L64: =sumifs('25.04'!$H$7:$H$411,'25.04'!$K$7:$K$411,L$62) -> 0 | U64: 2 | V64: 250000000 | W64: 45414 | Y64: 45779 | Z64: =(Y64-W64)/30 -> 12.166667 | AA64: 0.05 | AB64: =V64+V64*AA64/12*Z64 -> 2.6267361e+08
D65: Out | E65: =Sumifs('25.04'!$H$7:$H$411,'25.04'!$F$7:$F$411,E$62) -> 320000 | F65: =Sumifs('25.04'!$H$7:$H$411,'25.04'!$F$7:$F$411,F$62) -> 0 | G65: =Sumifs('25.04'!$H$7:$H$411,'25.04'!$F$7:$F$411,G$62) -> 3580144 | H65: =Sumifs('25.04'!$H$7:$H$411,'25.04'!$F$7:$F$411,H$62) -> 0 | I65: =Sumifs('25.04'!$H$7:$H$411,'25.04'!$F$7:$F$411,I$62) -> 0 | J65: =Sumifs('25.04'!$H$7:$H$411,'25.04'!$F$7:$F$411,J$62) -> 0 | K65: =Sumifs('25.04'!$H$7:$H$411,'25.04'!$F$7:$F$411,K$62) -> 0 | L65: =Sumifs('25.04'!$H$7:$H$411,'25.04'!$F$7:$F$411,L$62) -> 0 | O65: =7127400-8900000 -> -1772600 | U65: 3 | V65: 540000000 | W65: 45624 | Y65: 45805 | Z65: =(Y65-W65)/30 -> 6.0333333 | AA65: 0.045 | AB65: =V65+V65*AA65/12*Z65 -> 552217500 | AC65: ?
D66: Change | E66: =E64-E65 -> 17980000 | F66: =F64-F65 -> 0 | G66: =G64-G65 -> -3580144 | H66: =H64-H65 -> 0 | I66: =I64-I65 -> 0 | J66: =J64-J65 -> 0 | K66: =K64-K65 -> 0 | L66: =L64-L65 -> 0 | U66: 4 | V66: 300000000 | W66: 45649 | Y66: 45831 | Z66: =(Y66-W66)/30 -> 6.0666667 | AA66: 0.059 | AB66: =V66+V66*AA66/12*Z66 -> 3.0894833e+08
D67: Last | E67: =E63+E64-E65 -> 18417000 | F67: =F63+F64-F65 -> 3850110 | G67: =G63+G64-G65 -> 58421430 | H67: =H63+H64-H65 -> -1665854 | I67: =I63+I64-I65 -> 0 | J67: =J63+J64-J65 -> 14250 | K67: =K63+K64-K65 -> 3088 | L67: =L63+L64-L65 -> 2849500000 | N67: =19023059-G67 -> -39398371 | U67: 5 | V67: 200000000 | W67: 45476 | Y67: 45841 | Z67: =(Y67-W67)/30 -> 12.166667 | AA67: 0.058 | AB67: =V67+V67*AA67/12*Z67 -> 2.1176111e+08
E68: =sum(E67:L67) -> 2928540024 | U68: 6 | V68: 500000000 | W68: 45665 | Y68: 45846 | Z68: =(Y68-W68)/30 -> 6.0333333 | AA68: 0.055 | AB68: =V68+V68*AA68/12*Z68 -> 5.1382639e+08
U69: 7 | V69: 500000000 | W69: 45665 | Y69: 45846 | Z69: =(Y69-W69)/30 -> 6.0333333 | AA69: 0.059 | AB69: =V69+V69*AA69/12*Z69 -> 5.1483194e+08
C70: Funds | D70: Account | E70: Education | F70: Enjoy | G70: For give | H70: Health | I70: Living | J70: Savings | K70: N&M studio | L70: Togohub management | M70: Totto Fund | N70: Lego Fund | O70: Papa fund | P70: Nghia fund | Q70: ID student | R70: A4 Class | S70: Loan | U70: 8 | V70: 109500000 | W70: 45694 | Y70: 45875 | Z70: =(Y70-W70)/30 -> 6.0333333 | AA70: 0.055 | AB70: =V70+V70*AA70/12*Z70 -> 1.1252798e+08
D71: Balance | E71: -7733000 | F71: -3360000 | G71: -11683000 | H71: -29686879 | I71: -29686879 | J71: 0 | K71: 62520972 | L71: -979053593 | M71: 10314000 | N71: 14672000 | O71: 51242400 | P71: 13000000 | Q71: 2077300 | R71: 10369250 | S71: -273800000 | U71: 9 | V71: 230000000 | W71: 45675 | Y71: 46039 | Z71: =(Y71-W71)/30 -> 12.133333 | AA71: 0.0605 | AB71: =V71+V71*AA71/12*Z71 -> 2.4406961e+08
D72: Out | E72: =sum(N4:N9) -> 0 | F72: =sum(N$10:N$16) -> 320000 | G72: =sum(N17:N22) -> 0 | H72: =sum(N23:N28) -> 0 | I72: =sum(N29:N47) -> 3580144 | J72: =sum(N48:N49) -> 0 | K72: =sumifs('25.04'!$H$7:$H$411,'25.04'!$G$7:$G$411,#REF!)+sumifs('25.04'!$H$7:$H$411,'25.04'!$G$7:$G$411,$D50)+sumifs('25.04'!$H$7:$H$411,'25.04'!$G$7:$G$411,$D51) -> 0 | L72: =sum(N52:N59) -> 0 | M72: =sumifs('25.04'!$H$7:$H$411,'25.04'!$G$7:$G$411,M$70) -> 0 | N72: =sumifs('25.04'!$H$7:$H$411,'25.04'!$G$7:$G$411,N$70) -> 0 | O72: =sumifs('25.04'!$H$7:$H$411,'25.04'!$G$7:$G$411,O$70) -> 0 | P72: =sumifs('25.04'!$H$7:$H$411,'25.04'!$G$7:$G$411,P$70) -> 0 | Q72: =sumifs('25.04'!$H$7:$H$411,'25.04'!$G$7:$G$411,Q$70) -> 0 | R72: =sumifs('25.04'!$H$7:$H$411,'25.04'!$G$7:$G$411,R$70) -> 0 | S72: =sumifs('25.04'!$H$7:$H$409,'25.04'!$G$7:$G$409,S$70) -> 0 | U72: 10
D73: In | E73: =sumifs('25.04'!$H$7:$H$411,'25.04'!$J$7:$J$411,E$70) -> 0 | F73: =sumifs('25.04'!$H$7:$H$411,'25.04'!$J$7:$J$411,F$70) -> 0 | G73: =sumifs('25.04'!$H$7:$H$411,'25.04'!$J$7:$J$411,G$70) -> 0 | H73: =sumifs('25.04'!$H$7:$H$411,'25.04'!$J$7:$J$411,H$70) -> 0 | I73: =sumifs('25.04'!$H$7:$H$411,'25.04'!$J$7:$J$411,I$70) -> 0 | J73: =sumifs('25.04'!$H$7:$H$411,'25.04'!$J$7:$J$411,J$70) -> 0 | K73: =sumifs('25.04'!$H$7:$H$411,'25.04'!$J$7:$J$411,#REF!)+sumifs('25.04'!$H$7:$H$411,'25.04'!$J$7:$J$411,$D50)+sumifs('25.04'!$H$7:$H$411,'25.04'!$J$7:$J$411,$D51) -> 0 | L73: =sum(AC52:AC59) -> 0 | M73: =sumifs('25.04'!$H$7:$H$411,'25.04'!$J$7:$J$411,M$70) -> 0 | N73: =sumifs('25.04'!$H$7:$H$411,'25.04'!$J$7:$J$411,N$70) -> 0 | O73: =sumifs('25.04'!$H$7:$H$411,'25.04'!$J$7:$J$411,O$70) -> 0 | P73: =sumifs('25.04'!$H$7:$H$411,'25.04'!$J$7:$J$411,P$70) -> 0 | Q73: =sumifs('25.04'!$H$7:$H$411,'25.04'!$J$7:$J$411,Q$70) -> 0 | R73: =sumifs('25.04'!$H$7:$H$411,'25.04'!$J$7:$J$411,R$70) -> 0 | S73: =Sumifs('25.04'!$H$7:$H$409,'25.04'!$J$7:$J$409,S$70) -> 0 | U73: 11
D74: Change | E74: =E73-E72 -> 0 | F74: =F72-F73 -> 320000 | G74: =G72-G73 -> 0 | H74: =H72-H73 -> 0 | I74: =I72-I73 -> 3580144 | J74: =J72-J73 -> 0 | K74: =K72-K73 -> 0 | L74: =L72-L73 -> 0 | M74: =M72-M73 -> 0 | ... S74: =S72-S73 -> 0 | V74: =SUM(V63:V73) -> 2849500000 | AA74: =SUM(AA63:AA73) -> 0.4975 | AB74: =SUM(AB63:AB73) -> 2947084924
D75: Last | E75: =E71-E72+E73 -> -7733000 | F75: =F71-F72+F73 -> -3680000 | G75: =G71-G72+G73 -> -11683000 | H75: =H71-H72+H73 -> -29686879 | I75: =I71-I72+I73 -> -33267023 | J75: =J71-J72+J73 -> 0 | K75: =K71-K72+K73 -> 62520972 | L75: =L71-L72+L73 -> -979053593 | ... S75: =S71-S72+S73 -> -273800000 | U75: 1 | V75: =M89/sum($M89:$S89) -> 0.17380959 | W75: =N89/sum($M89:$S89) -> 0.079801386 | X75: =P89/sum($M89:$S89) -> 0.37284409 | Y75: =Q89/sum($M89:$S89) -> 0.015102748 | Z75: =R89/sum($M89:$S89) -> 0.35844219 | AA75: =S89/sum($M89:$S89) -> 0 | AB75: =3000000000-V74 -> 150500000
E76: =sum(E75:S75) -> -1174707573 | U76: 2 | V76: =M90/sum($M90:$S90) -> 0.10104113 | W76: =N90/sum($M90:$S90) -> 0.0079430541 | X76: =P90/sum($M90:$S90) -> 0.065886264 | Y76: =Q90/sum($M90:$S90) -> 0.26820133 | Z76: =R90/sum($M90:$S90) -> 0.55692822 | AA76: =S90/sum($M90:$S90) -> 0
S77: =G67+F67+E67-R75-Q75-N75-M75 -> 43255990 | U77: 3 | V77: =M91/sum($M91:$S91) -> 0.17514043 | W77: =N91/sum($M91:$S91) -> 0.03051047 | X77: =P91/sum($M91:$S91) -> 0.02444414 | Y77: =Q91/sum($M91:$S91) -> 0.004654126 | Z77: =R91/sum($M91:$S91) -> 0.76525083 | AA77: =S91/sum($M91:$S91) -> 0
C78: Sources | D78: Account | E78: Private | G78: Salary | I78: Interest | K78: Togohub | L78: N&M studio | U78: 4 | V78: =M92/sum($M92:$S92) -> 0.06793045 | W78: =N92/sum($M92:$S92) -> 0.026612407 | X78: =P92/sum($M92:$S92) -> 0.032194673 | Y78: =Q92/sum($M92:$S92) -> 0.0063245058 | Z78: =R92/sum($M92:$S92) -> 0.86693796 | AA78: =S92/sum($M92:$S92) -> 0
E79: Family | F79: Gift | G79: UAD | H79: N&M Salary | I79: Saving interest | J79: Banking interest | K79: House rental money | L79: N&M studio | M79: Design | N79: Construction | P79: A4 Class Parents | Q79: Trash | U79: 5 | V79: =M93/sum($M93:$S93) -> 0.058723526 | W79: =N93/sum($M93:$S93) -> 0.038699423 | X79: =P93/sum($M93:$S93) -> 0.049923661 | Y79: =Q93/sum($M93:$S93) -> 0.095849058 | Z79: =R93/sum($M93:$S93) -> 0.75680433 | AA79: =S93/sum($M93:$S93) -> 0
D80: In | E80: =sumifs('25.04'!$H$7:$H$411,'25.04'!$D$7:$D$411,E$79) -> 5000000 | F80: =sumifs('25.04'!$H$7:$H$411,'25.04'!$D$7:$D$411,F$79) -> 0 | G80: =sumifs('25.04'!$H$7:$H$411,'25.04'!$D$7:$D$411,G$79) -> 0 | H80: =sumifs('25.04'!$H$7:$H$411,'25.04'!$J$7:$J$411,H$79) -> 0 | I80: =sumifs('25.04'!$H$7:$H$411,'25.04'!$D$7:$D$411,I$79) -> 0 | J80: =sumifs('25.04'!$H$7:$H$411,'25.04'!$D$7:$D$411,J$79) -> 11325000 | K80: =sumifs('25.04'!$H$7:$H$411,'25.04'!$D$7:$D$411,K$79) -> 13300000 | L80: =sumifs('25.04'!$H$7:$H$411,'25.04'!$D$7:$D$411,L$79) -> 0 | M80: =sumifs('25.04'!$H$7:$H$411,'25.04'!$D$7:$D$411,M$79) -> 0 | N80: =sumifs('25.04'!$H$7:$H$411,'25.04'!$D$7:$D$411,N$79) -> 0 | P80: =sumifs('25.04'!$H$7:$H$411,'25.04'!$D$7:$D$411,P$79) -> 0 | Q80: =sumifs('25.04'!$H$7:$H$411,'25.04'!$D$7:$D$411,Q$79) -> 0 | R80: =sum(E80:Q80) -> 29625000 | U80: 6 | V80: =M94/sum($M94:$S94) -> 0.027047056 | W80: =N94/sum($M94:$S94) -> 0.24642426 | X80: =P94/sum($M94:$S94) -> 0.0094211527 | Y80: =Q94/sum($M94:$S94) -> 0.0037267218 | Z80: =R94/sum($M94:$S94) -> 0.53449816 | AA80: =S94/sum($M94:$S94) -> 0.17888265
D81: Out | E81: =sumifs('25.04'!$H$7:$H$411,'25.04'!$G$7:$G$411,E$79) -> 0 | F81: =sumifs('25.04'!$H$7:$H$411,'25.04'!$G$7:$G$411,F$79) -> 0 | G81: =sumifs('25.04'!$H$7:$H$411,'25.04'!$G$7:$G$411,G$79) -> 0 | H81: =sumifs('25.04'!$H$7:$H$411,'25.04'!$D$7:$D$411,H$79) -> 0 | I81: =sumifs('25.04'!$H$7:$H$411,'25.04'!$G$7:$G$411,I$79) -> 0 | J81: =sumifs('25.04'!$H$7:$H$411,'25.04'!$G$7:$G$411,J$79) -> 0 | K81: =sum(N52:N59) -> 0 | L81: =sumifs('25.04'!$H$7:$H$411,'25.04'!$G$7:$G$411,L$79) -> 0 | M81: =sumifs('25.04'!$H$7:$H$411,'25.04'!$G$7:$G$411,M$79) -> 0 | N81: =sumifs('25.04'!$H$7:$H$411,'25.04'!$G$7:$G$411,N$79) -> 0 | P81: =sumifs('25.04'!$H$7:$H$411,'25.04'!$G$7:$G$411,R$70) -> 0 | Q81: =sumifs('25.04'!$H$7:$H$411,'25.04'!$G$7:$G$411,Q$79) -> 0 | R81: =sum(E81:Q81) -> 0 | U81: 7 | V81: =M95/sum($M95:$S95) -> 0.14236439 | W81: =N95/sum($M95:$S95) -> 0.16327866 | X81: =P95/sum($M95:$S95) -> 0 | Y81: =Q95/sum($M95:$S95) -> 0.23954583 | Z81: =R95/sum($M95:$S95) -> 0.45481112 | AA81: =S95/sum($M95:$S95) -> 0
D82: Change | E82: =E80-E81 -> 5000000 | F82: =F80-F81 -> 0 | G82: =G80-G81 -> 0 | H82: =H80-H81 -> 0 | I82: =I80-I81 -> 0 | J82: =J80-J81 -> 11325000 | K82: =K80-K81 -> 13300000 | L82: =L80-L81 -> 0 | ... N82: =N80-N81 -> 0 | P82: =P80-P81 -> 0 | Q82: =Q80-Q81 -> 0 | R82: =R80-R81 -> 29625000 | U82: 8 | V82: =M96/sum($M96:$S96) -> 0.00051644415 | W82: =N96/sum($M96:$S96) -> 0.1196716 | X82: =P96/sum($M96:$S96) -> 0.02385203 | Y82: =Q96/sum($M96:$S96) -> 0.025664784 | Z82: =R96/sum($M96:$S96) -> 0.40453641 | AA82: =S96/sum($M96:$S96) -> 0.42575873
D83: Last | E83: =E82+F82 -> 5000000 | G83: =G82+H82 -> 0 | I83: =I82+J82 -> 11325000 | K83: =K82 -> 13300000 | L83: =sum(L82:N82) -> 0 | U83: 9 | V83: =M97/sum($M97:$S97) -> 0.19491431 | W83: =N97/sum($M97:$S97) -> 0.20338871 | X83: =P97/sum($M97:$S97) -> 0.11684836 | Y83: =Q97/sum($M97:$S97) -> 0.032829409 | Z83: =R97/sum($M97:$S97) -> 0.45201922 | AA83: =S97/sum($M97:$S97) -> 0
E84: =sum(E83:N83) -> 29625000 | U84: 10 | V84: =M98/sum($M98:$S98) -> 0.11910368 | W84: =N98/sum($M98:$S98) -> 0.01673161 | X84: =P98/sum($M98:$S98) -> 0.034544954 | Y84: =Q98/sum($M98:$S98) -> 0.45422193 | Z84: =R98/sum($M98:$S98) -> 0.14450632 | AA84: =S98/sum($M98:$S98) -> 0.23089151
E85: =E88*E84 -> 7406250 | F85: =F88*E84 -> 4147500 | G85: =G88*E84 -> 2370000 | H85: =H88*E84 -> 2370000 | I85: =I88*E84 -> 8887500 | J85: =J88*E84 -> 4443750 | U85: 11 | V85: =M99/sum($M99:$S99) -> 0.12098896 | W85: =N99/sum($M99:$S99) -> 0.027033532 | X85: =P99/sum($M99:$S99) -> 0.41217531 | Y85: =Q99/sum($M99:$S99) -> 0.28246202 | Z85: =R99/sum($M99:$S99) -> 0.15734019 | AA85: =S99/sum($M99:$S99) -> 0
E86: 110751668 | F86: 68848813 | G86: 24811770 | H86: 40700816 | I86: 85429754 | J86: 161520567
C87: Điều kiện | D87: Funds | E87: Education | F87: Enjoy | G87: For give | H87: Health | I87: Living | J87: Savings | K87: Thực tế | L87: Funds | M87: Education | N87: Enjoy | P87: For give | Q87: Health | R87: Living | S87: Savings | T87: Chênh lệch | U87: 12 | V87: =M100/sum($M100:$S100) -> 0 | W87: =N100/sum($M100:$S100) -> 0.082048253 | X87: =P100/sum($M100:$S100) -> 0 | Y87: =Q100/sum($M100:$S100) -> 0 | Z87: =R100/sum($M100:$S100) -> 0.91795175 | AA87: =S100/sum($M100:$S100) -> 0
E88: 0.25 | F88: 0.14 | G88: 0.08 | H88: 0.08 | I88: 0.3 | J88: 0.15 | U88: Funds | V88: Education | W88: Enjoy | X88: For give | Y88: Health | Z88: Living | AA88: Savings
D89: 1 | E89: =$E$84*E$88 -> 7406250 | F89: =$E$84*F$88 -> 4147500 | G89: =$E$84*G$88 -> 2370000 | H89: =$E$84*H$88 -> 2370000 | I89: =$E$84*I$88 -> 8887500 | J89: =$E$84*J$88 -> 4443750 | L89: 1 | M89: 8148000 | N89: 3741000 | P89: 17478515 | Q89: 708000 | R89: 16803370 | S89: =J$72 -> 0
D90: 2 | E90: =$E$84*E$88 -> 7406250 | F90: =$E$84*F$88 -> 4147500 | G90: =$E$84*G$88 -> 2370000 | H90: =$E$84*H$88 -> 2370000 | I90: =$E$84*I$88 -> 8887500 | J90: =$E$84*J$88 -> 4443750 | L90: 2 | M90: 1844500 | N90: 145000 | P90: 1202750 | Q90: 4896000 | R90: 10166693 | S90: =J$72 -> 0 | U90: 1 | V90: =E89-M89 -> -741750 | W90: =N89-F89 -> -406500 | X90: =G89-P89 -> -15108515 | Y90: =Q89-H89 -> -1662000 | Z90: =I89-R89 -> -7915870 | AA90: =J89-S89 -> 4443750
D91: 3 | E91: =$E$84*E$88 -> 7406250 | F91: =$E$84*F$88 -> 4147500 | G91: =$E$84*G$88 -> 2370000 | H91: =$E$84*H$88 -> 2370000 | I91: =$E$84*I$88 -> 8887500 | J91: =$E$84*J$88 -> 4443750 | L91: 3 | M91: 21939000 | N91: 3821900 | P91: 3062000 | Q91: 583000 | R91: 95859294 | S91: =J$72 -> 0 | U91: 2 | V91: =E90-M90 -> 5561750 | W91: =N90-F90 -> -4002500 | X91: =G90-P90 -> 1167250 | Y91: =Q90-H90 -> 2526000 | Z91: =I90-R90 -> -1279193 | AA91: =J90-S90 -> 4443750
D92: 4 | E92: =$E$84*E$88 -> 7406250 | F92: =$E$84*F$88 -> 4147500 | G92: =$E$84*G$88 -> 2370000 | H92: =$E$84*H$88 -> 2370000 | I92: =$E$84*I$88 -> 8887500 | J92: =$E$84*J$88 -> 4443750 | L92: 4 | M92: 4393000 | N92: 1721000 | P92: 2082000 | Q92: 409000 | R92: 56064084 | S92: =J$72 -> 0 | U92: 3 | V92: =E91-M91 -> -14532750 | W92: =N91-F91 -> -325600 | X92: =G91-P91 -> -692000 | Y92: =Q91-H91 -> -1787000 | Z92: =I91-R91 -> -86971794 | AA92: =J91-S91 -> 4443750
D93: 5 | E93: =$E$84*E$88 -> 7406250 | F93: =$E$84*F$88 -> 4147500 | G93: =$E$84*G$88 -> 2370000 | H93: =$E$84*H$88 -> 2370000 | I93: =$E$84*I$88 -> 8887500 | J93: =$E$84*J$88 -> 4443750 | L93: 5 | M93: 3761700 | N93: 2479000 | P93: 3198000 | Q93: 6139880 | R93: 48479222 | S93: =J$72 -> 0 | U93: 4 | V93: =E92-M92 -> 3013250 | W93: =N92-F92 -> -2426500 | X93: =G92-P92 -> 288000 | Y93: =Q92-H92 -> -1961000 | Z93: =I92-R92 -> -47176584 | AA93: =J92-S92 -> 4443750
D94: 6 | E94: =$E$84*E$88 -> 7406250 | F94: =$E$84*F$88 -> 4147500 | G94: =$E$84*G$88 -> 2370000 | H94: =$E$84*H$88 -> 2370000 | I94: =$E$84*I$88 -> 8887500 | J94: =$E$84*J$88 -> 4443750 | L94: 6 | M94: 1814400 | N94: 16530900 | P94: 632000 | Q94: 250000 | R94: 35855786 | S94: 12000000 | U94: 5 | V94: =E93-M93 -> 3644550 | W94: =N93-F93 -> -1668500 | X94: =G93-P93 -> -828000 | Y94: =Q93-H93 -> 3769880 | Z94: =I93-R93 -> -39591722 | AA94: =J93-S93 -> 4443750
D95: 7 | E95: =$E$84*E$88 -> 7406250 | F95: =$E$84*F$88 -> 4147500 | G95: =$E$84*G$88 -> 2370000 | H95: =$E$84*H$88 -> 2370000 | I95: =$E$84*I$88 -> 8887500 | J95: =$E$84*J$88 -> 4443750 | L95: 7 | M95: 2909740 | N95: 3337200 | P95: 0 | Q95: 4896000 | R95: 9295738 | S95: =J$72 -> 0 | U95: 6 | V95: =E94-M94 -> 5591850 | W95: =N94-F94 -> 12383400 | X95: =G94-P94 -> 1738000 | Y95: =Q94-H94 -> -2120000 | Z95: =I94-R94 -> -26968286 | AA95: =J94-S94 -> -7556250
D96: 8 | E96: =$E$84*E$88 -> 7406250 | F96: =$E$84*F$88 -> 4147500 | G96: =$E$84*G$88 -> 2370000 | H96: =$E$84*H$88 -> 2370000 | I96: =$E$84*I$88 -> 8887500 | J96: =$E$84*J$88 -> 4443750 | L96: 8 | M96: 21652 | N96: 5017250 | P96: 1000000 | Q96: 1076000 | R96: 16960251 | S96: 17850000 | U96: 7 | V96: =E95-M95 -> 4496510 | W96: =N95-F95 -> -810300 | X96: =G95-P95 -> 2370000 | Y96: =Q95-H95 -> 2526000 | Z96: =I95-R95 -> -408238 | AA96: =J95-S95 -> 4443750
D97: 9 | E97: =$E$84*E$88 -> 7406250 | F97: =$E$84*F$88 -> 4147500 | G97: =$E$84*G$88 -> 2370000 | H97: =$E$84*H$88 -> 2370000 | I97: =$E$84*I$88 -> 8887500 | J97: =$E$84*J$88 -> 4443750 | L97: 9 | M97: 4669003 | N97: 4872000 | P97: 2799001 | Q97: 786400 | R97: 10827728 | S97: =J$72 -> 0 | U97: 8 | V97: =E96-M96 -> 7384598 | W97: =N96-F96 -> 869750 | X97: =G96-P96 -> 1370000 | Y97: =Q96-H96 -> -1294000 | Z97: =I96-R96 -> -8072751 | AA97: =J96-S96 -> -13406250
D98: 10 | E98: =$E$84*E$88 -> 7406250 | F98: =$E$84*F$88 -> 4147500 | G98: =$E$84*G$88 -> 2370000 | H98: =$E$84*H$88 -> 2370000 | I98: =$E$84*I$88 -> 8887500 | J98: =$E$84*J$88 -> 4443750 | L98: 10 | M98: 10129601 | N98: 1423000 | P98: 2938000 | Q98: 38630940 | R98: 12290060 | S98: 19637000 | U98: 9 | V98: =E97-M97 -> 2737247 | W98: =N97-F97 -> 724500 | X98: =G97-P97 -> -429001 | Y98: =Q97-H97 -> -1583600 | Z98: =I97-R97 -> -1940228 | AA98: =J97-S97 -> 4443750
D99: 11 | E99: 50243210 | F99: 28136198 | G99: 16077827 | H99: 16077827 | I99: 60291852 | J99: 30145926 | L99: 11 | M99: 4569500 | N99: 1021000 | P99: 15567000 | Q99: 10668000 | R99: 5942410 | S99: =J$72 -> 0 | U99: 10 | V99: =E98-M98 -> -2723351 | W99: =N98-F98 -> -2724500 | X99: =G98-P98 -> -568000 | Y99: =Q98-H98 -> 36260940 | Z99: =I98-R98 -> -3402560 | AA99: =J98-S98 -> -15193250
D100: 12 | E100: =$E$84*E$88 -> 7406250 | F100: =$E$84*F$88 -> 4147500 | G100: =$E$84*G$88 -> 2370000 | H100: =$E$84*H$88 -> 2370000 | I100: =$E$84*I$88 -> 8887500 | J100: =$E$84*J$88 -> 4443750 | L100: 12 | M100: =E$72 -> 0 | N100: =F$72 -> 320000 | P100: =G$72 -> 0 | Q100: =H$72 -> 0 | R100: =I$72 -> 3580144 | S100: =J$72 -> 0 | U100: 11 | V100: =E99-M99 -> 45673710 | W100: =N99-F99 -> -27115198 | X100: =G99-P99 -> 510827 | Y100: =Q99-H99 -> -5409827 | Z100: =I99-R99 -> 54349442 | AA100: =J99-S99 -> 30145926
E101: =sum(E89:E100) -> 131711960 | F101: =sum(F89:F100) -> 73758698 | G101: =sum(G89:G100) -> 42147827 | H101: =sum(H89:H100) -> 42147827 | I101: =sum(I89:I100) -> 158054352 | J101: =sum(J89:J100) -> 79027176 | L101: =sum(L89:L100) -> 0 | M101: =sum(M89:M100) -> 64200096 | N101: =sum(N89:N100) -> 44429250 | P101: =sum(P89:P100) -> 49959266 | Q101: =sum(Q89:Q100) -> 69043220 | R101: =sum(R89:R100) -> 322124780 | S101: =sum(S89:S100) -> 49487000 | U101: 12 | V101: =E100-M100 -> 7406250 | W101: =N100-F100 -> -3827500 | X101: =G100-P100 -> 2370000 | Y101: =Q100-H100 -> -2370000 | Z101: =I100-R100 -> 5307356 | AA101: =J100-S100 -> 4443750
...

Sheet Money plan yearly
B1: 2023 | C1: ='25.04'!H419 -> #REF!
B2: Income | C2: Private | D2: Salary | E2: Interest | F2: Togohub | G2: N&M studio | H2: Tổng
B3: 1 | C3: 21558531 | D3: 20700000 | E3: 880 | F3: -41027927 | G3: 25182248 | H3: =sum(C3:G3) -> 26413732
B4: 2
B5: 3
B6: 4
B7: 5
B8: 6
B9: 7
B10: 8
B11: 9
B12: 10
B13: 11
B14: 12
B15: Total | C15: =sum(C3:C14)/12 -> 1796544.2 | D15: =sum(D3:D14)/12 -> 1725000 | E15: =sum(E3:E14)/12 -> 73.333333 | F15: =sum(F3:F14)/12 -> -3418993.9 | G15: =sum(G3:G14)/12 -> 2098520.7 | H15: =sum(H3:H14)/12 -> 2201144.3
B17: Funds | C17: Education | D17: Enjoy | E17: For give | F17: Health | G17: Living | H17: Savings
B18: 1 | C18: 10155000 | D18: 515000 | E18: 4679000 | F18: 0 | G18: 23138163 | H18: 0
B19: 2 | C19: =$H4*#REF! -> #REF! | D19: =$H4*#REF! -> #REF! | E19: =$H4*#REF! -> #REF! | F19: =$H4*#REF! -> #REF! | G19: =$H4*#REF! -> #REF! | H19: =$H4*#REF! -> #REF!
B20: 3 | C20: =$H5*#REF! -> #REF! | D20: =$H5*#REF! -> #REF! | E20: =$H5*#REF! -> #REF! | F20: =$H5*#REF! -> #REF! | G20: =$H5*#REF! -> #REF! | H20: =$H5*#REF! -> #REF!
B21: 4 | C21: =$H6*#REF! -> #REF! | D21: =$H6*#REF! -> #REF! | E21: =$H6*#REF! -> #REF! | F21: =$H6*#REF! -> #REF! | G21: =$H6*#REF! -> #REF! | H21: =$H6*#REF! -> #REF!
B22: 5 | C22: =$H7*#REF! -> #REF! | D22: =$H7*#REF! -> #REF! | E22: =$H7*#REF! -> #REF! | F22: =$H7*#REF! -> #REF! | G22: =$H7*#REF! -> #REF! | H22: =$H7*#REF! -> #REF!
B23: 6 | C23: =$H8*#REF! -> #REF! | D23: =$H8*#REF! -> #REF! | E23: =$H8*#REF! -> #REF! | F23: =$H8*#REF! -> #REF! | G23: =$H8*#REF! -> #REF! | H23: =$H8*#REF! -> #REF!
B24: 7 | C24: =$H9*#REF! -> #REF! | D24: =$H9*#REF! -> #REF! | E24: =$H9*#REF! -> #REF! | F24: =$H9*#REF! -> #REF! | G24: =$H9*#REF! -> #REF! | H24: =$H9*#REF! -> #REF!
B25: 8 | C25: =$H10*#REF! -> #REF! | D25: =$H10*#REF! -> #REF! | E25: =$H10*#REF! -> #REF! | F25: =$H10*#REF! -> #REF! | G25: =$H10*#REF! -> #REF! | H25: =$H10*#REF! -> #REF!
B26: 9 | C26: =$H11*#REF! -> #REF! | D26: =$H11*#REF! -> #REF! | E26: =$H11*#REF! -> #REF! | F26: =$H11*#REF! -> #REF! | G26: =$H11*#REF! -> #REF! | H26: =$H11*#REF! -> #REF!
B27: 10 | C27: =$H12*#REF! -> #REF! | D27: =$H12*#REF! -> #REF! | E27: =$H12*#REF! -> #REF! | F27: =$H12*#REF! -> #REF! | G27: =$H12*#REF! -> #REF! | H27: =$H12*#REF! -> #REF!
B28: 11 | C28: =$H13*#REF! -> #REF! | D28: =$H13*#REF! -> #REF! | E28: =$H13*#REF! -> #REF! | F28: =$H13*#REF! -> #REF! | G28: =$H13*#REF! -> #REF! | H28: =$H13*#REF! -> #REF!
B29: 12 | C29: =$H14*#REF! -> #REF! | D29: =$H14*#REF! -> #REF! | E29: =$H14*#REF! -> #REF! | F29: =$H14*#REF! -> #REF! | G29: =$H14*#REF! -> #REF! | H29: =$H14*#REF! -> #REF!
C30: =SUM(C18:C29) -> #REF! | D30: =SUM(D18:D29) -> #REF! | E30: =SUM(E18:E29) -> #REF! | F30: =SUM(F18:F29) -> #REF! | G30: =SUM(G18:G29) -> #REF! | H30: =SUM(H18:H29) -> #REF! | I30: =SUM(C30:H30) -> #REF!
