Workbook

Sheet 25.06
B2: this month is | E2: May | F2: 2025
B4: How much money do you have coming in? and spend out?
D5: ( + ) | F5: (-) | I5: ( + )
B6: Month | C6: Date | D6: SOURCE | E6: Name | F6: Account | G6: Fund | H6: AMOUNT | I6: Fund | J6: Account
C7: 45810 | E7: Trả commission | F7: Vietcombank | G7: Togohub management | H7: 6000000
F8: Vietcombank | G8: T. Mainternance
C9: 45822 | E9: nước | F9: Vietcombank | G9: T. Water | H9: 1033850
C10: 45811 | E10: điện | F10: Vietcombank | G10: T. Electricity | H10: 4544704
E11: trả Phương Anh cọc nhà | F11: Vietcombank | G11: Togohub management | H11: 10730000
C12: 45828 | D12: House rental money | E12: Lợi trả tiền điện nước | H12: 4157000 | I12: T. Electricity | J12: Vietcombank
C13: 45821 | D13: House rental money | E13: Lợi trả tiền nhà | H13: 36000000 | I13: Togohub management | J13: Vietcombank
C14: 45821 | D14: House rental money | E14: Nhận cọc nhà | H14: 11000000 | I14: Togohub management | J14: Vietcombank
C15: 45836 | D15: House rental money | E15: Tiền thuê nhà | H15: 33000000 | I15: Togohub management | J15: Vietcombank
C74: 45322
C75: 45322
C76: 45322
C77: 45322
C78: 45322
C79: 45322
C80: 45322
E163: TOTAL (A) | H163: =sum(H7:H162) -> 106465554
B165: How much money do you have going out? | E165: =#REF! -> #REF!
B168: How much money do you have available to you?
B169: TOTAL (A) | D169: - | E169: TOTAL (B) | F169: = | H169: TOTAL (C)
B170: =H163 -> 106465554 | E170: =#REF! -> #REF! | H170: =B170-E170 -> #REF!
B172: How much money do you want to save
B173: TOTAL (D) | E173: ='Spending 25.06'!F99+#REF! -> #REF!
B175: What for?
B181: How much should you spend?
B182: TOTAL (C) | D182: - | E182: TOTAL (D) | F182: = | H182: TOTAL (E) (PER MONTH)
B183: =H170 -> #REF! | E183: =E173 -> #REF! | H183: =H170-E173 -> #REF!
B185: TOTAL (E) | D185: / | E185: No OF WEEKS | F185: = | H185: TOTAL (PER WEEK)
B186: =H183 -> #REF! | E186: 5 | H186: =B186/E186 -> #REF!
B188: NOTES

Sheet Spending 25.06
A1: Chi tiêu thực tế
C2: (-) | S2: ( + )
C3: Cash | D3: BIDV | E3: Vietcombank | F3: Vp bank Lady | G3: Moca | H3: Momo | I3: Zalo | J3: Saving | K3: Loan | L3: Total out | N3: % | O3: % | R3: Cash | S3: BIDV | T3: Vietcombank | U3: Vp bank Lady | V3: Moca | W3: Momo | X3: Zalo | Y3: Saving | Z3: Loan | AA3: Total in
A4: 1 | B4: Education | C4: =sumifs('25.06'!$H$7:$H$162,'25.06'!$G$7:$G$162,$B4,'25.06'!$F$7:$F$162,C$3) -> 0 | D4: =sumifs('25.06'!$H$7:$H$162,'25.06'!$G$7:$G$162,$B4,'25.06'!$F$7:$F$162,D$3) -> 0 | E4: =sumifs('25.06'!$H$7:$H$162,'25.06'!$G$7:$G$162,$B4,'25.06'!$F$7:$F$162,E$3) -> 0 | F4: =sumifs('25.06'!$H$7:$H$162,'25.06'!$G$7:$G$162,$B4,'25.06'!$F$7:$F$162,F$3) -> 0 | G4: =sumifs('25.06'!$H$7:$H$162,'25.06'!$G$7:$G$162,$B4,'25.06'!$F$7:$F$162,G$3) -> 0 | H4: =sumifs('25.06'!$H$7:$H$162,'25.06'!$G$7:$G$162,$B4,'25.06'!$F$7:$F$162,H$3) -> 0 | I4: =sumifs('25.06'!$H$7:$H$162,'25.06'!$G$7:$G$162,$B4,'25.06'!$F$7:$F$162,I$3) -> 0 | J4: =sumifs('25.06'!$H$7:$H$162,'25.06'!$G$7:$G$162,$B4,'25.06'!$F$7:$F$162,J$3) -> 0 | K4: =sumifs('25.06'!$H$7:$H$162,'25.06'!$G$7:$G$162,$B4,'25.06'!$F$7:$F$162,K$3) -> 0 | L4: =sum(C4:K4) -> 0 | N4: =L4/sum(L$4:L$9) -> #DIV/0! | P4: =sum(L4:L9) -> 0 | Q4: =P4/sum($P$4:$P$57) -> #DIV/0! | R4: =sumifs('25.06'!$H$7:$H$162,'25.06'!$I$7:$I$162,$B4,'25.06'!$J$7:$J$162,R$3) -> 0 | S4: =sumifs('25.06'!$H$7:$H$162,'25.06'!$I$7:$I$162,$B4,'25.06'!$J$7:$J$162,S$3) -> 0 | T4: =sumifs('25.06'!$H$7:$H$162,'25.06'!$I$7:$I$162,$B4,'25.06'!$J$7:$J$162,T$3) -> 0 | U4: =sumifs('25.06'!$H$7:$H$162,'25.06'!$I$7:$I$162,$B4,'25.06'!$J$7:$J$162,U$3) -> 0 | V4: =sumifs('25.06'!$H$7:$H$162,'25.06'!$I$7:$I$162,$B4,'25.06'!$J$7:$J$162,V$3) -> 0 | W4: =sumifs('25.06'!$H$7:$H$162,'25.06'!$I$7:$I$162,$B4,'25.06'!$J$7:$J$162,W$3) -> 0 | X4: =sumifs('25.06'!$H$7:$H$162,'25.06'!$I$7:$I$162,$B4,'25.06'!$J$7:$J$162,X$3) -> 0 | Y4: =sumifs('25.06'!$H$7:$H$162,'25.06'!$I$7:$I$162,$B4,'25.06'!$J$7:$J$162,Y$3) -> 0 | Z4: =sumifs('25.06'!$H$7:$H$162,'25.06'!$I$7:$I$162,$B4,'25.06'!$J$7:$J$162,Z$3) -> 0 | AA4: =sum(R4:Z4) -> 0
A5: 44927 | B5: Education fee | C5: =sumifs('25.06'!$H$7:$H$162,'25.06'!$G$7:$G$162,$B5,'25.06'!$F$7:$F$162,C$3) -> 0 | D5: =sumifs('25.06'!$H$7:$H$162,'25.06'!$G$7:$G$162,$B5,'25.06'!$F$7:$F$162,D$3) -> 0 | E5: =sumifs('25.06'!$H$7:$H$162,'25.06'!$G$7:$G$162,$B5,'25.06'!$F$7:$F$162,E$3) -> 0 | F5: =sumifs('25.06'!$H$7:$H$162,'25.06'!$G$7:$G$162,$B5,'25.06'!$F$7:$F$162,F$3) -> 0 | G5: =sumifs('25.06'!$H$7:$H$162,'25.06'!$G$7:$G$162,$B5,'25.06'!$F$7:$F$162,G$3) -> 0 | H5: =sumifs('25.06'!$H$7:$H$162,'25.06'!$G$7:$G$162,$B5,'25.06'!$F$7:$F$162,H$3) -> 0 | I5: =sumifs('25.06'!$H$7:$H$162,'25.06'!$G$7:$G$162,$B5,'25.06'!$F$7:$F$162,I$3) -> 0 | J5: =sumifs('25.06'!$H$7:$H$162,'25.06'!$G$7:$G$162,$B5,'25.06'!$F$7:$F$162,J$3) -> 0 | K5: =sumifs('25.06'!$H$7:$H$162,'25.06'!$G$7:$G$162,$B5,'25.06'!$F$7:$F$162,K$3) -> 0 | L5: =sum(C5:K5) -> 0 | N5: =L5/sum(L$4:L$9) -> #DIV/0! | R5: =sumifs('25.06'!$H$7:$H$162,'25.06'!$I$7:$I$162,$B5,'25.06'!$J$7:$J$162,R$3) -> 0 | S5: =sumifs('25.06'!$H$7:$H$162,'25.06'!$I$7:$I$162,$B5,'25.06'!$J$7:$J$162,S$3) -> 0 | T5: =sumifs('25.06'!$H$7:$H$162,'25.06'!$I$7:$I$162,$B5,'25.06'!$J$7:$J$162,T$3) -> 0 | U5: =sumifs('25.06'!$H$7:$H$162,'25.06'!$I$7:$I$162,$B5,'25.06'!$J$7:$J$162,U$3) -> 0 | V5: =sumifs('25.06'!$H$7:$H$162,'25.06'!$I$7:$I$162,$B5,'25.06'!$J$7:$J$162,V$3) -> 0 | W5: =sumifs('25.06'!$H$7:$H$162,'25.06'!$I$7:$I$162,$B5,'25.06'!$J$7:$J$162,W$3) -> 0 | X5: =sumifs('25.06'!$H$7:$H$162,'25.06'!$I$7:$I$162,$B5,'25.06'!$J$7:$J$162,X$3) -> 0 | Y5: =sumifs('25.06'!$H$7:$H$162,'25.06'!$I$7:$I$162,$B5,'25.06'!$J$7:$J$162,Y$3) -> 0 | Z5: =sumifs('25.06'!$H$7:$H$162,'25.06'!$I$7:$I$162,$B5,'25.06'!$J$7:$J$162,Z$3) -> 0 | AA5: =sum(R5:Z5) -> 0
A6: 44958 | B6: Extra Education fee | C6: =sumifs('25.06'!$H$7:$H$162,'25.06'!$G$7:$G$162,$B6,'25.06'!$F$7:$F$162,C$3) -> 0 | D6: =sumifs('25.06'!$H$7:$H$162,'25.06'!$G$7:$G$162,$B6,'25.06'!$F$7:$F$162,D$3) -> 0 | E6: =sumifs('25.06'!$H$7:$H$162,'25.06'!$G$7:$G$162,$B6,'25.06'!$F$7:$F$162,E$3) -> 0 | F6: =sumifs('25.06'!$H$7:$H$162,'25.06'!$G$7:$G$162,$B6,'25.06'!$F$7:$F$162,F$3) -> 0 | G6: =sumifs('25.06'!$H$7:$H$162,'25.06'!$G$7:$G$162,$B6,'25.06'!$F$7:$F$162,G$3) -> 0 | H6: =sumifs('25.06'!$H$7:$H$162,'25.06'!$G$7:$G$162,$B6,'25.06'!$F$7:$F$162,H$3) -> 0 | I6: =sumifs('25.06'!$H$7:$H$162,'25.06'!$G$7:$G$162,$B6,'25.06'!$F$7:$F$162,I$3) -> 0 | J6: =sumifs('25.06'!$H$7:$H$162,'25.06'!$G$7:$G$162,$B6,'25.06'!$F$7:$F$162,J$3) -> 0 | K6: =sumifs('25.06'!$H$7:$H$162,'25.06'!$G$7:$G$162,$B6,'25.06'!$F$7:$F$162,K$3) -> 0 | L6: =sum(C6:K6) -> 0 | N6: =L6/sum(L$4:L$9) -> #DIV/0! | R6: =sumifs('25.06'!$H$7:$H$162,'25.06'!$I$7:$I$162,$B6,'25.06'!$J$7:$J$162,R$3) -> 0 | S6: =sumifs('25.06'!$H$7:$H$162,'25.06'!$I$7:$I$162,$B6,'25.06'!$J$7:$J$162,S$3) -> 0 | T6: =sumifs('25.06'!$H$7:$H$162,'25.06'!$I$7:$I$162,$B6,'25.06'!$J$7:$J$162,T$3) -> 0 | U6: =sumifs('25.06'!$H$7:$H$162,'25.06'!$I$7:$I$162,$B6,'25.06'!$J$7:$J$162,U$3) -> 0 | V6: =sumifs('25.06'!$H$7:$H$162,'25.06'!$I$7:$I$162,$B6,'25.06'!$J$7:$J$162,V$3) -> 0 | W6: =sumifs('25.06'!$H$7:$H$162,'25.06'!$I$7:$I$162,$B6,'25.06'!$J$7:$J$162,W$3) -> 0 | X6: =sumifs('25.06'!$H$7:$H$162,'25.06'!$I$7:$I$162,$B6,'25.06'!$J$7:$J$162,X$3) -> 0 | Y6: =sumifs('25.06'!$H$7:$H$162,'25.06'!$I$7:$I$162,$B6,'25.06'!$J$7:$J$162,Y$3) -> 0 | Z6: =sumifs('25.06'!$H$7:$H$162,'25.06'!$I$7:$I$162,$B6,'25.06'!$J$7:$J$162,Z$3) -> 0 | AA6: =sum(R6:Z6) -> 0
A7: 44986 | B7: Talent Education fee | C7: =sumifs('25.06'!$H$7:$H$162,'25.06'!$G$7:$G$162,$B7,'25.06'!$F$7:$F$162,C$3) -> 0 | D7: =sumifs('25.06'!$H$7:$H$162,'25.06'!$G$7:$G$162,$B7,'25.06'!$F$7:$F$162,D$3) -> 0 | E7: =sumifs('25.06'!$H$7:$H$162,'25.06'!$G$7:$G$162,$B7,'25.06'!$F$7:$F$162,E$3) -> 0 | F7: =sumifs('25.06'!$H$7:$H$162,'25.06'!$G$7:$G$162,$B7,'25.06'!$F$7:$F$162,F$3) -> 0 | G7: =sumifs('25.06'!$H$7:$H$162,'25.06'!$G$7:$G$162,$B7,'25.06'!$F$7:$F$162,G$3) -> 0 | H7: =sumifs('25.06'!$H$7:$H$162,'25.06'!$G$7:$G$162,$B7,'25.06'!$F$7:$F$162,H$3) -> 0 | I7: =sumifs('25.06'!$H$7:$H$162,'25.06'!$G$7:$G$162,$B7,'25.06'!$F$7:$F$162,I$3) -> 0 | J7: =sumifs('25.06'!$H$7:$H$162,'25.06'!$G$7:$G$162,$B7,'25.06'!$F$7:$F$162,J$3) -> 0 | K7: =sumifs('25.06'!$H$7:$H$162,'25.06'!$G$7:$G$162,$B7,'25.06'!$F$7:$F$162,K$3) -> 0 | L7: =sum(C7:K7) -> 0 | N7: =L7/sum(L$4:L$9) -> #DIV/0! | R7: =sumifs('25.06'!$H$7:$H$162,'25.06'!$I$7:$I$162,$B7,'25.06'!$J$7:$J$162,R$3) -> 0 | S7: =sumifs('25.06'!$H$7:$H$162,'25.06'!$I$7:$I$162,$B7,'25.06'!$J$7:$J$162,S$3) -> 0 | T7: =sumifs('25.06'!$H$7:$H$162,'25.06'!$I$7:$I$162,$B7,'25.06'!$J$7:$J$162,T$3) -> 0 | U7: =sumifs('25.06'!$H$7:$H$162,'25.06'!$I$7:$I$162,$B7,'25.06'!$J$7:$J$162,U$3) -> 0 | V7: =sumifs('25.06'!$H$7:$H$162,'25.06'!$I$7:$I$162,$B7,'25.06'!$J$7:$J$162,V$3) -> 0 | W7: =sumifs('25.06'!$H$7:$H$162,'25.06'!$I$7:$I$162,$B7,'25.06'!$J$7:$J$162,W$3) -> 0 | X7: =sumifs('25.06'!$H$7:$H$162,'25.06'!$I$7:$I$162,$B7,'25.06'!$J$7:$J$162,X$3) -> 0 | Y7: =sumifs('25.06'!$H$7:$H$162,'25.06'!$I$7:$I$162,$B7,'25.06'!$J$7:$J$162,Y$3) -> 0 | Z7: =sumifs('25.06'!$H$7:$H$162,'25.06'!$I$7:$I$162,$B7,'25.06'!$J$7:$J$162,Z$3) -> 0 | AA7: =sum(R7:Z7) -> 0
A8: 45017 | B8: Books | C8: =sumifs('25.06'!$H$7:$H$162,'25.06'!$G$7:$G$162,$B8,'25.06'!$F$7:$F$162,C$3) -> 0 | D8: =sumifs('25.06'!$H$7:$H$162,'25.06'!$G$7:$G$162,$B8,'25.06'!$F$7:$F$162,D$3) -> 0 | E8: =sumifs('25.06'!$H$7:$H$162,'25.06'!$G$7:$G$162,$B8,'25.06'!$F$7:$F$162,E$3) -> 0 | F8: =sumifs('25.06'!$H$7:$H$162,'25.06'!$G$7:$G$162,$B8,'25.06'!$F$7:$F$162,F$3) -> 0 | G8: =sumifs('25.06'!$H$7:$H$162,'25.06'!$G$7:$G$162,$B8,'25.06'!$F$7:$F$162,G$3) -> 0 | H8: =sumifs('25.06'!$H$7:$H$162,'25.06'!$G$7:$G$162,$B8,'25.06'!$F$7:$F$162,H$3) -> 0 | I8: =sumifs('25.06'!$H$7:$H$162,'25.06'!$G$7:$G$162,$B8,'25.06'!$F$7:$F$162,I$3) -> 0 | J8: =sumifs('25.06'!$H$7:$H$162,'25.06'!$G$7:$G$162,$B8,'25.06'!$F$7:$F$162,J$3) -> 0 | K8: =sumifs('25.06'!$H$7:$H$162,'25.06'!$G$7:$G$162,$B8,'25.06'!$F$7:$F$162,K$3) -> 0 | L8: =sum(C8:K8) -> 0 | N8: =L8/sum(L$4:L$9) -> #DIV/0! | R8: =sumifs('25.06'!$H$7:$H$162,'25.06'!$I$7:$I$162,$B8,'25.06'!$J$7:$J$162,R$3) -> 0 | S8: =sumifs('25.06'!$H$7:$H$162,'25.06'!$I$7:$I$162,$B8,'25.06'!$J$7:$J$162,S$3) -> 0 | T8: =sumifs('25.06'!$H$7:$H$162,'25.06'!$I$7:$I$162,$B8,'25.06'!$J$7:$J$162,T$3) -> 0 | U8: =sumifs('25.06'!$H$7:$H$162,'25.06'!$I$7:$I$162,$B8,'25.06'!$J$7:$J$162,U$3) -> 0 | V8: =sumifs('25.06'!$H$7:$H$162,'25.06'!$I$7:$I$162,$B8,'25.06'!$J$7:$J$162,V$3) -> 0 | W8: =sumifs('25.06'!$H$7:$H$162,'25.06'!$I$7:$I$162,$B8,'25.06'!$J$7:$J$162,W$3) -> 0 | X8: =sumifs('25.06'!$H$7:$H$162,'25.06'!$I$7:$I$162,$B8,'25.06'!$J$7:$J$162,X$3) -> 0 | Y8: =sumifs('25.06'!$H$7:$H$162,'25.06'!$I$7:$I$162,$B8,'25.06'!$J$7:$J$162,Y$3) -> 0 | Z8: =sumifs('25.06'!$H$7:$H$162,'25.06'!$I$7:$I$162,$B8,'25.06'!$J$7:$J$162,Z$3) -> 0 | AA8: =sum(R8:Z8) -> 0
A9: 45047 | B9: Stationery | C9: =sumifs('25.06'!$H$7:$H$162,'25.06'!$G$7:$G$162,$B9,'25.06'!$F$7:$F$162,C$3) -> 0 | D9: =sumifs('25.06'!$H$7:$H$162,'25.06'!$G$7:$G$162,$B9,'25.06'!$F$7:$F$162,D$3) -> 0 | E9: =sumifs('25.06'!$H$7:$H$162,'25.06'!$G$7:$G$162,$B9,'25.06'!$F$7:$F$162,E$3) -> 0 | F9: =sumifs('25.06'!$H$7:$H$162,'25.06'!$G$7:$G$162,$B9,'25.06'!$F$7:$F$162,F$3) -> 0 | G9: =sumifs('25.06'!$H$7:$H$162,'25.06'!$G$7:$G$162,$B9,'25.06'!$F$7:$F$162,G$3) -> 0 | H9: =sumifs('25.06'!$H$7:$H$162,'25.06'!$G$7:$G$162,$B9,'25.06'!$F$7:$F$162,H$3) -> 0 | I9: =sumifs('25.06'!$H$7:$H$162,'25.06'!$G$7:$G$162,$B9,'25.06'!$F$7:$F$162,I$3) -> 0 | J9: =sumifs('25.06'!$H$7:$H$162,'25.06'!$G$7:$G$162,$B9,'25.06'!$F$7:$F$162,J$3) -> 0 | K9: =sumifs('25.06'!$H$7:$H$162,'25.06'!$G$7:$G$162,$B9,'25.06'!$F$7:$F$162,K$3) -> 0 | L9: =sum(C9:K9) -> 0 | N9: =L9/sum(L$4:L$9) -> #DIV/0! | R9: =sumifs('25.06'!$H$7:$H$162,'25.06'!$I$7:$I$162,$B9,'25.06'!$J$7:$J$162,R$3) -> 0 | S9: =sumifs('25.06'!$H$7:$H$162,'25.06'!$I$7:$I$162,$B9,'25.06'!$J$7:$J$162,S$3) -> 0 | T9: =sumifs('25.06'!$H$7:$H$162,'25.06'!$I$7:$I$162,$B9,'25.06'!$J$7:$J$162,T$3) -> 0 | U9: =sumifs('25.06'!$H$7:$H$162,'25.06'!$I$7:$I$162,$B9,'25.06'!$J$7:$J$162,U$3) -> 0 | V9: =sumifs('25.06'!$H$7:$H$162,'25.06'!$I$7:$I$162,$B9,'25.06'!$J$7:$J$162,V$3) -> 0 | W9: =sumifs('25.06'!$H$7:$H$162,'25.06'!$I$7:$I$162,$B9,'25.06'!$J$7:$J$162,W$3) -> 0 | X9: =sumifs('25.06'!$H$7:$H$162,'25.06'!$I$7:$I$162,$B9,'25.06'!$J$7:$J$162,X$3) -> 0 | Y9: =sumifs('25.06'!$H$7:$H$162,'25.06'!$I$7:$I$162,$B9,'25.06'!$J$7:$J$162,Y$3) -> 0 | Z9: =sumifs('25.06'!$H$7:$H$162,'25.06'!$I$7:$I$162,$B9,'25.06'!$J$7:$J$162,Z$3) -> 0 | AA9: =sum(R9:Z9) -> 0
A10: 2 | B10: Enjoy | C10: =sumifs('25.06'!$H$7:$H$162,'25.06'!$G$7:$G$162,$B10,'25.06'!$F$7:$F$162,C$3) -> 0 | D10: =sumifs('25.06'!$H$7:$H$162,'25.06'!$G$7:$G$162,$B10,'25.06'!$F$7:$F$162,D$3) -> 0 | E10: =sumifs('25.06'!$H$7:$H$162,'25.06'!$G$7:$G$162,$B10,'25.06'!$F$7:$F$162,E$3) -> 0 | F10: =sumifs('25.06'!$H$7:$H$162,'25.06'!$G$7:$G$162,$B10,'25.06'!$F$7:$F$162,F$3) -> 0 | G10: =sumifs('25.06'!$H$7:$H$162,'25.06'!$G$7:$G$162,$B10,'25.06'!$F$7:$F$162,G$3) -> 0 | H10: =sumifs('25.06'!$H$7:$H$162,'25.06'!$G$7:$G$162,$B10,'25.06'!$F$7:$F$162,H$3) -> 0 | I10: =sumifs('25.06'!$H$7:$H$162,'25.06'!$G$7:$G$162,$B10,'25.06'!$F$7:$F$162,I$3) -> 0 | J10: =sumifs('25.06'!$H$7:$H$162,'25.06'!$G$7:$G$162,$B10,'25.06'!$F$7:$F$162,J$3) -> 0 | K10: =sumifs('25.06'!$H$7:$H$162,'25.06'!$G$7:$G$162,$B10,'25.06'!$F$7:$F$162,K$3) -> 0 | L10: =sum(C10:K10) -> 0 | N10: =L10/sum(L$10:L$16) -> #DIV/0! | P10: =sum(L10:L16) -> 0 | Q10: =P10/sum($P$4:$P$57) -> #DIV/0! | R10: =sumifs('25.06'!$H$7:$H$162,'25.06'!$I$7:$I$162,$B10,'25.06'!$J$7:$J$162,R$3) -> 0 | S10: =sumifs('25.06'!$H$7:$H$162,'25.06'!$I$7:$I$162,$B10,'25.06'!$J$7:$J$162,S$3) -> 0 | T10: =sumifs('25.06'!$H$7:$H$162,'25.06'!$I$7:$I$162,$B10,'25.06'!$J$7:$J$162,T$3) -> 0 | U10: =sumifs('25.06'!$H$7:$H$162,'25.06'!$I$7:$I$162,$B10,'25.06'!$J$7:$J$162,U$3) -> 0 | V10: =sumifs('25.06'!$H$7:$H$162,'25.06'!$I$7:$I$162,$B10,'25.06'!$J$7:$J$162,V$3) -> 0 | W10: =sumifs('25.06'!$H$7:$H$162,'25.06'!$I$7:$I$162,$B10,'25.06'!$J$7:$J$162,W$3) -> 0 | X10: =sumifs('25.06'!$H$7:$H$162,'25.06'!$I$7:$I$162,$B10,'25.06'!$J$7:$J$162,X$3) -> 0 | Y10: =sumifs('25.06'!$H$7:$H$162,'25.06'!$I$7:$I$162,$B10,'25.06'!$J$7:$J$162,Y$3) -> 0 | Z10: =sumifs('25.06'!$H$7:$H$162,'25.06'!$I$7:$I$162,$B10,'25.06'!$J$7:$J$162,Z$3) -> 0 | AA10: =sum(R10:Z10) -> 0
A11: 44928 | B11: Travel | C11: =sumifs('25.06'!$H$7:$H$162,'25.06'!$G$7:$G$162,$B11,'25.06'!$F$7:$F$162,C$3) -> 0 | D11: =sumifs('25.06'!$H$7:$H$162,'25.06'!$G$7:$G$162,$B11,'25.06'!$F$7:$F$162,D$3) -> 0 | E11: =sumifs('25.06'!$H$7:$H$162,'25.06'!$G$7:$G$162,$B11,'25.06'!$F$7:$F$162,E$3) -> 0 | F11: =sumifs('25.06'!$H$7:$H$162,'25.06'!$G$7:$G$162,$B11,'25.06'!$F$7:$F$162,F$3) -> 0 | G11: =sumifs('25.06'!$H$7:$H$162,'25.06'!$G$7:$G$162,$B11,'25.06'!$F$7:$F$162,G$3) -> 0 | H11: =sumifs('25.06'!$H$7:$H$162,'25.06'!$G$7:$G$162,$B11,'25.06'!$F$7:$F$162,H$3) -> 0 | I11: =sumifs('25.06'!$H$7:$H$162,'25.06'!$G$7:$G$162,$B11,'25.06'!$F$7:$F$162,I$3) -> 0 | J11: =sumifs('25.06'!$H$7:$H$162,'25.06'!$G$7:$G$162,$B11,'25.06'!$F$7:$F$162,J$3) -> 0 | K11: =sumifs('25.06'!$H$7:$H$162,'25.06'!$G$7:$G$162,$B11,'25.06'!$F$7:$F$162,K$3) -> 0 | L11: =sum(C11:K11) -> 0 | N11: =L11/sum(L$10:L$16) -> #DIV/0! | R11: =sumifs('25.06'!$H$7:$H$162,'25.06'!$I$7:$I$162,$B11,'25.06'!$J$7:$J$162,R$3) -> 0 | S11: =sumifs('25.06'!$H$7:$H$162,'25.06'!$I$7:$I$162,$B11,'25.06'!$J$7:$J$162,S$3) -> 0 | T11: =sumifs('25.06'!$H$7:$H$162,'25.06'!$I$7:$I$162,$B11,'25.06'!$J$7:$J$162,T$3) -> 0 | U11: =sumifs('25.06'!$H$7:$H$162,'25.06'!$I$7:$I$162,$B11,'25.06'!$J$7:$J$162,U$3) -> 0 | V11: =sumifs('25.06'!$H$7:$H$162,'25.06'!$I$7:$I$162,$B11,'25.06'!$J$7:$J$162,V$3) -> 0 | W11: =sumifs('25.06'!$H$7:$H$162,'25.06'!$I$7:$I$162,$B11,'25.06'!$J$7:$J$162,W$3) -> 0 | X11: =sumifs('25.06'!$H$7:$H$162,'25.06'!$I$7:$I$162,$B11,'25.06'!$J$7:$J$162,X$3) -> 0 | Y11: =sumifs('25.06'!$H$7:$H$162,'25.06'!$I$7:$I$162,$B11,'25.06'!$J$7:$J$162,Y$3) -> 0 | Z11: =sumifs('25.06'!$H$7:$H$162,'25.06'!$I$7:$I$162,$B11,'25.06'!$J$7:$J$162,Z$3) -> 0 | AA11: =sum(R11:Z11) -> 0
A12: 44959 | B12: Café | C12: =sumifs('25.06'!$H$7:$H$162,'25.06'!$G$7:$G$162,$B12,'25.06'!$F$7:$F$162,C$3) -> 0 | D12: =sumifs('25.06'!$H$7:$H$162,'25.06'!$G$7:$G$162,$B12,'25.06'!$F$7:$F$162,D$3) -> 0 | E12: =sumifs('25.06'!$H$7:$H$162,'25.06'!$G$7:$G$162,$B12,'25.06'!$F$7:$F$162,E$3) -> 0 | F12: =sumifs('25.06'!$H$7:$H$162,'25.06'!$G$7:$G$162,$B12,'25.06'!$F$7:$F$162,F$3) -> 0 | G12: =sumifs('25.06'!$H$7:$H$162,'25.06'!$G$7:$G$162,$B12,'25.06'!$F$7:$F$162,G$3) -> 0 | H12: =sumifs('25.06'!$H$7:$H$162,'25.06'!$G$7:$G$162,$B12,'25.06'!$F$7:$F$162,H$3) -> 0 | I12: =sumifs('25.06'!$H$7:$H$162,'25.06'!$G$7:$G$162,$B12,'25.06'!$F$7:$F$162,I$3) -> 0 | J12: =sumifs('25.06'!$H$7:$H$162,'25.06'!$G$7:$G$162,$B12,'25.06'!$F$7:$F$162,J$3) -> 0 | K12: =sumifs('25.06'!$H$7:$H$162,'25.06'!$G$7:$G$162,$B12,'25.06'!$F$7:$F$162,K$3) -> 0 | L12: =sum(C12:K12) -> 0 | N12: =L12/sum(L$10:L$16) -> #DIV/0! | R12: =sumifs('25.06'!$H$7:$H$162,'25.06'!$I$7:$I$162,$B12,'25.06'!$J$7:$J$162,R$3) -> 0 | S12: =sumifs('25.06'!$H$7:$H$162,'25.06'!$I$7:$I$162,$B12,'25.06'!$J$7:$J$162,S$3) -> 0 | T12: =sumifs('25.06'!$H$7:$H$162,'25.06'!$I$7:$I$162,$B12,'25.06'!$J$7:$J$162,T$3) -> 0 | U12: =sumifs('25.06'!$H$7:$H$162,'25.06'!$I$7:$I$162,$B12,'25.06'!$J$7:$J$162,U$3) -> 0 | V12: =sumifs('25.06'!$H$7:$H$162,'25.06'!$I$7:$I$162,$B12,'25.06'!$J$7:$J$162,V$3) -> 0 | W12: =sumifs('25.06'!$H$7:$H$162,'25.06'!$I$7:$I$162,$B12,'25.06'!$J$7:$J$162,W$3) -> 0 | X12: =sumifs('25.06'!$H$7:$H$162,'25.06'!$I$7:$I$162,$B12,'25.06'!$J$7:$J$162,X$3) -> 0 | Y12: =sumifs('25.06'!$H$7:$H$162,'25.06'!$I$7:$I$162,$B12,'25.06'!$J$7:$J$162,Y$3) -> 0 | Z12: =sumifs('25.06'!$H$7:$H$162,'25.06'!$I$7:$I$162,$B12,'25.06'!$J$7:$J$162,Z$3) -> 0 | AA12: =sum(R12:Z12) -> 0
A13: 44987 | B13: Restaurant | C13: =sumifs('25.06'!$H$7:$H$162,'25.06'!$G$7:$G$162,$B13,'25.06'!$F$7:$F$162,C$3) -> 0 | D13: =sumifs('25.06'!$H$7:$H$162,'25.06'!$G$7:$G$162,$B13,'25.06'!$F$7:$F$162,D$3) -> 0 | E13: =sumifs('25.06'!$H$7:$H$162,'25.06'!$G$7:$G$162,$B13,'25.06'!$F$7:$F$162,E$3) -> 0 | F13: =sumifs('25.06'!$H$7:$H$162,'25.06'!$G$7:$G$162,$B13,'25.06'!$F$7:$F$162,F$3) -> 0 | G13: =sumifs('25.06'!$H$7:$H$162,'25.06'!$G$7:$G$162,$B13,'25.06'!$F$7:$F$162,G$3) -> 0 | H13: =sumifs('25.06'!$H$7:$H$162,'25.06'!$G$7:$G$162,$B13,'25.06'!$F$7:$F$162,H$3) -> 0 | I13: =sumifs('25.06'!$H$7:$H$162,'25.06'!$G$7:$G$162,$B13,'25.06'!$F$7:$F$162,I$3) -> 0 | J13: =sumifs('25.06'!$H$7:$H$162,'25.06'!$G$7:$G$162,$B13,'25.06'!$F$7:$F$162,J$3) -> 0 | K13: =sumifs('25.06'!$H$7:$H$162,'25.06'!$G$7:$G$162,$B13,'25.06'!$F$7:$F$162,K$3) -> 0 | L13: =sum(C13:K13) -> 0 | N13: =L13/sum(L$10:L$16) -> #DIV/0! | R13: =sumifs('25.06'!$H$7:$H$162,'25.06'!$I$7:$I$162,$B13,'25.06'!$J$7:$J$162,R$3) -> 0 | S13: =sumifs('25.06'!$H$7:$H$162,'25.06'!$I$7:$I$162,$B13,'25.06'!$J$7:$J$162,S$3) -> 0 | T13: =sumifs('25.06'!$H$7:$H$162,'25.06'!$I$7:$I$162,$B13,'25.06'!$J$7:$J$162,T$3) -> 0 | U13: =sumifs('25.06'!$H$7:$H$162,'25.06'!$I$7:$I$162,$B13,'25.06'!$J$7:$J$162,U$3) -> 0 | V13: =sumifs('25.06'!$H$7:$H$162,'25.06'!$I$7:$I$162,$B13,'25.06'!$J$7:$J$162,V$3) -> 0 | W13: =sumifs('25.06'!$H$7:$H$162,'25.06'!$I$7:$I$162,$B13,'25.06'!$J$7:$J$162,W$3) -> 0 | X13: =sumifs('25.06'!$H$7:$H$162,'25.06'!$I$7:$I$162,$B13,'25.06'!$J$7:$J$162,X$3) -> 0 | Y13: =sumifs('25.06'!$H$7:$H$162,'25.06'!$I$7:$I$162,$B13,'25.06'!$J$7:$J$162,Y$3) -> 0 | Z13: =sumifs('25.06'!$H$7:$H$162,'25.06'!$I$7:$I$162,$B13,'25.06'!$J$7:$J$162,Z$3) -> 0 | AA13: =sum(R13:Z13) -> 0
A14: 45018 | B14: Sightseeing | C14: =sumifs('25.06'!$H$7:$H$162,'25.06'!$G$7:$G$162,$B14,'25.06'!$F$7:$F$162,C$3) -> 0 | D14: =sumifs('25.06'!$H$7:$H$162,'25.06'!$G$7:$G$162,$B14,'25.06'!$F$7:$F$162,D$3) -> 0 | E14: =sumifs('25.06'!$H$7:$H$162,'25.06'!$G$7:$G$162,$B14,'25.06'!$F$7:$F$162,E$3) -> 0 | F14: =sumifs('25.06'!$H$7:$H$162,'25.06'!$G$7:$G$162,$B14,'25.06'!$F$7:$F$162,F$3) -> 0 | G14: =sumifs('25.06'!$H$7:$H$162,'25.06'!$G$7:$G$162,$B14,'25.06'!$F$7:$F$162,G$3) -> 0 | H14: =sumifs('25.06'!$H$7:$H$162,'25.06'!$G$7:$G$162,$B14,'25.06'!$F$7:$F$162,H$3) -> 0 | I14: =sumifs('25.06'!$H$7:$H$162,'25.06'!$G$7:$G$162,$B14,'25.06'!$F$7:$F$162,I$3) -> 0 | J14: =sumifs('25.06'!$H$7:$H$162,'25.06'!$G$7:$G$162,$B14,'25.06'!$F$7:$F$162,J$3) -> 0 | K14: =sumifs('25.06'!$H$7:$H$162,'25.06'!$G$7:$G$162,$B14,'25.06'!$F$7:$F$162,K$3) -> 0 | L14: =sum(C14:K14) -> 0 | N14: =L14/sum(L$10:L$16) -> #DIV/0! | R14: =sumifs('25.06'!$H$7:$H$162,'25.06'!$I$7:$I$162,$B14,'25.06'!$J$7:$J$162,R$3) -> 0 | S14: =sumifs('25.06'!$H$7:$H$162,'25.06'!$I$7:$I$162,$B14,'25.06'!$J$7:$J$162,S$3) -> 0 | T14: =sumifs('25.06'!$H$7:$H$162,'25.06'!$I$7:$I$162,$B14,'25.06'!$J$7:$J$162,T$3) -> 0 | U14: =sumifs('25.06'!$H$7:$H$162,'25.06'!$I$7:$I$162,$B14,'25.06'!$J$7:$J$162,U$3) -> 0 | V14: =sumifs('25.06'!$H$7:$H$162,'25.06'!$I$7:$I$162,$B14,'25.06'!$J$7:$J$162,V$3) -> 0 | W14: =sumifs('25.06'!$H$7:$H$162,'25.06'!$I$7:$I$162,$B14,'25.06'!$J$7:$J$162,W$3) -> 0 | X14: =sumifs('25.06'!$H$7:$H$162,'25.06'!$I$7:$I$162,$B14,'25.06'!$J$7:$J$162,X$3) -> 0 | Y14: =sumifs('25.06'!$H$7:$H$162,'25.06'!$I$7:$I$162,$B14,'25.06'!$J$7:$J$162,Y$3) -> 0 | Z14: =sumifs('25.06'!$H$7:$H$162,'25.06'!$I$7:$I$162,$B14,'25.06'!$J$7:$J$162,Z$3) -> 0 | AA14: =sum(R14:Z14) -> 0
A15: 45048 | B15: Exhibition | C15: =sumifs('25.06'!$H$7:$H$162,'25.06'!$G$7:$G$162,$B15,'25.06'!$F$7:$F$162,C$3) -> 0 | D15: =sumifs('25.06'!$H$7:$H$162,'25.06'!$G$7:$G$162,$B15,'25.06'!$F$7:$F$162,D$3) -> 0 | E15: =sumifs('25.06'!$H$7:$H$162,'25.06'!$G$7:$G$162,$B15,'25.06'!$F$7:$F$162,E$3) -> 0 | F15: =sumifs('25.06'!$H$7:$H$162,'25.06'!$G$7:$G$162,$B15,'25.06'!$F$7:$F$162,F$3) -> 0 | G15: =sumifs('25.06'!$H$7:$H$162,'25.06'!$G$7:$G$162,$B15,'25.06'!$F$7:$F$162,G$3) -> 0 | H15: =sumifs('25.06'!$H$7:$H$162,'25.06'!$G$7:$G$162,$B15,'25.06'!$F$7:$F$162,H$3) -> 0 | I15: =sumifs('25.06'!$H$7:$H$162,'25.06'!$G$7:$G$162,$B15,'25.06'!$F$7:$F$162,I$3) -> 0 | J15: =sumifs('25.06'!$H$7:$H$162,'25.06'!$G$7:$G$162,$B15,'25.06'!$F$7:$F$162,J$3) -> 0 | K15: =sumifs('25.06'!$H$7:$H$162,'25.06'!$G$7:$G$162,$B15,'25.06'!$F$7:$F$162,K$3) -> 0 | L15: =sum(C15:K15) -> 0 | N15: =L15/sum(L$10:L$16) -> #DIV/0! | R15: =sumifs('25.06'!$H$7:$H$162,'25.06'!$I$7:$I$162,$B15,'25.06'!$J$7:$J$162,R$3) -> 0 | S15: =sumifs('25.06'!$H$7:$H$162,'25.06'!$I$7:$I$162,$B15,'25.06'!$J$7:$J$162,S$3) -> 0 | T15: =sumifs('25.06'!$H$7:$H$162,'25.06'!$I$7:$I$162,$B15,'25.06'!$J$7:$J$162,T$3) -> 0 | U15: =sumifs('25.06'!$H$7:$H$162,'25.06'!$I$7:$I$162,$B15,'25.06'!$J$7:$J$162,U$3) -> 0 | V15: =sumifs('25.06'!$H$7:$H$162,'25.06'!$I$7:$I$162,$B15,'25.06'!$J$7:$J$162,V$3) -> 0 | W15: =sumifs('25.06'!$H$7:$H$162,'25.06'!$I$7:$I$162,$B15,'25.06'!$J$7:$J$162,W$3) -> 0 | X15: =sumifs('25.06'!$H$7:$H$162,'25.06'!$I$7:$I$162,$B15,'25.06'!$J$7:$J$162,X$3) -> 0 | Y15: =sumifs('25.06'!$H$7:$H$162,'25.06'!$I$7:$I$162,$B15,'25.06'!$J$7:$J$162,Y$3) -> 0 | Z15: =sumifs('25.06'!$H$7:$H$162,'25.06'!$I$7:$I$162,$B15,'25.06'!$J$7:$J$162,Z$3) -> 0 | AA15: =sum(R15:Z15) -> 0
A16: 45079 | B16: Museum | C16: =sumifs('25.06'!$H$7:$H$162,'25.06'!$G$7:$G$162,$B16,'25.06'!$F$7:$F$162,C$3) -> 0 | D16: =sumifs('25.06'!$H$7:$H$162,'25.06'!$G$7:$G$162,$B16,'25.06'!$F$7:$F$162,D$3) -> 0 | E16: =sumifs('25.06'!$H$7:$H$162,'25.06'!$G$7:$G$162,$B16,'25.06'!$F$7:$F$162,E$3) -> 0 | F16: =sumifs('25.06'!$H$7:$H$162,'25.06'!$G$7:$G$162,$B16,'25.06'!$F$7:$F$162,F$3) -> 0 | G16: =sumifs('25.06'!$H$7:$H$162,'25.06'!$G$7:$G$162,$B16,'25.06'!$F$7:$F$162,G$3) -> 0 | H16: =sumifs('25.06'!$H$7:$H$162,'25.06'!$G$7:$G$162,$B16,'25.06'!$F$7:$F$162,H$3) -> 0 | I16: =sumifs('25.06'!$H$7:$H$162,'25.06'!$G$7:$G$162,$B16,'25.06'!$F$7:$F$162,I$3) -> 0 | J16: =sumifs('25.06'!$H$7:$H$162,'25.06'!$G$7:$G$162,$B16,'25.06'!$F$7:$F$162,J$3) -> 0 | K16: =sumifs('25.06'!$H$7:$H$162,'25.06'!$G$7:$G$162,$B16,'25.06'!$F$7:$F$162,K$3) -> 0 | L16: =sum(C16:K16) -> 0 | N16: =L16/sum(L$10:L$16) -> #DIV/0! | R16: =sumifs('25.06'!$H$7:$H$162,'25.06'!$I$7:$I$162,$B16,'25.06'!$J$7:$J$162,R$3) -> 0 | S16: =sumifs('25.06'!$H$7:$H$162,'25.06'!$I$7:$I$162,$B16,'25.06'!$J$7:$J$162,S$3) -> 0 | T16: =sumifs('25.06'!$H$7:$H$162,'25.06'!$I$7:$I$162,$B16,'25.06'!$J$7:$J$162,T$3) -> 0 | U16: =sumifs('25.06'!$H$7:$H$162,'25.06'!$I$7:$I$162,$B16,'25.06'!$J$7:$J$162,U$3) -> 0 | V16: =sumifs('25.06'!$H$7:$H$162,'25.06'!$I$7:$I$162,$B16,'25.06'!$J$7:$J$162,V$3) -> 0 | W16: =sumifs('25.06'!$H$7:$H$162,'25.06'!$I$7:$I$162,$B16,'25.06'!$J$7:$J$162,W$3) -> 0 | X16: =sumifs('25.06'!$H$7:$H$162,'25.06'!$I$7:$I$162,$B16,'25.06'!$J$7:$J$162,X$3) -> 0 | Y16: =sumifs('25.06'!$H$7:$H$162,'25.06'!$I$7:$I$162,$B16,'25.06'!$J$7:$J$162,Y$3) -> 0 | Z16: =sumifs('25.06'!$H$7:$H$162,'25.06'!$I$7:$I$162,$B16,'25.06'!$J$7:$J$162,Z$3) -> 0 | AA16: =sum(R16:Z16) -> 0
A17: 3 | B17: For give | C17: =sumifs('25.06'!$H$7:$H$162,'25.06'!$G$7:$G$162,$B17,'25.06'!$F$7:$F$162,C$3) -> 0 | D17: =sumifs('25.06'!$H$7:$H$162,'25.06'!$G$7:$G$162,$B17,'25.06'!$F$7:$F$162,D$3) -> 0 | E17: =sumifs('25.06'!$H$7:$H$162,'25.06'!$G$7:$G$162,$B17,'25.06'!$F$7:$F$162,E$3) -> 0 | F17: =sumifs('25.06'!$H$7:$H$162,'25.06'!$G$7:$G$162,$B17,'25.06'!$F$7:$F$162,F$3) -> 0 | G17: =sumifs('25.06'!$H$7:$H$162,'25.06'!$G$7:$G$162,$B17,'25.06'!$F$7:$F$162,G$3) -> 0 | H17: =sumifs('25.06'!$H$7:$H$162,'25.06'!$G$7:$G$162,$B17,'25.06'!$F$7:$F$162,H$3) -> 0 | I17: =sumifs('25.06'!$H$7:$H$162,'25.06'!$G$7:$G$162,$B17,'25.06'!$F$7:$F$162,I$3) -> 0 | J17: =sumifs('25.06'!$H$7:$H$162,'25.06'!$G$7:$G$162,$B17,'25.06'!$F$7:$F$162,J$3) -> 0 | K17: =sumifs('25.06'!$H$7:$H$162,'25.06'!$G$7:$G$162,$B17,'25.06'!$F$7:$F$162,K$3) -> 0 | L17: =sum(C17:K17) -> 0 | N17: =L17/sum(L$17:L$22) -> #DIV/0! | P17: =sum(L17:L22) -> 0 | Q17: =P17/sum($P$4:$P$57) -> #DIV/0! | R17: =sumifs('25.06'!$H$7:$H$162,'25.06'!$I$7:$I$162,$B17,'25.06'!$J$7:$J$162,R$3) -> 0 | S17: =sumifs('25.06'!$H$7:$H$162,'25.06'!$I$7:$I$162,$B17,'25.06'!$J$7:$J$162,S$3) -> 0 | T17: =sumifs('25.06'!$H$7:$H$162,'25.06'!$I$7:$I$162,$B17,'25.06'!$J$7:$J$162,T$3) -> 0 | U17: =sumifs('25.06'!$H$7:$H$162,'25.06'!$I$7:$I$162,$B17,'25.06'!$J$7:$J$162,U$3) -> 0 | V17: =sumifs('25.06'!$H$7:$H$162,'25.06'!$I$7:$I$162,$B17,'25.06'!$J$7:$J$162,V$3) -> 0 | W17: =sumifs('25.06'!$H$7:$H$162,'25.06'!$I$7:$I$162,$B17,'25.06'!$J$7:$J$162,W$3) -> 0 | X17: =sumifs('25.06'!$H$7:$H$162,'25.06'!$I$7:$I$162,$B17,'25.06'!$J$7:$J$162,X$3) -> 0 | Y17: =sumifs('25.06'!$H$7:$H$162,'25.06'!$I$7:$I$162,$B17,'25.06'!$J$7:$J$162,Y$3) -> 0 | Z17: =sumifs('25.06'!$H$7:$H$162,'25.06'!$I$7:$I$162,$B17,'25.06'!$J$7:$J$162,Z$3) -> 0 | AA17: =sum(R17:Z17) -> 0
A18: 44929 | B18: Funeral | C18: =sumifs('25.06'!$H$7:$H$162,'25.06'!$G$7:$G$162,$B18,'25.06'!$F$7:$F$162,C$3) -> 0 | D18: =sumifs('25.06'!$H$7:$H$162,'25.06'!$G$7:$G$162,$B18,'25.06'!$F$7:$F$162,D$3) -> 0 | E18: =sumifs('25.06'!$H$7:$H$162,'25.06'!$G$7:$G$162,$B18,'25.06'!$F$7:$F$162,E$3) -> 0 | F18: =sumifs('25.06'!$H$7:$H$162,'25.06'!$G$7:$G$162,$B18,'25.06'!$F$7:$F$162,F$3) -> 0 | G18: =sumifs('25.06'!$H$7:$H$162,'25.06'!$G$7:$G$162,$B18,'25.06'!$F$7:$F$162,G$3) -> 0 | H18: =sumifs('25.06'!$H$7:$H$162,'25.06'!$G$7:$G$162,$B18,'25.06'!$F$7:$F$162,H$3) -> 0 | I18: =sumifs('25.06'!$H$7:$H$162,'25.06'!$G$7:$G$162,$B18,'25.06'!$F$7:$F$162,I$3) -> 0 | J18: =sumifs('25.06'!$H$7:$H$162,'25.06'!$G$7:$G$162,$B18,'25.06'!$F$7:$F$162,J$3) -> 0 | K18: =sumifs('25.06'!$H$7:$H$162,'25.06'!$G$7:$G$162,$B18,'25.06'!$F$7:$F$162,K$3) -> 0 | L18: =sum(C18:K18) -> 0 | N18: =L18/sum(L$17:L$22) -> #DIV/0! | R18: =sumifs('25.06'!$H$7:$H$162,'25.06'!$I$7:$I$162,$B18,'25.06'!$J$7:$J$162,R$3) -> 0 | S18: =sumifs('25.06'!$H$7:$H$162,'25.06'!$I$7:$I$162,$B18,'25.06'!$J$7:$J$162,S$3) -> 0 | T18: =sumifs('25.06'!$H$7:$H$162,'25.06'!$I$7:$I$162,$B18,'25.06'!$J$7:$J$162,T$3) -> 0 | U18: =sumifs('25.06'!$H$7:$H$162,'25.06'!$I$7:$I$162,$B18,'25.06'!$J$7:$J$162,U$3) -> 0 | V18: =sumifs('25.06'!$H$7:$H$162,'25.06'!$I$7:$I$162,$B18,'25.06'!$J$7:$J$162,V$3) -> 0 | W18: =sumifs('25.06'!$H$7:$H$162,'25.06'!$I$7:$I$162,$B18,'25.06'!$J$7:$J$162,W$3) -> 0 | X18: =sumifs('25.06'!$H$7:$H$162,'25.06'!$I$7:$I$162,$B18,'25.06'!$J$7:$J$162,X$3) -> 0 | Y18: =sumifs('25.06'!$H$7:$H$162,'25.06'!$I$7:$I$162,$B18,'25.06'!$J$7:$J$162,Y$3) -> 0 | Z18: =sumifs('25.06'!$H$7:$H$162,'25.06'!$I$7:$I$162,$B18,'25.06'!$J$7:$J$162,Z$3) -> 0 | AA18: =sum(R18:Z18) -> 0
A19: 44960 | B19: Wedding | C19: =sumifs('25.06'!$H$7:$H$162,'25.06'!$G$7:$G$162,$B19,'25.06'!$F$7:$F$162,C$3) -> 0 | D19: =sumifs('25.06'!$H$7:$H$162,'25.06'!$G$7:$G$162,$B19,'25.06'!$F$7:$F$162,D$3) -> 0 | E19: =sumifs('25.06'!$H$7:$H$162,'25.06'!$G$7:$G$162,$B19,'25.06'!$F$7:$F$162,E$3) -> 0 | F19: =sumifs('25.06'!$H$7:$H$162,'25.06'!$G$7:$G$162,$B19,'25.06'!$F$7:$F$162,F$3) -> 0 | G19: =sumifs('25.06'!$H$7:$H$162,'25.06'!$G$7:$G$162,$B19,'25.06'!$F$7:$F$162,G$3) -> 0 | H19: =sumifs('25.06'!$H$7:$H$162,'25.06'!$G$7:$G$162,$B19,'25.06'!$F$7:$F$162,H$3) -> 0 | I19: =sumifs('25.06'!$H$7:$H$162,'25.06'!$G$7:$G$162,$B19,'25.06'!$F$7:$F$162,I$3) -> 0 | J19: =sumifs('25.06'!$H$7:$H$162,'25.06'!$G$7:$G$162,$B19,'25.06'!$F$7:$F$162,J$3) -> 0 | K19: =sumifs('25.06'!$H$7:$H$162,'25.06'!$G$7:$G$162,$B19,'25.06'!$F$7:$F$162,K$3) -> 0 | L19: =sum(C19:K19) -> 0 | N19: =L19/sum(L$17:L$22) -> #DIV/0! | R19: =sumifs('25.06'!$H$7:$H$162,'25.06'!$I$7:$I$162,$B19,'25.06'!$J$7:$J$162,R$3) -> 0 | S19: =sumifs('25.06'!$H$7:$H$162,'25.06'!$I$7:$I$162,$B19,'25.06'!$J$7:$J$162,S$3) -> 0 | T19: =sumifs('25.06'!$H$7:$H$162,'25.06'!$I$7:$I$162,$B19,'25.06'!$J$7:$J$162,T$3) -> 0 | U19: =sumifs('25.06'!$H$7:$H$162,'25.06'!$I$7:$I$162,$B19,'25.06'!$J$7:$J$162,U$3) -> 0 | V19: =sumifs('25.06'!$H$7:$H$162,'25.06'!$I$7:$I$162,$B19,'25.06'!$J$7:$J$162,V$3) -> 0 | W19: =sumifs('25.06'!$H$7:$H$162,'25.06'!$I$7:$I$162,$B19,'25.06'!$J$7:$J$162,W$3) -> 0 | X19: =sumifs('25.06'!$H$7:$H$162,'25.06'!$I$7:$I$162,$B19,'25.06'!$J$7:$J$162,X$3) -> 0 | Y19: =sumifs('25.06'!$H$7:$H$162,'25.06'!$I$7:$I$162,$B19,'25.06'!$J$7:$J$162,Y$3) -> 0 | Z19: =sumifs('25.06'!$H$7:$H$162,'25.06'!$I$7:$I$162,$B19,'25.06'!$J$7:$J$162,Z$3) -> 0 | AA19: =sum(R19:Z19) -> 0
A20: 44988 | B20: Gift | C20: =sumifs('25.06'!$H$7:$H$162,'25.06'!$G$7:$G$162,$B20,'25.06'!$F$7:$F$162,C$3) -> 0 | D20: =sumifs('25.06'!$H$7:$H$162,'25.06'!$G$7:$G$162,$B20,'25.06'!$F$7:$F$162,D$3) -> 0 | E20: =sumifs('25.06'!$H$7:$H$162,'25.06'!$G$7:$G$162,$B20,'25.06'!$F$7:$F$162,E$3) -> 0 | F20: =sumifs('25.06'!$H$7:$H$162,'25.06'!$G$7:$G$162,$B20,'25.06'!$F$7:$F$162,F$3) -> 0 | G20: =sumifs('25.06'!$H$7:$H$162,'25.06'!$G$7:$G$162,$B20,'25.06'!$F$7:$F$162,G$3) -> 0 | H20: =sumifs('25.06'!$H$7:$H$162,'25.06'!$G$7:$G$162,$B20,'25.06'!$F$7:$F$162,H$3) -> 0 | I20: =sumifs('25.06'!$H$7:$H$162,'25.06'!$G$7:$G$162,$B20,'25.06'!$F$7:$F$162,I$3) -> 0 | J20: =sumifs('25.06'!$H$7:$H$162,'25.06'!$G$7:$G$162,$B20,'25.06'!$F$7:$F$162,J$3) -> 0 | K20: =sumifs('25.06'!$H$7:$H$162,'25.06'!$G$7:$G$162,$B20,'25.06'!$F$7:$F$162,K$3) -> 0 | L20: =sum(C20:K20) -> 0 | N20: =L20/sum(L$17:L$22) -> #DIV/0! | R20: =sumifs('25.06'!$H$7:$H$162,'25.06'!$I$7:$I$162,$B20,'25.06'!$J$7:$J$162,R$3) -> 0 | S20: =sumifs('25.06'!$H$7:$H$162,'25.06'!$I$7:$I$162,$B20,'25.06'!$J$7:$J$162,S$3) -> 0 | T20: =sumifs('25.06'!$H$7:$H$162,'25.06'!$I$7:$I$162,$B20,'25.06'!$J$7:$J$162,T$3) -> 0 | U20: =sumifs('25.06'!$H$7:$H$162,'25.06'!$I$7:$I$162,$B20,'25.06'!$J$7:$J$162,U$3) -> 0 | V20: =sumifs('25.06'!$H$7:$H$162,'25.06'!$I$7:$I$162,$B20,'25.06'!$J$7:$J$162,V$3) -> 0 | W20: =sumifs('25.06'!$H$7:$H$162,'25.06'!$I$7:$I$162,$B20,'25.06'!$J$7:$J$162,W$3) -> 0 | X20: =sumifs('25.06'!$H$7:$H$162,'25.06'!$I$7:$I$162,$B20,'25.06'!$J$7:$J$162,X$3) -> 0 | Y20: =sumifs('25.06'!$H$7:$H$162,'25.06'!$I$7:$I$162,$B20,'25.06'!$J$7:$J$162,Y$3) -> 0 | Z20: =sumifs('25.06'!$H$7:$H$162,'25.06'!$I$7:$I$162,$B20,'25.06'!$J$7:$J$162,Z$3) -> 0 | AA20: =sum(R20:Z20) -> 0
A21: 45019 | B21: Charity | C21: =sumifs('25.06'!$H$7:$H$162,'25.06'!$G$7:$G$162,$B21,'25.06'!$F$7:$F$162,C$3) -> 0 | D21: =sumifs('25.06'!$H$7:$H$162,'25.06'!$G$7:$G$162,$B21,'25.06'!$F$7:$F$162,D$3) -> 0 | E21: =sumifs('25.06'!$H$7:$H$162,'25.06'!$G$7:$G$162,$B21,'25.06'!$F$7:$F$162,E$3) -> 0 | F21: =sumifs('25.06'!$H$7:$H$162,'25.06'!$G$7:$G$162,$B21,'25.06'!$F$7:$F$162,F$3) -> 0 | G21: =sumifs('25.06'!$H$7:$H$162,'25.06'!$G$7:$G$162,$B21,'25.06'!$F$7:$F$162,G$3) -> 0 | H21: =sumifs('25.06'!$H$7:$H$162,'25.06'!$G$7:$G$162,$B21,'25.06'!$F$7:$F$162,H$3) -> 0 | I21: =sumifs('25.06'!$H$7:$H$162,'25.06'!$G$7:$G$162,$B21,'25.06'!$F$7:$F$162,I$3) -> 0 | J21: =sumifs('25.06'!$H$7:$H$162,'25.06'!$G$7:$G$162,$B21,'25.06'!$F$7:$F$162,J$3) -> 0 | K21: =sumifs('25.06'!$H$7:$H$162,'25.06'!$G$7:$G$162,$B21,'25.06'!$F$7:$F$162,K$3) -> 0 | L21: =sum(C21:K21) -> 0 | N21: =L21/sum(L$17:L$22) -> #DIV/0! | R21: =sumifs('25.06'!$H$7:$H$162,'25.06'!$I$7:$I$162,$B21,'25.06'!$J$7:$J$162,R$3) -> 0 | S21: =sumifs('25.06'!$H$7:$H$162,'25.06'!$I$7:$I$162,$B21,'25.06'!$J$7:$J$162,S$3) -> 0 | T21: =sumifs('25.06'!$H$7:$H$162,'25.06'!$I$7:$I$162,$B21,'25.06'!$J$7:$J$162,T$3) -> 0 | U21: =sumifs('25.06'!$H$7:$H$162,'25.06'!$I$7:$I$162,$B21,'25.06'!$J$7:$J$162,U$3) -> 0 | V21: =sumifs('25.06'!$H$7:$H$162,'25.06'!$I$7:$I$162,$B21,'25.06'!$J$7:$J$162,V$3) -> 0 | W21: =sumifs('25.06'!$H$7:$H$162,'25.06'!$I$7:$I$162,$B21,'25.06'!$J$7:$J$162,W$3) -> 0 | X21: =sumifs('25.06'!$H$7:$H$162,'25.06'!$I$7:$I$162,$B21,'25.06'!$J$7:$J$162,X$3) -> 0 | Y21: =sumifs('25.06'!$H$7:$H$162,'25.06'!$I$7:$I$162,$B21,'25.06'!$J$7:$J$162,Y$3) -> 0 | Z21: =sumifs('25.06'!$H$7:$H$162,'25.06'!$I$7:$I$162,$B21,'25.06'!$J$7:$J$162,Z$3) -> 0 | AA21: =sum(R21:Z21) -> 0
A22: 45049 | B22: Spirituality | C22: =sumifs('25.06'!$H$7:$H$162,'25.06'!$G$7:$G$162,$B22,'25.06'!$F$7:$F$162,C$3) -> 0 | D22: =sumifs('25.06'!$H$7:$H$162,'25.06'!$G$7:$G$162,$B22,'25.06'!$F$7:$F$162,D$3) -> 0 | E22: =sumifs('25.06'!$H$7:$H$162,'25.06'!$G$7:$G$162,$B22,'25.06'!$F$7:$F$162,E$3) -> 0 | F22: =sumifs('25.06'!$H$7:$H$162,'25.06'!$G$7:$G$162,$B22,'25.06'!$F$7:$F$162,F$3) -> 0 | G22: =sumifs('25.06'!$H$7:$H$162,'25.06'!$G$7:$G$162,$B22,'25.06'!$F$7:$F$162,G$3) -> 0 | H22: =sumifs('25.06'!$H$7:$H$162,'25.06'!$G$7:$G$162,$B22,'25.06'!$F$7:$F$162,H$3) -> 0 | I22: =sumifs('25.06'!$H$7:$H$162,'25.06'!$G$7:$G$162,$B22,'25.06'!$F$7:$F$162,I$3) -> 0 | J22: =sumifs('25.06'!$H$7:$H$162,'25.06'!$G$7:$G$162,$B22,'25.06'!$F$7:$F$162,J$3) -> 0 | K22: =sumifs('25.06'!$H$7:$H$162,'25.06'!$G$7:$G$162,$B22,'25.06'!$F$7:$F$162,K$3) -> 0 | L22: =sum(C22:K22) -> 0 | N22: =L22/sum(L$17:L$22) -> #DIV/0! | R22: =sumifs('25.06'!$H$7:$H$162,'25.06'!$I$7:$I$162,$B22,'25.06'!$J$7:$J$162,R$3) -> 0 | S22: =sumifs('25.06'!$H$7:$H$162,'25.06'!$I$7:$I$162,$B22,'25.06'!$J$7:$J$162,S$3) -> 0 | T22: =sumifs('25.06'!$H$7:$H$162,'25.06'!$I$7:$I$162,$B22,'25.06'!$J$7:$J$162,T$3) -> 0 | U22: =sumifs('25.06'!$H$7:$H$162,'25.06'!$I$7:$I$162,$B22,'25.06'!$J$7:$J$162,U$3) -> 0 | V22: =sumifs('25.06'!$H$7:$H$162,'25.06'!$I$7:$I$162,$B22,'25.06'!$J$7:$J$162,V$3) -> 0 | W22: =sumifs('25.06'!$H$7:$H$162,'25.06'!$I$7:$I$162,$B22,'25.06'!$J$7:$J$162,W$3) -> 0 | X22: =sumifs('25.06'!$H$7:$H$162,'25.06'!$I$7:$I$162,$B22,'25.06'!$J$7:$J$162,X$3) -> 0 | Y22: =sumifs('25.06'!$H$7:$H$162,'25.06'!$I$7:$I$162,$B22,'25.06'!$J$7:$J$162,Y$3) -> 0 | Z22: =sumifs('25.06'!$H$7:$H$162,'25.06'!$I$7:$I$162,$B22,'25.06'!$J$7:$J$162,Z$3) -> 0 | AA22: =sum(R22:Z22) -> 0
A23: 4 | B23: Health | C23: =sumifs('25.06'!$H$7:$H$162,'25.06'!$G$7:$G$162,$B23,'25.06'!$F$7:$F$162,C$3) -> 0 | D23: =sumifs('25.06'!$H$7:$H$162,'25.06'!$G$7:$G$162,$B23,'25.06'!$F$7:$F$162,D$3) -> 0 | E23: =sumifs('25.06'!$H$7:$H$162,'25.06'!$G$7:$G$162,$B23,'25.06'!$F$7:$F$162,E$3) -> 0 | F23: =sumifs('25.06'!$H$7:$H$162,'25.06'!$G$7:$G$162,$B23,'25.06'!$F$7:$F$162,F$3) -> 0 | G23: =sumifs('25.06'!$H$7:$H$162,'25.06'!$G$7:$G$162,$B23,'25.06'!$F$7:$F$162,G$3) -> 0 | H23: =sumifs('25.06'!$H$7:$H$162,'25.06'!$G$7:$G$162,$B23,'25.06'!$F$7:$F$162,H$3) -> 0 | I23: =sumifs('25.06'!$H$7:$H$162,'25.06'!$G$7:$G$162,$B23,'25.06'!$F$7:$F$162,I$3) -> 0 | J23: =sumifs('25.06'!$H$7:$H$162,'25.06'!$G$7:$G$162,$B23,'25.06'!$F$7:$F$162,J$3) -> 0 | K23: =sumifs('25.06'!$H$7:$H$162,'25.06'!$G$7:$G$162,$B23,'25.06'!$F$7:$F$162,K$3) -> 0 | L23: =sum(C23:K23) -> 0 | N23: =L23/sum(L$23:L$28) -> #DIV/0! | P23: =sum(L23:L28) -> 0 | Q23: =P22/sum($P$4:$P$57) -> #DIV/0! | R23: =sumifs('25.06'!$H$7:$H$162,'25.06'!$I$7:$I$162,$B23,'25.06'!$J$7:$J$162,R$3) -> 0 | S23: =sumifs('25.06'!$H$7:$H$162,'25.06'!$I$7:$I$162,$B23,'25.06'!$J$7:$J$162,S$3) -> 0 | T23: =sumifs('25.06'!$H$7:$H$162,'25.06'!$I$7:$I$162,$B23,'25.06'!$J$7:$J$162,T$3) -> 0 | U23: =sumifs('25.06'!$H$7:$H$162,'25.06'!$I$7:$I$162,$B23,'25.06'!$J$7:$J$162,U$3) -> 0 | V23: =sumifs('25.06'!$H$7:$H$162,'25.06'!$I$7:$I$162,$B23,'25.06'!$J$7:$J$162,V$3) -> 0 | W23: =sumifs('25.06'!$H$7:$H$162,'25.06'!$I$7:$I$162,$B23,'25.06'!$J$7:$J$162,W$3) -> 0 | X23: =sumifs('25.06'!$H$7:$H$162,'25.06'!$I$7:$I$162,$B23,'25.06'!$J$7:$J$162,X$3) -> 0 | Y23: =sumifs('25.06'!$H$7:$H$162,'25.06'!$I$7:$I$162,$B23,'25.06'!$J$7:$J$162,Y$3) -> 0 | Z23: =sumifs('25.06'!$H$7:$H$162,'25.06'!$I$7:$I$162,$B23,'25.06'!$J$7:$J$162,Z$3) -> 0 | AA23: =sum(R23:Z23) -> 0
A24: 44930 | B24: Medical exam | C24: =sumifs('25.06'!$H$7:$H$162,'25.06'!$G$7:$G$162,$B24,'25.06'!$F$7:$F$162,C$3) -> 0 | D24: =sumifs('25.06'!$H$7:$H$162,'25.06'!$G$7:$G$162,$B24,'25.06'!$F$7:$F$162,D$3) -> 0 | E24: =sumifs('25.06'!$H$7:$H$162,'25.06'!$G$7:$G$162,$B24,'25.06'!$F$7:$F$162,E$3) -> 0 | F24: =sumifs('25.06'!$H$7:$H$162,'25.06'!$G$7:$G$162,$B24,'25.06'!$F$7:$F$162,F$3) -> 0 | G24: =sumifs('25.06'!$H$7:$H$162,'25.06'!$G$7:$G$162,$B24,'25.06'!$F$7:$F$162,G$3) -> 0 | H24: =sumifs('25.06'!$H$7:$H$162,'25.06'!$G$7:$G$162,$B24,'25.06'!$F$7:$F$162,H$3) -> 0 | I24: =sumifs('25.06'!$H$7:$H$162,'25.06'!$G$7:$G$162,$B24,'25.06'!$F$7:$F$162,I$3) -> 0 | J24: =sumifs('25.06'!$H$7:$H$162,'25.06'!$G$7:$G$162,$B24,'25.06'!$F$7:$F$162,J$3) -> 0 | K24: =sumifs('25.06'!$H$7:$H$162,'25.06'!$G$7:$G$162,$B24,'25.06'!$F$7:$F$162,K$3) -> 0 | L24: =sum(C24:K24) -> 0 | N24: =L24/sum(L$23:L$28) -> #DIV/0! | R24: =sumifs('25.06'!$H$7:$H$162,'25.06'!$I$7:$I$162,$B24,'25.06'!$J$7:$J$162,R$3) -> 0 | S24: =sumifs('25.06'!$H$7:$H$162,'25.06'!$I$7:$I$162,$B24,'25.06'!$J$7:$J$162,S$3) -> 0 | T24: =sumifs('25.06'!$H$7:$H$162,'25.06'!$I$7:$I$162,$B24,'25.06'!$J$7:$J$162,T$3) -> 0 | U24: =sumifs('25.06'!$H$7:$H$162,'25.06'!$I$7:$I$162,$B24,'25.06'!$J$7:$J$162,U$3) -> 0 | V24: =sumifs('25.06'!$H$7:$H$162,'25.06'!$I$7:$I$162,$B24,'25.06'!$J$7:$J$162,V$3) -> 0 | W24: =sumifs('25.06'!$H$7:$H$162,'25.06'!$I$7:$I$162,$B24,'25.06'!$J$7:$J$162,W$3) -> 0 | X24: =sumifs('25.06'!$H$7:$H$162,'25.06'!$I$7:$I$162,$B24,'25.06'!$J$7:$J$162,X$3) -> 0 | Y24: =sumifs('25.06'!$H$7:$H$162,'25.06'!$I$7:$I$162,$B24,'25.06'!$J$7:$J$162,Y$3) -> 0 | Z24: =sumifs('25.06'!$H$7:$H$162,'25.06'!$I$7:$I$162,$B24,'25.06'!$J$7:$J$162,Z$3) -> 0 | AA24: =sum(R24:Z24) -> 0
B25: Tablets | C25: =sumifs('25.06'!$H$7:$H$162,'25.06'!$G$7:$G$162,$B25,'25.06'!$F$7:$F$162,C$3) -> 0 | D25: =sumifs('25.06'!$H$7:$H$162,'25.06'!$G$7:$G$162,$B25,'25.06'!$F$7:$F$162,D$3) -> 0 | E25: =sumifs('25.06'!$H$7:$H$162,'25.06'!$G$7:$G$162,$B25,'25.06'!$F$7:$F$162,E$3) -> 0 | F25: =sumifs('25.06'!$H$7:$H$162,'25.06'!$G$7:$G$162,$B25,'25.06'!$F$7:$F$162,F$3) -> 0 | G25: =sumifs('25.06'!$H$7:$H$162,'25.06'!$G$7:$G$162,$B25,'25.06'!$F$7:$F$162,G$3) -> 0 | H25: =sumifs('25.06'!$H$7:$H$162,'25.06'!$G$7:$G$162,$B25,'25.06'!$F$7:$F$162,H$3) -> 0 | I25: =sumifs('25.06'!$H$7:$H$162,'25.06'!$G$7:$G$162,$B25,'25.06'!$F$7:$F$162,I$3) -> 0 | J25: =sumifs('25.06'!$H$7:$H$162,'25.06'!$G$7:$G$162,$B25,'25.06'!$F$7:$F$162,J$3) -> 0 | K25: =sumifs('25.06'!$H$7:$H$162,'25.06'!$G$7:$G$162,$B25,'25.06'!$F$7:$F$162,K$3) -> 0 | L25: =sum(C25:K25) -> 0
A26: 44961 | B26: Body care | C26: =sumifs('25.06'!$H$7:$H$162,'25.06'!$G$7:$G$162,$B26,'25.06'!$F$7:$F$162,C$3) -> 0 | D26: =sumifs('25.06'!$H$7:$H$162,'25.06'!$G$7:$G$162,$B26,'25.06'!$F$7:$F$162,D$3) -> 0 | E26: =sumifs('25.06'!$H$7:$H$162,'25.06'!$G$7:$G$162,$B26,'25.06'!$F$7:$F$162,E$3) -> 0 | F26: =sumifs('25.06'!$H$7:$H$162,'25.06'!$G$7:$G$162,$B26,'25.06'!$F$7:$F$162,F$3) -> 0 | G26: =sumifs('25.06'!$H$7:$H$162,'25.06'!$G$7:$G$162,$B26,'25.06'!$F$7:$F$162,G$3) -> 0 | H26: =sumifs('25.06'!$H$7:$H$162,'25.06'!$G$7:$G$162,$B26,'25.06'!$F$7:$F$162,H$3) -> 0 | I26: =sumifs('25.06'!$H$7:$H$162,'25.06'!$G$7:$G$162,$B26,'25.06'!$F$7:$F$162,I$3) -> 0 | J26: =sumifs('25.06'!$H$7:$H$162,'25.06'!$G$7:$G$162,$B26,'25.06'!$F$7:$F$162,J$3) -> 0 | K26: =sumifs('25.06'!$H$7:$H$162,'25.06'!$G$7:$G$162,$B26,'25.06'!$F$7:$F$162,K$3) -> 0 | L26: =sum(C26:K26) -> 0 | N26: =L26/sum(L$23:L$28) -> #DIV/0! | R26: =sumifs('25.06'!$H$7:$H$162,'25.06'!$I$7:$I$162,$B26,'25.06'!$J$7:$J$162,R$3) -> 0 | S26: =sumifs('25.06'!$H$7:$H$162,'25.06'!$I$7:$I$162,$B26,'25.06'!$J$7:$J$162,S$3) -> 0 | T26: =sumifs('25.06'!$H$7:$H$162,'25.06'!$I$7:$I$162,$B26,'25.06'!$J$7:$J$162,T$3) -> 0 | U26: =sumifs('25.06'!$H$7:$H$162,'25.06'!$I$7:$I$162,$B26,'25.06'!$J$7:$J$162,U$3) -> 0 | V26: =sumifs('25.06'!$H$7:$H$162,'25.06'!$I$7:$I$162,$B26,'25.06'!$J$7:$J$162,V$3) -> 0 | W26: =sumifs('25.06'!$H$7:$H$162,'25.06'!$I$7:$I$162,$B26,'25.06'!$J$7:$J$162,W$3) -> 0 | X26: =sumifs('25.06'!$H$7:$H$162,'25.06'!$I$7:$I$162,$B26,'25.06'!$J$7:$J$162,X$3) -> 0 | Y26: =sumifs('25.06'!$H$7:$H$162,'25.06'!$I$7:$I$162,$B26,'25.06'!$J$7:$J$162,Y$3) -> 0 | Z26: =sumifs('25.06'!$H$7:$H$162,'25.06'!$I$7:$I$162,$B26,'25.06'!$J$7:$J$162,Z$3) -> 0 | AA26: =sum(R26:Z26) -> 0
A27: 44989 | B27: Cosmetic | C27: =sumifs('25.06'!$H$7:$H$162,'25.06'!$G$7:$G$162,$B27,'25.06'!$F$7:$F$162,C$3) -> 0 | E27: =sumifs('25.06'!$H$7:$H$162,'25.06'!$G$7:$G$162,$B27,'25.06'!$F$7:$F$162,E$3) -> 0 | F27: =sumifs('25.06'!$H$7:$H$162,'25.06'!$G$7:$G$162,$B27,'25.06'!$F$7:$F$162,F$3) -> 0 | G27: =sumifs('25.06'!$H$7:$H$162,'25.06'!$G$7:$G$162,$B27,'25.06'!$F$7:$F$162,G$3) -> 0 | H27: =sumifs('25.06'!$H$7:$H$162,'25.06'!$G$7:$G$162,$B27,'25.06'!$F$7:$F$162,H$3) -> 0 | I27: =sumifs('25.06'!$H$7:$H$162,'25.06'!$G$7:$G$162,$B27,'25.06'!$F$7:$F$162,I$3) -> 0 | J27: =sumifs('25.06'!$H$7:$H$162,'25.06'!$G$7:$G$162,$B27,'25.06'!$F$7:$F$162,J$3) -> 0 | K27: =sumifs('25.06'!$H$7:$H$162,'25.06'!$G$7:$G$162,$B27,'25.06'!$F$7:$F$162,K$3) -> 0 | L27: =sum(C27:K27) -> 0 | N27: =L27/sum(L$23:L$28) -> #DIV/0! | R27: =sumifs('25.06'!$H$7:$H$162,'25.06'!$I$7:$I$162,$B27,'25.06'!$J$7:$J$162,R$3) -> 0 | S27: =sumifs('25.06'!$H$7:$H$162,'25.06'!$I$7:$I$162,$B27,'25.06'!$J$7:$J$162,S$3) -> 0 | T27: =sumifs('25.06'!$H$7:$H$162,'25.06'!$I$7:$I$162,$B27,'25.06'!$J$7:$J$162,T$3) -> 0 | U27: =sumifs('25.06'!$H$7:$H$162,'25.06'!$I$7:$I$162,$B27,'25.06'!$J$7:$J$162,U$3) -> 0 | V27: =sumifs('25.06'!$H$7:$H$162,'25.06'!$I$7:$I$162,$B27,'25.06'!$J$7:$J$162,V$3) -> 0 | W27: =sumifs('25.06'!$H$7:$H$162,'25.06'!$I$7:$I$162,$B27,'25.06'!$J$7:$J$162,W$3) -> 0 | X27: =sumifs('25.06'!$H$7:$H$162,'25.06'!$I$7:$I$162,$B27,'25.06'!$J$7:$J$162,X$3) -> 0 | Y27: =sumifs('25.06'!$H$7:$H$162,'25.06'!$I$7:$I$162,$B27,'25.06'!$J$7:$J$162,Y$3) -> 0 | Z27: =sumifs('25.06'!$H$7:$H$162,'25.06'!$I$7:$I$162,$B27,'25.06'!$J$7:$J$162,Z$3) -> 0 | AA27: =sum(R27:Z27) -> 0
A28: 45020 | B28: Medical Insurrance | C28: =sumifs('25.06'!$H$7:$H$162,'25.06'!$G$7:$G$162,$B28,'25.06'!$F$7:$F$162,C$3) -> 0 | D28: =sumifs('25.06'!$H$7:$H$162,'25.06'!$G$7:$G$162,$B28,'25.06'!$F$7:$F$162,D$3) -> 0 | E28: =sumifs('25.06'!$H$7:$H$162,'25.06'!$G$7:$G$162,$B28,'25.06'!$F$7:$F$162,E$3) -> 0 | F28: =sumifs('25.06'!$H$7:$H$162,'25.06'!$G$7:$G$162,$B28,'25.06'!$F$7:$F$162,F$3) -> 0 | G28: =sumifs('25.06'!$H$7:$H$162,'25.06'!$G$7:$G$162,$B28,'25.06'!$F$7:$F$162,G$3) -> 0 | H28: =sumifs('25.06'!$H$7:$H$162,'25.06'!$G$7:$G$162,$B28,'25.06'!$F$7:$F$162,H$3) -> 0 | I28: =sumifs('25.06'!$H$7:$H$162,'25.06'!$G$7:$G$162,$B28,'25.06'!$F$7:$F$162,I$3) -> 0 | J28: =sumifs('25.06'!$H$7:$H$162,'25.06'!$G$7:$G$162,$B28,'25.06'!$F$7:$F$162,J$3) -> 0 | K28: =sumifs('25.06'!$H$7:$H$162,'25.06'!$G$7:$G$162,$B28,'25.06'!$F$7:$F$162,K$3) -> 0 | L28: =sum(C28:K28) -> 0 | N28: =L28/sum(L$23:L$28) -> #DIV/0! | R28: =sumifs('25.06'!$H$7:$H$162,'25.06'!$I$7:$I$162,$B28,'25.06'!$J$7:$J$162,R$3) -> 0 | S28: =sumifs('25.06'!$H$7:$H$162,'25.06'!$I$7:$I$162,$B28,'25.06'!$J$7:$J$162,S$3) -> 0 | T28: =sumifs('25.06'!$H$7:$H$162,'25.06'!$I$7:$I$162,$B28,'25.06'!$J$7:$J$162,T$3) -> 0 | U28: =sumifs('25.06'!$H$7:$H$162,'25.06'!$I$7:$I$162,$B28,'25.06'!$J$7:$J$162,U$3) -> 0 | V28: =sumifs('25.06'!$H$7:$H$162,'25.06'!$I$7:$I$162,$B28,'25.06'!$J$7:$J$162,V$3) -> 0 | W28: =sumifs('25.06'!$H$7:$H$162,'25.06'!$I$7:$I$162,$B28,'25.06'!$J$7:$J$162,W$3) -> 0 | X28: =sumifs('25.06'!$H$7:$H$162,'25.06'!$I$7:$I$162,$B28,'25.06'!$J$7:$J$162,X$3) -> 0 | Y28: =sumifs('25.06'!$H$7:$H$162,'25.06'!$I$7:$I$162,$B28,'25.06'!$J$7:$J$162,Y$3) -> 0 | Z28: =sumifs('25.06'!$H$7:$H$162,'25.06'!$I$7:$I$162,$B28,'25.06'!$J$7:$J$162,Z$3) -> 0 | AA28: =sum(R28:Z28) -> 0
A29: 5 | B29: Living | C29: =sumifs('25.06'!$H$7:$H$162,'25.06'!$G$7:$G$162,$B29,'25.06'!$F$7:$F$162,C$3) -> 0 | D29: =sumifs('25.06'!$H$7:$H$162,'25.06'!$G$7:$G$162,$B29,'25.06'!$F$7:$F$162,D$3) -> 0 | E29: =sumifs('25.06'!$H$7:$H$162,'25.06'!$G$7:$G$162,$B29,'25.06'!$F$7:$F$162,E$3) -> 0 | F29: =sumifs('25.06'!$H$7:$H$162,'25.06'!$G$7:$G$162,$B29,'25.06'!$F$7:$F$162,F$3) -> 0 | G29: =sumifs('25.06'!$H$7:$H$162,'25.06'!$G$7:$G$162,$B29,'25.06'!$F$7:$F$162,G$3) -> 0 | H29: =sumifs('25.06'!$H$7:$H$162,'25.06'!$G$7:$G$162,$B29,'25.06'!$F$7:$F$162,H$3) -> 0 | I29: =sumifs('25.06'!$H$7:$H$162,'25.06'!$G$7:$G$162,$B29,'25.06'!$F$7:$F$162,I$3) -> 0 | J29: =sumifs('25.06'!$H$7:$H$162,'25.06'!$G$7:$G$162,$B29,'25.06'!$F$7:$F$162,J$3) -> 0 | K29: =sumifs('25.06'!$H$7:$H$162,'25.06'!$G$7:$G$162,$B29,'25.06'!$F$7:$F$162,K$3) -> 0 | L29: =sum(C29:K29) -> 0 | N29: =L29/sum(L$29:L$54) -> #DIV/0! | P29: =sum(L29:L54) -> 0 | Q29: =P29/sum($P$4:$P$57) -> #DIV/0! | R29: =sumifs('25.06'!$H$7:$H$162,'25.06'!$I$7:$I$162,$B29,'25.06'!$J$7:$J$162,R$3) -> 0 | S29: =sumifs('25.06'!$H$7:$H$162,'25.06'!$I$7:$I$162,$B29,'25.06'!$J$7:$J$162,S$3) -> 0 | T29: =sumifs('25.06'!$H$7:$H$162,'25.06'!$I$7:$I$162,$B29,'25.06'!$J$7:$J$162,T$3) -> 0 | U29: =sumifs('25.06'!$H$7:$H$162,'25.06'!$I$7:$I$162,$B29,'25.06'!$J$7:$J$162,U$3) -> 0 | V29: =sumifs('25.06'!$H$7:$H$162,'25.06'!$I$7:$I$162,$B29,'25.06'!$J$7:$J$162,V$3) -> 0 | W29: =sumifs('25.06'!$H$7:$H$162,'25.06'!$I$7:$I$162,$B29,'25.06'!$J$7:$J$162,W$3) -> 0 | X29: =sumifs('25.06'!$H$7:$H$162,'25.06'!$I$7:$I$162,$B29,'25.06'!$J$7:$J$162,X$3) -> 0 | Y29: =sumifs('25.06'!$H$7:$H$162,'25.06'!$I$7:$I$162,$B29,'25.06'!$J$7:$J$162,Y$3) -> 0 | Z29: =sumifs('25.06'!$H$7:$H$162,'25.06'!$I$7:$I$162,$B29,'25.06'!$J$7:$J$162,Z$3) -> 0 | AA29: =sum(R29:Z29) -> 0
A30: 44931 | B30: Eating | C30: =sumifs('25.06'!$H$7:$H$162,'25.06'!$G$7:$G$162,$B30,'25.06'!$F$7:$F$162,C$3) -> 0 | D30: =sumifs('25.06'!$H$7:$H$162,'25.06'!$G$7:$G$162,$B30,'25.06'!$F$7:$F$162,D$3) -> 0 | E30: =sumifs('25.06'!$H$7:$H$162,'25.06'!$G$7:$G$162,$B30,'25.06'!$F$7:$F$162,E$3) -> 0 | F30: =sumifs('25.06'!$H$7:$H$162,'25.06'!$G$7:$G$162,$B30,'25.06'!$F$7:$F$162,F$3) -> 0 | G30: =sumifs('25.06'!$H$7:$H$162,'25.06'!$G$7:$G$162,$B30,'25.06'!$F$7:$F$162,G$3) -> 0 | H30: =sumifs('25.06'!$H$7:$H$162,'25.06'!$G$7:$G$162,$B30,'25.06'!$F$7:$F$162,H$3) -> 0 | I30: =sumifs('25.06'!$H$7:$H$162,'25.06'!$G$7:$G$162,$B30,'25.06'!$F$7:$F$162,I$3) -> 0 | J30: =sumifs('25.06'!$H$7:$H$162,'25.06'!$G$7:$G$162,$B30,'25.06'!$F$7:$F$162,J$3) -> 0 | K30: =sumifs('25.06'!$H$7:$H$162,'25.06'!$G$7:$G$162,$B30,'25.06'!$F$7:$F$162,K$3) -> 0 | L30: =sum(C30:K30) -> 0 | N30: =L30/sum(L$29:L$54) -> #DIV/0! | O30: =L30/sum(L$30:L$33) -> #DIV/0! | R30: =sumifs('25.06'!$H$7:$H$162,'25.06'!$I$7:$I$162,$B30,'25.06'!$J$7:$J$162,R$3) -> 0 | S30: =sumifs('25.06'!$H$7:$H$162,'25.06'!$I$7:$I$162,$B30,'25.06'!$J$7:$J$162,S$3) -> 0 | T30: =sumifs('25.06'!$H$7:$H$162,'25.06'!$I$7:$I$162,$B30,'25.06'!$J$7:$J$162,T$3) -> 0 | U30: =sumifs('25.06'!$H$7:$H$162,'25.06'!$I$7:$I$162,$B30,'25.06'!$J$7:$J$162,U$3) -> 0 | V30: =sumifs('25.06'!$H$7:$H$162,'25.06'!$I$7:$I$162,$B30,'25.06'!$J$7:$J$162,V$3) -> 0 | W30: =sumifs('25.06'!$H$7:$H$162,'25.06'!$I$7:$I$162,$B30,'25.06'!$J$7:$J$162,W$3) -> 0 | X30: =sumifs('25.06'!$H$7:$H$162,'25.06'!$I$7:$I$162,$B30,'25.06'!$J$7:$J$162,X$3) -> 0 | Y30: =sumifs('25.06'!$H$7:$H$162,'25.06'!$I$7:$I$162,$B30,'25.06'!$J$7:$J$162,Y$3) -> 0 | Z30: =sumifs('25.06'!$H$7:$H$162,'25.06'!$I$7:$I$162,$B30,'25.06'!$J$7:$J$162,Z$3) -> 0 | AA30: =sum(R30:Z30) -> 0
A31: a | B31: Go Market | C31: =sumifs('25.06'!$H$7:$H$162,'25.06'!$G$7:$G$162,$B31,'25.06'!$F$7:$F$162,C$3) -> 0 | D31: =sumifs('25.06'!$H$7:$H$162,'25.06'!$G$7:$G$162,$B31,'25.06'!$F$7:$F$162,D$3) -> 0 | E31: =sumifs('25.06'!$H$7:$H$162,'25.06'!$G$7:$G$162,$B31,'25.06'!$F$7:$F$162,E$3) -> 0 | F31: =sumifs('25.06'!$H$7:$H$162,'25.06'!$G$7:$G$162,$B31,'25.06'!$F$7:$F$162,F$3) -> 0 | G31: =sumifs('25.06'!$H$7:$H$162,'25.06'!$G$7:$G$162,$B31,'25.06'!$F$7:$F$162,G$3) -> 0 | H31: =sumifs('25.06'!$H$7:$H$162,'25.06'!$G$7:$G$162,$B31,'25.06'!$F$7:$F$162,H$3) -> 0 | I31: =sumifs('25.06'!$H$7:$H$162,'25.06'!$G$7:$G$162,$B31,'25.06'!$F$7:$F$162,I$3) -> 0 | J31: =sumifs('25.06'!$H$7:$H$162,'25.06'!$G$7:$G$162,$B31,'25.06'!$F$7:$F$162,J$3) -> 0 | K31: =sumifs('25.06'!$H$7:$H$162,'25.06'!$G$7:$G$162,$B31,'25.06'!$F$7:$F$162,K$3) -> 0 | L31: =sum(C31:K31) -> 0 | N31: =L31/sum(L$29:L$54) -> #DIV/0! | O31: =L31/sum(L$30:L$33) -> #DIV/0! | R31: =sumifs('25.06'!$H$7:$H$162,'25.06'!$I$7:$I$162,$B31,'25.06'!$J$7:$J$162,R$3) -> 0 | S31: =sumifs('25.06'!$H$7:$H$162,'25.06'!$I$7:$I$162,$B31,'25.06'!$J$7:$J$162,S$3) -> 0 | T31: =sumifs('25.06'!$H$7:$H$162,'25.06'!$I$7:$I$162,$B31,'25.06'!$J$7:$J$162,T$3) -> 0 | U31: =sumifs('25.06'!$H$7:$H$162,'25.06'!$I$7:$I$162,$B31,'25.06'!$J$7:$J$162,U$3) -> 0 | V31: =sumifs('25.06'!$H$7:$H$162,'25.06'!$I$7:$I$162,$B31,'25.06'!$J$7:$J$162,V$3) -> 0 | W31: =sumifs('25.06'!$H$7:$H$162,'25.06'!$I$7:$I$162,$B31,'25.06'!$J$7:$J$162,W$3) -> 0 | X31: =sumifs('25.06'!$H$7:$H$162,'25.06'!$I$7:$I$162,$B31,'25.06'!$J$7:$J$162,X$3) -> 0 | Y31: =sumifs('25.06'!$H$7:$H$162,'25.06'!$I$7:$I$162,$B31,'25.06'!$J$7:$J$162,Y$3) -> 0 | Z31: =sumifs('25.06'!$H$7:$H$162,'25.06'!$I$7:$I$162,$B31,'25.06'!$J$7:$J$162,Z$3) -> 0 | AA31: =sum(R31:Z31) -> 0
A32: b | B32: Breakfast | C32: =sumifs('25.06'!$H$7:$H$162,'25.06'!$G$7:$G$162,$B32,'25.06'!$F$7:$F$162,C$3) -> 0 | D32: =sumifs('25.06'!$H$7:$H$162,'25.06'!$G$7:$G$162,$B32,'25.06'!$F$7:$F$162,D$3) -> 0 | E32: =sumifs('25.06'!$H$7:$H$162,'25.06'!$G$7:$G$162,$B32,'25.06'!$F$7:$F$162,E$3) -> 0 | F32: =sumifs('25.06'!$H$7:$H$162,'25.06'!$G$7:$G$162,$B32,'25.06'!$F$7:$F$162,F$3) -> 0 | G32: =sumifs('25.06'!$H$7:$H$162,'25.06'!$G$7:$G$162,$B32,'25.06'!$F$7:$F$162,G$3) -> 0 | H32: =sumifs('25.06'!$H$7:$H$162,'25.06'!$G$7:$G$162,$B32,'25.06'!$F$7:$F$162,H$3) -> 0 | I32: =sumifs('25.06'!$H$7:$H$162,'25.06'!$G$7:$G$162,$B32,'25.06'!$F$7:$F$162,I$3) -> 0 | J32: =sumifs('25.06'!$H$7:$H$162,'25.06'!$G$7:$G$162,$B32,'25.06'!$F$7:$F$162,J$3) -> 0 | K32: =sumifs('25.06'!$H$7:$H$162,'25.06'!$G$7:$G$162,$B32,'25.06'!$F$7:$F$162,K$3) -> 0 | L32: =sum(C32:K32) -> 0 | N32: =L32/sum(L$29:L$54) -> #DIV/0! | O32: =L32/sum(L$30:L$33) -> #DIV/0! | R32: =sumifs('25.06'!$H$7:$H$162,'25.06'!$I$7:$I$162,$B32,'25.06'!$J$7:$J$162,R$3) -> 0 | S32: =sumifs('25.06'!$H$7:$H$162,'25.06'!$I$7:$I$162,$B32,'25.06'!$J$7:$J$162,S$3) -> 0 | T32: =sumifs('25.06'!$H$7:$H$162,'25.06'!$I$7:$I$162,$B32,'25.06'!$J$7:$J$162,T$3) -> 0 | U32: =sumifs('25.06'!$H$7:$H$162,'25.06'!$I$7:$I$162,$B32,'25.06'!$J$7:$J$162,U$3) -> 0 | V32: =sumifs('25.06'!$H$7:$H$162,'25.06'!$I$7:$I$162,$B32,'25.06'!$J$7:$J$162,V$3) -> 0 | W32: =sumifs('25.06'!$H$7:$H$162,'25.06'!$I$7:$I$162,$B32,'25.06'!$J$7:$J$162,W$3) -> 0 | X32: =sumifs('25.06'!$H$7:$H$162,'25.06'!$I$7:$I$162,$B32,'25.06'!$J$7:$J$162,X$3) -> 0 | Y32: =sumifs('25.06'!$H$7:$H$162,'25.06'!$I$7:$I$162,$B32,'25.06'!$J$7:$J$162,Y$3) -> 0 | Z32: =sumifs('25.06'!$H$7:$H$162,'25.06'!$I$7:$I$162,$B32,'25.06'!$J$7:$J$162,Z$3) -> 0 | AA32: =sum(R32:Z32) -> 0
A33: c | B33: Extra meal | C33: =sumifs('25.06'!$H$7:$H$162,'25.06'!$G$7:$G$162,$B33,'25.06'!$F$7:$F$162,C$3) -> 0 | D33: =sumifs('25.06'!$H$7:$H$162,'25.06'!$G$7:$G$162,$B33,'25.06'!$F$7:$F$162,D$3) -> 0 | E33: =sumifs('25.06'!$H$7:$H$162,'25.06'!$G$7:$G$162,$B33,'25.06'!$F$7:$F$162,E$3) -> 0 | F33: =sumifs('25.06'!$H$7:$H$162,'25.06'!$G$7:$G$162,$B33,'25.06'!$F$7:$F$162,F$3) -> 0 | G33: =sumifs('25.06'!$H$7:$H$162,'25.06'!$G$7:$G$162,$B33,'25.06'!$F$7:$F$162,G$3) -> 0 | H33: =sumifs('25.06'!$H$7:$H$162,'25.06'!$G$7:$G$162,$B33,'25.06'!$F$7:$F$162,H$3) -> 0 | I33: =sumifs('25.06'!$H$7:$H$162,'25.06'!$G$7:$G$162,$B33,'25.06'!$F$7:$F$162,I$3) -> 0 | J33: =sumifs('25.06'!$H$7:$H$162,'25.06'!$G$7:$G$162,$B33,'25.06'!$F$7:$F$162,J$3) -> 0 | K33: =sumifs('25.06'!$H$7:$H$162,'25.06'!$G$7:$G$162,$B33,'25.06'!$F$7:$F$162,K$3) -> 0 | L33: =sum(C33:K33) -> 0 | N33: =L33/sum(L$29:L$54) -> #DIV/0! | O33: =L33/sum(L$30:L$33) -> #DIV/0! | R33: =sumifs('25.06'!$H$7:$H$162,'25.06'!$I$7:$I$162,$B33,'25.06'!$J$7:$J$162,R$3) -> 0 | S33: =sumifs('25.06'!$H$7:$H$162,'25.06'!$I$7:$I$162,$B33,'25.06'!$J$7:$J$162,S$3) -> 0 | T33: =sumifs('25.06'!$H$7:$H$162,'25.06'!$I$7:$I$162,$B33,'25.06'!$J$7:$J$162,T$3) -> 0 | U33: =sumifs('25.06'!$H$7:$H$162,'25.06'!$I$7:$I$162,$B33,'25.06'!$J$7:$J$162,U$3) -> 0 | V33: =sumifs('25.06'!$H$7:$H$162,'25.06'!$I$7:$I$162,$B33,'25.06'!$J$7:$J$162,V$3) -> 0 | W33: =sumifs('25.06'!$H$7:$H$162,'25.06'!$I$7:$I$162,$B33,'25.06'!$J$7:$J$162,W$3) -> 0 | X33: =sumifs('25.06'!$H$7:$H$162,'25.06'!$I$7:$I$162,$B33,'25.06'!$J$7:$J$162,X$3) -> 0 | Y33: =sumifs('25.06'!$H$7:$H$162,'25.06'!$I$7:$I$162,$B33,'25.06'!$J$7:$J$162,Y$3) -> 0 | Z33: =sumifs('25.06'!$H$7:$H$162,'25.06'!$I$7:$I$162,$B33,'25.06'!$J$7:$J$162,Z$3) -> 0 | AA33: =sum(R33:Z33) -> 0
A34: 44962 | B34: Wearing | C34: =sumifs('25.06'!$H$7:$H$162,'25.06'!$G$7:$G$162,$B34,'25.06'!$F$7:$F$162,C$3) -> 0 | D34: =sumifs('25.06'!$H$7:$H$162,'25.06'!$G$7:$G$162,$B34,'25.06'!$F$7:$F$162,D$3) -> 0 | E34: =sumifs('25.06'!$H$7:$H$162,'25.06'!$G$7:$G$162,$B34,'25.06'!$F$7:$F$162,E$3) -> 0 | F34: =sumifs('25.06'!$H$7:$H$162,'25.06'!$G$7:$G$162,$B34,'25.06'!$F$7:$F$162,F$3) -> 0 | G34: =sumifs('25.06'!$H$7:$H$162,'25.06'!$G$7:$G$162,$B34,'25.06'!$F$7:$F$162,G$3) -> 0 | H34: =sumifs('25.06'!$H$7:$H$162,'25.06'!$G$7:$G$162,$B34,'25.06'!$F$7:$F$162,H$3) -> 0 | I34: =sumifs('25.06'!$H$7:$H$162,'25.06'!$G$7:$G$162,$B34,'25.06'!$F$7:$F$162,I$3) -> 0 | J34: =sumifs('25.06'!$H$7:$H$162,'25.06'!$G$7:$G$162,$B34,'25.06'!$F$7:$F$162,J$3) -> 0 | K34: =sumifs('25.06'!$H$7:$H$162,'25.06'!$G$7:$G$162,$B34,'25.06'!$F$7:$F$162,K$3) -> 0 | L34: =sum(C34:K34) -> 0 | N34: =L34/sum(L$29:L$54) -> #DIV/0! | O34: =L34/sum(L$34:L$38) -> #DIV/0! | R34: =sumifs('25.06'!$H$7:$H$162,'25.06'!$I$7:$I$162,$B34,'25.06'!$J$7:$J$162,R$3) -> 0 | S34: =sumifs('25.06'!$H$7:$H$162,'25.06'!$I$7:$I$162,$B34,'25.06'!$J$7:$J$162,S$3) -> 0 | T34: =sumifs('25.06'!$H$7:$H$162,'25.06'!$I$7:$I$162,$B34,'25.06'!$J$7:$J$162,T$3) -> 0 | U34: =sumifs('25.06'!$H$7:$H$162,'25.06'!$I$7:$I$162,$B34,'25.06'!$J$7:$J$162,U$3) -> 0 | V34: =sumifs('25.06'!$H$7:$H$162,'25.06'!$I$7:$I$162,$B34,'25.06'!$J$7:$J$162,V$3) -> 0 | W34: =sumifs('25.06'!$H$7:$H$162,'25.06'!$I$7:$I$162,$B34,'25.06'!$J$7:$J$162,W$3) -> 0 | X34: =sumifs('25.06'!$H$7:$H$162,'25.06'!$I$7:$I$162,$B34,'25.06'!$J$7:$J$162,X$3) -> 0 | Y34: =sumifs('25.06'!$H$7:$H$162,'25.06'!$I$7:$I$162,$B34,'25.06'!$J$7:$J$162,Y$3) -> 0 | Z34: =sumifs('25.06'!$H$7:$H$162,'25.06'!$I$7:$I$162,$B34,'25.06'!$J$7:$J$162,Z$3) -> 0 | AA34: =sum(R34:Z34) -> 0
A35: d | B35: Nghĩa | C35: =sumifs('25.06'!$H$7:$H$162,'25.06'!$G$7:$G$162,$B35,'25.06'!$F$7:$F$162,C$3) -> 0 | D35: =sumifs('25.06'!$H$7:$H$162,'25.06'!$G$7:$G$162,$B35,'25.06'!$F$7:$F$162,D$3) -> 0 | E35: =sumifs('25.06'!$H$7:$H$162,'25.06'!$G$7:$G$162,$B35,'25.06'!$F$7:$F$162,E$3) -> 0 | F35: =sumifs('25.06'!$H$7:$H$162,'25.06'!$G$7:$G$162,$B35,'25.06'!$F$7:$F$162,F$3) -> 0 | G35: =sumifs('25.06'!$H$7:$H$162,'25.06'!$G$7:$G$162,$B35,'25.06'!$F$7:$F$162,G$3) -> 0 | H35: =sumifs('25.06'!$H$7:$H$162,'25.06'!$G$7:$G$162,$B35,'25.06'!$F$7:$F$162,H$3) -> 0 | I35: =sumifs('25.06'!$H$7:$H$162,'25.06'!$G$7:$G$162,$B35,'25.06'!$F$7:$F$162,I$3) -> 0 | J35: =sumifs('25.06'!$H$7:$H$162,'25.06'!$G$7:$G$162,$B35,'25.06'!$F$7:$F$162,J$3) -> 0 | K35: =sumifs('25.06'!$H$7:$H$162,'25.06'!$G$7:$G$162,$B35,'25.06'!$F$7:$F$162,K$3) -> 0 | L35: =sum(C35:K35) -> 0 | N35: =L35/sum(L$29:L$54) -> #DIV/0! | O35: =L35/sum(L$34:L$38) -> #DIV/0! | R35: =sumifs('25.06'!$H$7:$H$162,'25.06'!$I$7:$I$162,$B35,'25.06'!$J$7:$J$162,R$3) -> 0 | S35: =sumifs('25.06'!$H$7:$H$162,'25.06'!$I$7:$I$162,$B35,'25.06'!$J$7:$J$162,S$3) -> 0 | T35: =sumifs('25.06'!$H$7:$H$162,'25.06'!$I$7:$I$162,$B35,'25.06'!$J$7:$J$162,T$3) -> 0 | U35: =sumifs('25.06'!$H$7:$H$162,'25.06'!$I$7:$I$162,$B35,'25.06'!$J$7:$J$162,U$3) -> 0 | V35: =sumifs('25.06'!$H$7:$H$162,'25.06'!$I$7:$I$162,$B35,'25.06'!$J$7:$J$162,V$3) -> 0 | W35: =sumifs('25.06'!$H$7:$H$162,'25.06'!$I$7:$I$162,$B35,'25.06'!$J$7:$J$162,W$3) -> 0 | X35: =sumifs('25.06'!$H$7:$H$162,'25.06'!$I$7:$I$162,$B35,'25.06'!$J$7:$J$162,X$3) -> 0 | Y35: =sumifs('25.06'!$H$7:$H$162,'25.06'!$I$7:$I$162,$B35,'25.06'!$J$7:$J$162,Y$3) -> 0 | Z35: =sumifs('25.06'!$H$7:$H$162,'25.06'!$I$7:$I$162,$B35,'25.06'!$J$7:$J$162,Z$3) -> 0 | AA35: =sum(R35:Z35) -> 0
A36: e | B36: Mai | C36: =sumifs('25.06'!$H$7:$H$162,'25.06'!$G$7:$G$162,$B36,'25.06'!$F$7:$F$162,C$3) -> 0 | D36: =sumifs('25.06'!$H$7:$H$162,'25.06'!$G$7:$G$162,$B36,'25.06'!$F$7:$F$162,D$3) -> 0 | E36: =sumifs('25.06'!$H$7:$H$162,'25.06'!$G$7:$G$162,$B36,'25.06'!$F$7:$F$162,E$3) -> 0 | F36: =sumifs('25.06'!$H$7:$H$162,'25.06'!$G$7:$G$162,$B36,'25.06'!$F$7:$F$162,F$3) -> 0 | G36: =sumifs('25.06'!$H$7:$H$162,'25.06'!$G$7:$G$162,$B36,'25.06'!$F$7:$F$162,G$3) -> 0 | H36: =sumifs('25.06'!$H$7:$H$162,'25.06'!$G$7:$G$162,$B36,'25.06'!$F$7:$F$162,H$3) -> 0 | I36: =sumifs('25.06'!$H$7:$H$162,'25.06'!$G$7:$G$162,$B36,'25.06'!$F$7:$F$162,I$3) -> 0 | J36: =sumifs('25.06'!$H$7:$H$162,'25.06'!$G$7:$G$162,$B36,'25.06'!$F$7:$F$162,J$3) -> 0 | K36: =sumifs('25.06'!$H$7:$H$162,'25.06'!$G$7:$G$162,$B36,'25.06'!$F$7:$F$162,K$3) -> 0 | L36: =sum(C36:K36) -> 0 | N36: =L36/sum(L$29:L$54) -> #DIV/0! | O36: =L36/sum(L$34:L$38) -> #DIV/0! | R36: =sumifs('25.06'!$H$7:$H$162,'25.06'!$I$7:$I$162,$B36,'25.06'!$J$7:$J$162,R$3) -> 0 | S36: =sumifs('25.06'!$H$7:$H$162,'25.06'!$I$7:$I$162,$B36,'25.06'!$J$7:$J$162,S$3) -> 0 | T36: =sumifs('25.06'!$H$7:$H$162,'25.06'!$I$7:$I$162,$B36,'25.06'!$J$7:$J$162,T$3) -> 0 | U36: =sumifs('25.06'!$H$7:$H$162,'25.06'!$I$7:$I$162,$B36,'25.06'!$J$7:$J$162,U$3) -> 0 | V36: =sumifs('25.06'!$H$7:$H$162,'25.06'!$I$7:$I$162,$B36,'25.06'!$J$7:$J$162,V$3) -> 0 | W36: =sumifs('25.06'!$H$7:$H$162,'25.06'!$I$7:$I$162,$B36,'25.06'!$J$7:$J$162,W$3) -> 0 | X36: =sumifs('25.06'!$H$7:$H$162,'25.06'!$I$7:$I$162,$B36,'25.06'!$J$7:$J$162,X$3) -> 0 | Y36: =sumifs('25.06'!$H$7:$H$162,'25.06'!$I$7:$I$162,$B36,'25.06'!$J$7:$J$162,Y$3) -> 0 | Z36: =sumifs('25.06'!$H$7:$H$162,'25.06'!$I$7:$I$162,$B36,'25.06'!$J$7:$J$162,Z$3) -> 0 | AA36: =sum(R36:Z36) -> 0
A37: g | B37: Totto | C37: =sumifs('25.06'!$H$7:$H$162,'25.06'!$G$7:$G$162,$B37,'25.06'!$F$7:$F$162,C$3) -> 0 | D37: =sumifs('25.06'!$H$7:$H$162,'25.06'!$G$7:$G$162,$B37,'25.06'!$F$7:$F$162,D$3) -> 0 | E37: =sumifs('25.06'!$H$7:$H$162,'25.06'!$G$7:$G$162,$B37,'25.06'!$F$7:$F$162,E$3) -> 0 | F37: =sumifs('25.06'!$H$7:$H$162,'25.06'!$G$7:$G$162,$B37,'25.06'!$F$7:$F$162,F$3) -> 0 | G37: =sumifs('25.06'!$H$7:$H$162,'25.06'!$G$7:$G$162,$B37,'25.06'!$F$7:$F$162,G$3) -> 0 | H37: =sumifs('25.06'!$H$7:$H$162,'25.06'!$G$7:$G$162,$B37,'25.06'!$F$7:$F$162,H$3) -> 0 | I37: =sumifs('25.06'!$H$7:$H$162,'25.06'!$G$7:$G$162,$B37,'25.06'!$F$7:$F$162,I$3) -> 0 | J37: =sumifs('25.06'!$H$7:$H$162,'25.06'!$G$7:$G$162,$B37,'25.06'!$F$7:$F$162,J$3) -> 0 | K37: =sumifs('25.06'!$H$7:$H$162,'25.06'!$G$7:$G$162,$B37,'25.06'!$F$7:$F$162,K$3) -> 0 | L37: =sum(C37:K37) -> 0 | N37: =L37/sum(L$29:L$54) -> #DIV/0! | O37: =L37/sum(L$34:L$38) -> #DIV/0! | R37: =sumifs('25.06'!$H$7:$H$162,'25.06'!$I$7:$I$162,$B37,'25.06'!$J$7:$J$162,R$3) -> 0 | S37: =sumifs('25.06'!$H$7:$H$162,'25.06'!$I$7:$I$162,$B37,'25.06'!$J$7:$J$162,S$3) -> 0 | T37: =sumifs('25.06'!$H$7:$H$162,'25.06'!$I$7:$I$162,$B37,'25.06'!$J$7:$J$162,T$3) -> 0 | U37: =sumifs('25.06'!$H$7:$H$162,'25.06'!$I$7:$I$162,$B37,'25.06'!$J$7:$J$162,U$3) -> 0 | V37: =sumifs('25.06'!$H$7:$H$162,'25.06'!$I$7:$I$162,$B37,'25.06'!$J$7:$J$162,V$3) -> 0 | W37: =sumifs('25.06'!$H$7:$H$162,'25.06'!$I$7:$I$162,$B37,'25.06'!$J$7:$J$162,W$3) -> 0 | X37: =sumifs('25.06'!$H$7:$H$162,'25.06'!$I$7:$I$162,$B37,'25.06'!$J$7:$J$162,X$3) -> 0 | Y37: =sumifs('25.06'!$H$7:$H$162,'25.06'!$I$7:$I$162,$B37,'25.06'!$J$7:$J$162,Y$3) -> 0 | Z37: =sumifs('25.06'!$H$7:$H$162,'25.06'!$I$7:$I$162,$B37,'25.06'!$J$7:$J$162,Z$3) -> 0 | AA37: =sum(R37:Z37) -> 0
A38: h | B38: Lego | C38: =sumifs('25.06'!$H$7:$H$162,'25.06'!$G$7:$G$162,$B38,'25.06'!$F$7:$F$162,C$3) -> 0 | D38: =sumifs('25.06'!$H$7:$H$162,'25.06'!$G$7:$G$162,$B38,'25.06'!$F$7:$F$162,D$3) -> 0 | E38: =sumifs('25.06'!$H$7:$H$162,'25.06'!$G$7:$G$162,$B38,'25.06'!$F$7:$F$162,E$3) -> 0 | F38: =sumifs('25.06'!$H$7:$H$162,'25.06'!$G$7:$G$162,$B38,'25.06'!$F$7:$F$162,F$3) -> 0 | G38: =sumifs('25.06'!$H$7:$H$162,'25.06'!$G$7:$G$162,$B38,'25.06'!$F$7:$F$162,G$3) -> 0 | H38: =sumifs('25.06'!$H$7:$H$162,'25.06'!$G$7:$G$162,$B38,'25.06'!$F$7:$F$162,H$3) -> 0 | I38: =sumifs('25.06'!$H$7:$H$162,'25.06'!$G$7:$G$162,$B38,'25.06'!$F$7:$F$162,I$3) -> 0 | J38: =sumifs('25.06'!$H$7:$H$162,'25.06'!$G$7:$G$162,$B38,'25.06'!$F$7:$F$162,J$3) -> 0 | K38: =sumifs('25.06'!$H$7:$H$162,'25.06'!$G$7:$G$162,$B38,'25.06'!$F$7:$F$162,K$3) -> 0 | L38: =sum(C38:K38) -> 0 | N38: =L38/sum(L$29:L$54) -> #DIV/0! | O38: =L38/sum(L$34:L$38) -> #DIV/0! | R38: =sumifs('25.06'!$H$7:$H$162,'25.06'!$I$7:$I$162,$B38,'25.06'!$J$7:$J$162,R$3) -> 0 | S38: =sumifs('25.06'!$H$7:$H$162,'25.06'!$I$7:$I$162,$B38,'25.06'!$J$7:$J$162,S$3) -> 0 | T38: =sumifs('25.06'!$H$7:$H$162,'25.06'!$I$7:$I$162,$B38,'25.06'!$J$7:$J$162,T$3) -> 0 | U38: =sumifs('25.06'!$H$7:$H$162,'25.06'!$I$7:$I$162,$B38,'25.06'!$J$7:$J$162,U$3) -> 0 | V38: =sumifs('25.06'!$H$7:$H$162,'25.06'!$I$7:$I$162,$B38,'25.06'!$J$7:$J$162,V$3) -> 0 | W38: =sumifs('25.06'!$H$7:$H$162,'25.06'!$I$7:$I$162,$B38,'25.06'!$J$7:$J$162,W$3) -> 0 | X38: =sumifs('25.06'!$H$7:$H$162,'25.06'!$I$7:$I$162,$B38,'25.06'!$J$7:$J$162,X$3) -> 0 | Y38: =sumifs('25.06'!$H$7:$H$162,'25.06'!$I$7:$I$162,$B38,'25.06'!$J$7:$J$162,Y$3) -> 0 | Z38: =sumifs('25.06'!$H$7:$H$162,'25.06'!$I$7:$I$162,$B38,'25.06'!$J$7:$J$162,Z$3) -> 0 | AA38: =sum(R38:Z38) -> 0
A39: 44990 | B39: Information | C39: =sumifs('25.06'!$H$7:$H$162,'25.06'!$G$7:$G$162,$B39,'25.06'!$F$7:$F$162,C$3) -> 0 | D39: =sumifs('25.06'!$H$7:$H$162,'25.06'!$G$7:$G$162,$B39,'25.06'!$F$7:$F$162,D$3) -> 0 | E39: =sumifs('25.06'!$H$7:$H$162,'25.06'!$G$7:$G$162,$B39,'25.06'!$F$7:$F$162,E$3) -> 0 | F39: =sumifs('25.06'!$H$7:$H$162,'25.06'!$G$7:$G$162,$B39,'25.06'!$F$7:$F$162,F$3) -> 0 | G39: =sumifs('25.06'!$H$7:$H$162,'25.06'!$G$7:$G$162,$B39,'25.06'!$F$7:$F$162,G$3) -> 0 | H39: =sumifs('25.06'!$H$7:$H$162,'25.06'!$G$7:$G$162,$B39,'25.06'!$F$7:$F$162,H$3) -> 0 | I39: =sumifs('25.06'!$H$7:$H$162,'25.06'!$G$7:$G$162,$B39,'25.06'!$F$7:$F$162,I$3) -> 0 | J39: =sumifs('25.06'!$H$7:$H$162,'25.06'!$G$7:$G$162,$B39,'25.06'!$F$7:$F$162,J$3) -> 0 | K39: =sumifs('25.06'!$H$7:$H$162,'25.06'!$G$7:$G$162,$B39,'25.06'!$F$7:$F$162,K$3) -> 0 | L39: =sum(C39:K39) -> 0 | N39: =L39/sum(L$29:L$54) -> #DIV/0! | O39: =L39/sum(L$39:L$43) -> #DIV/0! | R39: =sumifs('25.06'!$H$7:$H$162,'25.06'!$I$7:$I$162,$B39,'25.06'!$J$7:$J$162,R$3) -> 0 | S39: =sumifs('25.06'!$H$7:$H$162,'25.06'!$I$7:$I$162,$B39,'25.06'!$J$7:$J$162,S$3) -> 0 | T39: =sumifs('25.06'!$H$7:$H$162,'25.06'!$I$7:$I$162,$B39,'25.06'!$J$7:$J$162,T$3) -> 0 | U39: =sumifs('25.06'!$H$7:$H$162,'25.06'!$I$7:$I$162,$B39,'25.06'!$J$7:$J$162,U$3) -> 0 | V39: =sumifs('25.06'!$H$7:$H$162,'25.06'!$I$7:$I$162,$B39,'25.06'!$J$7:$J$162,V$3) -> 0 | W39: =sumifs('25.06'!$H$7:$H$162,'25.06'!$I$7:$I$162,$B39,'25.06'!$J$7:$J$162,W$3) -> 0 | X39: =sumifs('25.06'!$H$7:$H$162,'25.06'!$I$7:$I$162,$B39,'25.06'!$J$7:$J$162,X$3) -> 0 | Y39: =sumifs('25.06'!$H$7:$H$162,'25.06'!$I$7:$I$162,$B39,'25.06'!$J$7:$J$162,Y$3) -> 0 | Z39: =sumifs('25.06'!$H$7:$H$162,'25.06'!$I$7:$I$162,$B39,'25.06'!$J$7:$J$162,Z$3) -> 0 | AA39: =sum(R39:Z39) -> 0
A40: i | B40: Phone | C40: =sumifs('25.06'!$H$7:$H$162,'25.06'!$G$7:$G$162,$B40,'25.06'!$F$7:$F$162,C$3) -> 0 | D40: =sumifs('25.06'!$H$7:$H$162,'25.06'!$G$7:$G$162,$B40,'25.06'!$F$7:$F$162,D$3) -> 0 | E40: =sumifs('25.06'!$H$7:$H$162,'25.06'!$G$7:$G$162,$B40,'25.06'!$F$7:$F$162,E$3) -> 0 | F40: =sumifs('25.06'!$H$7:$H$162,'25.06'!$G$7:$G$162,$B40,'25.06'!$F$7:$F$162,F$3) -> 0 | G40: =sumifs('25.06'!$H$7:$H$162,'25.06'!$G$7:$G$162,$B40,'25.06'!$F$7:$F$162,G$3) -> 0 | H40: =sumifs('25.06'!$H$7:$H$162,'25.06'!$G$7:$G$162,$B40,'25.06'!$F$7:$F$162,H$3) -> 0 | I40: =sumifs('25.06'!$H$7:$H$162,'25.06'!$G$7:$G$162,$B40,'25.06'!$F$7:$F$162,I$3) -> 0 | J40: =sumifs('25.06'!$H$7:$H$162,'25.06'!$G$7:$G$162,$B40,'25.06'!$F$7:$F$162,J$3) -> 0 | K40: =sumifs('25.06'!$H$7:$H$162,'25.06'!$G$7:$G$162,$B40,'25.06'!$F$7:$F$162,K$3) -> 0 | L40: =sum(C40:K40) -> 0 | N40: =L40/sum(L$29:L$54) -> #DIV/0! | O40: =L40/sum(L$39:L$43) -> #DIV/0! | R40: =sumifs('25.06'!$H$7:$H$162,'25.06'!$I$7:$I$162,$B40,'25.06'!$J$7:$J$162,R$3) -> 0 | S40: =sumifs('25.06'!$H$7:$H$162,'25.06'!$I$7:$I$162,$B40,'25.06'!$J$7:$J$162,S$3) -> 0 | T40: =sumifs('25.06'!$H$7:$H$162,'25.06'!$I$7:$I$162,$B40,'25.06'!$J$7:$J$162,T$3) -> 0 | U40: =sumifs('25.06'!$H$7:$H$162,'25.06'!$I$7:$I$162,$B40,'25.06'!$J$7:$J$162,U$3) -> 0 | V40: =sumifs('25.06'!$H$7:$H$162,'25.06'!$I$7:$I$162,$B40,'25.06'!$J$7:$J$162,V$3) -> 0 | W40: =sumifs('25.06'!$H$7:$H$162,'25.06'!$I$7:$I$162,$B40,'25.06'!$J$7:$J$162,W$3) -> 0 | X40: =sumifs('25.06'!$H$7:$H$162,'25.06'!$I$7:$I$162,$B40,'25.06'!$J$7:$J$162,X$3) -> 0 | Y40: =sumifs('25.06'!$H$7:$H$162,'25.06'!$I$7:$I$162,$B40,'25.06'!$J$7:$J$162,Y$3) -> 0 | Z40: =sumifs('25.06'!$H$7:$H$162,'25.06'!$I$7:$I$162,$B40,'25.06'!$J$7:$J$162,Z$3) -> 0 | AA40: =sum(R40:Z40) -> 0
A41: j | B41: Internet | C41: =sumifs('25.06'!$H$7:$H$162,'25.06'!$G$7:$G$162,$B41,'25.06'!$F$7:$F$162,C$3) -> 0 | D41: =sumifs('25.06'!$H$7:$H$162,'25.06'!$G$7:$G$162,$B41,'25.06'!$F$7:$F$162,D$3) -> 0 | E41: =sumifs('25.06'!$H$7:$H$162,'25.06'!$G$7:$G$162,$B41,'25.06'!$F$7:$F$162,E$3) -> 0 | F41: =sumifs('25.06'!$H$7:$H$162,'25.06'!$G$7:$G$162,$B41,'25.06'!$F$7:$F$162,F$3) -> 0 | G41: =sumifs('25.06'!$H$7:$H$162,'25.06'!$G$7:$G$162,$B41,'25.06'!$F$7:$F$162,G$3) -> 0 | H41: =sumifs('25.06'!$H$7:$H$162,'25.06'!$G$7:$G$162,$B41,'25.06'!$F$7:$F$162,H$3) -> 0 | I41: =sumifs('25.06'!$H$7:$H$162,'25.06'!$G$7:$G$162,$B41,'25.06'!$F$7:$F$162,I$3) -> 0 | J41: =sumifs('25.06'!$H$7:$H$162,'25.06'!$G$7:$G$162,$B41,'25.06'!$F$7:$F$162,J$3) -> 0 | K41: =sumifs('25.06'!$H$7:$H$162,'25.06'!$G$7:$G$162,$B41,'25.06'!$F$7:$F$162,K$3) -> 0 | L41: =sum(C41:K41) -> 0 | N41: =L41/sum(L$29:L$54) -> #DIV/0! | O41: =L41/sum(L$39:L$43) -> #DIV/0! | R41: =sumifs('25.06'!$H$7:$H$162,'25.06'!$I$7:$I$162,$B41,'25.06'!$J$7:$J$162,R$3) -> 0 | S41: =sumifs('25.06'!$H$7:$H$162,'25.06'!$I$7:$I$162,$B41,'25.06'!$J$7:$J$162,S$3) -> 0 | T41: =sumifs('25.06'!$H$7:$H$162,'25.06'!$I$7:$I$162,$B41,'25.06'!$J$7:$J$162,T$3) -> 0 | U41: =sumifs('25.06'!$H$7:$H$162,'25.06'!$I$7:$I$162,$B41,'25.06'!$J$7:$J$162,U$3) -> 0 | V41: =sumifs('25.06'!$H$7:$H$162,'25.06'!$I$7:$I$162,$B41,'25.06'!$J$7:$J$162,V$3) -> 0 | W41: =sumifs('25.06'!$H$7:$H$162,'25.06'!$I$7:$I$162,$B41,'25.06'!$J$7:$J$162,W$3) -> 0 | X41: =sumifs('25.06'!$H$7:$H$162,'25.06'!$I$7:$I$162,$B41,'25.06'!$J$7:$J$162,X$3) -> 0 | Y41: =sumifs('25.06'!$H$7:$H$162,'25.06'!$I$7:$I$162,$B41,'25.06'!$J$7:$J$162,Y$3) -> 0 | Z41: =sumifs('25.06'!$H$7:$H$162,'25.06'!$I$7:$I$162,$B41,'25.06'!$J$7:$J$162,Z$3) -> 0 | AA41: =sum(R41:Z41) -> 0
A42: k | B42: Spotify | C42: =sumifs('25.06'!$H$7:$H$162,'25.06'!$G$7:$G$162,$B42,'25.06'!$F$7:$F$162,C$3) -> 0 | D42: =sumifs('25.06'!$H$7:$H$162,'25.06'!$G$7:$G$162,$B42,'25.06'!$F$7:$F$162,D$3) -> 0 | E42: =sumifs('25.06'!$H$7:$H$162,'25.06'!$G$7:$G$162,$B42,'25.06'!$F$7:$F$162,E$3) -> 0 | F42: =sumifs('25.06'!$H$7:$H$162,'25.06'!$G$7:$G$162,$B42,'25.06'!$F$7:$F$162,F$3) -> 0 | G42: =sumifs('25.06'!$H$7:$H$162,'25.06'!$G$7:$G$162,$B42,'25.06'!$F$7:$F$162,G$3) -> 0 | H42: =sumifs('25.06'!$H$7:$H$162,'25.06'!$G$7:$G$162,$B42,'25.06'!$F$7:$F$162,H$3) -> 0 | I42: =sumifs('25.06'!$H$7:$H$162,'25.06'!$G$7:$G$162,$B42,'25.06'!$F$7:$F$162,I$3) -> 0 | J42: =sumifs('25.06'!$H$7:$H$162,'25.06'!$G$7:$G$162,$B42,'25.06'!$F$7:$F$162,J$3) -> 0 | K42: =sumifs('25.06'!$H$7:$H$162,'25.06'!$G$7:$G$162,$B42,'25.06'!$F$7:$F$162,K$3) -> 0 | L42: =sum(C42:K42) -> 0 | N42: =L42/sum(L$29:L$54) -> #DIV/0! | O42: =L42/sum(L$39:L$43) -> #DIV/0! | R42: =sumifs('25.06'!$H$7:$H$162,'25.06'!$I$7:$I$162,$B42,'25.06'!$J$7:$J$162,R$3) -> 0 | S42: =sumifs('25.06'!$H$7:$H$162,'25.06'!$I$7:$I$162,$B42,'25.06'!$J$7:$J$162,S$3) -> 0 | T42: =sumifs('25.06'!$H$7:$H$162,'25.06'!$I$7:$I$162,$B42,'25.06'!$J$7:$J$162,T$3) -> 0 | U42: =sumifs('25.06'!$H$7:$H$162,'25.06'!$I$7:$I$162,$B42,'25.06'!$J$7:$J$162,U$3) -> 0 | V42: =sumifs('25.06'!$H$7:$H$162,'25.06'!$I$7:$I$162,$B42,'25.06'!$J$7:$J$162,V$3) -> 0 | W42: =sumifs('25.06'!$H$7:$H$162,'25.06'!$I$7:$I$162,$B42,'25.06'!$J$7:$J$162,W$3) -> 0 | X42: =sumifs('25.06'!$H$7:$H$162,'25.06'!$I$7:$I$162,$B42,'25.06'!$J$7:$J$162,X$3) -> 0 | Y42: =sumifs('25.06'!$H$7:$H$162,'25.06'!$I$7:$I$162,$B42,'25.06'!$J$7:$J$162,Y$3) -> 0 | Z42: =sumifs('25.06'!$H$7:$H$162,'25.06'!$I$7:$I$162,$B42,'25.06'!$J$7:$J$162,Z$3) -> 0 | AA42: =sum(R42:Z42) -> 0
A43: l | B43: Banking information | C43: =sumifs('25.06'!$H$7:$H$162,'25.06'!$G$7:$G$162,$B43,'25.06'!$F$7:$F$162,C$3) -> 0 | D43: =sumifs('25.06'!$H$7:$H$162,'25.06'!$G$7:$G$162,$B43,'25.06'!$F$7:$F$162,D$3) -> 0 | E43: =sumifs('25.06'!$H$7:$H$162,'25.06'!$G$7:$G$162,$B43,'25.06'!$F$7:$F$162,E$3) -> 0 | F43: =sumifs('25.06'!$H$7:$H$162,'25.06'!$G$7:$G$162,$B43,'25.06'!$F$7:$F$162,F$3) -> 0 | G43: =sumifs('25.06'!$H$7:$H$162,'25.06'!$G$7:$G$162,$B43,'25.06'!$F$7:$F$162,G$3) -> 0 | H43: =sumifs('25.06'!$H$7:$H$162,'25.06'!$G$7:$G$162,$B43,'25.06'!$F$7:$F$162,H$3) -> 0 | I43: =sumifs('25.06'!$H$7:$H$162,'25.06'!$G$7:$G$162,$B43,'25.06'!$F$7:$F$162,I$3) -> 0 | J43: =sumifs('25.06'!$H$7:$H$162,'25.06'!$G$7:$G$162,$B43,'25.06'!$F$7:$F$162,J$3) -> 0 | K43: =sumifs('25.06'!$H$7:$H$162,'25.06'!$G$7:$G$162,$B43,'25.06'!$F$7:$F$162,K$3) -> 0 | L43: =sum(C43:K43) -> 0 | N43: =L43/sum(L$29:L$54) -> #DIV/0! | O43: =L43/sum(L$39:L$43) -> #DIV/0! | R43: =sumifs('25.06'!$H$7:$H$162,'25.06'!$I$7:$I$162,$B43,'25.06'!$J$7:$J$162,R$3) -> 0 | S43: =sumifs('25.06'!$H$7:$H$162,'25.06'!$I$7:$I$162,$B43,'25.06'!$J$7:$J$162,S$3) -> 0 | T43: =sumifs('25.06'!$H$7:$H$162,'25.06'!$I$7:$I$162,$B43,'25.06'!$J$7:$J$162,T$3) -> 0 | U43: =sumifs('25.06'!$H$7:$H$162,'25.06'!$I$7:$I$162,$B43,'25.06'!$J$7:$J$162,U$3) -> 0 | V43: =sumifs('25.06'!$H$7:$H$162,'25.06'!$I$7:$I$162,$B43,'25.06'!$J$7:$J$162,V$3) -> 0 | W43: =sumifs('25.06'!$H$7:$H$162,'25.06'!$I$7:$I$162,$B43,'25.06'!$J$7:$J$162,W$3) -> 0 | X43: =sumifs('25.06'!$H$7:$H$162,'25.06'!$I$7:$I$162,$B43,'25.06'!$J$7:$J$162,X$3) -> 0 | Y43: =sumifs('25.06'!$H$7:$H$162,'25.06'!$I$7:$I$162,$B43,'25.06'!$J$7:$J$162,Y$3) -> 0 | Z43: =sumifs('25.06'!$H$7:$H$162,'25.06'!$I$7:$I$162,$B43,'25.06'!$J$7:$J$162,Z$3) -> 0 | AA43: =sum(R43:Z43) -> 0
A44: 45021 | B44: Transportation | C44: =sumifs('25.06'!$H$7:$H$162,'25.06'!$G$7:$G$162,$B44,'25.06'!$F$7:$F$162,C$3) -> 0 | D44: =sumifs('25.06'!$H$7:$H$162,'25.06'!$G$7:$G$162,$B44,'25.06'!$F$7:$F$162,D$3) -> 0 | E44: =sumifs('25.06'!$H$7:$H$162,'25.06'!$G$7:$G$162,$B44,'25.06'!$F$7:$F$162,E$3) -> 0 | F44: =sumifs('25.06'!$H$7:$H$162,'25.06'!$G$7:$G$162,$B44,'25.06'!$F$7:$F$162,F$3) -> 0 | G44: =sumifs('25.06'!$H$7:$H$162,'25.06'!$G$7:$G$162,$B44,'25.06'!$F$7:$F$162,G$3) -> 0 | H44: =sumifs('25.06'!$H$7:$H$162,'25.06'!$G$7:$G$162,$B44,'25.06'!$F$7:$F$162,H$3) -> 0 | I44: =sumifs('25.06'!$H$7:$H$162,'25.06'!$G$7:$G$162,$B44,'25.06'!$F$7:$F$162,I$3) -> 0 | J44: =sumifs('25.06'!$H$7:$H$162,'25.06'!$G$7:$G$162,$B44,'25.06'!$F$7:$F$162,J$3) -> 0 | K44: =sumifs('25.06'!$H$7:$H$162,'25.06'!$G$7:$G$162,$B44,'25.06'!$F$7:$F$162,K$3) -> 0 | L44: =sum(C44:K44) -> 0 | N44: =L44/sum(L$29:L$54) -> #DIV/0! | O44: =L44/sum(L$44:L$47) -> #DIV/0! | R44: =sumifs('25.06'!$H$7:$H$162,'25.06'!$I$7:$I$162,$B44,'25.06'!$J$7:$J$162,R$3) -> 0 | S44: =sumifs('25.06'!$H$7:$H$162,'25.06'!$I$7:$I$162,$B44,'25.06'!$J$7:$J$162,S$3) -> 0 | T44: =sumifs('25.06'!$H$7:$H$162,'25.06'!$I$7:$I$162,$B44,'25.06'!$J$7:$J$162,T$3) -> 0 | U44: =sumifs('25.06'!$H$7:$H$162,'25.06'!$I$7:$I$162,$B44,'25.06'!$J$7:$J$162,U$3) -> 0 | V44: =sumifs('25.06'!$H$7:$H$162,'25.06'!$I$7:$I$162,$B44,'25.06'!$J$7:$J$162,V$3) -> 0 | W44: =sumifs('25.06'!$H$7:$H$162,'25.06'!$I$7:$I$162,$B44,'25.06'!$J$7:$J$162,W$3) -> 0 | X44: =sumifs('25.06'!$H$7:$H$162,'25.06'!$I$7:$I$162,$B44,'25.06'!$J$7:$J$162,X$3) -> 0 | Y44: =sumifs('25.06'!$H$7:$H$162,'25.06'!$I$7:$I$162,$B44,'25.06'!$J$7:$J$162,Y$3) -> 0 | Z44: =sumifs('25.06'!$H$7:$H$162,'25.06'!$I$7:$I$162,$B44,'25.06'!$J$7:$J$162,Z$3) -> 0 | AA44: =sum(R44:Z44) -> 0
A45: m | B45: Fuel | C45: =sumifs('25.06'!$H$7:$H$162,'25.06'!$G$7:$G$162,$B45,'25.06'!$F$7:$F$162,C$3) -> 0 | D45: =sumifs('25.06'!$H$7:$H$162,'25.06'!$G$7:$G$162,$B45,'25.06'!$F$7:$F$162,D$3) -> 0 | E45: =sumifs('25.06'!$H$7:$H$162,'25.06'!$G$7:$G$162,$B45,'25.06'!$F$7:$F$162,E$3) -> 0 | F45: =sumifs('25.06'!$H$7:$H$162,'25.06'!$G$7:$G$162,$B45,'25.06'!$F$7:$F$162,F$3) -> 0 | G45: =sumifs('25.06'!$H$7:$H$162,'25.06'!$G$7:$G$162,$B45,'25.06'!$F$7:$F$162,G$3) -> 0 | H45: =sumifs('25.06'!$H$7:$H$162,'25.06'!$G$7:$G$162,$B45,'25.06'!$F$7:$F$162,H$3) -> 0 | I45: =sumifs('25.06'!$H$7:$H$162,'25.06'!$G$7:$G$162,$B45,'25.06'!$F$7:$F$162,I$3) -> 0 | J45: =sumifs('25.06'!$H$7:$H$162,'25.06'!$G$7:$G$162,$B45,'25.06'!$F$7:$F$162,J$3) -> 0 | K45: =sumifs('25.06'!$H$7:$H$162,'25.06'!$G$7:$G$162,$B45,'25.06'!$F$7:$F$162,K$3) -> 0 | L45: =sum(C45:K45) -> 0 | N45: =L45/sum(L$29:L$54) -> #DIV/0! | O45: =L45/sum(L$44:L$47) -> #DIV/0! | R45: =sumifs('25.06'!$H$7:$H$162,'25.06'!$I$7:$I$162,$B45,'25.06'!$J$7:$J$162,R$3) -> 0 | S45: =sumifs('25.06'!$H$7:$H$162,'25.06'!$I$7:$I$162,$B45,'25.06'!$J$7:$J$162,S$3) -> 0 | T45: =sumifs('25.06'!$H$7:$H$162,'25.06'!$I$7:$I$162,$B45,'25.06'!$J$7:$J$162,T$3) -> 0 | U45: =sumifs('25.06'!$H$7:$H$162,'25.06'!$I$7:$I$162,$B45,'25.06'!$J$7:$J$162,U$3) -> 0 | V45: =sumifs('25.06'!$H$7:$H$162,'25.06'!$I$7:$I$162,$B45,'25.06'!$J$7:$J$162,V$3) -> 0 | W45: =sumifs('25.06'!$H$7:$H$162,'25.06'!$I$7:$I$162,$B45,'25.06'!$J$7:$J$162,W$3) -> 0 | X45: =sumifs('25.06'!$H$7:$H$162,'25.06'!$I$7:$I$162,$B45,'25.06'!$J$7:$J$162,X$3) -> 0 | Y45: =sumifs('25.06'!$H$7:$H$162,'25.06'!$I$7:$I$162,$B45,'25.06'!$J$7:$J$162,Y$3) -> 0 | Z45: =sumifs('25.06'!$H$7:$H$162,'25.06'!$I$7:$I$162,$B45,'25.06'!$J$7:$J$162,Z$3) -> 0 | AA45: =sum(R45:Z45) -> 0
A46: n | B46: Motorcycle maintenance | C46: =sumifs('25.06'!$H$7:$H$162,'25.06'!$G$7:$G$162,$B46,'25.06'!$F$7:$F$162,C$3) -> 0 | D46: =sumifs('25.06'!$H$7:$H$162,'25.06'!$G$7:$G$162,$B46,'25.06'!$F$7:$F$162,D$3) -> 0 | E46: =sumifs('25.06'!$H$7:$H$162,'25.06'!$G$7:$G$162,$B46,'25.06'!$F$7:$F$162,E$3) -> 0 | F46: =sumifs('25.06'!$H$7:$H$162,'25.06'!$G$7:$G$162,$B46,'25.06'!$F$7:$F$162,F$3) -> 0 | G46: =sumifs('25.06'!$H$7:$H$162,'25.06'!$G$7:$G$162,$B46,'25.06'!$F$7:$F$162,G$3) -> 0 | H46: =sumifs('25.06'!$H$7:$H$162,'25.06'!$G$7:$G$162,$B46,'25.06'!$F$7:$F$162,H$3) -> 0 | I46: =sumifs('25.06'!$H$7:$H$162,'25.06'!$G$7:$G$162,$B46,'25.06'!$F$7:$F$162,I$3) -> 0 | J46: =sumifs('25.06'!$H$7:$H$162,'25.06'!$G$7:$G$162,$B46,'25.06'!$F$7:$F$162,J$3) -> 0 | K46: =sumifs('25.06'!$H$7:$H$162,'25.06'!$G$7:$G$162,$B46,'25.06'!$F$7:$F$162,K$3) -> 0 | L46: =sum(C46:K46) -> 0 | N46: =L46/sum(L$29:L$54) -> #DIV/0! | O46: =L46/sum(L$44:L$47) -> #DIV/0! | R46: =sumifs('25.06'!$H$7:$H$162,'25.06'!$I$7:$I$162,$B46,'25.06'!$J$7:$J$162,R$3) -> 0 | S46: =sumifs('25.06'!$H$7:$H$162,'25.06'!$I$7:$I$162,$B46,'25.06'!$J$7:$J$162,S$3) -> 0 | T46: =sumifs('25.06'!$H$7:$H$162,'25.06'!$I$7:$I$162,$B46,'25.06'!$J$7:$J$162,T$3) -> 0 | U46: =sumifs('25.06'!$H$7:$H$162,'25.06'!$I$7:$I$162,$B46,'25.06'!$J$7:$J$162,U$3) -> 0 | V46: =sumifs('25.06'!$H$7:$H$162,'25.06'!$I$7:$I$162,$B46,'25.06'!$J$7:$J$162,V$3) -> 0 | W46: =sumifs('25.06'!$H$7:$H$162,'25.06'!$I$7:$I$162,$B46,'25.06'!$J$7:$J$162,W$3) -> 0 | X46: =sumifs('25.06'!$H$7:$H$162,'25.06'!$I$7:$I$162,$B46,'25.06'!$J$7:$J$162,X$3) -> 0 | Y46: =sumifs('25.06'!$H$7:$H$162,'25.06'!$I$7:$I$162,$B46,'25.06'!$J$7:$J$162,Y$3) -> 0 | Z46: =sumifs('25.06'!$H$7:$H$162,'25.06'!$I$7:$I$162,$B46,'25.06'!$J$7:$J$162,Z$3) -> 0 | AA46: =sum(R46:Z46) -> 0
A47: o | B47: Parking | C47: =sumifs('25.06'!$H$7:$H$162,'25.06'!$G$7:$G$162,$B47,'25.06'!$F$7:$F$162,C$3) -> 0 | D47: =sumifs('25.06'!$H$7:$H$162,'25.06'!$G$7:$G$162,$B47,'25.06'!$F$7:$F$162,D$3) -> 0 | E47: =sumifs('25.06'!$H$7:$H$162,'25.06'!$G$7:$G$162,$B47,'25.06'!$F$7:$F$162,E$3) -> 0 | F47: =sumifs('25.06'!$H$7:$H$162,'25.06'!$G$7:$G$162,$B47,'25.06'!$F$7:$F$162,F$3) -> 0 | G47: =sumifs('25.06'!$H$7:$H$162,'25.06'!$G$7:$G$162,$B47,'25.06'!$F$7:$F$162,G$3) -> 0 | H47: =sumifs('25.06'!$H$7:$H$162,'25.06'!$G$7:$G$162,$B47,'25.06'!$F$7:$F$162,H$3) -> 0 | I47: =sumifs('25.06'!$H$7:$H$162,'25.06'!$G$7:$G$162,$B47,'25.06'!$F$7:$F$162,I$3) -> 0 | J47: =sumifs('25.06'!$H$7:$H$162,'25.06'!$G$7:$G$162,$B47,'25.06'!$F$7:$F$162,J$3) -> 0 | K47: =sumifs('25.06'!$H$7:$H$162,'25.06'!$G$7:$G$162,$B47,'25.06'!$F$7:$F$162,K$3) -> 0 | L47: =sum(C47:K47) -> 0 | N47: =L47/sum(L$29:L$54) -> #DIV/0! | O47: =L47/sum(L$44:L$47) -> #DIV/0! | R47: =sumifs('25.06'!$H$7:$H$162,'25.06'!$I$7:$I$162,$B47,'25.06'!$J$7:$J$162,R$3) -> 0 | S47: =sumifs('25.06'!$H$7:$H$162,'25.06'!$I$7:$I$162,$B47,'25.06'!$J$7:$J$162,S$3) -> 0 | T47: =sumifs('25.06'!$H$7:$H$162,'25.06'!$I$7:$I$162,$B47,'25.06'!$J$7:$J$162,T$3) -> 0 | U47: =sumifs('25.06'!$H$7:$H$162,'25.06'!$I$7:$I$162,$B47,'25.06'!$J$7:$J$162,U$3) -> 0 | V47: =sumifs('25.06'!$H$7:$H$162,'25.06'!$I$7:$I$162,$B47,'25.06'!$J$7:$J$162,V$3) -> 0 | W47: =sumifs('25.06'!$H$7:$H$162,'25.06'!$I$7:$I$162,$B47,'25.06'!$J$7:$J$162,W$3) -> 0 | X47: =sumifs('25.06'!$H$7:$H$162,'25.06'!$I$7:$I$162,$B47,'25.06'!$J$7:$J$162,X$3) -> 0 | Y47: =sumifs('25.06'!$H$7:$H$162,'25.06'!$I$7:$I$162,$B47,'25.06'!$J$7:$J$162,Y$3) -> 0 | Z47: =sumifs('25.06'!$H$7:$H$162,'25.06'!$I$7:$I$162,$B47,'25.06'!$J$7:$J$162,Z$3) -> 0 | AA47: =sum(R47:Z47) -> 0
A48: 45051 | B48: Housing maintenance | C48: =sumifs('25.06'!$H$7:$H$162,'25.06'!$G$7:$G$162,$B48,'25.06'!$F$7:$F$162,C$3) -> 0 | D48: =sumifs('25.06'!$H$7:$H$162,'25.06'!$G$7:$G$162,$B48,'25.06'!$F$7:$F$162,D$3) -> 0 | E48: =sumifs('25.06'!$H$7:$H$162,'25.06'!$G$7:$G$162,$B48,'25.06'!$F$7:$F$162,E$3) -> 0 | F48: =sumifs('25.06'!$H$7:$H$162,'25.06'!$G$7:$G$162,$B48,'25.06'!$F$7:$F$162,F$3) -> 0 | G48: =sumifs('25.06'!$H$7:$H$162,'25.06'!$G$7:$G$162,$B48,'25.06'!$F$7:$F$162,G$3) -> 0 | H48: =sumifs('25.06'!$H$7:$H$162,'25.06'!$G$7:$G$162,$B48,'25.06'!$F$7:$F$162,H$3) -> 0 | I48: =sumifs('25.06'!$H$7:$H$162,'25.06'!$G$7:$G$162,$B48,'25.06'!$F$7:$F$162,I$3) -> 0 | J48: =sumifs('25.06'!$H$7:$H$162,'25.06'!$G$7:$G$162,$B48,'25.06'!$F$7:$F$162,J$3) -> 0 | K48: =sumifs('25.06'!$H$7:$H$162,'25.06'!$G$7:$G$162,$B48,'25.06'!$F$7:$F$162,K$3) -> 0 | L48: =sum(C48:K48) -> 0 | N48: =L48/sum(L$29:L$54) -> #DIV/0! | O48: =L48/sum(L$48:L$51) -> #DIV/0! | R48: =sumifs('25.06'!$H$7:$H$162,'25.06'!$I$7:$I$162,$B48,'25.06'!$J$7:$J$162,R$3) -> 0 | S48: =sumifs('25.06'!$H$7:$H$162,'25.06'!$I$7:$I$162,$B48,'25.06'!$J$7:$J$162,S$3) -> 0 | T48: =sumifs('25.06'!$H$7:$H$162,'25.06'!$I$7:$I$162,$B48,'25.06'!$J$7:$J$162,T$3) -> 0 | U48: =sumifs('25.06'!$H$7:$H$162,'25.06'!$I$7:$I$162,$B48,'25.06'!$J$7:$J$162,U$3) -> 0 | V48: =sumifs('25.06'!$H$7:$H$162,'25.06'!$I$7:$I$162,$B48,'25.06'!$J$7:$J$162,V$3) -> 0 | W48: =sumifs('25.06'!$H$7:$H$162,'25.06'!$I$7:$I$162,$B48,'25.06'!$J$7:$J$162,W$3) -> 0 | X48: =sumifs('25.06'!$H$7:$H$162,'25.06'!$I$7:$I$162,$B48,'25.06'!$J$7:$J$162,X$3) -> 0 | Y48: =sumifs('25.06'!$H$7:$H$162,'25.06'!$I$7:$I$162,$B48,'25.06'!$J$7:$J$162,Y$3) -> 0 | Z48: =sumifs('25.06'!$H$7:$H$162,'25.06'!$I$7:$I$162,$B48,'25.06'!$J$7:$J$162,Z$3) -> 0 | AA48: =sum(R48:Z48) -> 0
A49: p | B49: Cleaning home | C49: =sumifs('25.06'!$H$7:$H$162,'25.06'!$G$7:$G$162,$B49,'25.06'!$F$7:$F$162,C$3) -> 0 | D49: =sumifs('25.06'!$H$7:$H$162,'25.06'!$G$7:$G$162,$B49,'25.06'!$F$7:$F$162,D$3) -> 0 | E49: =sumifs('25.06'!$H$7:$H$162,'25.06'!$G$7:$G$162,$B49,'25.06'!$F$7:$F$162,E$3) -> 0 | F49: =sumifs('25.06'!$H$7:$H$162,'25.06'!$G$7:$G$162,$B49,'25.06'!$F$7:$F$162,F$3) -> 0 | G49: =sumifs('25.06'!$H$7:$H$162,'25.06'!$G$7:$G$162,$B49,'25.06'!$F$7:$F$162,G$3) -> 0 | H49: =sumifs('25.06'!$H$7:$H$162,'25.06'!$G$7:$G$162,$B49,'25.06'!$F$7:$F$162,H$3) -> 0 | I49: =sumifs('25.06'!$H$7:$H$162,'25.06'!$G$7:$G$162,$B49,'25.06'!$F$7:$F$162,I$3) -> 0 | J49: =sumifs('25.06'!$H$7:$H$162,'25.06'!$G$7:$G$162,$B49,'25.06'!$F$7:$F$162,J$3) -> 0 | K49: =sumifs('25.06'!$H$7:$H$162,'25.06'!$G$7:$G$162,$B49,'25.06'!$F$7:$F$162,K$3) -> 0 | L49: =sum(C49:K49) -> 0 | N49: =L49/sum(L$29:L$54) -> #DIV/0! | O49: =L49/sum(L$48:L$51) -> #DIV/0! | R49: =sumifs('25.06'!$H$7:$H$162,'25.06'!$I$7:$I$162,$B49,'25.06'!$J$7:$J$162,R$3) -> 0 | S49: =sumifs('25.06'!$H$7:$H$162,'25.06'!$I$7:$I$162,$B49,'25.06'!$J$7:$J$162,S$3) -> 0 | T49: =sumifs('25.06'!$H$7:$H$162,'25.06'!$I$7:$I$162,$B49,'25.06'!$J$7:$J$162,T$3) -> 0 | U49: =sumifs('25.06'!$H$7:$H$162,'25.06'!$I$7:$I$162,$B49,'25.06'!$J$7:$J$162,U$3) -> 0 | V49: =sumifs('25.06'!$H$7:$H$162,'25.06'!$I$7:$I$162,$B49,'25.06'!$J$7:$J$162,V$3) -> 0 | W49: =sumifs('25.06'!$H$7:$H$162,'25.06'!$I$7:$I$162,$B49,'25.06'!$J$7:$J$162,W$3) -> 0 | X49: =sumifs('25.06'!$H$7:$H$162,'25.06'!$I$7:$I$162,$B49,'25.06'!$J$7:$J$162,X$3) -> 0 | Y49: =sumifs('25.06'!$H$7:$H$162,'25.06'!$I$7:$I$162,$B49,'25.06'!$J$7:$J$162,Y$3) -> 0 | Z49: =sumifs('25.06'!$H$7:$H$162,'25.06'!$I$7:$I$162,$B49,'25.06'!$J$7:$J$162,Z$3) -> 0 | AA49: =sum(R49:Z49) -> 0
A50: q | B50: House shopping | C50: =sumifs('25.06'!$H$7:$H$162,'25.06'!$G$7:$G$162,$B50,'25.06'!$F$7:$F$162,C$3) -> 0 | D50: =sumifs('25.06'!$H$7:$H$162,'25.06'!$G$7:$G$162,$B50,'25.06'!$F$7:$F$162,D$3) -> 0 | E50: =sumifs('25.06'!$H$7:$H$162,'25.06'!$G$7:$G$162,$B50,'25.06'!$F$7:$F$162,E$3) -> 0 | F50: =sumifs('25.06'!$H$7:$H$162,'25.06'!$G$7:$G$162,$B50,'25.06'!$F$7:$F$162,F$3) -> 0 | G50: =sumifs('25.06'!$H$7:$H$162,'25.06'!$G$7:$G$162,$B50,'25.06'!$F$7:$F$162,G$3) -> 0 | H50: =sumifs('25.06'!$H$7:$H$162,'25.06'!$G$7:$G$162,$B50,'25.06'!$F$7:$F$162,H$3) -> 0 | I50: =sumifs('25.06'!$H$7:$H$162,'25.06'!$G$7:$G$162,$B50,'25.06'!$F$7:$F$162,I$3) -> 0 | J50: =sumifs('25.06'!$H$7:$H$162,'25.06'!$G$7:$G$162,$B50,'25.06'!$F$7:$F$162,J$3) -> 0 | K50: =sumifs('25.06'!$H$7:$H$162,'25.06'!$G$7:$G$162,$B50,'25.06'!$F$7:$F$162,K$3) -> 0 | L50: =sum(C50:K50) -> 0 | N50: =L50/sum(L$29:L$54) -> #DIV/0! | O50: =L50/sum(L$48:L$51) -> #DIV/0! | R50: =sumifs('25.06'!$H$7:$H$162,'25.06'!$I$7:$I$162,$B50,'25.06'!$J$7:$J$162,R$3) -> 0 | S50: =sumifs('25.06'!$H$7:$H$162,'25.06'!$I$7:$I$162,$B50,'25.06'!$J$7:$J$162,S$3) -> 0 | T50: =sumifs('25.06'!$H$7:$H$162,'25.06'!$I$7:$I$162,$B50,'25.06'!$J$7:$J$162,T$3) -> 0 | U50: =sumifs('25.06'!$H$7:$H$162,'25.06'!$I$7:$I$162,$B50,'25.06'!$J$7:$J$162,U$3) -> 0 | V50: =sumifs('25.06'!$H$7:$H$162,'25.06'!$I$7:$I$162,$B50,'25.06'!$J$7:$J$162,V$3) -> 0 | W50: =sumifs('25.06'!$H$7:$H$162,'25.06'!$I$7:$I$162,$B50,'25.06'!$J$7:$J$162,W$3) -> 0 | X50: =sumifs('25.06'!$H$7:$H$162,'25.06'!$I$7:$I$162,$B50,'25.06'!$J$7:$J$162,X$3) -> 0 | Y50: =sumifs('25.06'!$H$7:$H$162,'25.06'!$I$7:$I$162,$B50,'25.06'!$J$7:$J$162,Y$3) -> 0 | Z50: =sumifs('25.06'!$H$7:$H$162,'25.06'!$I$7:$I$162,$B50,'25.06'!$J$7:$J$162,Z$3) -> 0 | AA50: =sum(R50:Z50) -> 0
A51: r | B51: House repair | C51: =sumifs('25.06'!$H$7:$H$162,'25.06'!$G$7:$G$162,$B51,'25.06'!$F$7:$F$162,C$3) -> 0 | D51: =sumifs('25.06'!$H$7:$H$162,'25.06'!$G$7:$G$162,$B51,'25.06'!$F$7:$F$162,D$3) -> 0 | E51: =sumifs('25.06'!$H$7:$H$162,'25.06'!$G$7:$G$162,$B51,'25.06'!$F$7:$F$162,E$3) -> 0 | F51: =sumifs('25.06'!$H$7:$H$162,'25.06'!$G$7:$G$162,$B51,'25.06'!$F$7:$F$162,F$3) -> 0 | G51: =sumifs('25.06'!$H$7:$H$162,'25.06'!$G$7:$G$162,$B51,'25.06'!$F$7:$F$162,G$3) -> 0 | H51: =sumifs('25.06'!$H$7:$H$162,'25.06'!$G$7:$G$162,$B51,'25.06'!$F$7:$F$162,H$3) -> 0 | I51: =sumifs('25.06'!$H$7:$H$162,'25.06'!$G$7:$G$162,$B51,'25.06'!$F$7:$F$162,I$3) -> 0 | J51: =sumifs('25.06'!$H$7:$H$162,'25.06'!$G$7:$G$162,$B51,'25.06'!$F$7:$F$162,J$3) -> 0 | K51: =sumifs('25.06'!$H$7:$H$162,'25.06'!$G$7:$G$162,$B51,'25.06'!$F$7:$F$162,K$3) -> 0 | L51: =sum(C51:K51) -> 0 | N51: =L51/sum(L$29:L$54) -> #DIV/0! | O51: =L51/sum(L$48:L$51) -> #DIV/0! | R51: =sumifs('25.06'!$H$7:$H$162,'25.06'!$I$7:$I$162,$B51,'25.06'!$J$7:$J$162,R$3) -> 0 | S51: =sumifs('25.06'!$H$7:$H$162,'25.06'!$I$7:$I$162,$B51,'25.06'!$J$7:$J$162,S$3) -> 0 | T51: =sumifs('25.06'!$H$7:$H$162,'25.06'!$I$7:$I$162,$B51,'25.06'!$J$7:$J$162,T$3) -> 0 | U51: =sumifs('25.06'!$H$7:$H$162,'25.06'!$I$7:$I$162,$B51,'25.06'!$J$7:$J$162,U$3) -> 0 | V51: =sumifs('25.06'!$H$7:$H$162,'25.06'!$I$7:$I$162,$B51,'25.06'!$J$7:$J$162,V$3) -> 0 | W51: =sumifs('25.06'!$H$7:$H$162,'25.06'!$I$7:$I$162,$B51,'25.06'!$J$7:$J$162,W$3) -> 0 | X51: =sumifs('25.06'!$H$7:$H$162,'25.06'!$I$7:$I$162,$B51,'25.06'!$J$7:$J$162,X$3) -> 0 | Y51: =sumifs('25.06'!$H$7:$H$162,'25.06'!$I$7:$I$162,$B51,'25.06'!$J$7:$J$162,Y$3) -> 0 | Z51: =sumifs('25.06'!$H$7:$H$162,'25.06'!$I$7:$I$162,$B51,'25.06'!$J$7:$J$162,Z$3) -> 0 | AA51: =sum(R51:Z51) -> 0
A52: 45082 | B52: Living Expense | C52: =sumifs('25.06'!$H$7:$H$162,'25.06'!$G$7:$G$162,$B52,'25.06'!$F$7:$F$162,C$3) -> 0 | D52: =sumifs('25.06'!$H$7:$H$162,'25.06'!$G$7:$G$162,$B52,'25.06'!$F$7:$F$162,D$3) -> 0 | E52: =sumifs('25.06'!$H$7:$H$162,'25.06'!$G$7:$G$162,$B52,'25.06'!$F$7:$F$162,E$3) -> 0 | F52: =sumifs('25.06'!$H$7:$H$162,'25.06'!$G$7:$G$162,$B52,'25.06'!$F$7:$F$162,F$3) -> 0 | G52: =sumifs('25.06'!$H$7:$H$162,'25.06'!$G$7:$G$162,$B52,'25.06'!$F$7:$F$162,G$3) -> 0 | H52: =sumifs('25.06'!$H$7:$H$162,'25.06'!$G$7:$G$162,$B52,'25.06'!$F$7:$F$162,H$3) -> 0 | I52: =sumifs('25.06'!$H$7:$H$162,'25.06'!$G$7:$G$162,$B52,'25.06'!$F$7:$F$162,I$3) -> 0 | J52: =sumifs('25.06'!$H$7:$H$162,'25.06'!$G$7:$G$162,$B52,'25.06'!$F$7:$F$162,J$3) -> 0 | K52: =sumifs('25.06'!$H$7:$H$162,'25.06'!$G$7:$G$162,$B52,'25.06'!$F$7:$F$162,K$3) -> 0 | L52: =sum(C52:K52) -> 0 | N52: =L52/sum(L$29:L$54) -> #DIV/0! | O52: =L52/sum(L$52:L$54) -> #DIV/0! | R52: =sumifs('25.06'!$H$7:$H$162,'25.06'!$I$7:$I$162,$B52,'25.06'!$J$7:$J$162,R$3) -> 0 | S52: =sumifs('25.06'!$H$7:$H$162,'25.06'!$I$7:$I$162,$B52,'25.06'!$J$7:$J$162,S$3) -> 0 | T52: =sumifs('25.06'!$H$7:$H$162,'25.06'!$I$7:$I$162,$B52,'25.06'!$J$7:$J$162,T$3) -> 0 | U52: =sumifs('25.06'!$H$7:$H$162,'25.06'!$I$7:$I$162,$B52,'25.06'!$J$7:$J$162,U$3) -> 0 | V52: =sumifs('25.06'!$H$7:$H$162,'25.06'!$I$7:$I$162,$B52,'25.06'!$J$7:$J$162,V$3) -> 0 | W52: =sumifs('25.06'!$H$7:$H$162,'25.06'!$I$7:$I$162,$B52,'25.06'!$J$7:$J$162,W$3) -> 0 | X52: =sumifs('25.06'!$H$7:$H$162,'25.06'!$I$7:$I$162,$B52,'25.06'!$J$7:$J$162,X$3) -> 0 | Y52: =sumifs('25.06'!$H$7:$H$162,'25.06'!$I$7:$I$162,$B52,'25.06'!$J$7:$J$162,Y$3) -> 0 | Z52: =sumifs('25.06'!$H$7:$H$162,'25.06'!$I$7:$I$162,$B52,'25.06'!$J$7:$J$162,Z$3) -> 0 | AA52: =sum(R52:Z52) -> 0
A53: s | B53: Electricity | C53: =sumifs('25.06'!$H$7:$H$162,'25.06'!$G$7:$G$162,$B53,'25.06'!$F$7:$F$162,C$3) -> 0 | D53: =sumifs('25.06'!$H$7:$H$162,'25.06'!$G$7:$G$162,$B53,'25.06'!$F$7:$F$162,D$3) -> 0 | E53: =sumifs('25.06'!$H$7:$H$162,'25.06'!$G$7:$G$162,$B53,'25.06'!$F$7:$F$162,E$3) -> 0 | F53: =sumifs('25.06'!$H$7:$H$162,'25.06'!$G$7:$G$162,$B53,'25.06'!$F$7:$F$162,F$3) -> 0 | G53: =sumifs('25.06'!$H$7:$H$162,'25.06'!$G$7:$G$162,$B53,'25.06'!$F$7:$F$162,G$3) -> 0 | H53: =sumifs('25.06'!$H$7:$H$162,'25.06'!$G$7:$G$162,$B53,'25.06'!$F$7:$F$162,H$3) -> 0 | I53: =sumifs('25.06'!$H$7:$H$162,'25.06'!$G$7:$G$162,$B53,'25.06'!$F$7:$F$162,I$3) -> 0 | J53: =sumifs('25.06'!$H$7:$H$162,'25.06'!$G$7:$G$162,$B53,'25.06'!$F$7:$F$162,J$3) -> 0 | K53: =sumifs('25.06'!$H$7:$H$162,'25.06'!$G$7:$G$162,$B53,'25.06'!$F$7:$F$162,K$3) -> 0 | L53: =sum(C53:K53) -> 0 | N53: =L53/sum(L$29:L$54) -> #DIV/0! | R53: =sumifs('25.06'!$H$7:$H$162,'25.06'!$I$7:$I$162,$B53,'25.06'!$J$7:$J$162,R$3) -> 0 | S53: =sumifs('25.06'!$H$7:$H$162,'25.06'!$I$7:$I$162,$B53,'25.06'!$J$7:$J$162,S$3) -> 0 | T53: =sumifs('25.06'!$H$7:$H$162,'25.06'!$I$7:$I$162,$B53,'25.06'!$J$7:$J$162,T$3) -> 0 | U53: =sumifs('25.06'!$H$7:$H$162,'25.06'!$I$7:$I$162,$B53,'25.06'!$J$7:$J$162,U$3) -> 0 | V53: =sumifs('25.06'!$H$7:$H$162,'25.06'!$I$7:$I$162,$B53,'25.06'!$J$7:$J$162,V$3) -> 0 | W53: =sumifs('25.06'!$H$7:$H$162,'25.06'!$I$7:$I$162,$B53,'25.06'!$J$7:$J$162,W$3) -> 0 | X53: =sumifs('25.06'!$H$7:$H$162,'25.06'!$I$7:$I$162,$B53,'25.06'!$J$7:$J$162,X$3) -> 0 | Y53: =sumifs('25.06'!$H$7:$H$162,'25.06'!$I$7:$I$162,$B53,'25.06'!$J$7:$J$162,Y$3) -> 0 | Z53: =sumifs('25.06'!$H$7:$H$162,'25.06'!$I$7:$I$162,$B53,'25.06'!$J$7:$J$162,Z$3) -> 0 | AA53: =sum(R53:Z53) -> 0
A54: t | B54: Water | C54: =sumifs('25.06'!$H$7:$H$162,'25.06'!$G$7:$G$162,$B54,'25.06'!$F$7:$F$162,C$3) -> 0 | D54: =sumifs('25.06'!$H$7:$H$162,'25.06'!$G$7:$G$162,$B54,'25.06'!$F$7:$F$162,D$3) -> 0 | E54: =sumifs('25.06'!$H$7:$H$162,'25.06'!$G$7:$G$162,$B54,'25.06'!$F$7:$F$162,E$3) -> 0 | F54: =sumifs('25.06'!$H$7:$H$162,'25.06'!$G$7:$G$162,$B54,'25.06'!$F$7:$F$162,F$3) -> 0 | G54: =sumifs('25.06'!$H$7:$H$162,'25.06'!$G$7:$G$162,$B54,'25.06'!$F$7:$F$162,G$3) -> 0 | H54: =sumifs('25.06'!$H$7:$H$162,'25.06'!$G$7:$G$162,$B54,'25.06'!$F$7:$F$162,H$3) -> 0 | I54: =sumifs('25.06'!$H$7:$H$162,'25.06'!$G$7:$G$162,$B54,'25.06'!$F$7:$F$162,I$3) -> 0 | J54: =sumifs('25.06'!$H$7:$H$162,'25.06'!$G$7:$G$162,$B54,'25.06'!$F$7:$F$162,J$3) -> 0 | K54: =sumifs('25.06'!$H$7:$H$162,'25.06'!$G$7:$G$162,$B54,'25.06'!$F$7:$F$162,K$3) -> 0 | L54: =sum(C54:K54) -> 0 | N54: =L54/sum(L$29:L$54) -> #DIV/0! | R54: =sumifs('25.06'!$H$7:$H$162,'25.06'!$I$7:$I$162,$B54,'25.06'!$J$7:$J$162,R$3) -> 0 | S54: =sumifs('25.06'!$H$7:$H$162,'25.06'!$I$7:$I$162,$B54,'25.06'!$J$7:$J$162,S$3) -> 0 | T54: =sumifs('25.06'!$H$7:$H$162,'25.06'!$I$7:$I$162,$B54,'25.06'!$J$7:$J$162,T$3) -> 0 | U54: =sumifs('25.06'!$H$7:$H$162,'25.06'!$I$7:$I$162,$B54,'25.06'!$J$7:$J$162,U$3) -> 0 | V54: =sumifs('25.06'!$H$7:$H$162,'25.06'!$I$7:$I$162,$B54,'25.06'!$J$7:$J$162,V$3) -> 0 | W54: =sumifs('25.06'!$H$7:$H$162,'25.06'!$I$7:$I$162,$B54,'25.06'!$J$7:$J$162,W$3) -> 0 | X54: =sumifs('25.06'!$H$7:$H$162,'25.06'!$I$7:$I$162,$B54,'25.06'!$J$7:$J$162,X$3) -> 0 | Y54: =sumifs('25.06'!$H$7:$H$162,'25.06'!$I$7:$I$162,$B54,'25.06'!$J$7:$J$162,Y$3) -> 0 | Z54: =sumifs('25.06'!$H$7:$H$162,'25.06'!$I$7:$I$162,$B54,'25.06'!$J$7:$J$162,Z$3) -> 0 | AA54: =sum(R54:Z54) -> 0
A55: 6 | B55: Savings | C55: =sumifs('25.06'!$H$7:$H$162,'25.06'!$G$7:$G$162,$B55,'25.06'!$F$7:$F$162,C$3) -> 0 | D55: =sumifs('25.06'!$H$7:$H$162,'25.06'!$G$7:$G$162,$B55,'25.06'!$F$7:$F$162,D$3) -> 0 | E55: =sumifs('25.06'!$H$7:$H$162,'25.06'!$G$7:$G$162,$B55,'25.06'!$F$7:$F$162,E$3) -> 0 | F55: =sumifs('25.06'!$H$7:$H$162,'25.06'!$G$7:$G$162,$B55,'25.06'!$F$7:$F$162,F$3) -> 0 | G55: =sumifs('25.06'!$H$7:$H$162,'25.06'!$G$7:$G$162,$B55,'25.06'!$F$7:$F$162,G$3) -> 0 | H55: =sumifs('25.06'!$H$7:$H$162,'25.06'!$G$7:$G$162,$B55,'25.06'!$F$7:$F$162,H$3) -> 0 | I55: =sumifs('25.06'!$H$7:$H$162,'25.06'!$G$7:$G$162,$B55,'25.06'!$F$7:$F$162,I$3) -> 0 | J55: =sumifs('25.06'!$H$7:$H$162,'25.06'!$G$7:$G$162,$B55,'25.06'!$F$7:$F$162,J$3) -> 0 | K55: =sumifs('25.06'!$H$7:$H$162,'25.06'!$G$7:$G$162,$B55,'25.06'!$F$7:$F$162,K$3) -> 0 | L55: =sum(C55:K55) -> 0 | N55: =L55/sum(L$55:L$57) -> #DIV/0! | P55: =sum(L55:L57) -> 0 | Q55: =P55/sum($P$4:$P$57) -> #DIV/0! | R55: =sumifs('25.06'!$H$7:$H$162,'25.06'!$I$7:$I$162,$B55,'25.06'!$J$7:$J$162,R$3) -> 0 | S55: =sumifs('25.06'!$H$7:$H$162,'25.06'!$I$7:$I$162,$B55,'25.06'!$J$7:$J$162,S$3) -> 0 | T55: =sumifs('25.06'!$H$7:$H$162,'25.06'!$I$7:$I$162,$B55,'25.06'!$J$7:$J$162,T$3) -> 0 | U55: =sumifs('25.06'!$H$7:$H$162,'25.06'!$I$7:$I$162,$B55,'25.06'!$J$7:$J$162,U$3) -> 0 | V55: =sumifs('25.06'!$H$7:$H$162,'25.06'!$I$7:$I$162,$B55,'25.06'!$J$7:$J$162,V$3) -> 0 | W55: =sumifs('25.06'!$H$7:$H$162,'25.06'!$I$7:$I$162,$B55,'25.06'!$J$7:$J$162,W$3) -> 0 | X55: =sumifs('25.06'!$H$7:$H$162,'25.06'!$I$7:$I$162,$B55,'25.06'!$J$7:$J$162,X$3) -> 0 | Y55: =sumifs('25.06'!$H$7:$H$162,'25.06'!$I$7:$I$162,$B55,'25.06'!$J$7:$J$162,Y$3) -> 0 | Z55: =sumifs('25.06'!$H$7:$H$162,'25.06'!$I$7:$I$162,$B55,'25.06'!$J$7:$J$162,Z$3) -> 0 | AA55: =sum(R55:Z55) -> 0
A56: 44932 | B56: Savings | C56: =sumifs('25.06'!$H$7:$H$162,'25.06'!$G$7:$G$162,$B56,'25.06'!$F$7:$F$162,C$3) -> 0 | D56: =sumifs('25.06'!$H$7:$H$162,'25.06'!$G$7:$G$162,$B56,'25.06'!$F$7:$F$162,D$3) -> 0 | E56: =sumifs('25.06'!$H$7:$H$162,'25.06'!$G$7:$G$162,$B56,'25.06'!$F$7:$F$162,E$3) -> 0 | F56: =sumifs('25.06'!$H$7:$H$162,'25.06'!$G$7:$G$162,$B56,'25.06'!$F$7:$F$162,F$3) -> 0 | G56: =sumifs('25.06'!$H$7:$H$162,'25.06'!$G$7:$G$162,$B56,'25.06'!$F$7:$F$162,G$3) -> 0 | H56: =sumifs('25.06'!$H$7:$H$162,'25.06'!$G$7:$G$162,$B56,'25.06'!$F$7:$F$162,H$3) -> 0 | I56: =sumifs('25.06'!$H$7:$H$162,'25.06'!$G$7:$G$162,$B56,'25.06'!$F$7:$F$162,I$3) -> 0 | J56: =sumifs('25.06'!$H$7:$H$162,'25.06'!$G$7:$G$162,$B56,'25.06'!$F$7:$F$162,J$3) -> 0 | K56: =sumifs('25.06'!$H$7:$H$162,'25.06'!$G$7:$G$162,$B56,'25.06'!$F$7:$F$162,K$3) -> 0 | L56: =sum(C56:K56) -> 0 | N56: =L56/sum(L$55:L$57) -> #DIV/0! | R56: =sumifs('25.06'!$H$7:$H$162,'25.06'!$I$7:$I$162,$B56,'25.06'!$J$7:$J$162,R$3) -> 0 | S56: =sumifs('25.06'!$H$7:$H$162,'25.06'!$I$7:$I$162,$B56,'25.06'!$J$7:$J$162,S$3) -> 0 | T56: =sumifs('25.06'!$H$7:$H$162,'25.06'!$I$7:$I$162,$B56,'25.06'!$J$7:$J$162,T$3) -> 0 | U56: =sumifs('25.06'!$H$7:$H$162,'25.06'!$I$7:$I$162,$B56,'25.06'!$J$7:$J$162,U$3) -> 0 | V56: =sumifs('25.06'!$H$7:$H$162,'25.06'!$I$7:$I$162,$B56,'25.06'!$J$7:$J$162,V$3) -> 0 | W56: =sumifs('25.06'!$H$7:$H$162,'25.06'!$I$7:$I$162,$B56,'25.06'!$J$7:$J$162,W$3) -> 0 | X56: =sumifs('25.06'!$H$7:$H$162,'25.06'!$I$7:$I$162,$B56,'25.06'!$J$7:$J$162,X$3) -> 0 | Y56: =sumifs('25.06'!$H$7:$H$162,'25.06'!$I$7:$I$162,$B56,'25.06'!$J$7:$J$162,Y$3) -> 0 | Z56: =sumifs('25.06'!$H$7:$H$162,'25.06'!$I$7:$I$162,$B56,'25.06'!$J$7:$J$162,Z$3) -> 0 | AA56: =sum(R56:Z56) -> 0
A57: 44963 | B57: Life Insurance | C57: =sumifs('25.06'!$H$7:$H$162,'25.06'!$G$7:$G$162,$B57,'25.06'!$F$7:$F$162,C$3) -> 0 | D57: =sumifs('25.06'!$H$7:$H$162,'25.06'!$G$7:$G$162,$B57,'25.06'!$F$7:$F$162,D$3) -> 0 | E57: =sumifs('25.06'!$H$7:$H$162,'25.06'!$G$7:$G$162,$B57,'25.06'!$F$7:$F$162,E$3) -> 0 | F57: =sumifs('25.06'!$H$7:$H$162,'25.06'!$G$7:$G$162,$B57,'25.06'!$F$7:$F$162,F$3) -> 0 | G57: =sumifs('25.06'!$H$7:$H$162,'25.06'!$G$7:$G$162,$B57,'25.06'!$F$7:$F$162,G$3) -> 0 | H57: =sumifs('25.06'!$H$7:$H$162,'25.06'!$G$7:$G$162,$B57,'25.06'!$F$7:$F$162,H$3) -> 0 | I57: =sumifs('25.06'!$H$7:$H$162,'25.06'!$G$7:$G$162,$B57,'25.06'!$F$7:$F$162,I$3) -> 0 | J57: =sumifs('25.06'!$H$7:$H$162,'25.06'!$G$7:$G$162,$B57,'25.06'!$F$7:$F$162,J$3) -> 0 | K57: =sumifs('25.06'!$H$7:$H$162,'25.06'!$G$7:$G$162,$B57,'25.06'!$F$7:$F$162,K$3) -> 0 | L57: =sum(C57:K57) -> 0 | N57: =L57/sum(L$55:L$57) -> #DIV/0! | R57: =sumifs('25.06'!$H$7:$H$162,'25.06'!$I$7:$I$162,$B57,'25.06'!$J$7:$J$162,R$3) -> 0 | S57: =sumifs('25.06'!$H$7:$H$162,'25.06'!$I$7:$I$162,$B57,'25.06'!$J$7:$J$162,S$3) -> 0 | T57: =sumifs('25.06'!$H$7:$H$162,'25.06'!$I$7:$I$162,$B57,'25.06'!$J$7:$J$162,T$3) -> 0 | U57: =sumifs('25.06'!$H$7:$H$162,'25.06'!$I$7:$I$162,$B57,'25.06'!$J$7:$J$162,U$3) -> 0 | V57: =sumifs('25.06'!$H$7:$H$162,'25.06'!$I$7:$I$162,$B57,'25.06'!$J$7:$J$162,V$3) -> 0 | W57: =sumifs('25.06'!$H$7:$H$162,'25.06'!$I$7:$I$162,$B57,'25.06'!$J$7:$J$162,W$3) -> 0 | X57: =sumifs('25.06'!$H$7:$H$162,'25.06'!$I$7:$I$162,$B57,'25.06'!$J$7:$J$162,X$3) -> 0 | Y57: =sumifs('25.06'!$H$7:$H$162,'25.06'!$I$7:$I$162,$B57,'25.06'!$J$7:$J$162,Y$3) -> 0 | Z57: =sumifs('25.06'!$H$7:$H$162,'25.06'!$I$7:$I$162,$B57,'25.06'!$J$7:$J$162,Z$3) -> 0 | AA57: =sum(R57:Z57) -> 0
A58: 7 | B58: N&M studio | C58: =sumifs('25.06'!$H$7:$H$162,'25.06'!$G$7:$G$162,$B58,'25.06'!$F$7:$F$162,C$3) -> 0 | D58: =sumifs('25.06'!$H$7:$H$162,'25.06'!$G$7:$G$162,$B58,'25.06'!$F$7:$F$162,D$3) -> 0 | E58: =sumifs('25.06'!$H$7:$H$162,'25.06'!$G$7:$G$162,$B58,'25.06'!$F$7:$F$162,E$3) -> 0 | F58: =sumifs('25.06'!$H$7:$H$162,'25.06'!$G$7:$G$162,$B58,'25.06'!$F$7:$F$162,F$3) -> 0 | G58: =sumifs('25.06'!$H$7:$H$162,'25.06'!$G$7:$G$162,$B58,'25.06'!$F$7:$F$162,G$3) -> 0 | H58: =sumifs('25.06'!$H$7:$H$162,'25.06'!$G$7:$G$162,$B58,'25.06'!$F$7:$F$162,H$3) -> 0 | I58: =sumifs('25.06'!$H$7:$H$162,'25.06'!$G$7:$G$162,$B58,'25.06'!$F$7:$F$162,I$3) -> 0 | J58: =sumifs('25.06'!$H$7:$H$162,'25.06'!$G$7:$G$162,$B58,'25.06'!$F$7:$F$162,J$3) -> 0 | K58: =sumifs('25.06'!$H$7:$H$162,'25.06'!$G$7:$G$162,$B58,'25.06'!$F$7:$F$162,K$3) -> 0 | L58: =sum(C58:K58) -> 0 | N58: =L58/sum(L$58:L$60) -> #DIV/0! | R58: =sumifs('25.06'!$H$7:$H$162,'25.06'!$I$7:$I$162,$B58,'25.06'!$J$7:$J$162,R$3) -> 0 | S58: =sumifs('25.06'!$H$7:$H$162,'25.06'!$I$7:$I$162,$B58,'25.06'!$J$7:$J$162,S$3) -> 0 | T58: =sumifs('25.06'!$H$7:$H$162,'25.06'!$I$7:$I$162,$B58,'25.06'!$J$7:$J$162,T$3) -> 0 | U58: =sumifs('25.06'!$H$7:$H$162,'25.06'!$I$7:$I$162,$B58,'25.06'!$J$7:$J$162,U$3) -> 0 | V58: =sumifs('25.06'!$H$7:$H$162,'25.06'!$I$7:$I$162,$B58,'25.06'!$J$7:$J$162,V$3) -> 0 | W58: =sumifs('25.06'!$H$7:$H$162,'25.06'!$I$7:$I$162,$B58,'25.06'!$J$7:$J$162,W$3) -> 0 | X58: =sumifs('25.06'!$H$7:$H$162,'25.06'!$I$7:$I$162,$B58,'25.06'!$J$7:$J$162,X$3) -> 0 | Y58: =sumifs('25.06'!$H$7:$H$162,'25.06'!$I$7:$I$162,$B58,'25.06'!$J$7:$J$162,Y$3) -> 0 | Z58: =sumifs('25.06'!$H$7:$H$162,'25.06'!$I$7:$I$162,$B58,'25.06'!$J$7:$J$162,Z$3) -> 0 | AA58: =sum(R58:Z58) -> 0
A59: 44933 | B59: Design | C59: =sumifs('25.06'!$H$7:$H$162,'25.06'!$G$7:$G$162,$B59,'25.06'!$F$7:$F$162,C$3) -> 0 | D59: =sumifs('25.06'!$H$7:$H$162,'25.06'!$G$7:$G$162,$B59,'25.06'!$F$7:$F$162,D$3) -> 0 | E59: =sumifs('25.06'!$H$7:$H$162,'25.06'!$G$7:$G$162,$B59,'25.06'!$F$7:$F$162,E$3) -> 0 | F59: =sumifs('25.06'!$H$7:$H$162,'25.06'!$G$7:$G$162,$B59,'25.06'!$F$7:$F$162,F$3) -> 0 | G59: =sumifs('25.06'!$H$7:$H$162,'25.06'!$G$7:$G$162,$B59,'25.06'!$F$7:$F$162,G$3) -> 0 | H59: =sumifs('25.06'!$H$7:$H$162,'25.06'!$G$7:$G$162,$B59,'25.06'!$F$7:$F$162,H$3) -> 0 | I59: =sumifs('25.06'!$H$7:$H$162,'25.06'!$G$7:$G$162,$B59,'25.06'!$F$7:$F$162,I$3) -> 0 | J59: =sumifs('25.06'!$H$7:$H$162,'25.06'!$G$7:$G$162,$B59,'25.06'!$F$7:$F$162,J$3) -> 0 | K59: =sumifs('25.06'!$H$7:$H$162,'25.06'!$G$7:$G$162,$B59,'25.06'!$F$7:$F$162,K$3) -> 0 | L59: =sum(C59:K59) -> 0 | N59: =L59/sum(L$58:L$60) -> #DIV/0! | R59: =sumifs('25.06'!$H$7:$H$162,'25.06'!$I$7:$I$162,$B59,'25.06'!$J$7:$J$162,R$3) -> 0 | S59: =sumifs('25.06'!$H$7:$H$162,'25.06'!$I$7:$I$162,$B59,'25.06'!$J$7:$J$162,S$3) -> 0 | T59: =sumifs('25.06'!$H$7:$H$162,'25.06'!$I$7:$I$162,$B59,'25.06'!$J$7:$J$162,T$3) -> 0 | U59: =sumifs('25.06'!$H$7:$H$162,'25.06'!$I$7:$I$162,$B59,'25.06'!$J$7:$J$162,U$3) -> 0 | V59: =sumifs('25.06'!$H$7:$H$162,'25.06'!$I$7:$I$162,$B59,'25.06'!$J$7:$J$162,V$3) -> 0 | W59: =sumifs('25.06'!$H$7:$H$162,'25.06'!$I$7:$I$162,$B59,'25.06'!$J$7:$J$162,W$3) -> 0 | X59: =sumifs('25.06'!$H$7:$H$162,'25.06'!$I$7:$I$162,$B59,'25.06'!$J$7:$J$162,X$3) -> 0 | Y59: =sumifs('25.06'!$H$7:$H$162,'25.06'!$I$7:$I$162,$B59,'25.06'!$J$7:$J$162,Y$3) -> 0 | Z59: =sumifs('25.06'!$H$7:$H$162,'25.06'!$I$7:$I$162,$B59,'25.06'!$J$7:$J$162,Z$3) -> 0 | AA59: =sum(R59:Z59) -> 0
A60: 44964 | B60: Construction | C60: =sumifs('25.06'!$H$7:$H$162,'25.06'!$G$7:$G$162,$B60,'25.06'!$F$7:$F$162,C$3) -> 0 | D60: =sumifs('25.06'!$H$7:$H$162,'25.06'!$G$7:$G$162,$B60,'25.06'!$F$7:$F$162,D$3) -> 0 | E60: =sumifs('25.06'!$H$7:$H$162,'25.06'!$G$7:$G$162,$B60,'25.06'!$F$7:$F$162,E$3) -> 0 | F60: =sumifs('25.06'!$H$7:$H$162,'25.06'!$G$7:$G$162,$B60,'25.06'!$F$7:$F$162,F$3) -> 0 | G60: =sumifs('25.06'!$H$7:$H$162,'25.06'!$G$7:$G$162,$B60,'25.06'!$F$7:$F$162,G$3) -> 0 | H60: =sumifs('25.06'!$H$7:$H$162,'25.06'!$G$7:$G$162,$B60,'25.06'!$F$7:$F$162,H$3) -> 0 | I60: =sumifs('25.06'!$H$7:$H$162,'25.06'!$G$7:$G$162,$B60,'25.06'!$F$7:$F$162,I$3) -> 0 | J60: =sumifs('25.06'!$H$7:$H$162,'25.06'!$G$7:$G$162,$B60,'25.06'!$F$7:$F$162,J$3) -> 0 | K60: =sumifs('25.06'!$H$7:$H$162,'25.06'!$G$7:$G$162,$B60,'25.06'!$F$7:$F$162,K$3) -> 0 | L60: =sum(C60:K60) -> 0 | N60: =L60/sum(L$58:L$60) -> #DIV/0! | R60: =sumifs('25.06'!$H$7:$H$162,'25.06'!$I$7:$I$162,$B60,'25.06'!$J$7:$J$162,R$3) -> 0 | S60: =sumifs('25.06'!$H$7:$H$162,'25.06'!$I$7:$I$162,$B60,'25.06'!$J$7:$J$162,S$3) -> 0 | T60: =sumifs('25.06'!$H$7:$H$162,'25.06'!$I$7:$I$162,$B60,'25.06'!$J$7:$J$162,T$3) -> 0 | U60: =sumifs('25.06'!$H$7:$H$162,'25.06'!$I$7:$I$162,$B60,'25.06'!$J$7:$J$162,U$3) -> 0 | V60: =sumifs('25.06'!$H$7:$H$162,'25.06'!$I$7:$I$162,$B60,'25.06'!$J$7:$J$162,V$3) -> 0 | W60: =sumifs('25.06'!$H$7:$H$162,'25.06'!$I$7:$I$162,$B60,'25.06'!$J$7:$J$162,W$3) -> 0 | X60: =sumifs('25.06'!$H$7:$H$162,'25.06'!$I$7:$I$162,$B60,'25.06'!$J$7:$J$162,X$3) -> 0 | Y60: =sumifs('25.06'!$H$7:$H$162,'25.06'!$I$7:$I$162,$B60,'25.06'!$J$7:$J$162,Y$3) -> 0 | Z60: =sumifs('25.06'!$H$7:$H$162,'25.06'!$I$7:$I$162,$B60,'25.06'!$J$7:$J$162,Z$3) -> 0 | AA60: =sum(R60:Z60) -> 0
A61: 8 | B61: Togohub management | C61: =sumifs('25.06'!$H$7:$H$162,'25.06'!$G$7:$G$162,$B61,'25.06'!$F$7:$F$162,C$3) -> 0 | D61: =sumifs('25.06'!$H$7:$H$162,'25.06'!$G$7:$G$162,$B61,'25.06'!$F$7:$F$162,D$3) -> 0 | E61: =sumifs('25.06'!$H$7:$H$162,'25.06'!$G$7:$G$162,$B61,'25.06'!$F$7:$F$162,E$3) -> 16730000 | F61: =sumifs('25.06'!$H$7:$H$162,'25.06'!$G$7:$G$162,$B61,'25.06'!$F$7:$F$162,F$3) -> 0 | G61: =sumifs('25.06'!$H$7:$H$162,'25.06'!$G$7:$G$162,$B61,'25.06'!$F$7:$F$162,G$3) -> 0 | H61: =sumifs('25.06'!$H$7:$H$162,'25.06'!$G$7:$G$162,$B61,'25.06'!$F$7:$F$162,H$3) -> 0 | I61: =sumifs('25.06'!$H$7:$H$162,'25.06'!$G$7:$G$162,$B61,'25.06'!$F$7:$F$162,I$3) -> 0 | J61: =sumifs('25.06'!$H$7:$H$162,'25.06'!$G$7:$G$162,$B61,'25.06'!$F$7:$F$162,J$3) -> 0 | K61: =sumifs('25.06'!$H$7:$H$162,'25.06'!$G$7:$G$162,$B61,'25.06'!$F$7:$F$162,K$3) -> 0 | L61: =sum(C61:K61) -> 16730000 | N61: =L61/sum(L$61:L$69) -> 0.74993655 | R61: =sumifs('25.06'!$H$7:$H$162,'25.06'!$I$7:$I$162,$B61,'25.06'!$J$7:$J$162,R$3) -> 0 | S61: =sumifs('25.06'!$H$7:$H$162,'25.06'!$I$7:$I$162,$B61,'25.06'!$J$7:$J$162,S$3) -> 0 | T61: =sumifs('25.06'!$H$7:$H$162,'25.06'!$I$7:$I$162,$B61,'25.06'!$J$7:$J$162,T$3) -> 80000000 | U61: =sumifs('25.06'!$H$7:$H$162,'25.06'!$I$7:$I$162,$B61,'25.06'!$J$7:$J$162,U$3) -> 0 | V61: =sumifs('25.06'!$H$7:$H$162,'25.06'!$I$7:$I$162,$B61,'25.06'!$J$7:$J$162,V$3) -> 0 | W61: =sumifs('25.06'!$H$7:$H$162,'25.06'!$I$7:$I$162,$B61,'25.06'!$J$7:$J$162,W$3) -> 0 | X61: =sumifs('25.06'!$H$7:$H$162,'25.06'!$I$7:$I$162,$B61,'25.06'!$J$7:$J$162,X$3) -> 0 | Y61: =sumifs('25.06'!$H$7:$H$162,'25.06'!$I$7:$I$162,$B61,'25.06'!$J$7:$J$162,Y$3) -> 0 | Z61: =sumifs('25.06'!$H$7:$H$162,'25.06'!$I$7:$I$162,$B61,'25.06'!$J$7:$J$162,Z$3) -> 0 | AA61: =sum(R61:Z61) -> 80000000
A62: 44934 | B62: T. Electricity | C62: =sumifs('25.06'!$H$7:$H$162,'25.06'!$G$7:$G$162,$B62,'25.06'!$F$7:$F$162,C$3) -> 0 | D62: =sumifs('25.06'!$H$7:$H$162,'25.06'!$G$7:$G$162,$B62,'25.06'!$F$7:$F$162,D$3) -> 0 | E62: =sumifs('25.06'!$H$7:$H$162,'25.06'!$G$7:$G$162,$B62,'25.06'!$F$7:$F$162,E$3) -> 4544704 | F62: =sumifs('25.06'!$H$7:$H$162,'25.06'!$G$7:$G$162,$B62,'25.06'!$F$7:$F$162,F$3) -> 0 | G62: =sumifs('25.06'!$H$7:$H$162,'25.06'!$G$7:$G$162,$B62,'25.06'!$F$7:$F$162,G$3) -> 0 | H62: =sumifs('25.06'!$H$7:$H$162,'25.06'!$G$7:$G$162,$B62,'25.06'!$F$7:$F$162,H$3) -> 0 | I62: =sumifs('25.06'!$H$7:$H$162,'25.06'!$G$7:$G$162,$B62,'25.06'!$F$7:$F$162,I$3) -> 0 | J62: =sumifs('25.06'!$H$7:$H$162,'25.06'!$G$7:$G$162,$B62,'25.06'!$F$7:$F$162,J$3) -> 0 | K62: =sumifs('25.06'!$H$7:$H$162,'25.06'!$G$7:$G$162,$B62,'25.06'!$F$7:$F$162,K$3) -> 0 | L62: =sum(C62:K62) -> 4544704 | N62: =L62/sum(L$61:L$69) -> 0.20372024 | Q62: =L62+L63 -> 5578554 | R62: =sumifs('25.06'!$H$7:$H$162,'25.06'!$I$7:$I$162,$B62,'25.06'!$J$7:$J$162,R$3) -> 0 | S62: =sumifs('25.06'!$H$7:$H$162,'25.06'!$I$7:$I$162,$B62,'25.06'!$J$7:$J$162,S$3) -> 0 | T62: =sumifs('25.06'!$H$7:$H$162,'25.06'!$I$7:$I$162,$B62,'25.06'!$J$7:$J$162,T$3) -> 4157000 | U62: =sumifs('25.06'!$H$7:$H$162,'25.06'!$I$7:$I$162,$B62,'25.06'!$J$7:$J$162,U$3) -> 0 | V62: =sumifs('25.06'!$H$7:$H$162,'25.06'!$I$7:$I$162,$B62,'25.06'!$J$7:$J$162,V$3) -> 0 | W62: =sumifs('25.06'!$H$7:$H$162,'25.06'!$I$7:$I$162,$B62,'25.06'!$J$7:$J$162,W$3) -> 0 | X62: =sumifs('25.06'!$H$7:$H$162,'25.06'!$I$7:$I$162,$B62,'25.06'!$J$7:$J$162,X$3) -> 0 | Y62: =sumifs('25.06'!$H$7:$H$162,'25.06'!$I$7:$I$162,$B62,'25.06'!$J$7:$J$162,Y$3) -> 0 | Z62: =sumifs('25.06'!$H$7:$H$162,'25.06'!$I$7:$I$162,$B62,'25.06'!$J$7:$J$162,Z$3) -> 0 | AA62: =sum(R62:Z62) -> 4157000
A63: 44965 | B63: T. Water | C63: =sumifs('25.06'!$H$7:$H$162,'25.06'!$G$7:$G$162,$B63,'25.06'!$F$7:$F$162,C$3) -> 0 | D63: =sumifs('25.06'!$H$7:$H$162,'25.06'!$G$7:$G$162,$B63,'25.06'!$F$7:$F$162,D$3) -> 0 | E63: =sumifs('25.06'!$H$7:$H$162,'25.06'!$G$7:$G$162,$B63,'25.06'!$F$7:$F$162,E$3) -> 1033850 | F63: =sumifs('25.06'!$H$7:$H$162,'25.06'!$G$7:$G$162,$B63,'25.06'!$F$7:$F$162,F$3) -> 0 | G63: =sumifs('25.06'!$H$7:$H$162,'25.06'!$G$7:$G$162,$B63,'25.06'!$F$7:$F$162,G$3) -> 0 | H63: =sumifs('25.06'!$H$7:$H$162,'25.06'!$G$7:$G$162,$B63,'25.06'!$F$7:$F$162,H$3) -> 0 | I63: =sumifs('25.06'!$H$7:$H$162,'25.06'!$G$7:$G$162,$B63,'25.06'!$F$7:$F$162,I$3) -> 0 | J63: =sumifs('25.06'!$H$7:$H$162,'25.06'!$G$7:$G$162,$B63,'25.06'!$F$7:$F$162,J$3) -> 0 | K63: =sumifs('25.06'!$H$7:$H$162,'25.06'!$G$7:$G$162,$B63,'25.06'!$F$7:$F$162,K$3) -> 0 | L63: =sum(C63:K63) -> 1033850 | N63: =L63/sum(L$61:L$69) -> 0.04634321 | Q63: =AA62+AA63 -> 4157000 | R63: =sumifs('25.06'!$H$7:$H$162,'25.06'!$I$7:$I$162,$B63,'25.06'!$J$7:$J$162,R$3) -> 0 | S63: =sumifs('25.06'!$H$7:$H$162,'25.06'!$I$7:$I$162,$B63,'25.06'!$J$7:$J$162,S$3) -> 0 | T63: =sumifs('25.06'!$H$7:$H$162,'25.06'!$I$7:$I$162,$B63,'25.06'!$J$7:$J$162,T$3) -> 0 | U63: =sumifs('25.06'!$H$7:$H$162,'25.06'!$I$7:$I$162,$B63,'25.06'!$J$7:$J$162,U$3) -> 0 | V63: =sumifs('25.06'!$H$7:$H$162,'25.06'!$I$7:$I$162,$B63,'25.06'!$J$7:$J$162,V$3) -> 0 | W63: =sumifs('25.06'!$H$7:$H$162,'25.06'!$I$7:$I$162,$B63,'25.06'!$J$7:$J$162,W$3) -> 0 | X63: =sumifs('25.06'!$H$7:$H$162,'25.06'!$I$7:$I$162,$B63,'25.06'!$J$7:$J$162,X$3) -> 0 | Y63: =sumifs('25.06'!$H$7:$H$162,'25.06'!$I$7:$I$162,$B63,'25.06'!$J$7:$J$162,Y$3) -> 0 | Z63: =sumifs('25.06'!$H$7:$H$162,'25.06'!$I$7:$I$162,$B63,'25.06'!$J$7:$J$162,Z$3) -> 0 | AA63: =sum(R63:Z63) -> 0
A64: 44993 | B64: T. Cleaning | C64: =sumifs('25.06'!$H$7:$H$162,'25.06'!$G$7:$G$162,$B64,'25.06'!$F$7:$F$162,C$3) -> 0 | D64: =sumifs('25.06'!$H$7:$H$162,'25.06'!$G$7:$G$162,$B64,'25.06'!$F$7:$F$162,D$3) -> 0 | E64: =sumifs('25.06'!$H$7:$H$162,'25.06'!$G$7:$G$162,$B64,'25.06'!$F$7:$F$162,E$3) -> 0 | F64: =sumifs('25.06'!$H$7:$H$162,'25.06'!$G$7:$G$162,$B64,'25.06'!$F$7:$F$162,F$3) -> 0 | G64: =sumifs('25.06'!$H$7:$H$162,'25.06'!$G$7:$G$162,$B64,'25.06'!$F$7:$F$162,G$3) -> 0 | H64: =sumifs('25.06'!$H$7:$H$162,'25.06'!$G$7:$G$162,$B64,'25.06'!$F$7:$F$162,H$3) -> 0 | I64: =sumifs('25.06'!$H$7:$H$162,'25.06'!$G$7:$G$162,$B64,'25.06'!$F$7:$F$162,I$3) -> 0 | J64: =sumifs('25.06'!$H$7:$H$162,'25.06'!$G$7:$G$162,$B64,'25.06'!$F$7:$F$162,J$3) -> 0 | K64: =sumifs('25.06'!$H$7:$H$162,'25.06'!$G$7:$G$162,$B64,'25.06'!$F$7:$F$162,K$3) -> 0 | L64: =sum(C64:K64) -> 0 | N64: =L64/sum(L$61:L$69) -> 0 | Q64: =Q62-Q63 -> 1421554 | R64: =sumifs('25.06'!$H$7:$H$162,'25.06'!$I$7:$I$162,$B64,'25.06'!$J$7:$J$162,R$3) -> 0 | S64: =sumifs('25.06'!$H$7:$H$162,'25.06'!$I$7:$I$162,$B64,'25.06'!$J$7:$J$162,S$3) -> 0 | T64: =sumifs('25.06'!$H$7:$H$162,'25.06'!$I$7:$I$162,$B64,'25.06'!$J$7:$J$162,T$3) -> 0 | U64: =sumifs('25.06'!$H$7:$H$162,'25.06'!$I$7:$I$162,$B64,'25.06'!$J$7:$J$162,U$3) -> 0 | V64: =sumifs('25.06'!$H$7:$H$162,'25.06'!$I$7:$I$162,$B64,'25.06'!$J$7:$J$162,V$3) -> 0 | W64: =sumifs('25.06'!$H$7:$H$162,'25.06'!$I$7:$I$162,$B64,'25.06'!$J$7:$J$162,W$3) -> 0 | X64: =sumifs('25.06'!$H$7:$H$162,'25.06'!$I$7:$I$162,$B64,'25.06'!$J$7:$J$162,X$3) -> 0 | Y64: =sumifs('25.06'!$H$7:$H$162,'25.06'!$I$7:$I$162,$B64,'25.06'!$J$7:$J$162,Y$3) -> 0 | Z64: =sumifs('25.06'!$H$7:$H$162,'25.06'!$I$7:$I$162,$B64,'25.06'!$J$7:$J$162,Z$3) -> 0 | AA64: =sum(R64:Z64) -> 0
A65: 45024 | B65: T. shopping | C65: =sumifs('25.06'!$H$7:$H$162,'25.06'!$G$7:$G$162,$B65,'25.06'!$F$7:$F$162,C$3) -> 0 | D65: =sumifs('25.06'!$H$7:$H$162,'25.06'!$G$7:$G$162,$B65,'25.06'!$F$7:$F$162,D$3) -> 0 | E65: =sumifs('25.06'!$H$7:$H$162,'25.06'!$G$7:$G$162,$B65,'25.06'!$F$7:$F$162,E$3) -> 0 | F65: =sumifs('25.06'!$H$7:$H$162,'25.06'!$G$7:$G$162,$B65,'25.06'!$F$7:$F$162,F$3) -> 0 | G65: =sumifs('25.06'!$H$7:$H$162,'25.06'!$G$7:$G$162,$B65,'25.06'!$F$7:$F$162,G$3) -> 0 | H65: =sumifs('25.06'!$H$7:$H$162,'25.06'!$G$7:$G$162,$B65,'25.06'!$F$7:$F$162,H$3) -> 0 | I65: =sumifs('25.06'!$H$7:$H$162,'25.06'!$G$7:$G$162,$B65,'25.06'!$F$7:$F$162,I$3) -> 0 | J65: =sumifs('25.06'!$H$7:$H$162,'25.06'!$G$7:$G$162,$B65,'25.06'!$F$7:$F$162,J$3) -> 0 | K65: =sumifs('25.06'!$H$7:$H$162,'25.06'!$G$7:$G$162,$B65,'25.06'!$F$7:$F$162,K$3) -> 0 | L65: =sum(C65:K65) -> 0 | N65: =L65/sum(L$61:L$69) -> 0 | R65: =sumifs('25.06'!$H$7:$H$162,'25.06'!$I$7:$I$162,$B65,'25.06'!$J$7:$J$162,R$3) -> 0 | S65: =sumifs('25.06'!$H$7:$H$162,'25.06'!$I$7:$I$162,$B65,'25.06'!$J$7:$J$162,S$3) -> 0 | T65: =sumifs('25.06'!$H$7:$H$162,'25.06'!$I$7:$I$162,$B65,'25.06'!$J$7:$J$162,T$3) -> 0 | U65: =sumifs('25.06'!$H$7:$H$162,'25.06'!$I$7:$I$162,$B65,'25.06'!$J$7:$J$162,U$3) -> 0 | V65: =sumifs('25.06'!$H$7:$H$162,'25.06'!$I$7:$I$162,$B65,'25.06'!$J$7:$J$162,V$3) -> 0 | W65: =sumifs('25.06'!$H$7:$H$162,'25.06'!$I$7:$I$162,$B65,'25.06'!$J$7:$J$162,W$3) -> 0 | X65: =sumifs('25.06'!$H$7:$H$162,'25.06'!$I$7:$I$162,$B65,'25.06'!$J$7:$J$162,X$3) -> 0 | Y65: =sumifs('25.06'!$H$7:$H$162,'25.06'!$I$7:$I$162,$B65,'25.06'!$J$7:$J$162,Y$3) -> 0 | Z65: =sumifs('25.06'!$H$7:$H$162,'25.06'!$I$7:$I$162,$B65,'25.06'!$J$7:$J$162,Z$3) -> 0 | AA65: =sum(R65:Z65) -> 0
A66: 45054 | B66: T. Mainternance | C66: =sumifs('25.06'!$H$7:$H$162,'25.06'!$G$7:$G$162,$B66,'25.06'!$F$7:$F$162,C$3) -> 0 | D66: =sumifs('25.06'!$H$7:$H$162,'25.06'!$G$7:$G$162,$B66,'25.06'!$F$7:$F$162,D$3) -> 0 | E66: =sumifs('25.06'!$H$7:$H$162,'25.06'!$G$7:$G$162,$B66,'25.06'!$F$7:$F$162,E$3) -> 0 | F66: =sumifs('25.06'!$H$7:$H$162,'25.06'!$G$7:$G$162,$B66,'25.06'!$F$7:$F$162,F$3) -> 0 | G66: =sumifs('25.06'!$H$7:$H$162,'25.06'!$G$7:$G$162,$B66,'25.06'!$F$7:$F$162,G$3) -> 0 | H66: =sumifs('25.06'!$H$7:$H$162,'25.06'!$G$7:$G$162,$B66,'25.06'!$F$7:$F$162,H$3) -> 0 | I66: =sumifs('25.06'!$H$7:$H$162,'25.06'!$G$7:$G$162,$B66,'25.06'!$F$7:$F$162,I$3) -> 0 | J66: =sumifs('25.06'!$H$7:$H$162,'25.06'!$G$7:$G$162,$B66,'25.06'!$F$7:$F$162,J$3) -> 0 | K66: =sumifs('25.06'!$H$7:$H$162,'25.06'!$G$7:$G$162,$B66,'25.06'!$F$7:$F$162,K$3) -> 0 | L66: =sum(C66:K66) -> 0 | N66: =L66/sum(L$61:L$69) -> 0 | R66: =sumifs('25.06'!$H$7:$H$162,'25.06'!$I$7:$I$162,$B66,'25.06'!$J$7:$J$162,R$3) -> 0 | S66: =sumifs('25.06'!$H$7:$H$162,'25.06'!$I$7:$I$162,$B66,'25.06'!$J$7:$J$162,S$3) -> 0 | T66: =sumifs('25.06'!$H$7:$H$162,'25.06'!$I$7:$I$162,$B66,'25.06'!$J$7:$J$162,T$3) -> 0 | U66: =sumifs('25.06'!$H$7:$H$162,'25.06'!$I$7:$I$162,$B66,'25.06'!$J$7:$J$162,U$3) -> 0 | V66: =sumifs('25.06'!$H$7:$H$162,'25.06'!$I$7:$I$162,$B66,'25.06'!$J$7:$J$162,V$3) -> 0 | W66: =sumifs('25.06'!$H$7:$H$162,'25.06'!$I$7:$I$162,$B66,'25.06'!$J$7:$J$162,W$3) -> 0 | X66: =sumifs('25.06'!$H$7:$H$162,'25.06'!$I$7:$I$162,$B66,'25.06'!$J$7:$J$162,X$3) -> 0 | Y66: =sumifs('25.06'!$H$7:$H$162,'25.06'!$I$7:$I$162,$B66,'25.06'!$J$7:$J$162,Y$3) -> 0 | Z66: =sumifs('25.06'!$H$7:$H$162,'25.06'!$I$7:$I$162,$B66,'25.06'!$J$7:$J$162,Z$3) -> 0 | AA66: =sum(R66:Z66) -> 0
A67: 45085 | B67: T. Exchange | C67: =sumifs('25.06'!$H$7:$H$162,'25.06'!$G$7:$G$162,$B67,'25.06'!$F$7:$F$162,C$3) -> 0 | D67: =sumifs('25.06'!$H$7:$H$162,'25.06'!$G$7:$G$162,$B67,'25.06'!$F$7:$F$162,D$3) -> 0 | E67: =sumifs('25.06'!$H$7:$H$162,'25.06'!$G$7:$G$162,$B67,'25.06'!$F$7:$F$162,E$3) -> 0 | F67: =sumifs('25.06'!$H$7:$H$162,'25.06'!$G$7:$G$162,$B67,'25.06'!$F$7:$F$162,F$3) -> 0 | G67: =sumifs('25.06'!$H$7:$H$162,'25.06'!$G$7:$G$162,$B67,'25.06'!$F$7:$F$162,G$3) -> 0 | H67: =sumifs('25.06'!$H$7:$H$162,'25.06'!$G$7:$G$162,$B67,'25.06'!$F$7:$F$162,H$3) -> 0 | I67: =sumifs('25.06'!$H$7:$H$162,'25.06'!$G$7:$G$162,$B67,'25.06'!$F$7:$F$162,I$3) -> 0 | J67: =sumifs('25.06'!$H$7:$H$162,'25.06'!$G$7:$G$162,$B67,'25.06'!$F$7:$F$162,J$3) -> 0 | K67: =sumifs('25.06'!$H$7:$H$162,'25.06'!$G$7:$G$162,$B67,'25.06'!$F$7:$F$162,K$3) -> 0 | L67: =sum(C67:K67) -> 0 | N67: =L67/sum(L$61:L$69) -> 0 | R67: =sumifs('25.06'!$H$7:$H$162,'25.06'!$I$7:$I$162,$B67,'25.06'!$J$7:$J$162,R$3) -> 0 | S67: =sumifs('25.06'!$H$7:$H$162,'25.06'!$I$7:$I$162,$B67,'25.06'!$J$7:$J$162,S$3) -> 0 | T67: =sumifs('25.06'!$H$7:$H$162,'25.06'!$I$7:$I$162,$B67,'25.06'!$J$7:$J$162,T$3) -> 0 | U67: =sumifs('25.06'!$H$7:$H$162,'25.06'!$I$7:$I$162,$B67,'25.06'!$J$7:$J$162,U$3) -> 0 | V67: =sumifs('25.06'!$H$7:$H$162,'25.06'!$I$7:$I$162,$B67,'25.06'!$J$7:$J$162,V$3) -> 0 | W67: =sumifs('25.06'!$H$7:$H$162,'25.06'!$I$7:$I$162,$B67,'25.06'!$J$7:$J$162,W$3) -> 0 | X67: =sumifs('25.06'!$H$7:$H$162,'25.06'!$I$7:$I$162,$B67,'25.06'!$J$7:$J$162,X$3) -> 0 | Y67: =sumifs('25.06'!$H$7:$H$162,'25.06'!$I$7:$I$162,$B67,'25.06'!$J$7:$J$162,Y$3) -> 0 | Z67: =sumifs('25.06'!$H$7:$H$162,'25.06'!$I$7:$I$162,$B67,'25.06'!$J$7:$J$162,Z$3) -> 0 | AA67: =sum(R67:Z67) -> 0
A68: 45115 | B68: T. Tax & Social | C68: =sumifs('25.06'!$H$7:$H$162,'25.06'!$G$7:$G$162,$B68,'25.06'!$F$7:$F$162,C$3) -> 0 | D68: =sumifs('25.06'!$H$7:$H$162,'25.06'!$G$7:$G$162,$B68,'25.06'!$F$7:$F$162,D$3) -> 0 | E68: =sumifs('25.06'!$H$7:$H$162,'25.06'!$G$7:$G$162,$B68,'25.06'!$F$7:$F$162,E$3) -> 0 | F68: =sumifs('25.06'!$H$7:$H$162,'25.06'!$G$7:$G$162,$B68,'25.06'!$F$7:$F$162,F$3) -> 0 | G68: =sumifs('25.06'!$H$7:$H$162,'25.06'!$G$7:$G$162,$B68,'25.06'!$F$7:$F$162,G$3) -> 0 | H68: =sumifs('25.06'!$H$7:$H$162,'25.06'!$G$7:$G$162,$B68,'25.06'!$F$7:$F$162,H$3) -> 0 | I68: =sumifs('25.06'!$H$7:$H$162,'25.06'!$G$7:$G$162,$B68,'25.06'!$F$7:$F$162,I$3) -> 0 | J68: =sumifs('25.06'!$H$7:$H$162,'25.06'!$G$7:$G$162,$B68,'25.06'!$F$7:$F$162,J$3) -> 0 | K68: =sumifs('25.06'!$H$7:$H$162,'25.06'!$G$7:$G$162,$B68,'25.06'!$F$7:$F$162,K$3) -> 0 | L68: =sum(C68:K68) -> 0 | N68: =L68/sum(L$61:L$69) -> 0 | R68: =sumifs('25.06'!$H$7:$H$162,'25.06'!$I$7:$I$162,$B68,'25.06'!$J$7:$J$162,R$3) -> 0 | S68: =sumifs('25.06'!$H$7:$H$162,'25.06'!$I$7:$I$162,$B68,'25.06'!$J$7:$J$162,S$3) -> 0 | T68: =sumifs('25.06'!$H$7:$H$162,'25.06'!$I$7:$I$162,$B68,'25.06'!$J$7:$J$162,T$3) -> 0 | U68: =sumifs('25.06'!$H$7:$H$162,'25.06'!$I$7:$I$162,$B68,'25.06'!$J$7:$J$162,U$3) -> 0 | V68: =sumifs('25.06'!$H$7:$H$162,'25.06'!$I$7:$I$162,$B68,'25.06'!$J$7:$J$162,V$3) -> 0 | W68: =sumifs('25.06'!$H$7:$H$162,'25.06'!$I$7:$I$162,$B68,'25.06'!$J$7:$J$162,W$3) -> 0 | X68: =sumifs('25.06'!$H$7:$H$162,'25.06'!$I$7:$I$162,$B68,'25.06'!$J$7:$J$162,X$3) -> 0 | Y68: =sumifs('25.06'!$H$7:$H$162,'25.06'!$I$7:$I$162,$B68,'25.06'!$J$7:$J$162,Y$3) -> 0 | Z68: =sumifs('25.06'!$H$7:$H$162,'25.06'!$I$7:$I$162,$B68,'25.06'!$J$7:$J$162,Z$3) -> 0 | AA68: =sum(R68:Z68) -> 0
A69: 45146 | B69: T. Renovation | C69: =sumifs('25.06'!$H$7:$H$162,'25.06'!$G$7:$G$162,$B69,'25.06'!$F$7:$F$162,C$3) -> 0 | D69: =sumifs('25.06'!$H$7:$H$162,'25.06'!$G$7:$G$162,$B69,'25.06'!$F$7:$F$162,D$3) -> 0 | E69: =sumifs('25.06'!$H$7:$H$162,'25.06'!$G$7:$G$162,$B69,'25.06'!$F$7:$F$162,E$3) -> 0 | F69: =sumifs('25.06'!$H$7:$H$162,'25.06'!$G$7:$G$162,$B69,'25.06'!$F$7:$F$162,F$3) -> 0 | G69: =sumifs('25.06'!$H$7:$H$162,'25.06'!$G$7:$G$162,$B69,'25.06'!$F$7:$F$162,G$3) -> 0 | H69: =sumifs('25.06'!$H$7:$H$162,'25.06'!$G$7:$G$162,$B69,'25.06'!$F$7:$F$162,H$3) -> 0 | I69: =sumifs('25.06'!$H$7:$H$162,'25.06'!$G$7:$G$162,$B69,'25.06'!$F$7:$F$162,I$3) -> 0 | J69: =sumifs('25.06'!$H$7:$H$162,'25.06'!$G$7:$G$162,$B69,'25.06'!$F$7:$F$162,J$3) -> 0 | K69: =sumifs('25.06'!$H$7:$H$162,'25.06'!$G$7:$G$162,$B69,'25.06'!$F$7:$F$162,K$3) -> 0 | L69: =sum(C69:K69) -> 0 | N69: =L69/sum(L$61:L$69) -> 0 | R69: =sumifs('25.06'!$H$7:$H$162,'25.06'!$I$7:$I$162,$B69,'25.06'!$J$7:$J$162,R$3) -> 0 | S69: =sumifs('25.06'!$H$7:$H$162,'25.06'!$I$7:$I$162,$B69,'25.06'!$J$7:$J$162,S$3) -> 0 | T69: =sumifs('25.06'!$H$7:$H$162,'25.06'!$I$7:$I$162,$B69,'25.06'!$J$7:$J$162,T$3) -> 0 | U69: =sumifs('25.06'!$H$7:$H$162,'25.06'!$I$7:$I$162,$B69,'25.06'!$J$7:$J$162,U$3) -> 0 | V69: =sumifs('25.06'!$H$7:$H$162,'25.06'!$I$7:$I$162,$B69,'25.06'!$J$7:$J$162,V$3) -> 0 | W69: =sumifs('25.06'!$H$7:$H$162,'25.06'!$I$7:$I$162,$B69,'25.06'!$J$7:$J$162,W$3) -> 0 | X69: =sumifs('25.06'!$H$7:$H$162,'25.06'!$I$7:$I$162,$B69,'25.06'!$J$7:$J$162,X$3) -> 0 | Y69: =sumifs('25.06'!$H$7:$H$162,'25.06'!$I$7:$I$162,$B69,'25.06'!$J$7:$J$162,Y$3) -> 0 | Z69: =sumifs('25.06'!$H$7:$H$162,'25.06'!$I$7:$I$162,$B69,'25.06'!$J$7:$J$162,Z$3) -> 0 | AA69: =sum(R69:Z69) -> 0
B70: Total | C70: =sum(C4:C69) -> 0 | D70: =sum(D4:D69) -> 0 | E70: =sum(E4:E69) -> 22308554 | F70: =sum(F4:F69) -> 0 | G70: =sum(G4:G69) -> 0 | H70: =sum(H4:H69) -> 0 | I70: =sum(I4:I69) -> 0 | J70: =sum(J4:J69) -> 0 | ... L70: =sum(L4:L69) -> 22308554 | N70: =sum(N4:N69) -> #DIV/0! | O70: =sum(O4:O69) -> #DIV/0! | R70: =sum(R4:R69) -> 0 | S70: =sum(S4:S69) -> 0 | T70: =sum(T4:T69) -> 84157000 | U70: =sum(U4:U69) -> 0 | V70: =sum(V4:V69) -> 0 | W70: =sum(W4:W69) -> 0 | X70: =sum(X4:X69) -> 0 | Y70: =sum(Y4:Y69) -> 0 | ... AA70: =sum(AA4:AA69) -> 84157000
A72: Accounts | B72: Account | C72: Cash | D72: BIDV | E72: Vietcombank | F72: Vp bank Lady | G72: Moca | H72: Momo | I72: Zalo | J72: Saving | R72: Sổ tiết kiệm | S72: Stt | T72: Số tiền | U72: Bắt đầu | W72: Kết thúc | X72: Số tháng | Y72: Tỉ lệ lãi | Z72: Cuối kì
B73: Balance | C73: 22500000 | D73: 78345768 | E73: 45650059 | F73: 2145050 | G73: 0 | H73: 9250 | I73: 3088 | J73: =T84 -> 2849500000 | M73: -851568107 | S73: 1 | T73: 230000000 | U73: 45308 | W73: 45674 | X73: =(W73-U73)/30 -> 12.2 | Y73: 0.058 | Z73: =T73+T73*Y73/12*X73 -> 2.4356233e+08
B74: In | C74: =sumifs('25.06'!$H$7:$H$162,'25.06'!$J$7:$J$162,C$72) -> 0 | D74: =sumifs('25.06'!$H$7:$H$162,'25.06'!$J$7:$J$162,D$72) -> 0 | E74: =sumifs('25.06'!$H$7:$H$162,'25.06'!$J$7:$J$162,E$72) -> 84157000 | F74: =sumifs('25.06'!$H$7:$H$162,'25.06'!$J$7:$J$162,F$72) -> 0 | G74: =sumifs('25.06'!$H$7:$H$162,'25.06'!$J$7:$J$162,G$72) -> 0 | H74: =sumifs('25.06'!$H$7:$H$162,'25.06'!$J$7:$J$162,H$72) -> 0 | I74: =sumifs('25.06'!$H$7:$H$162,'25.06'!$J$7:$J$162,I$72) -> 0 | J74: =sumifs('25.06'!$H$7:$H$162,'25.06'!$J$7:$J$162,J$72) -> 0 | S74: 2 | T74: 109500000 | U74: 45325 | W74: 45691 | X74: =(W74-U74)/30 -> 12.2 | Y74: 0.048 | Z74: =T74+T74*Y74/12*X74 -> 114843600
B75: Out | C75: =Sumifs('25.06'!$H$7:$H$162,'25.06'!$F$7:$F$162,C$72) -> 0 | D75: =Sumifs('25.06'!$H$7:$H$162,'25.06'!$F$7:$F$162,D$72) -> 0 | E75: =Sumifs('25.06'!$H$7:$H$162,'25.06'!$F$7:$F$162,E$72) -> 22308554 | F75: =Sumifs('25.06'!$H$7:$H$162,'25.06'!$F$7:$F$162,F$72) -> 0 | G75: =Sumifs('25.06'!$H$7:$H$162,'25.06'!$F$7:$F$162,G$72) -> 0 | H75: =Sumifs('25.06'!$H$7:$H$162,'25.06'!$F$7:$F$162,H$72) -> 0 | I75: =Sumifs('25.06'!$H$7:$H$162,'25.06'!$F$7:$F$162,I$72) -> 0 | J75: =Sumifs('25.06'!$H$7:$H$162,'25.06'!$F$7:$F$162,J$72) -> 0 | M75: =7127400-8900000 -> -1772600 | S75: 3 | AA75: ?
B76: Change | C76: =C74-C75 -> 0 | D76: =D74-D75 -> 0 | E76: =E74-E75 -> 61848446 | F76: =F74-F75 -> 0 | G76: =G74-G75 -> 0 | H76: =H74-H75 -> 0 | I76: =I74-I75 -> 0 | J76: =J74-J75 -> 0 | M76: -910749104 | S76: 4 | T76: 250000000 | U76: 45414 | W76: 45779 | X76: =(W76-U76)/30 -> 12.166667 | Y76: 0.05 | Z76: =T76+T76*Y76/12*X76 -> 2.6267361e+08
B77: Last | C77: =C73+C74-C75 -> 22500000 | D77: =D73+D74-D75 -> 78345768 | E77: =E73+E74-E75 -> 107498505 | F77: =F73+F74-F75 -> 2145050 | G77: =G73+G74-G75 -> 0 | H77: =H73+H74-H75 -> 9250 | I77: =I73+I74-I75 -> 3088 | J77: =J73+J74-J75 -> 2849500000 | L77: =19023059-E77 -> -88475446 | M77: -9749119104 | S77: 5 | T77: 300000000 | U77: 45649 | W77: 45831 | X77: =(W77-U77)/30 -> 6.0666667 | Y77: 0.059 | Z77: =T77+T77*Y77/12*X77 -> 3.0894833e+08
C78: =sum(C77:J77) -> 3060001661 | S78: 6 | T78: 200000000 | U78: 45476 | W78: 45841 | X78: =(W78-U78)/30 -> 12.166667 | Y78: 0.058 | Z78: =T78+T78*Y78/12*X78 -> 2.1176111e+08
S79: 7 | T79: 500000000 | U79: 45665 | W79: 45846 | X79: =(W79-U79)/30 -> 6.0333333 | Y79: 0.055 | Z79: =T79+T79*Y79/12*X79 -> 5.1382639e+08
A80: Funds | B80: Account | C80: Education | D80: Enjoy | E80: For give | F80: Health | G80: Living | H80: Savings | I80: N&M studio | J80: Togohub management | K80: Totto Fund | L80: Lego Fund | M80: Papa fund | N80: Nghia fund | O80: ID student | P80: A4 Class | Q80: Loan | S80: 8 | T80: 540000000 | U80: 45624 | W80: 45805 | X80: =(W80-U80)/30 -> 6.0333333 | Y80: 0.045 | Z80: =T80+T80*Y80/12*X80 -> 552217500
B81: Balance | C81: 0 | D81: 0 | E81: 0 | F81: 0 | G81: 0 | H81: 0 | I81: 0 | J81: -908560104 | K81: 10314000 | L81: 14672000 | M81: 35931800 | N81: 13000000 | O81: 2077300 | P81: 33430250 | Q81: -273800000 | S81: 9 | T81: 220000000 | U81: 45551 | W81: 45733 | X81: =(W81-U81)/30 -> 6.0666667 | Y81: 0.056 | Z81: =T81+T81*Y81/12*X81 -> 2.2622844e+08
B82: Out | C82: =sum(L4:L9) -> 0 | D82: =sum(L$10:L$16) -> 0 | E82: =sum(L17:L22) -> 0 | F82: =sum(L23:L28) -> 0 | G82: =sum(L29:L54) -> 0 | H82: =sum(L55:L57) -> 0 | I82: =sumifs('25.06'!$H$7:$H$162,'25.06'!$G$7:$G$162,$B58)+sumifs('25.06'!$H$7:$H$162,'25.06'!$G$7:$G$162,$B59)+sumifs('25.06'!$H$7:$H$162,'25.06'!$G$7:$G$162,$B60) -> 0 | J82: =sum(L61:L69) -> 22308554 | K82: =sumifs('25.06'!$H$7:$H$162,'25.06'!$G$7:$G$162,K$80) -> 0 | L82: =sumifs('25.06'!$H$7:$H$162,'25.06'!$G$7:$G$162,L$80) -> 0 | M82: =sumifs('25.06'!$H$7:$H$162,'25.06'!$G$7:$G$162,M$80) -> 0 | N82: =sumifs('25.06'!$H$7:$H$162,'25.06'!$G$7:$G$162,N$80) -> 0 | O82: =sumifs('25.06'!$H$7:$H$162,'25.06'!$G$7:$G$162,O$80) -> 0 | P82: =sumifs('25.06'!$H$7:$H$162,'25.06'!$G$7:$G$162,P$80) -> 0 | Q82: =sumifs('25.06'!$H$7:$H$160,'25.06'!$G$7:$G$160,Q$80) -> 0 | S82: 10 | T82: 500000000 | U82: 45665 | W82: 45846 | X82: =(W82-U82)/30 -> 6.0333333 | Y82: 0.059 | Z82: =T82+T82*Y82/12*X82 -> 5.1483194e+08
B83: In | C83: =sumifs('25.06'!$H$7:$H$162,'25.06'!$I$7:$I$162,C$80) -> 0 | D83: =sumifs('25.06'!$H$7:$H$162,'25.06'!$I$7:$I$162,D$80) -> 0 | E83: =sumifs('25.06'!$H$7:$H$162,'25.06'!$I$7:$I$162,E$80) -> 0 | F83: =sumifs('25.06'!$H$7:$H$162,'25.06'!$I$7:$I$162,F$80) -> 0 | G83: =sumifs('25.06'!$H$7:$H$162,'25.06'!$I$7:$I$162,G$80) -> 0 | H83: =sumifs('25.06'!$H$7:$H$162,'25.06'!$I$7:$I$162,H$80) -> 0 | I83: =sumifs('25.06'!$H$7:$H$162,'25.06'!$I$7:$I$162,$B58)+sumifs('25.06'!$H$7:$H$162,'25.06'!$I$7:$I$162,$B59)+sumifs('25.06'!$H$7:$H$162,'25.06'!$I$7:$I$162,$B60) -> 0 | J83: =sum(AA61:AA69) -> 84157000 | K83: =sumifs('25.06'!$H$7:$H$162,'25.06'!$I$7:$I$162,K$80) -> 0 | L83: =sumifs('25.06'!$H$7:$H$162,'25.06'!$I$7:$I$162,L$80) -> 0 | M83: =sumifs('25.06'!$H$7:$H$162,'25.06'!$I$7:$I$162,M$80) -> 0 | N83: =sumifs('25.06'!$H$7:$H$162,'25.06'!$I$7:$I$162,N$80) -> 0 | O83: =sumifs('25.06'!$H$7:$H$162,'25.06'!$I$7:$I$162,O$80) -> 0 | P83: =sumifs('25.06'!$H$7:$H$162,'25.06'!$I$7:$I$162,P$80) -> 0 | Q83: =Sumifs('25.06'!$H$7:$H$160,'25.06'!$I$7:$I$160,Q$80) -> 0 | S83: 11
B84: Change | C84: =C83-C82 -> 0 | D84: =D82-D83 -> 0 | E84: =E82-E83 -> 0 | F84: =F82-F83 -> 0 | G84: =G82-G83 -> 0 | H84: =H82-H83 -> 0 | I84: =I82-I83 -> 0 | J84: =J82-J83 -> -61848446 | K84: =K82-K83 -> 0 | ... Q84: =Q82-Q83 -> 0 | T84: =SUM(T73:T83) -> 2849500000 | Y84: =SUM(Y73:Y83) -> 0.488 | Z84: =SUM(Z73:Z83) -> 2948893267
B85: Last | C85: =C81-C82+C83 -> 0 | D85: =D81-D82+D83 -> 0 | E85: =E81-E82+E83 -> 0 | F85: =F81-F82+F83 -> 0 | G85: =G81-G82+G83 -> 0 | H85: =H81-H82+H83 -> 0 | I85: =I81-I82+I83 -> 0 | J85: =J81-J82+J83 -> -846711658 | ... P85: =P81-P82+P83 -> 33430250 | Q85: =Q81-Q82+Q83+Q84 -> -273800000 | S85: 1 | T85: =K99/sum($K99:$Q99) -> 0.17380959 | U85: =L99/sum($K99:$Q99) -> 0.079801386 | V85: =N99/sum($K99:$Q99) -> 0.37284409 | W85: =O99/sum($K99:$Q99) -> 0.015102748 | X85: =P99/sum($K99:$Q99) -> 0.35844219 | Y85: =Q99/sum($K99:$Q99) -> 0
C86: =sum(C85:Q85) -> -1011086308 | S86: 2 | T86: =K100/sum($K100:$Q100) -> 0.10104113 | U86: =L100/sum($K100:$Q100) -> 0.0079430541 | V86: =N100/sum($K100:$Q100) -> 0.065886264 | W86: =O100/sum($K100:$Q100) -> 0.26820133 | X86: =P100/sum($K100:$Q100) -> 0.55692822 | Y86: =Q100/sum($K100:$Q100) -> 0
Q87: =E77+D77+C77-P85-O85-L85-K85 -> 147850723 | S87: 3 | T87: =K101/sum($K101:$Q101) -> 0.17514043 | U87: =L101/sum($K101:$Q101) -> 0.03051047 | V87: =N101/sum($K101:$Q101) -> 0.02444414 | W87: =O101/sum($K101:$Q101) -> 0.004654126 | X87: =P101/sum($K101:$Q101) -> 0.76525083 | Y87: =Q101/sum($K101:$Q101) -> 0
A88: Sources | B88: Account | C88: Private | E88: Salary | G88: Interest | I88: Togohub | J88: N&M studio | S88: 4 | T88: =K102/sum($K102:$Q102) -> 0.06793045 | U88: =L102/sum($K102:$Q102) -> 0.026612407 | V88: =N102/sum($K102:$Q102) -> 0.032194673 | W88: =O102/sum($K102:$Q102) -> 0.0063245058 | X88: =P102/sum($K102:$Q102) -> 0.86693796 | Y88: =Q102/sum($K102:$Q102) -> 0
C89: Family | D89: Gift | E89: UAD | F89: N&M Salary | G89: Saving interest | H89: Banking interest | I89: House rental money | J89: N&M studio | K89: Design | L89: Construction | N89: A4 Class Parents | O89: Trash | S89: 5 | T89: =K103/sum($K103:$Q103) -> 0.058723526 | U89: =L103/sum($K103:$Q103) -> 0.038699423 | V89: =N103/sum($K103:$Q103) -> 0.049923661 | W89: =O103/sum($K103:$Q103) -> 0.095849058 | X89: =P103/sum($K103:$Q103) -> 0.75680433 | Y89: =Q103/sum($K103:$Q103) -> 0
B90: In | C90: =sumifs('25.06'!$H$7:$H$162,'25.06'!$D$7:$D$162,C$89) -> 0 | D90: =sumifs('25.06'!$H$7:$H$162,'25.06'!$D$7:$D$162,D$89) -> 0 | E90: =sumifs('25.06'!$H$7:$H$162,'25.06'!$D$7:$D$162,E$89) -> 0 | F90: =sumifs('25.06'!$H$7:$H$162,'25.06'!$I$7:$I$162,F$89) -> 0 | G90: =sumifs('25.06'!$H$7:$H$162,'25.06'!$D$7:$D$162,G$89) -> 0 | H90: =sumifs('25.06'!$H$7:$H$162,'25.06'!$D$7:$D$162,H$89) -> 0 | I90: =sumifs('25.06'!$H$7:$H$162,'25.06'!$D$7:$D$162,I$89) -> 84157000 | J90: =sumifs('25.06'!$H$7:$H$162,'25.06'!$D$7:$D$162,J$89) -> 0 | K90: =sumifs('25.06'!$H$7:$H$162,'25.06'!$D$7:$D$162,K$89) -> 0 | L90: =sumifs('25.06'!$H$7:$H$162,'25.06'!$D$7:$D$162,L$89) -> 0 | N90: =sumifs('25.06'!$H$7:$H$162,'25.06'!$D$7:$D$162,N$89) -> 0 | O90: =sumifs('25.06'!$H$7:$H$162,'25.06'!$D$7:$D$162,O$89) -> 0 | P90: =sum(C90:O90) -> 84157000 | S90: 6 | T90: =K104/sum($K104:$Q104) -> 0.027047056 | U90: =L104/sum($K104:$Q104) -> 0.24642426 | V90: =N104/sum($K104:$Q104) -> 0.0094211527 | W90: =O104/sum($K104:$Q104) -> 0.0037267218 | X90: =P104/sum($K104:$Q104) -> 0.53449816 | Y90: =Q104/sum($K104:$Q104) -> 0.17888265
B91: Out | C91: =sumifs('25.06'!$H$7:$H$162,'25.06'!$G$7:$G$162,C$89) -> 0 | D91: =sumifs('25.06'!$H$7:$H$162,'25.06'!$G$7:$G$162,D$89) -> 0 | E91: =sumifs('25.06'!$H$7:$H$162,'25.06'!$G$7:$G$162,E$89) -> 0 | F91: =sumifs('25.06'!$H$7:$H$162,'25.06'!$D$7:$D$162,F$89) -> 0 | G91: =sumifs('25.06'!$H$7:$H$162,'25.06'!$G$7:$G$162,G$89) -> 0 | H91: =sumifs('25.06'!$H$7:$H$162,'25.06'!$G$7:$G$162,H$89) -> 0 | I91: =sum(L61:L69) -> 22308554 | J91: =sumifs('25.06'!$H$7:$H$162,'25.06'!$G$7:$G$162,J$89) -> 0 | K91: =sumifs('25.06'!$H$7:$H$162,'25.06'!$G$7:$G$162,K$89) -> 0 | L91: =sumifs('25.06'!$H$7:$H$162,'25.06'!$G$7:$G$162,L$89) -> 0 | N91: =sumifs('25.06'!$H$7:$H$162,'25.06'!$G$7:$G$162,P$80) -> 0 | O91: =sumifs('25.06'!$H$7:$H$162,'25.06'!$G$7:$G$162,O$89) -> 0 | P91: =sum(C91:O91) -> 22308554 | S91: 7 | T91: =K105/sum($K105:$Q105) -> 0.14236439 | U91: =L105/sum($K105:$Q105) -> 0.16327866 | V91: =N105/sum($K105:$Q105) -> 0 | W91: =O105/sum($K105:$Q105) -> 0.23954583 | X91: =P105/sum($K105:$Q105) -> 0.45481112 | Y91: =Q105/sum($K105:$Q105) -> 0
B92: Change | C92: =C90-C91 -> 0 | D92: =D90-D91 -> 0 | E92: =E90-E91 -> 0 | F92: =F90-F91 -> 0 | G92: =G90-G91 -> 0 | H92: =H90-H91 -> 0 | I92: =I90-I91 -> 61848446 | J92: =J90-J91 -> 0 | ... L92: =L90-L91 -> 0 | N92: =N90-N91 -> 0 | O92: =O90-O91 -> 0 | P92: =P90-P91 -> 61848446 | S92: 8 | T92: =K106/sum($K106:$Q106) -> 0.00051644415 | U92: =L106/sum($K106:$Q106) -> 0.1196716 | V92: =N106/sum($K106:$Q106) -> 0.02385203 | W92: =O106/sum($K106:$Q106) -> 0.025664784 | X92: =P106/sum($K106:$Q106) -> 0.40453641 | Y92: =Q106/sum($K106:$Q106) -> 0.42575873
B93: Last | C93: =C92+D92 -> 0 | E93: =E92+F92 -> 0 | G93: =G92+H92 -> 0 | I93: =I92 -> 61848446 | J93: =sum(J92:L92) -> 0 | S93: 9 | T93: =K107/sum($K107:$Q107) -> 0.19491431 | U93: =L107/sum($K107:$Q107) -> 0.20338871 | V93: =N107/sum($K107:$Q107) -> 0.11684836 | W93: =O107/sum($K107:$Q107) -> 0.032829409 | X93: =P107/sum($K107:$Q107) -> 0.45201922 | Y93: =Q107/sum($K107:$Q107) -> 0
C94: =sum(C93:L93) -> 61848446 | S94: 10 | T94: =K108/sum($K108:$Q108) -> 0.11910368 | U94: =L108/sum($K108:$Q108) -> 0.01673161 | V94: =N108/sum($K108:$Q108) -> 0.034544954 | W94: =O108/sum($K108:$Q108) -> 0.45422193 | X94: =P108/sum($K108:$Q108) -> 0.14450632 | Y94: =Q108/sum($K108:$Q108) -> 0.23089151
C95: =C98*C94 -> 15462112 | D95: =D98*C94 -> 8658782.4 | E95: =E98*C94 -> 4947875.7 | F95: =F98*C94 -> 4947875.7 | G95: =G98*C94 -> 18554534 | H95: =H98*C94 -> 9277266.9 | S95: 11 | T95: =K109/sum($K109:$Q109) -> 0.12098896 | U95: =L109/sum($K109:$Q109) -> 0.027033532 | V95: =N109/sum($K109:$Q109) -> 0.41217531 | W95: =O109/sum($K109:$Q109) -> 0.28246202 | X95: =P109/sum($K109:$Q109) -> 0.15734019 | Y95: =Q109/sum($K109:$Q109) -> 0
C96: 110751668 | D96: 68848813 | E96: 24811770 | F96: 40700816 | G96: 85429754 | H96: 161520567
A97: Điều kiện | B97: Funds | C97: Education | D97: Enjoy | E97: For give | F97: Health | G97: Living | H97: Savings | I97: Thực tế | J97: Funds | K97: Education | L97: Enjoy | N97: For give | O97: Health | P97: Living | Q97: Savings | R97: Chênh lệch | S97: 12 | T97: =K110/sum($K110:$Q110) -> #DIV/0! | U97: =L110/sum($K110:$Q110) -> #DIV/0! | V97: =N110/sum($K110:$Q110) -> #DIV/0! | W97: =O110/sum($K110:$Q110) -> #DIV/0! | X97: =P110/sum($K110:$Q110) -> #DIV/0! | Y97: =Q110/sum($K110:$Q110) -> #DIV/0!
C98: 0.25 | D98: 0.14 | E98: 0.08 | F98: 0.08 | G98: 0.3 | H98: 0.15 | S98: Funds | T98: Education | U98: Enjoy | V98: For give | W98: Health | X98: Living | Y98: Savings
B99: 1 | C99: =$C$94*C$98 -> 15462112 | D99: =$C$94*D$98 -> 8658782.4 | E99: =$C$94*E$98 -> 4947875.7 | F99: =$C$94*F$98 -> 4947875.7 | G99: =$C$94*G$98 -> 18554534 | H99: =$C$94*H$98 -> 9277266.9 | J99: 1 | K99: 8148000 | L99: 3741000 | N99: 17478515 | O99: 708000 | P99: 16803370 | Q99: =H$82 -> 0
B100: 2 | C100: =$C$94*C$98 -> 15462112 | D100: =$C$94*D$98 -> 8658782.4 | E100: =$C$94*E$98 -> 4947875.7 | F100: =$C$94*F$98 -> 4947875.7 | G100: =$C$94*G$98 -> 18554534 | H100: =$C$94*H$98 -> 9277266.9 | J100: 2 | K100: 1844500 | L100: 145000 | N100: 1202750 | O100: 4896000 | P100: 10166693 | Q100: =H$82 -> 0 | S100: 1 | T100: =C99-K99 -> 7314111.5 | U100: =L99-D99 -> -4917782.4 | V100: =E99-N99 -> -12530639 | W100: =O99-F99 -> -4239875.7 | X100: =G99-P99 -> 1751163.8 | Y100: =H99-Q99 -> 9277266.9
B101: 3 | C101: =$C$94*C$98 -> 15462112 | D101: =$C$94*D$98 -> 8658782.4 | E101: =$C$94*E$98 -> 4947875.7 | F101: =$C$94*F$98 -> 4947875.7 | G101: =$C$94*G$98 -> 18554534 | H101: =$C$94*H$98 -> 9277266.9 | J101: 3 | K101: 21939000 | L101: 3821900 | N101: 3062000 | O101: 583000 | P101: 95859294 | Q101: =H$82 -> 0 | S101: 2 | T101: =C100-K100 -> 13617612 | U101: =L100-D100 -> -8513782.4 | V101: =E100-N100 -> 3745125.7 | W101: =O100-F100 -> -51875.68 | X101: =G100-P100 -> 8387840.8 | Y101: =H100-Q100 -> 9277266.9
...

Sheet Money plan yearly
B1: 2023 | C1: ='25.06'!H170 -> #REF!
B2: Income | C2: Private | D2: Salary | E2: Interest | F2: Togohub | G2: N&M studio | H2: Tổng
B3: 1 | C3: 21558531 | D3: 20700000 | E3: 880 | F3: -41027927 | G3: 25182248 | H3: =sum(C3:G3) -> 26413732
B4: 2
B5: 3
B6: 4
B7: 5
B8: 6
B9: 7
B10: 8
B11: 9
B12: 10
B13: 11
B14: 12
B15: Total | C15: =sum(C3:C14)/12 -> 1796544.2 | D15: =sum(D3:D14)/12 -> 1725000 | E15: =sum(E3:E14)/12 -> 73.333333 | F15: =sum(F3:F14)/12 -> -3418993.9 | G15: =sum(G3:G14)/12 -> 2098520.7 | H15: =sum(H3:H14)/12 -> 2201144.3
B17: Funds | C17: Education | D17: Enjoy | E17: For give | F17: Health | G17: Living | H17: Savings
B18: 1 | C18: 10155000 | D18: 515000 | E18: 4679000 | F18: 0 | G18: 23138163 | H18: 0
B19: 2 | C19: =$H4*#REF! -> #REF! | D19: =$H4*#REF! -> #REF! | E19: =$H4*#REF! -> #REF! | F19: =$H4*#REF! -> #REF! | G19: =$H4*#REF! -> #REF! | H19: =$H4*#REF! -> #REF!
B20: 3 | C20: =$H5*#REF! -> #REF! | D20: =$H5*#REF! -> #REF! | E20: =$H5*#REF! -> #REF! | F20: =$H5*#REF! -> #REF! | G20: =$H5*#REF! -> #REF! | H20: =$H5*#REF! -> #REF!
B21: 4 | C21: =$H6*#REF! -> #REF! | D21: =$H6*#REF! -> #REF! | E21: =$H6*#REF! -> #REF! | F21: =$H6*#REF! -> #REF! | G21: =$H6*#REF! -> #REF! | H21: =$H6*#REF! -> #REF!
B22: 5 | C22: =$H7*#REF! -> #REF! | D22: =$H7*#REF! -> #REF! | E22: =$H7*#REF! -> #REF! | F22: =$H7*#REF! -> #REF! | G22: =$H7*#REF! -> #REF! | H22: =$H7*#REF! -> #REF!
B23: 6 | C23: =$H8*#REF! -> #REF! | D23: =$H8*#REF! -> #REF! | E23: =$H8*#REF! -> #REF! | F23: =$H8*#REF! -> #REF! | G23: =$H8*#REF! -> #REF! | H23: =$H8*#REF! -> #REF!
B24: 7 | C24: =$H9*#REF! -> #REF! | D24: =$H9*#REF! -> #REF! | E24: =$H9*#REF! -> #REF! | F24: =$H9*#REF! -> #REF! | G24: =$H9*#REF! -> #REF! | H24: =$H9*#REF! -> #REF!
B25: 8 | C25: =$H10*#REF! -> #REF! | D25: =$H10*#REF! -> #REF! | E25: =$H10*#REF! -> #REF! | F25: =$H10*#REF! -> #REF! | G25: =$H10*#REF! -> #REF! | H25: =$H10*#REF! -> #REF!
B26: 9 | C26: =$H11*#REF! -> #REF! | D26: =$H11*#REF! -> #REF! | E26: =$H11*#REF! -> #REF! | F26: =$H11*#REF! -> #REF! | G26: =$H11*#REF! -> #REF! | H26: =$H11*#REF! -> #REF!
B27: 10 | C27: =$H12*#REF! -> #REF! | D27: =$H12*#REF! -> #REF! | E27: =$H12*#REF! -> #REF! | F27: =$H12*#REF! -> #REF! | G27: =$H12*#REF! -> #REF! | H27: =$H12*#REF! -> #REF!
B28: 11 | C28: =$H13*#REF! -> #REF! | D28: =$H13*#REF! -> #REF! | E28: =$H13*#REF! -> #REF! | F28: =$H13*#REF! -> #REF! | G28: =$H13*#REF! -> #REF! | H28: =$H13*#REF! -> #REF!
B29: 12 | C29: =$H14*#REF! -> #REF! | D29: =$H14*#REF! -> #REF! | E29: =$H14*#REF! -> #REF! | F29: =$H14*#REF! -> #REF! | G29: =$H14*#REF! -> #REF! | H29: =$H14*#REF! -> #REF!
C30: =SUM(C18:C29) -> #REF! | D30: =SUM(D18:D29) -> #REF! | E30: =SUM(E18:E29) -> #REF! | F30: =SUM(F18:F29) -> #REF! | G30: =SUM(G18:G29) -> #REF! | H30: =SUM(H18:H29) -> #REF! | I30: =SUM(C30:H30) -> #REF!
